Workbook

Sheet BOT
A1: Value | B1: 2025/11/17 | C1: 2025/11/30 | D1: 2025/12/31 | E1: 2026/01/31 | F1: 2026/02/28 | G1: 2026/03/31 | H1: 2026/04/30 | I1: 2026/05/31 | J1: 2026/06/30 | K1: 2026/07/31 | L1: 2026/08/31 | M1: 2026/09/30 | N1: 2026/10/31 | O1: 2026/11/30 | P1: 2026/12/31 | Q1: 2027/01/31 | R1: 2027/02/28 | S1: 2027/03/31 | T1: 2027/04/30 | U1: 2027/05/31 | V1: 2027/06/30 | W1: 2027/07/31 | X1: 2027/08/31 | Y1: 2027/09/30 | Z1: 2027/10/31 | AA1: 2027/11/30 | AB1: 2027/12/31 | AC1: 2028/01/31 | AD1: 2028/02/29 | AE1: 2028/03/31 | AF1: 2028/04/30 | AG1: 2028/05/31 | AH1: 2028/06/30 | AI1: 2028/07/31 | AJ1: 2028/08/31 | AK1: 2028/09/30 | AL1: 2028/10/31 | AM1: 2028/11/30 | AN1: 2028/12/31 | AO1: 2029/01/31 | AP1: 2029/02/28 | AQ1: 2029/03/31 | AR1: 2029/04/30 | AS1: 2029/05/31 | AT1: 2029/06/30 | AU1: 2029/07/31 | AV1: 2029/08/31 | AW1: 2029/09/30 | AX1: 2029/10/31 | AY1: 2029/11/30 | AZ1: 2029/12/31 | BA1: 2030/01/31 | BB1: 2030/02/28 | BC1: 2030/03/31 | BD1: 2030/04/30 | BE1: 2030/05/31 | BF1: 2030/06/30 | BG1: 2030/07/31 | BH1: 2030/08/31 | BI1: 2030/09/30 | BJ1: 2030/10/31 | BK1: 2030/11/30 | BL1: 2030/12/31
A2: fml_count | B2: 455 | C2: 367 | D2: 361 | E2: 360 | F2: 357 | G2: 336 | H2: 323 | I2: 293 | J2: 277 | K2: 268 | L2: 258 | M2: 240 | N2: 234 | O2: 223 | P2: 215 | Q2: 208 | R2: 203 | S2: 194 | T2: 190 | U2: 184 | V2: 182 | W2: 177 | X2: 166 | Y2: 162 | Z2: 150 | AA2: 148 | AB2: 147 | AC2: 146 | AD2: 142 | AE2: 135 | AF2: 108 | AG2: 89 | AH2: 86 | AI2: 80 | AJ2: 76 | AK2: 68 | AL2: 61 | AM2: 53 | AN2: 53 | AO2: 50 | AP2: 46 | AQ2: 43 | AR2: 42 | AS2: 39 | AT2: 37 | AU2: 29 | AV2: 28 | AW2: 23 | AX2: 21 | AY2: 16 | AZ2: 14 | BA2: 13 | BB2: 11 | BC2: 11 | BD2: 7 | BE2: 3 | BF2: 2 | BG2: 2 | BH2: 0 | BI2: 0 | BJ2: 0 | BK2: 0 | BL2: 0
A3: olmm_count | B3: 25 | C3: 21 | D3: 20 | E3: 20 | F3: 20 | G3: 19 | H3: 18 | I3: 18 | J3: 18 | K3: 18 | L3: 18 | M3: 17 | N3: 17 | O3: 17 | P3: 17 | Q3: 17 | R3: 16 | S3: 15 | T3: 14 | U3: 13 | V3: 12 | W3: 12 | X3: 10 | Y3: 10 | Z3: 10 | AA3: 10 | AB3: 9 | AC3: 9 | AD3: 9 | AE3: 8 | AF3: 8 | AG3: 8 | AH3: 8 | AI3: 7 | AJ3: 6 | AK3: 6 | AL3: 6 | AM3: 6 | AN3: 6 | AO3: 6 | AP3: 6 | AQ3: 6 | AR3: 6 | AS3: 6 | AT3: 6 | AU3: 6 | AV3: 6 | AW3: 5 | AX3: 5 | AY3: 5 | AZ3: 5 | BA3: 5 | BB3: 5 | BC3: 5 | BD3: 5 | BE3: 5 | BF3: 5 | BG3: 4 | BH3: 4 | BI3: 1 | BJ3: 1 | BK3: 1 | BL3: 1
A4: pl_count | B4: 0 | C4: 0 | D4: 0 | E4: 0 | F4: 0 | G4: 0 | H4: 0 | I4: 0 | J4: 0 | K4: 0 | L4: 0 | M4: 0 | N4: 0 | O4: 0 | P4: 0 | Q4: 0 | R4: 0 | S4: 0 | T4: 0 | U4: 0 | V4: 0 | W4: 0 | X4: 0 | Y4: 0 | Z4: 0 | AA4: 0 | AB4: 0 | AC4: 0 | AD4: 0 | AE4: 0 | AF4: 0 | AG4: 0 | AH4: 0 | AI4: 0 | AJ4: 0 | AK4: 0 | AL4: 0 | AM4: 0 | AN4: 0 | AO4: 0 | AP4: 0 | AQ4: 0 | AR4: 0 | AS4: 0 | AT4: 0 | AU4: 0 | AV4: 0 | AW4: 0 | AX4: 0 | AY4: 0 | AZ4: 0 | BA4: 0 | BB4: 0 | BC4: 0 | BD4: 0 | BE4: 0 | BF4: 0 | BG4: 0 | BH4: 0 | BI4: 0 | BJ4: 0 | BK4: 0 | BL4: 0
A5: revenue_p_m | B5: 5081053.4 | C5: 4259103.1 | D5: 4215213.9 | E5: 4201713.7 | F5: 4163586 | G5: 4012113.7 | H5: 3884762.8 | I5: 3615460.8 | J5: 3440605 | K5: 3347418.7 | L5: 3250530.3 | M5: 3029093.2 | N5: 2921123.3 | O5: 2783749.3 | P5: 2679016.6 | Q5: 2589491.8 | R5: 2502689.1 | S5: 2402952.8 | T5: 2343937.8 | U5: 2251476 | V5: 2217258.3 | W5: 2099640.8 | X5: 1999478.7 | Y5: 1906524.7 | Z5: 1744996.8 | AA5: 1726710 | AB5: 1705233.4 | AC5: 1672656.5 | AD5: 1621986.3 | AE5: 1533685.4 | AF5: 1359397.8 | AG5: 1144108.4 | AH5: 1121500.8 | AI5: 1047594 | AJ5: 963186.9 | AK5: 876411.53 | AL5: 770158.16 | AM5: 686904.21 | AN5: 686904.21 | AO5: 625687.02 | AP5: 586084.54 | AQ5: 535785.79 | AR5: 523697.24 | AS5: 498067.55 | AT5: 478026.26 | AU5: 382320.6 | AV5: 369861.19 | AW5: 284181.19 | AX5: 261172.78 | AY5: 201693.16 | AZ5: 182956.89 | BA5: 176550.81 | BB5: 156874.08 | BC5: 156874.08 | BD5: 100112.61 | BE5: 49390.65 | BF5: 43907.04 | BG5: 31287.92 | BH5: 19619.79 | BI5: 10503.15 | BJ5: 10503.15 | BK5: 10503.15 | BL5: 10503.15
A6: depreciation_p_m | B6: 2704957.9 | C6: 2263032.2 | D6: 2241103.3 | E6: 2236227.1 | F6: 2221835.2 | G6: 2136646.7 | H6: 2062584.1 | I6: 1916210.9 | J6: 1832675.7 | K6: 1783498.2 | L6: 1733536.6 | M6: 1615629 | N6: 1547048 | O6: 1470202.3 | P6: 1412206.2 | Q6: 1362511.9 | R6: 1314408 | S6: 1268642.7 | T6: 1244772.8 | U6: 1192984.9 | V6: 1172053.4 | W6: 1096276.6 | X6: 1045111.1 | Y6: 989256.22 | Z6: 901352.72 | AA6: 890433.03 | AB6: 878216.27 | AC6: 857611.09 | AD6: 828357.02 | AE6: 778039.68 | AF6: 690893.47 | AG6: 578882.87 | AH6: 568221.35 | AI6: 527652.4 | AJ6: 496873.66 | AK6: 451456.19 | AL6: 402067.54 | AM6: 362324.8 | AN6: 362324.8 | AO6: 328738.14 | AP6: 307304.06 | AQ6: 289051.68 | AR6: 282317.77 | AS6: 270157.78 | AT6: 258923.05 | AU6: 205998.01 | AV6: 199712.05 | AW6: 155344.06 | AX6: 143126.42 | AY6: 110991.3 | AZ6: 100519.45 | BA6: 96992.55 | BB6: 85497.51 | BC6: 85497.51 | BD6: 51528.76 | BE6: 26495.25 | BF6: 23840.28 | BG6: 16079.75 | BH6: 11836.53 | BI6: 5534.64 | BJ6: 5534.64 | BK6: 5534.64 | BL6: 5534.64
A7: interest_p_m | B7: 802604.78 | C7: 696309.83 | D7: 689179.69 | E7: 688931.9 | F7: 685952.7 | G7: 671246.26 | H7: 649724.25 | I7: 598057.12 | J7: 565759.68 | K7: 552064.44 | L7: 533286.16 | M7: 492336.41 | N7: 480321.86 | O7: 459917.68 | P7: 444407.19 | Q7: 429647.67 | R7: 418621.18 | S7: 405561.62 | T7: 400294.79 | U7: 384194.73 | V7: 379116.85 | W7: 362999.9 | X7: 344304.4 | Y7: 332893.74 | Z7: 304752.6 | AA7: 301432.86 | AB7: 296778.97 | AC7: 291326.41 | AD7: 281558.9 | AE7: 263621.09 | AF7: 233339.2 | AG7: 194645.43 | AH7: 190255.64 | AI7: 177490.37 | AJ7: 167030.66 | AK7: 153788.87 | AL7: 137889.56 | AM7: 122518.46 | AN7: 122518.46 | AO7: 113494.62 | AP7: 105947.28 | AQ7: 98680.53 | AR7: 95850.58 | AS7: 91819.71 | AT7: 87563.37 | AU7: 73390.06 | AV7: 70842.46 | AW7: 55630.7 | AX7: 49816.35 | AY7: 39772.01 | AZ7: 36315.24 | BA7: 35152.43 | BB7: 31438.7 | BC7: 31438.7 | BD7: 20415.04 | BE7: 11131.83 | BF7: 10209.01 | BG7: 7401.02 | BH7: 4344.87 | BI7: 2841.42 | BJ7: 2841.42 | BK7: 2841.42 | BL7: 2841.42
A8: admin_p_m | B8: 489997.36 | C8: 431525.42 | D8: 426758.97 | E8: 425687.86 | F8: 423369.59 | G8: 415521.48 | H8: 405527.27 | I8: 375865.38 | J8: 355192.08 | K8: 348406.48 | L8: 338345.75 | M8: 313490.72 | N8: 304532.16 | O8: 293559.67 | P8: 287025.78 | Q8: 278053.11 | R8: 271281.25 | S8: 259393.74 | T8: 251844.55 | U8: 241961.76 | V8: 238799.2 | W8: 230312.85 | X8: 220828.39 | Y8: 214591.51 | Z8: 200231.91 | AA8: 198421.07 | AB8: 195645.68 | AC8: 190122.04 | AD8: 184816.77 | AE8: 174495.21 | AF8: 156077.27 | AG8: 132348.94 | AH8: 129886.81 | AI8: 122281.94 | AJ8: 115397.14 | AK8: 106549.94 | AL8: 94529.18 | AM8: 85341.2 | AN8: 85341.2 | AO8: 79559.89 | AP8: 75501.4 | AQ8: 70851.96 | AR8: 69408.98 | AS8: 66956.94 | AT8: 64468.16 | AU8: 50919.39 | AV8: 49606.17 | AW8: 36166.25 | AX8: 33251.41 | AY8: 26615.18 | AZ8: 24698.47 | BA8: 24052.97 | BB8: 21976.77 | BC8: 21976.77 | BD8: 15854.01 | BE8: 9102.14 | BF8: 8040.16 | BG8: 6049.56 | BH8: 3198.39 | BI8: 2067.09 | BJ8: 2067.09 | BK8: 2067.09 | BL8: 2067.09
A9: maint_prov_p_m | B9: 23793608 | C9: 13694590 | D9: 13411201 | E9: 13307409 | F9: 13022969 | G9: 12093983 | H9: 11396089 | I9: 10506372 | J9: 9657186.3 | K9: 9108787.8 | L9: 8748463.2 | M9: 8103467 | N9: 7768700.7 | O9: 7252087.7 | P9: 6910355.1 | Q9: 6601900.9 | R9: 6334706.2 | S9: 5731543.8 | T9: 5359900.7 | U9: 5061280 | V9: 4891609.6 | W9: 4718584 | X9: 4245833.9 | Y9: 4090488.5 | Z9: 3732560.7 | AA9: 3689503.8 | AB9: 3648450.1 | AC9: 3643772.5 | AD9: 3490718 | AE9: 3374598 | AF9: 3099699.9 | AG9: 2469819.1 | AH9: 2355964.9 | AI9: 2157147.3 | AJ9: 1816139.8 | AK9: 1603586.4 | AL9: 1339627.1 | AM9: 1048719.6 | AN9: 1048719.6 | AO9: 873919.51 | AP9: 719562.65 | AQ9: 567511.54 | AR9: 547077.34 | AS9: 479044.31 | AT9: 450442.69 | AU9: 357859.96 | AV9: 321817.88 | AW9: 271512.09 | AX9: 246500.15 | AY9: 147772.19 | AZ9: 118390.91 | BA9: 111507.21 | BB9: 96052.99 | BC9: 96052.99 | BD9: 61425.67 | BE9: 8111.97 | BF9: 4192.77 | BG9: 4192.77 | BH9: 0 | BI9: 0 | BJ9: 0 | BK9: 0 | BL9: 0
A10: maintenance_fund | B10: 12792296 | C10: 8527201.5 | D10: 8339842.6 | E10: 8287906.2 | F10: 8290527.1 | G10: 8071824.8 | H10: 7916841.3 | I10: 7560305.3 | J10: 6977642.2 | K10: 6791445 | L10: 6638330.7 | M10: 6206277 | N10: 5917667.4 | O10: 5559477.5 | P10: 5294400.1 | Q10: 5072172.4 | R10: 4919233.5 | S10: 4543706.3 | T10: 4265201 | U10: 4049833.9 | V10: 3903250 | W10: 3737477.7 | X10: 3342452.2 | Y10: 3210868.4 | Z10: 3035698.1 | AA10: 2992641.2 | AB10: 2961078.3 | AC10: 2956400.7 | AD10: 2834266.4 | AE10: 2730930.4 | AF10: 2466745.8 | AG10: 2073474.4 | AH10: 1967344.5 | AI10: 1784375.9 | AJ10: 1516336.2 | AK10: 1322066.6 | AL10: 1083338.7 | AM10: 819419.21 | AN10: 819419.21 | AO10: 731835.08 | AP10: 620691.3 | AQ10: 546082.9 | AR10: 525648.7 | AS10: 460979.83 | AT10: 432378.21 | AU10: 343786.7 | AV10: 317721.97 | AW10: 267416.18 | AX10: 243884.92 | AY10: 147772.19 | AZ10: 118390.91 | BA10: 111507.21 | BB10: 96052.99 | BC10: 96052.99 | BD10: 61425.67 | BE10: 8111.97 | BF10: 4192.77 | BG10: 4192.77 | BH10: 0 | BI10: 0 | BJ10: 0 | BK10: 0 | BL10: 0
A11: other_fee_p_m | B11: 186516.38 | C11: 176401.72 | D11: 175196 | E11: 175136 | F11: 172664.36 | G11: 169821.88 | H11: 169041.88 | I11: 157782.24 | J11: 148221.6 | K11: 147375.1 | L11: 142717.98 | M11: 134267.59 | N11: 128629.94 | O11: 121352.95 | P11: 108985.7 | Q11: 104511.04 | R11: 97598.52 | S11: 96692.02 | T11: 93287.09 | U11: 88994.18 | V11: 88794.18 | W11: 87406.66 | X11: 84856.36 | Y11: 81721.93 | Z11: 75460.56 | AA11: 74122.17 | AB11: 74002.17 | AC11: 73942.17 | AD11: 73319.67 | AE11: 71207.17 | AF11: 60644.99 | AG11: 53122.81 | AH11: 52620.31 | AI11: 51232.81 | AJ11: 40216.25 | AK11: 38446.25 | AL11: 33543.11 | AM11: 28161.51 | AN11: 28161.51 | AO11: 22042.63 | AP11: 21802.63 | AQ11: 13449.75 | AR11: 13389.75 | AS11: 12137.18 | AT11: 12017.18 | AU11: 9924.68 | AV11: 9864.68 | AW11: 7101.62 | AX11: 6921.62 | AY11: 4485.02 | AZ11: 4042.52 | BA11: 3660.02 | BB11: 2895.02 | BC11: 2895.02 | BD11: 2010.02 | BE11: 480 | BF11: 420 | BG11: 360 | BH11: 240 | BI11: 60 | BJ11: 60 | BK11: 60 | BL11: 60
A12: total_cost | B12: 1.7865867e+08 | C12: 1.5218292e+08 | D12: 1.5033989e+08 | E12: 1.4991145e+08 | F12: 1.4900384e+08 | G12: 1.4485934e+08 | H12: 1.4026212e+08 | I12: 1.3018792e+08 | J12: 1.2309499e+08 | K12: 1.198191e+08 | L12: 1.1604043e+08 | M12: 1.0781393e+08 | N12: 1.0507005e+08 | O12: 1.0014909e+08 | P12: 96943121 | Q12: 93993419 | R12: 91605057 | S12: 87809120 | T12: 85838949 | U12: 82368472 | V12: 81063396 | W12: 77624907 | X12: 73494245 | Y12: 71081450 | Z12: 65613812 | AA12: 64834473 | AB12: 63881584 | AC12: 62845900 | AD12: 60802147 | AE12: 57164565 | AF12: 51179077 | AG12: 43551122 | AH12: 42606578 | AI12: 39427460 | AJ12: 36807026 | AK12: 33809975 | AL12: 30216176 | AM12: 26953292 | AN12: 26953292 | AO12: 24646125 | AP12: 22943558 | AQ12: 21237419 | AR12: 20660226 | AS12: 19778281 | AT12: 18846749 | AU12: 15573877 | AV12: 15048587 | AW12: 11744475 | AX12: 10578537 | AY12: 8488059.1 | AZ12: 7706603.3 | BA12: 7439497.6 | BB12: 6578543.9 | BC12: 6578543.9 | BD12: 4099184.7 | BE12: 2325924.9 | BF12: 2126802.1 | BG12: 1529619.2 | BH12: 995023.58 | BI12: 659528.18 | BJ12: 659528.18 | BK12: 659528.18 | BL12: 659528.18
A13: nbv | B13: 1.0879258e+08 | C13: 1.0200352e+08 | D13: 99053581 | E13: 96757912 | F13: 94175153 | G13: 90761327 | H13: 86929354 | I13: 79930875 | J13: 74789415 | K13: 71813398 | L13: 68252490 | M13: 62681568 | N13: 60522457 | O13: 57065719 | P13: 54361809 | Q13: 51816373 | R13: 49665417 | S13: 47303198 | T13: 45711285 | U13: 43469731 | V13: 42114025 | W13: 39862797 | X13: 37214802 | Y13: 35624884 | Z13: 32309959 | AA13: 31208412 | AB13: 30027752 | AC13: 28732007 | AD13: 27307112 | AE13: 25008271 | AF13: 21441280 | AG13: 18065835 | AH13: 17060561 | AI13: 15618985 | AJ13: 14558392 | AK13: 13218890 | AL13: 11801219 | AM13: 10363091 | AN13: 10000766 | AO13: 9333707.8 | AP13: 8589391.8 | AQ13: 7767678.6 | AR13: 7305468.5 | AS13: 6790879.4 | AT13: 6178672.4 | AU13: 5246444.9 | AV13: 4892315 | AW13: 3786105.4 | AX13: 3191897.2 | AY13: 2639548.3 | AZ13: 2375412.2 | BA13: 2215874.1 | BB13: 1943714.8 | BC13: 1858217.3 | BD13: 1312769.9 | BE13: 786790.62 | BF13: 717815.79 | BG13: 562424.41 | BH13: 262099.03 | BI13: 292880.5 | BJ13: 287345.86 | BK13: 281811.22 | BL13: 276276.58
... A16: olmm_fleet_drop | B16: 0 | C16: 4 | D16: 1 | E16: 0 | F16: 0 | G16: 1 | H16: 1 | I16: 0 | J16: 0 | K16: 0 | L16: 0 | M16: 1 | N16: 0 | O16: 0 | P16: 0 | Q16: 0 | R16: 1 | S16: 1 | T16: 1 | U16: 1 | V16: 1 | W16: 0 | X16: 2 | Y16: 0 | Z16: 0 | AA16: 0 | AB16: 1 | AC16: 0 | AD16: 0 | AE16: 1 | AF16: 0 | AG16: 0 | AH16: 0 | AI16: 1 | AJ16: 1 | AK16: 0 | AL16: 0 | AM16: 0 | AN16: 0 | AO16: 0 | AP16: 0 | AQ16: 0 | AR16: 0 | AS16: 0 | AT16: 0 | AU16: 0 | AV16: 0 | AW16: 1 | AX16: 0 | AY16: 0 | AZ16: 0 | BA16: 0 | BB16: 0 | BC16: 0 | BD16: 0 | BE16: 0 | BF16: 0 | BG16: 1 | BH16: 0 | BI16: 3 | BJ16: 0 | BK16: 0 | BL16: 0

Sheet GHA
A1: Value | B1: 2025/11/17 | C1: 2025/11/30 | D1: 2025/12/31 | E1: 2026/01/31 | F1: 2026/02/28 | G1: 2026/03/31 | H1: 2026/04/30 | I1: 2026/05/31 | J1: 2026/06/30 | K1: 2026/07/31 | L1: 2026/08/31 | M1: 2026/09/30 | N1: 2026/10/31 | O1: 2026/11/30 | P1: 2026/12/31 | Q1: 2027/01/31 | R1: 2027/02/28 | S1: 2027/03/31 | T1: 2027/04/30 | U1: 2027/05/31 | V1: 2027/06/30 | W1: 2027/07/31 | X1: 2027/08/31 | Y1: 2027/09/30 | Z1: 2027/10/31 | AA1: 2027/11/30 | AB1: 2027/12/31 | AC1: 2028/01/31 | AD1: 2028/02/29 | AE1: 2028/03/31 | AF1: 2028/04/30 | AG1: 2028/05/31 | AH1: 2028/06/30 | AI1: 2028/07/31 | AJ1: 2028/08/31 | AK1: 2028/09/30 | AL1: 2028/10/31 | AM1: 2028/11/30 | AN1: 2028/12/31 | AO1: 2029/01/31 | AP1: 2029/02/28 | AQ1: 2029/03/31 | AR1: 2029/04/30 | AS1: 2029/05/31 | AT1: 2029/06/30 | AU1: 2029/07/31 | AV1: 2029/08/31 | AW1: 2029/09/30 | AX1: 2029/10/31 | AY1: 2029/11/30 | AZ1: 2029/12/31 | BA1: 2030/01/31 | BB1: 2030/02/28 | BC1: 2030/03/31 | BD1: 2030/04/30 | BE1: 2030/05/31 | BF1: 2030/06/30 | BG1: 2030/07/31 | BH1: 2030/08/31 | BI1: 2030/09/30 | BJ1: 2030/10/31 | BK1: 2030/11/30 | BL1: 2030/12/31
A2: fml_count | B2: 5 | C2: 4 | D2: 0 | E2: 0 | F2: 0 | G2: 0 | H2: 0 | I2: 0 | J2: 0 | K2: 0 | L2: 0 | M2: 0 | N2: 0 | O2: 0 | P2: 0 | Q2: 0 | R2: 0 | S2: 0 | T2: 0 | U2: 0 | V2: 0 | W2: 0 | X2: 0 | Y2: 0 | Z2: 0 | AA2: 0 | AB2: 0 | AC2: 0 | AD2: 0 | AE2: 0 | AF2: 0 | AG2: 0 | AH2: 0 | AI2: 0 | AJ2: 0 | AK2: 0 | AL2: 0 | AM2: 0 | AN2: 0 | AO2: 0 | AP2: 0 | AQ2: 0 | AR2: 0 | AS2: 0 | AT2: 0 | AU2: 0 | AV2: 0 | AW2: 0 | AX2: 0 | AY2: 0 | AZ2: 0 | BA2: 0 | BB2: 0 | BC2: 0 | BD2: 0 | BE2: 0 | BF2: 0 | BG2: 0 | BH2: 0 | BI2: 0 | BJ2: 0 | BK2: 0 | BL2: 0
A3: olmm_count | B3: 0 | C3: 0 | D3: 0 | E3: 0 | F3: 0 | G3: 0 | H3: 0 | I3: 0 | J3: 0 | K3: 0 | L3: 0 | M3: 0 | N3: 0 | O3: 0 | P3: 0 | Q3: 0 | R3: 0 | S3: 0 | T3: 0 | U3: 0 | V3: 0 | W3: 0 | X3: 0 | Y3: 0 | Z3: 0 | AA3: 0 | AB3: 0 | AC3: 0 | AD3: 0 | AE3: 0 | AF3: 0 | AG3: 0 | AH3: 0 | AI3: 0 | AJ3: 0 | AK3: 0 | AL3: 0 | AM3: 0 | AN3: 0 | AO3: 0 | AP3: 0 | AQ3: 0 | AR3: 0 | AS3: 0 | AT3: 0 | AU3: 0 | AV3: 0 | AW3: 0 | AX3: 0 | AY3: 0 | AZ3: 0 | BA3: 0 | BB3: 0 | BC3: 0 | BD3: 0 | BE3: 0 | BF3: 0 | BG3: 0 | BH3: 0 | BI3: 0 | BJ3: 0 | BK3: 0 | BL3: 0
A4: pl_count | B4: 0 | C4: 0 | D4: 0 | E4: 0 | F4: 0 | G4: 0 | H4: 0 | I4: 0 | J4: 0 | K4: 0 | L4: 0 | M4: 0 | N4: 0 | O4: 0 | P4: 0 | Q4: 0 | R4: 0 | S4: 0 | T4: 0 | U4: 0 | V4: 0 | W4: 0 | X4: 0 | Y4: 0 | Z4: 0 | AA4: 0 | AB4: 0 | AC4: 0 | AD4: 0 | AE4: 0 | AF4: 0 | AG4: 0 | AH4: 0 | AI4: 0 | AJ4: 0 | AK4: 0 | AL4: 0 | AM4: 0 | AN4: 0 | AO4: 0 | AP4: 0 | AQ4: 0 | AR4: 0 | AS4: 0 | AT4: 0 | AU4: 0 | AV4: 0 | AW4: 0 | AX4: 0 | AY4: 0 | AZ4: 0 | BA4: 0 | BB4: 0 | BC4: 0 | BD4: 0 | BE4: 0 | BF4: 0 | BG4: 0 | BH4: 0 | BI4: 0 | BJ4: 0 | BK4: 0 | BL4: 0
A5: revenue_p_m | B5: 2199.37 | C5: 1804.33 | D5: 0 | E5: 0 | F5: 0 | G5: 0 | H5: 0 | I5: 0 | J5: 0 | K5: 0 | L5: 0 | M5: 0 | N5: 0 | O5: 0 | P5: 0 | Q5: 0 | R5: 0 | S5: 0 | T5: 0 | U5: 0 | V5: 0 | W5: 0 | X5: 0 | Y5: 0 | Z5: 0 | AA5: 0 | AB5: 0 | AC5: 0 | AD5: 0 | AE5: 0 | AF5: 0 | AG5: 0 | AH5: 0 | AI5: 0 | AJ5: 0 | AK5: 0 | AL5: 0 | AM5: 0 | AN5: 0 | AO5: 0 | AP5: 0 | AQ5: 0 | AR5: 0 | AS5: 0 | AT5: 0 | AU5: 0 | AV5: 0 | AW5: 0 | AX5: 0 | AY5: 0 | AZ5: 0 | BA5: 0 | BB5: 0 | BC5: 0 | BD5: 0 | BE5: 0 | BF5: 0 | BG5: 0 | BH5: 0 | BI5: 0 | BJ5: 0 | BK5: 0 | BL5: 0
A6: depreciation_p_m | B6: 425.01 | C6: 358.15 | D6: 0 | E6: 0 | F6: 0 | G6: 0 | H6: 0 | I6: 0 | J6: 0 | K6: 0 | L6: 0 | M6: 0 | N6: 0 | O6: 0 | P6: 0 | Q6: 0 | R6: 0 | S6: 0 | T6: 0 | U6: 0 | V6: 0 | W6: 0 | X6: 0 | Y6: 0 | Z6: 0 | AA6: 0 | AB6: 0 | AC6: 0 | AD6: 0 | AE6: 0 | AF6: 0 | AG6: 0 | AH6: 0 | AI6: 0 | AJ6: 0 | AK6: 0 | AL6: 0 | AM6: 0 | AN6: 0 | AO6: 0 | AP6: 0 | AQ6: 0 | AR6: 0 | AS6: 0 | AT6: 0 | AU6: 0 | AV6: 0 | AW6: 0 | AX6: 0 | AY6: 0 | AZ6: 0 | BA6: 0 | BB6: 0 | BC6: 0 | BD6: 0 | BE6: 0 | BF6: 0 | BG6: 0 | BH6: 0 | BI6: 0 | BJ6: 0 | BK6: 0 | BL6: 0
A7: interest_p_m | B7: 341.63 | C7: 316.52 | D7: 0 | E7: 0 | F7: 0 | G7: 0 | H7: 0 | I7: 0 | J7: 0 | K7: 0 | L7: 0 | M7: 0 | N7: 0 | O7: 0 | P7: 0 | Q7: 0 | R7: 0 | S7: 0 | T7: 0 | U7: 0 | V7: 0 | W7: 0 | X7: 0 | Y7: 0 | Z7: 0 | AA7: 0 | AB7: 0 | AC7: 0 | AD7: 0 | AE7: 0 | AF7: 0 | AG7: 0 | AH7: 0 | AI7: 0 | AJ7: 0 | AK7: 0 | AL7: 0 | AM7: 0 | AN7: 0 | AO7: 0 | AP7: 0 | AQ7: 0 | AR7: 0 | AS7: 0 | AT7: 0 | AU7: 0 | AV7: 0 | AW7: 0 | AX7: 0 | AY7: 0 | AZ7: 0 | BA7: 0 | BB7: 0 | BC7: 0 | BD7: 0 | BE7: 0 | BF7: 0 | BG7: 0 | BH7: 0 | BI7: 0 | BJ7: 0 | BK7: 0 | BL7: 0
A8: admin_p_m | B8: 400 | C8: 320 | D8: 0 | E8: 0 | F8: 0 | G8: 0 | H8: 0 | I8: 0 | J8: 0 | K8: 0 | L8: 0 | M8: 0 | N8: 0 | O8: 0 | P8: 0 | Q8: 0 | R8: 0 | S8: 0 | T8: 0 | U8: 0 | V8: 0 | W8: 0 | X8: 0 | Y8: 0 | Z8: 0 | AA8: 0 | AB8: 0 | AC8: 0 | AD8: 0 | AE8: 0 | AF8: 0 | AG8: 0 | AH8: 0 | AI8: 0 | AJ8: 0 | AK8: 0 | AL8: 0 | AM8: 0 | AN8: 0 | AO8: 0 | AP8: 0 | AQ8: 0 | AR8: 0 | AS8: 0 | AT8: 0 | AU8: 0 | AV8: 0 | AW8: 0 | AX8: 0 | AY8: 0 | AZ8: 0 | BA8: 0 | BB8: 0 | BC8: 0 | BD8: 0 | BE8: 0 | BF8: 0 | BG8: 0 | BH8: 0 | BI8: 0 | BJ8: 0 | BK8: 0 | BL8: 0
A9: maint_prov_p_m | B9: 29541.93 | C9: 23286.77 | D9: 0 | E9: 0 | F9: 0 | G9: 0 | H9: 0 | I9: 0 | J9: 0 | K9: 0 | L9: 0 | M9: 0 | N9: 0 | O9: 0 | P9: 0 | Q9: 0 | R9: 0 | S9: 0 | T9: 0 | U9: 0 | V9: 0 | W9: 0 | X9: 0 | Y9: 0 | Z9: 0 | AA9: 0 | AB9: 0 | AC9: 0 | AD9: 0 | AE9: 0 | AF9: 0 | AG9: 0 | AH9: 0 | AI9: 0 | AJ9: 0 | AK9: 0 | AL9: 0 | AM9: 0 | AN9: 0 | AO9: 0 | AP9: 0 | AQ9: 0 | AR9: 0 | AS9: 0 | AT9: 0 | AU9: 0 | AV9: 0 | AW9: 0 | AX9: 0 | AY9: 0 | AZ9: 0 | BA9: 0 | BB9: 0 | BC9: 0 | BD9: 0 | BE9: 0 | BF9: 0 | BG9: 0 | BH9: 0 | BI9: 0 | BJ9: 0 | BK9: 0 | BL9: 0
A10: maintenance_fund | B10: 7649.6 | C10: 4685.07 | D10: 0 | E10: 0 | F10: 0 | G10: 0 | H10: 0 | I10: 0 | J10: 0 | K10: 0 | L10: 0 | M10: 0 | N10: 0 | O10: 0 | P10: 0 | Q10: 0 | R10: 0 | S10: 0 | T10: 0 | U10: 0 | V10: 0 | W10: 0 | X10: 0 | Y10: 0 | Z10: 0 | AA10: 0 | AB10: 0 | AC10: 0 | AD10: 0 | AE10: 0 | AF10: 0 | AG10: 0 | AH10: 0 | AI10: 0 | AJ10: 0 | AK10: 0 | AL10: 0 | AM10: 0 | AN10: 0 | AO10: 0 | AP10: 0 | AQ10: 0 | AR10: 0 | AS10: 0 | AT10: 0 | AU10: 0 | AV10: 0 | AW10: 0 | AX10: 0 | AY10: 0 | AZ10: 0 | BA10: 0 | BB10: 0 | BC10: 0 | BD10: 0 | BE10: 0 | BF10: 0 | BG10: 0 | BH10: 0 | BI10: 0 | BJ10: 0 | BK10: 0 | BL10: 0
A11: other_fee_p_m | B11: 543.57 | C11: 434.84 | D11: 0 | E11: 0 | F11: 0 | G11: 0 | H11: 0 | I11: 0 | J11: 0 | K11: 0 | L11: 0 | M11: 0 | N11: 0 | O11: 0 | P11: 0 | Q11: 0 | R11: 0 | S11: 0 | T11: 0 | U11: 0 | V11: 0 | W11: 0 | X11: 0 | Y11: 0 | Z11: 0 | AA11: 0 | AB11: 0 | AC11: 0 | AD11: 0 | AE11: 0 | AF11: 0 | AG11: 0 | AH11: 0 | AI11: 0 | AJ11: 0 | AK11: 0 | AL11: 0 | AM11: 0 | AN11: 0 | AO11: 0 | AP11: 0 | AQ11: 0 | AR11: 0 | AS11: 0 | AT11: 0 | AU11: 0 | AV11: 0 | AW11: 0 | AX11: 0 | AY11: 0 | AZ11: 0 | BA11: 0 | BB11: 0 | BC11: 0 | BD11: 0 | BE11: 0 | BF11: 0 | BG11: 0 | BH11: 0 | BI11: 0 | BJ11: 0 | BK11: 0 | BL11: 0
A12: total_cost | B12: 66498.7 | C12: 53197 | D12: 0 | E12: 0 | F12: 0 | G12: 0 | H12: 0 | I12: 0 | J12: 0 | K12: 0 | L12: 0 | M12: 0 | N12: 0 | O12: 0 | P12: 0 | Q12: 0 | R12: 0 | S12: 0 | T12: 0 | U12: 0 | V12: 0 | W12: 0 | X12: 0 | Y12: 0 | Z12: 0 | AA12: 0 | AB12: 0 | AC12: 0 | AD12: 0 | AE12: 0 | AF12: 0 | AG12: 0 | AH12: 0 | AI12: 0 | AJ12: 0 | AK12: 0 | AL12: 0 | AM12: 0 | AN12: 0 | AO12: 0 | AP12: 0 | AQ12: 0 | AR12: 0 | AS12: 0 | AT12: 0 | AU12: 0 | AV12: 0 | AW12: 0 | AX12: 0 | AY12: 0 | AZ12: 0 | BA12: 0 | BB12: 0 | BC12: 0 | BD12: 0 | BE12: 0 | BF12: 0 | BG12: 0 | BH12: 0 | BI12: 0 | BJ12: 0 | BK12: 0 | BL12: 0
A13: nbv | B13: 16610.2 | C13: 14926.72 | D13: 0 | E13: 0 | F13: 0 | G13: 0 | H13: 0 | I13: 0 | J13: 0 | K13: 0 | L13: 0 | M13: 0 | N13: 0 | O13: 0 | P13: 0 | Q13: 0 | R13: 0 | S13: 0 | T13: 0 | U13: 0 | V13: 0 | W13: 0 | X13: 0 | Y13: 0 | Z13: 0 | AA13: 0 | AB13: 0 | AC13: 0 | AD13: 0 | AE13: 0 | AF13: 0 | AG13: 0 | AH13: 0 | AI13: 0 | AJ13: 0 | AK13: 0 | AL13: 0 | AM13: 0 | AN13: 0 | AO13: 0 | AP13: 0 | AQ13: 0 | AR13: 0 | AS13: 0 | AT13: 0 | AU13: 0 | AV13: 0 | AW13: 0 | AX13: 0 | AY13: 0 | AZ13: 0 | BA13: 0 | BB13: 0 | BC13: 0 | BD13: 0 | BE13: 0 | BF13: 0 | BG13: 0 | BH13: 0 | BI13: 0 | BJ13: 0 | BK13: 0 | BL13: 0
... A16: olmm_fleet_drop | B16: 0 | C16: 0 | D16: 0 | E16: 0 | F16: 0 | G16: 0 | H16: 0 | I16: 0 | J16: 0 | K16: 0 | L16: 0 | M16: 0 | N16: 0 | O16: 0 | P16: 0 | Q16: 0 | R16: 0 | S16: 0 | T16: 0 | U16: 0 | V16: 0 | W16: 0 | X16: 0 | Y16: 0 | Z16: 0 | AA16: 0 | AB16: 0 | AC16: 0 | AD16: 0 | AE16: 0 | AF16: 0 | AG16: 0 | AH16: 0 | AI16: 0 | AJ16: 0 | AK16: 0 | AL16: 0 | AM16: 0 | AN16: 0 | AO16: 0 | AP16: 0 | AQ16: 0 | AR16: 0 | AS16: 0 | AT16: 0 | AU16: 0 | AV16: 0 | AW16: 0 | AX16: 0 | AY16: 0 | AZ16: 0 | BA16: 0 | BB16: 0 | BC16: 0 | BD16: 0 | BE16: 0 | BF16: 0 | BG16: 0 | BH16: 0 | BI16: 0 | BJ16: 0 | BK16: 0 | BL16: 0

Sheet GHC
A1: Value | B1: 2025/11/17 | C1: 2025/11/30 | D1: 2025/12/31 | E1: 2026/01/31 | F1: 2026/02/28 | G1: 2026/03/31 | H1: 2026/04/30 | I1: 2026/05/31 | J1: 2026/06/30 | K1: 2026/07/31 | L1: 2026/08/31 | M1: 2026/09/30 | N1: 2026/10/31 | O1: 2026/11/30 | P1: 2026/12/31 | Q1: 2027/01/31 | R1: 2027/02/28 | S1: 2027/03/31 | T1: 2027/04/30 | U1: 2027/05/31 | V1: 2027/06/30 | W1: 2027/07/31 | X1: 2027/08/31 | Y1: 2027/09/30 | Z1: 2027/10/31 | AA1: 2027/11/30 | AB1: 2027/12/31 | AC1: 2028/01/31 | AD1: 2028/02/29 | AE1: 2028/03/31 | AF1: 2028/04/30 | AG1: 2028/05/31 | AH1: 2028/06/30 | AI1: 2028/07/31 | AJ1: 2028/08/31 | AK1: 2028/09/30 | AL1: 2028/10/31 | AM1: 2028/11/30 | AN1: 2028/12/31 | AO1: 2029/01/31 | AP1: 2029/02/28 | AQ1: 2029/03/31 | AR1: 2029/04/30 | AS1: 2029/05/31 | AT1: 2029/06/30 | AU1: 2029/07/31 | AV1: 2029/08/31 | AW1: 2029/09/30 | AX1: 2029/10/31 | AY1: 2029/11/30 | AZ1: 2029/12/31 | BA1: 2030/01/31 | BB1: 2030/02/28 | BC1: 2030/03/31 | BD1: 2030/04/30 | BE1: 2030/05/31 | BF1: 2030/06/30 | BG1: 2030/07/31 | BH1: 2030/08/31 | BI1: 2030/09/30 | BJ1: 2030/10/31 | BK1: 2030/11/30 | BL1: 2030/12/31
A2: fml_count | B2: 156 | C2: 135 | D2: 134 | E2: 133 | F2: 130 | G2: 121 | H2: 120 | I2: 107 | J2: 104 | K2: 103 | L2: 68 | M2: 67 | N2: 67 | O2: 67 | P2: 67 | Q2: 66 | R2: 64 | S2: 59 | T2: 58 | U2: 58 | V2: 47 | W2: 47 | X2: 46 | Y2: 46 | Z2: 46 | AA2: 46 | AB2: 46 | AC2: 44 | AD2: 44 | AE2: 44 | AF2: 44 | AG2: 44 | AH2: 44 | AI2: 43 | AJ2: 43 | AK2: 42 | AL2: 42 | AM2: 42 | AN2: 42 | AO2: 42 | AP2: 42 | AQ2: 42 | AR2: 42 | AS2: 41 | AT2: 1 | AU2: 1 | AV2: 1 | AW2: 0 | AX2: 0 | AY2: 0 | AZ2: 0 | BA2: 0 | BB2: 0 | BC2: 0 | BD2: 0 | BE2: 0 | BF2: 0 | BG2: 0 | BH2: 0 | BI2: 0 | BJ2: 0 | BK2: 0 | BL2: 0
A3: olmm_count | B3: 0 | C3: 0 | D3: 0 | E3: 0 | F3: 0 | G3: 0 | H3: 0 | I3: 0 | J3: 0 | K3: 0 | L3: 0 | M3: 0 | N3: 0 | O3: 0 | P3: 0 | Q3: 0 | R3: 0 | S3: 0 | T3: 0 | U3: 0 | V3: 0 | W3: 0 | X3: 0 | Y3: 0 | Z3: 0 | AA3: 0 | AB3: 0 | AC3: 0 | AD3: 0 | AE3: 0 | AF3: 0 | AG3: 0 | AH3: 0 | AI3: 0 | AJ3: 0 | AK3: 0 | AL3: 0 | AM3: 0 | AN3: 0 | AO3: 0 | AP3: 0 | AQ3: 0 | AR3: 0 | AS3: 0 | AT3: 0 | AU3: 0 | AV3: 0 | AW3: 0 | AX3: 0 | AY3: 0 | AZ3: 0 | BA3: 0 | BB3: 0 | BC3: 0 | BD3: 0 | BE3: 0 | BF3: 0 | BG3: 0 | BH3: 0 | BI3: 0 | BJ3: 0 | BK3: 0 | BL3: 0
A4: pl_count | B4: 0 | C4: 0 | D4: 0 | E4: 0 | F4: 0 | G4: 0 | H4: 0 | I4: 0 | J4: 0 | K4: 0 | L4: 0 | M4: 0 | N4: 0 | O4: 0 | P4: 0 | Q4: 0 | R4: 0 | S4: 0 | T4: 0 | U4: 0 | V4: 0 | W4: 0 | X4: 0 | Y4: 0 | Z4: 0 | AA4: 0 | AB4: 0 | AC4: 0 | AD4: 0 | AE4: 0 | AF4: 0 | AG4: 0 | AH4: 0 | AI4: 0 | AJ4: 0 | AK4: 0 | AL4: 0 | AM4: 0 | AN4: 0 | AO4: 0 | AP4: 0 | AQ4: 0 | AR4: 0 | AS4: 0 | AT4: 0 | AU4: 0 | AV4: 0 | AW4: 0 | AX4: 0 | AY4: 0 | AZ4: 0 | BA4: 0 | BB4: 0 | BC4: 0 | BD4: 0 | BE4: 0 | BF4: 0 | BG4: 0 | BH4: 0 | BI4: 0 | BJ4: 0 | BK4: 0 | BL4: 0
A5: revenue_p_m | B5: 2581623 | C5: 2438219.6 | D5: 2427539.8 | E5: 2422632.9 | F5: 2396392.4 | G5: 2321409.6 | H5: 2309260.8 | I5: 2189055.5 | J5: 2137963 | K5: 2129865.1 | L5: 1783905.7 | M5: 1761137.1 | N5: 1761137.1 | O5: 1761137.1 | P5: 1761137.1 | Q5: 1733951.6 | R5: 1712641.7 | S5: 1662008 | T5: 1652026.7 | U5: 1652026.7 | V5: 1319308.9 | W5: 1319308.9 | X5: 1307002.4 | Y5: 1307002.4 | Z5: 1307002.4 | AA5: 1307002.4 | AB5: 1307002.4 | AC5: 1261301.6 | AD5: 1261301.6 | AE5: 1261301.6 | AF5: 1261301.6 | AG5: 1261301.6 | AH5: 1261301.6 | AI5: 1242826.4 | AJ5: 1242826.4 | AK5: 1222232.9 | AL5: 1222232.9 | AM5: 1222232.9 | AN5: 1222232.9 | AO5: 1222232.9 | AP5: 1222232.9 | AQ5: 1222232.9 | AR5: 1222232.9 | AS5: 1170874.2 | AT5: 53283.12 | AU5: 53283.12 | AV5: 53283.12 | AW5: 0 | AX5: 0 | AY5: 0 | AZ5: 0 | BA5: 0 | BB5: 0 | BC5: 0 | BD5: 0 | BE5: 0 | BF5: 0 | BG5: 0 | BH5: 0 | BI5: 0 | BJ5: 0 | BK5: 0 | BL5: 0
A6: depreciation_p_m | B6: 681549.87 | C6: 650889.88 | D6: 649903.75 | E6: 649326.31 | F6: 646950.81 | G6: 635463.51 | H6: 633257.7 | I6: 598011.2 | J6: 584597.88 | K6: 582703.14 | L6: 525935.64 | M6: 518846.57 | N6: 518846.57 | O6: 518846.57 | P6: 518846.57 | Q6: 512065.39 | R6: 509604.22 | S6: 496075.42 | T6: 493072.15 | U6: 493072.15 | V6: 371382.61 | W6: 371382.61 | X6: 369912.03 | Y6: 369912.03 | Z6: 369912.03 | AA6: 369912.03 | AB6: 369912.03 | AC6: 357769.37 | AD6: 357769.37 | AE6: 357769.37 | AF6: 357769.37 | AG6: 357769.37 | AH6: 357769.37 | AI6: 352515.79 | AJ6: 352515.79 | AK6: 347492.57 | AL6: 347492.57 | AM6: 347492.57 | AN6: 347492.57 | AO6: 347492.57 | AP6: 347492.57 | AQ6: 347492.57 | AR6: 347492.57 | AS6: 332726.37 | AT6: 17606.19 | AU6: 17606.19 | AV6: 17606.19 | AW6: 0 | AX6: 0 | AY6: 0 | AZ6: 0 | BA6: 0 | BB6: 0 | BC6: 0 | BD6: 0 | BE6: 0 | BF6: 0 | BG6: 0 | BH6: 0 | BI6: 0 | BJ6: 0 | BK6: 0 | BL6: 0
A7: interest_p_m | B7: 788844.33 | C7: 785491.08 | D7: 784216.77 | E7: 783015.15 | F7: 779507.71 | G7: 759252.34 | H7: 756371.47 | I7: 726189.68 | J7: 705810.56 | K7: 702820.23 | L7: 614085.27 | M7: 605513.64 | N7: 605513.64 | O7: 605513.64 | P7: 605513.64 | Q7: 593741.66 | R7: 588957.91 | S7: 575913.95 | T7: 573236.27 | U7: 573236.27 | V7: 466201.6 | W7: 466201.6 | X7: 463247.82 | Y7: 463247.82 | Z7: 463247.82 | AA7: 463247.82 | AB7: 463247.82 | AC7: 448109.06 | AD7: 448109.06 | AE7: 448109.06 | AF7: 448109.06 | AG7: 448109.06 | AH7: 448109.06 | AI7: 441649.64 | AJ7: 441649.64 | AK7: 435084.11 | AL7: 435084.11 | AM7: 435084.11 | AN7: 435084.11 | AO7: 435084.11 | AP7: 435084.11 | AQ7: 435084.11 | AR7: 435084.11 | AS7: 412867.42 | AT7: 23615.34 | AU7: 23615.34 | AV7: 23615.34 | AW7: 0 | AX7: 0 | AY7: 0 | AZ7: 0 | BA7: 0 | BB7: 0 | BC7: 0 | BD7: 0 | BE7: 0 | BF7: 0 | BG7: 0 | BH7: 0 | BI7: 0 | BJ7: 0 | BK7: 0 | BL7: 0
A8: admin_p_m | B8: 207094.8 | C8: 181269.11 | D8: 179301.92 | E8: 178052.09 | F8: 175087.52 | G8: 165850.82 | H8: 164397.75 | I8: 155147.61 | J8: 151763.05 | K8: 150661.85 | L8: 109922.39 | M8: 107304.74 | N8: 107304.74 | O8: 107304.74 | P8: 107304.74 | Q8: 105071.36 | R8: 103158.63 | S8: 98377.04 | T8: 97057.47 | U8: 97057.47 | V8: 69870.41 | W8: 69870.41 | X8: 68554.51 | Y8: 68554.51 | Z8: 68554.51 | AA8: 68554.51 | AB8: 68554.51 | AC8: 65045.61 | AD8: 65045.61 | AE8: 65045.61 | AF8: 65045.61 | AG8: 65045.61 | AH8: 65045.61 | AI8: 63644.85 | AJ8: 63644.85 | AK8: 62533.85 | AL8: 62533.85 | AM8: 62533.85 | AN8: 62533.85 | AO8: 62533.85 | AP8: 62533.85 | AQ8: 62533.85 | AR8: 62533.85 | AS8: 58842.3 | AT8: 3619.07 | AU8: 3619.07 | AV8: 3619.07 | AW8: 0 | AX8: 0 | AY8: 0 | AZ8: 0 | BA8: 0 | BB8: 0 | BC8: 0 | BD8: 0 | BE8: 0 | BF8: 0 | BG8: 0 | BH8: 0 | BI8: 0 | BJ8: 0 | BK8: 0 | BL8: 0
A9: maint_prov_p_m | B9: 11506883 | C9: 9036976.6 | D9: 8958349.4 | E9: 8851066.2 | F9: 8382776.3 | G9: 7439986.9 | H9: 7346267.6 | I9: 6553890.5 | J9: 6391642.5 | K9: 6372081.5 | L9: 3573444.7 | M9: 3530029 | N9: 3530029 | O9: 3530029 | P9: 3530029 | Q9: 3476659.3 | R9: 3316247.6 | S9: 2978051.3 | T9: 2939359.4 | U9: 2939359.4 | V9: 2538745.7 | W9: 2538745.7 | X9: 2471593.2 | Y9: 2471593.2 | Z9: 2471593.2 | AA9: 2471593.2 | AB9: 2471593.2 | AC9: 2270193.2 | AD9: 2270193.2 | AE9: 2270193.2 | AF9: 2270193.2 | AG9: 2270193.2 | AH9: 2270193.2 | AI9: 2211484.8 | AJ9: 2211484.8 | AK9: 2166284.8 | AL9: 2166284.8 | AM9: 2166284.8 | AN9: 2166284.8 | AO9: 2166284.8 | AP9: 2166284.8 | AQ9: 2166284.8 | AR9: 2166284.8 | AS9: 2149148.8 | AT9: 109980.78 | AU9: 109980.78 | AV9: 109980.78 | AW9: 0 | AX9: 0 | AY9: 0 | AZ9: 0 | BA9: 0 | BB9: 0 | BC9: 0 | BD9: 0 | BE9: 0 | BF9: 0 | BG9: 0 | BH9: 0 | BI9: 0 | BJ9: 0 | BK9: 0 | BL9: 0
A10: maintenance_fund | B10: 5588732.6 | C10: 4182501.4 | D10: 4181438.6 | E10: 4122455.7 | F10: 3971393.1 | G10: 3606197.4 | H10: 3540489.9 | I10: 3287022.7 | J10: 3222842.5 | K10: 3217284.9 | L10: 2306356.4 | M10: 2291480.5 | N10: 2291480.5 | O10: 2291480.5 | P10: 2291480.5 | Q10: 2260283.7 | R10: 2256794.5 | S10: 2202955.3 | T10: 2194966.5 | U10: 2194966.5 | V10: 2011477.5 | W10: 2011477.5 | X10: 2033942.4 | Y10: 2033942.4 | Z10: 2033942.4 | AA10: 2033942.4 | AB10: 2033942.4 | AC10: 1907933.3 | AD10: 1907933.3 | AE10: 1907933.3 | AF10: 1907933.3 | AG10: 1907933.3 | AH10: 1907933.3 | AI10: 1886439.5 | AJ10: 1886439.5 | AK10: 1895181.9 | AL10: 1895181.9 | AM10: 1895181.9 | AN10: 1895181.9 | AO10: 1895181.9 | AP10: 1895181.9 | AQ10: 1895181.9 | AR10: 1895181.9 | AS10: 1878045.9 | AT10: 105871.77 | AU10: 105871.77 | AV10: 105871.77 | AW10: 0 | AX10: 0 | AY10: 0 | AZ10: 0 | BA10: 0 | BB10: 0 | BC10: 0 | BD10: 0 | BE10: 0 | BF10: 0 | BG10: 0 | BH10: 0 | BI10: 0 | BJ10: 0 | BK10: 0 | BL10: 0
A11: other_fee_p_m | B11: 479464.3 | C11: 460098.71 | D11: 458146.52 | E11: 458018.52 | F11: 455394.16 | G11: 448917.82 | H11: 446308.69 | I11: 425516.78 | J11: 416457.15 | K11: 414567.69 | L11: 354776.37 | M11: 351236.81 | N11: 351236.81 | O11: 351236.81 | P11: 351236.81 | Q11: 346298.45 | R11: 343168.57 | S11: 335570.34 | T11: 333542.34 | U11: 333542.34 | V11: 269326.31 | W11: 269326.31 | X11: 267287.94 | Y11: 267287.94 | Z11: 267287.94 | AA11: 267287.94 | AB11: 267287.94 | AC11: 260433.48 | AD11: 260433.48 | AE11: 260433.48 | AF11: 260433.48 | AG11: 260433.48 | AH11: 260433.48 | AI11: 257096.48 | AJ11: 257096.48 | AK11: 253531.51 | AL11: 253531.51 | AM11: 253531.51 | AN11: 253531.51 | AO11: 253531.51 | AP11: 253531.51 | AQ11: 253531.51 | AR11: 253531.51 | AS11: 245295.26 | AT11: 586.75 | AU11: 586.75 | AV11: 586.75 | AW11: 0 | AX11: 0 | AY11: 0 | AZ11: 0 | BA11: 0 | BB11: 0 | BC11: 0 | BD11: 0 | BE11: 0 | BF11: 0 | BG11: 0 | BH11: 0 | BI11: 0 | BJ11: 0 | BK11: 0 | BL11: 0
A12: total_cost | B12: 58351201 | C12: 54424638 | D12: 54118569 | E12: 53925074 | F12: 53405219 | G12: 51535047 | H12: 51210310 | I12: 48182020 | J12: 46878008 | K12: 46591950 | L12: 37818280 | M12: 37304750 | N12: 37304750 | O12: 37304750 | P12: 37304750 | Q12: 36649734 | R12: 36135651 | S12: 35012062 | T12: 34758147 | U12: 34758147 | V12: 25493859 | W12: 25493859 | X12: 25214041 | Y12: 25214041 | Z12: 25214041 | AA12: 25214041 | AB12: 25214041 | AC12: 24371905 | AD12: 24371905 | AE12: 24371905 | AF12: 24371905 | AG12: 24371905 | AH12: 24371905 | AI12: 23951675 | AJ12: 23951675 | AK12: 23547275 | AL12: 23547275 | AM12: 23547275 | AN12: 23547275 | AO12: 23547275 | AP12: 23547275 | AQ12: 23547275 | AR12: 23547275 | AS12: 22439810 | AT12: 1240825 | AU12: 1240825 | AV12: 1240825 | AW12: 0 | AX12: 0 | AY12: 0 | AZ12: 0 | BA12: 0 | BB12: 0 | BC12: 0 | BD12: 0 | BE12: 0 | BF12: 0 | BG12: 0 | BH12: 0 | BI12: 0 | BJ12: 0 | BK12: 0 | BL12: 0
A13: nbv | B13: 32316761 | C13: 31704628 | D13: 30976234 | E13: 30281419 | F13: 29515550 | G13: 28298599 | H13: 27570581 | I13: 26075069 | J13: 24982427 | K13: 24290271 | L13: 21416982 | M13: 20744360 | N13: 20225514 | O13: 19706667 | P13: 19187820 | Q13: 18399773 | R13: 17734798 | S13: 16935034 | T13: 16371063 | U13: 15877990 | V13: 12047591 | W13: 11676209 | X13: 11205964 | Y13: 10836052 | Z13: 10466140 | AA13: 10096227 | AB13: 9726315.5 | AC13: 9121400.3 | AD13: 8763630.9 | AE13: 8405861.5 | AF13: 8048092.2 | AG13: 7690322.8 | AH13: 7332553.4 | AI13: 6869768.3 | AJ13: 6517252.5 | AK13: 6058006.7 | AL13: 5710514.1 | AM13: 5363021.5 | AN13: 5015529 | AO13: 4668036.4 | AP13: 4320543.8 | AQ13: 3973051.3 | AR13: 3625558.7 | AS13: 2879378.6 | AT13: 254878.36 | AU13: 237272.17 | AV13: 219665.98 | AW13: 0 | AX13: 0 | AY13: 0 | AZ13: 0 | BA13: 0 | BB13: 0 | BC13: 0 | BD13: 0 | BE13: 0 | BF13: 0 | BG13: 0 | BH13: 0 | BI13: 0 | BJ13: 0 | BK13: 0 | BL13: 0
... A16: olmm_fleet_drop | B16: 0 | C16: 0 | D16: 0 | E16: 0 | F16: 0 | G16: 0 | H16: 0 | I16: 0 | J16: 0 | K16: 0 | L16: 0 | M16: 0 | N16: 0 | O16: 0 | P16: 0 | Q16: 0 | R16: 0 | S16: 0 | T16: 0 | U16: 0 | V16: 0 | W16: 0 | X16: 0 | Y16: 0 | Z16: 0 | AA16: 0 | AB16: 0 | AC16: 0 | AD16: 0 | AE16: 0 | AF16: 0 | AG16: 0 | AH16: 0 | AI16: 0 | AJ16: 0 | AK16: 0 | AL16: 0 | AM16: 0 | AN16: 0 | AO16: 0 | AP16: 0 | AQ16: 0 | AR16: 0 | AS16: 0 | AT16: 0 | AU16: 0 | AV16: 0 | AW16: 0 | AX16: 0 | AY16: 0 | AZ16: 0 | BA16: 0 | BB16: 0 | BC16: 0 | BD16: 0 | BE16: 0 | BF16: 0 | BG16: 0 | BH16: 0 | BI16: 0 | BJ16: 0 | BK16: 0 | BL16: 0

Sheet LES
A1: Value | B1: 2025/11/17 | C1: 2025/11/30 | D1: 2025/12/31 | E1: 2026/01/31 | F1: 2026/02/28 | G1: 2026/03/31 | H1: 2026/04/30 | I1: 2026/05/31 | J1: 2026/06/30 | K1: 2026/07/31 | L1: 2026/08/31 | M1: 2026/09/30 | N1: 2026/10/31 | O1: 2026/11/30 | P1: 2026/12/31 | Q1: 2027/01/31 | R1: 2027/02/28 | S1: 2027/03/31 | T1: 2027/04/30 | U1: 2027/05/31 | V1: 2027/06/30 | W1: 2027/07/31 | X1: 2027/08/31 | Y1: 2027/09/30 | Z1: 2027/10/31 | AA1: 2027/11/30 | AB1: 2027/12/31 | AC1: 2028/01/31 | AD1: 2028/02/29 | AE1: 2028/03/31 | AF1: 2028/04/30 | AG1: 2028/05/31 | AH1: 2028/06/30 | AI1: 2028/07/31 | AJ1: 2028/08/31 | AK1: 2028/09/30 | AL1: 2028/10/31 | AM1: 2028/11/30 | AN1: 2028/12/31 | AO1: 2029/01/31 | AP1: 2029/02/28 | AQ1: 2029/03/31 | AR1: 2029/04/30 | AS1: 2029/05/31 | AT1: 2029/06/30 | AU1: 2029/07/31 | AV1: 2029/08/31 | AW1: 2029/09/30 | AX1: 2029/10/31 | AY1: 2029/11/30 | AZ1: 2029/12/31 | BA1: 2030/01/31 | BB1: 2030/02/28 | BC1: 2030/03/31 | BD1: 2030/04/30 | BE1: 2030/05/31 | BF1: 2030/06/30 | BG1: 2030/07/31 | BH1: 2030/08/31 | BI1: 2030/09/30 | BJ1: 2030/10/31 | BK1: 2030/11/30 | BL1: 2030/12/31
A2: fml_count | B2: 181 | C2: 165 | D2: 163 | E2: 156 | F2: 155 | G2: 153 | H2: 150 | I2: 149 | J2: 149 | K2: 148 | L2: 145 | M2: 133 | N2: 132 | O2: 132 | P2: 131 | Q2: 129 | R2: 125 | S2: 125 | T2: 121 | U2: 116 | V2: 115 | W2: 113 | X2: 111 | Y2: 97 | Z2: 87 | AA2: 86 | AB2: 86 | AC2: 81 | AD2: 75 | AE2: 69 | AF2: 65 | AG2: 63 | AH2: 48 | AI2: 37 | AJ2: 35 | AK2: 34 | AL2: 29 | AM2: 29 | AN2: 28 | AO2: 22 | AP2: 22 | AQ2: 22 | AR2: 20 | AS2: 17 | AT2: 14 | AU2: 12 | AV2: 11 | AW2: 11 | AX2: 8 | AY2: 8 | AZ2: 8 | BA2: 8 | BB2: 8 | BC2: 6 | BD2: 5 | BE2: 3 | BF2: 3 | BG2: 2 | BH2: 1 | BI2: 1 | BJ2: 1 | BK2: 1 | BL2: 1
A3: olmm_count | B3: 9 | C3: 9 | D3: 9 | E3: 9 | F3: 8 | G3: 8 | H3: 8 | I3: 8 | J3: 8 | K3: 8 | L3: 8 | M3: 8 | N3: 8 | O3: 8 | P3: 8 | Q3: 8 | R3: 8 | S3: 8 | T3: 8 | U3: 7 | V3: 7 | W3: 7 | X3: 7 | Y3: 7 | Z3: 2 | AA3: 2 | AB3: 2 | AC3: 2 | AD3: 2 | AE3: 2 | AF3: 2 | AG3: 1 | AH3: 1 | AI3: 1 | AJ3: 1 | AK3: 1 | AL3: 1 | AM3: 1 | AN3: 1 | AO3: 1 | AP3: 1 | AQ3: 1 | AR3: 1 | AS3: 1 | AT3: 1 | AU3: 1 | AV3: 1 | AW3: 1 | AX3: 1 | AY3: 1 | AZ3: 1 | BA3: 1 | BB3: 1 | BC3: 0 | BD3: 0 | BE3: 0 | BF3: 0 | BG3: 0 | BH3: 0 | BI3: 0 | BJ3: 0 | BK3: 0 | BL3: 0
A4: pl_count | B4: 0 | C4: 0 | D4: 0 | E4: 0 | F4: 0 | G4: 0 | H4: 0 | I4: 0 | J4: 0 | K4: 0 | L4: 0 | M4: 0 | N4: 0 | O4: 0 | P4: 0 | Q4: 0 | R4: 0 | S4: 0 | T4: 0 | U4: 0 | V4: 0 | W4: 0 | X4: 0 | Y4: 0 | Z4: 0 | AA4: 0 | AB4: 0 | AC4: 0 | AD4: 0 | AE4: 0 | AF4: 0 | AG4: 0 | AH4: 0 | AI4: 0 | AJ4: 0 | AK4: 0 | AL4: 0 | AM4: 0 | AN4: 0 | AO4: 0 | AP4: 0 | AQ4: 0 | AR4: 0 | AS4: 0 | AT4: 0 | AU4: 0 | AV4: 0 | AW4: 0 | AX4: 0 | AY4: 0 | AZ4: 0 | BA4: 0 | BB4: 0 | BC4: 0 | BD4: 0 | BE4: 0 | BF4: 0 | BG4: 0 | BH4: 0 | BI4: 0 | BJ4: 0 | BK4: 0 | BL4: 0
A5: revenue_p_m | B5: 2983657.9 | C5: 2851671.5 | D5: 2821250.9 | E5: 2749320.5 | F5: 2728690.6 | G5: 2710170.1 | H5: 2682284.7 | I5: 2671786.7 | J5: 2671786.7 | K5: 2658626.4 | L5: 2624016.2 | M5: 2520804.6 | N5: 2515422.4 | O5: 2515422.4 | P5: 2508946.5 | Q5: 2471139.1 | R5: 2402942.1 | S5: 2402942.1 | T5: 2353233.8 | U5: 2239391.1 | V5: 2228613 | W5: 2201771 | X5: 2183719.9 | Y5: 1579648.3 | Z5: 1237894.6 | AA5: 1220328.6 | AB5: 1220328.6 | AC5: 1150233 | AD5: 1083409.4 | AE5: 1008373.8 | AF5: 966068.27 | AG5: 906861.93 | AH5: 783337.99 | AI5: 671960.78 | AJ5: 662237.12 | AK5: 648718.43 | AL5: 573481.17 | AM5: 573481.17 | AN5: 559661.9 | AO5: 483985.09 | AP5: 483985.09 | AQ5: 483985.09 | AR5: 439007.22 | AS5: 392004.64 | AT5: 349958.11 | AU5: 326501.13 | AV5: 311487.32 | AW5: 311487.32 | AX5: 268303.54 | AY5: 268303.54 | AZ5: 268303.54 | BA5: 268303.54 | BB5: 268303.54 | BC5: 136730.74 | BD5: 128963.45 | BE5: 103063.11 | BF5: 103063.11 | BG5: 88259.64 | BH5: 75021.41 | BI5: 75021.41 | BJ5: 75021.41 | BK5: 75021.41 | BL5: 75021.41
A6: depreciation_p_m | B6: 1373374.2 | C6: 1314913.1 | D6: 1303752.6 | E6: 1272085.1 | F6: 1260890.2 | G6: 1252857.4 | H6: 1241690.6 | I6: 1237122.9 | J6: 1237122.9 | K6: 1232141.4 | L6: 1213774.2 | M6: 1179340.7 | N6: 1177289 | O6: 1177289 | P6: 1174798.8 | Q6: 1157909.5 | R6: 1128698.9 | S6: 1128698.9 | T6: 1106566.3 | U6: 1049857.1 | V6: 1046153.9 | W6: 1034020.3 | X6: 1026062.1 | Y6: 697459.79 | Z6: 502274.58 | AA6: 494600.22 | AB6: 494600.22 | AC6: 469407.97 | AD6: 440570.84 | AE6: 406862.22 | AF6: 389716.65 | AG6: 357397.76 | AH6: 310788.99 | AI6: 272242.81 | AJ6: 268666.79 | AK6: 264076.36 | AL6: 234676.87 | AM6: 234676.87 | AN6: 230230.94 | AO6: 199549.95 | AP6: 199549.95 | AQ6: 199549.95 | AR6: 179950.43 | AS6: 162249.96 | AT6: 146453.03 | AU6: 138142.21 | AV6: 132181.49 | AW6: 132181.49 | AX6: 114535.16 | AY6: 114535.16 | AZ6: 114535.16 | BA6: 114535.16 | BB6: 114535.16 | BC6: 56303.72 | BD6: 53403.43 | BE6: 42635.18 | BF6: 42635.18 | BG6: 36920.86 | BH6: 31574.16 | BI6: 31574.16 | BJ6: 31574.16 | BK6: 31574.16 | BL6: 31574.16
A7: interest_p_m | B7: 732074.57 | C7: 703558.55 | D7: 697901.21 | E7: 677964.1 | F7: 672007.51 | G7: 667155.66 | H7: 661721.84 | I7: 658777.82 | J7: 658777.82 | K7: 654677.55 | L7: 650117.03 | M7: 628134.32 | N7: 626898.88 | O7: 626898.88 | P7: 625010.86 | Q7: 614761.04 | R7: 595700.14 | S7: 595700.14 | T7: 581914.85 | U7: 562703.26 | V7: 560359.61 | W7: 550964.11 | X7: 544235.08 | Y7: 437079.37 | Z7: 349101.62 | AA7: 343264.16 | AB7: 343264.16 | AC7: 321237.56 | AD7: 297413.02 | AE7: 275669.15 | AF7: 260886.71 | AG7: 249126.58 | AH7: 214913.48 | AI7: 180721.92 | AJ7: 177515.04 | AK7: 173634.48 | AL7: 153740.28 | AM7: 153740.28 | AN7: 150472.38 | AO7: 130029.09 | AP7: 130029.09 | AQ7: 130029.09 | AR7: 118417.67 | AS7: 105242.27 | AT7: 92856.99 | AU7: 85164.77 | AV7: 80909.14 | AW7: 80909.14 | AX7: 67652.02 | AY7: 67652.02 | AZ7: 67652.02 | BA7: 67652.02 | BB7: 67652.02 | BC7: 36265.9 | BD7: 34783.77 | BE7: 29207.52 | BF7: 29207.52 | BG7: 24635.88 | BH7: 20130 | BI7: 20130 | BJ7: 20130 | BK7: 20130 | BL7: 20130
A8: admin_p_m | B8: 187249.11 | C8: 178308.7 | D8: 176431.11 | E8: 172682.52 | F8: 172055.11 | G8: 171229.26 | H8: 169993.26 | I8: 169685.46 | J8: 169685.46 | K8: 168734.97 | L8: 166823.83 | M8: 154736.48 | N8: 154316.48 | O8: 154316.48 | P8: 153756.81 | Q8: 151369.82 | R8: 146871.19 | S8: 146871.19 | T8: 143227.34 | U8: 136572.21 | V8: 135509.09 | W8: 133307.57 | X8: 131754.83 | Y8: 102327 | Z8: 87801.96 | AA8: 87451.96 | AB8: 87451.96 | AC8: 83206.86 | AD8: 79185.38 | AE8: 73629.51 | AF8: 70003.01 | AG8: 65896.08 | AH8: 59823.72 | AI8: 50590.37 | AJ8: 49785.77 | AK8: 48690.15 | AL8: 43175.82 | AM8: 43175.82 | AN8: 42055.71 | AO8: 36075.64 | AP8: 36075.64 | AQ8: 36075.64 | AR8: 32810.94 | AS8: 29385.36 | AT8: 26029.99 | AU8: 24002.62 | AV8: 22870.67 | AW8: 22870.67 | AX8: 19393.15 | AY8: 19393.15 | AZ8: 19393.15 | BA8: 19393.15 | BB8: 19393.15 | BC8: 10251.02 | BD8: 9813.25 | BE8: 8173.8 | BF8: 8173.8 | BG8: 6994.2 | BH8: 5826.68 | BI8: 5826.68 | BJ8: 5826.68 | BK8: 5826.68 | BL8: 5826.68
A9: maint_prov_p_m | B9: 8378143.9 | C9: 7182478.7 | D9: 6978291.7 | E9: 6804364.1 | F9: 6775809.5 | G9: 6719442.7 | H9: 6380891.1 | I9: 6354463.6 | J9: 6354463.6 | K9: 6322978.3 | L9: 6145957.1 | M9: 5575452.9 | N9: 5529407.1 | O9: 5529407.1 | P9: 5460646.1 | Q9: 5444374.9 | R9: 5401765.2 | S9: 5401765.2 | T9: 5285674.1 | U9: 4739333.8 | V9: 4689867.3 | W9: 4642487.5 | X9: 4625540.9 | Y9: 3431886.8 | Z9: 3161375 | AA9: 3147046.4 | AB9: 3147046.4 | AC9: 2889882.8 | AD9: 2625013.8 | AE9: 2431551.5 | AF9: 2369519.7 | AG9: 2281338.8 | AH9: 1612672.3 | AI9: 1305472.8 | AJ9: 1251846.5 | AK9: 1210325.9 | AL9: 996299.87 | AM9: 996299.87 | AN9: 904421.02 | AO9: 678329.86 | AP9: 678329.86 | AQ9: 678329.86 | AR9: 606872.76 | AS9: 450042.12 | AT9: 371878.73 | AU9: 309824.76 | AV9: 267391 | AW9: 267391 | AX9: 189139.86 | AY9: 189139.86 | AZ9: 189139.86 | BA9: 189139.86 | BB9: 189139.86 | BC9: 71758.82 | BD9: 58358.18 | BE9: 36033.02 | BF9: 36033.02 | BG9: 24785.52 | BH9: 19966.64 | BI9: 19966.64 | BJ9: 19966.64 | BK9: 19966.64 | BL9: 19966.64
A10: maintenance_fund | B10: 4838646 | C10: 4445256.6 | D10: 4428157.8 | E10: 4337526.3 | F10: 4331284.2 | G10: 4289222.1 | H10: 4282543 | I10: 4266368 | J10: 4266368 | K10: 4254848.4 | L10: 4165403.7 | M10: 3959008.1 | N10: 3947143.9 | O10: 3947143.9 | P10: 3895635.7 | Q10: 3887549.4 | R10: 3852403.6 | S10: 3852403.6 | T10: 3795149.1 | U10: 3556367.9 | V10: 3531454.7 | W10: 3519751.6 | X10: 3508214.5 | Y10: 2546461.5 | Z10: 2340240.5 | AA10: 2325911.9 | AB10: 2325911.9 | AC10: 2145859.3 | AD10: 1943023.6 | AE10: 1792809.1 | AF10: 1751999.4 | AG10: 1695024.9 | AH10: 1267729.1 | AI10: 1076966.2 | AJ10: 1042186.9 | AK10: 1018331.7 | AL10: 855839.33 | AM10: 855839.33 | AN10: 779292.73 | AO10: 595136.53 | AP10: 595136.53 | AQ10: 595136.53 | AR10: 530599.46 | AS10: 393050.23 | AT10: 334033.84 | AU10: 286211.2 | AV10: 258308.2 | AW10: 258308.2 | AX10: 189139.86 | AY10: 189139.86 | AZ10: 189139.86 | BA10: 189139.86 | BB10: 189139.86 | BC10: 71758.82 | BD10: 58358.18 | BE10: 36033.02 | BF10: 36033.02 | BG10: 24785.52 | BH10: 19966.64 | BI10: 19966.64 | BJ10: 19966.64 | BK10: 19966.64 | BL10: 19966.64
A11: other_fee_p_m | B11: 315192.43 | C11: 305717.25 | D11: 303552.64 | E11: 292526.73 | F11: 290252.3 | G11: 287203.78 | H11: 286756.34 | I11: 284930.27 | J11: 284930.27 | K11: 282888.1 | L11: 279576.51 | M11: 277314.07 | N11: 277239.07 | O11: 277239.07 | P11: 277164.07 | Q11: 272085.82 | R11: 262330.7 | S11: 262330.7 | T11: 258324.24 | U11: 243939.13 | V11: 241660.76 | W11: 241510.76 | X11: 240790.76 | Y11: 182393.09 | Z11: 148651.73 | AA11: 146049.77 | AB11: 146049.77 | AC11: 136528.86 | AD11: 134368.86 | AE11: 127688.26 | AF11: 124392.44 | AG11: 115821.52 | AH11: 104419.81 | AI11: 85949.85 | AJ11: 85799.85 | AK11: 83385.57 | AL11: 71546.17 | AM11: 71546.17 | AN11: 69185.95 | AO11: 60093.82 | AP11: 60093.82 | AQ11: 60093.82 | AR11: 53352.49 | AS11: 49770.64 | AT11: 44550.74 | AU11: 42262.36 | AV11: 41248.96 | AW11: 41248.96 | AX11: 38208.76 | AY11: 38208.76 | AZ11: 38208.76 | BA11: 38208.76 | BB11: 38208.76 | BC11: 20068.28 | BD11: 18796.26 | BE11: 14600.73 | BF11: 14600.73 | BG11: 13512.32 | BH11: 12498.91 | BI11: 12498.91 | BJ11: 12498.91 | BK11: 12498.91 | BL11: 12498.91
A12: total_cost | B12: 1.0350131e+08 | C12: 99015807 | D12: 98069007 | E12: 95450285 | F12: 94579736 | G12: 93905462 | H12: 92975813 | I12: 92558193 | J12: 92558193 | K12: 92082946 | L12: 91157365 | M12: 87054089 | N12: 86865225 | O12: 86865225 | P12: 86585389 | Q12: 85435765 | R12: 83216445 | S12: 83216445 | T12: 81467112 | U12: 78215083 | V12: 77717620 | W12: 76616850 | X12: 75840471 | Y12: 60093320 | Z12: 48264735 | AA12: 47660555 | AB12: 47660555 | AC12: 44767881 | AD12: 41448696 | AE12: 38406843 | AF12: 36593588 | AG12: 34540116 | AH12: 29788728 | AI12: 25242024 | AJ12: 24839714 | AK12: 24291904 | AL12: 21534726 | AM12: 21534726 | AN12: 20974667 | AO12: 18006820 | AP12: 18006820 | AQ12: 18006820 | AR12: 16374462 | AS12: 14661662 | AT12: 12983970 | AU12: 11970281 | AV12: 11404306 | AW12: 11404306 | AX12: 9665545.4 | AY12: 9665545.4 | AZ12: 9665545.4 | BA12: 9665545.4 | BB12: 9665545.4 | BC12: 5114472.4 | BD12: 4895585.3 | BE12: 4075854.7 | BF12: 4075854.7 | BG12: 3486050.1 | BH12: 2913340 | BI12: 2913340 | BJ12: 2913340 | BK12: 2913340 | BL12: 2913340
A13: nbv | B13: 77404909 | C13: 75630020 | D13: 73854712 | E13: 70942671 | F13: 69185447 | G13: 67531432 | H13: 65972461 | I13: 64477585 | J13: 63240462 | K13: 61707429 | L13: 60179696 | M13: 57024919 | N13: 55764744 | O13: 54587456 | P13: 53277252 | Q13: 51311387 | R13: 48672213 | S13: 47543514 | T13: 45468456 | U13: 43258699 | V13: 42022629 | W13: 40300382 | X13: 38773599 | Y13: 33341545 | Z13: 28015234 | AA13: 27185056 | AB13: 26690455 | AC13: 24643406 | AD13: 22560631 | AE13: 20701176 | AF13: 19244639 | AG13: 18200942 | AH13: 15680933 | AI13: 13021670 | AJ13: 12558103 | AK13: 12017052 | AL13: 10554279 | AM13: 10319603 | AN13: 9840527.4 | AO13: 8501156 | AP13: 8301606 | AQ13: 8102056.1 | AR13: 7426519.8 | AS13: 6537435.6 | AT13: 5602271.2 | AU13: 4963959 | AV13: 4617484.9 | AW13: 4485303.4 | AX13: 3667065 | AY13: 3552529.8 | AZ13: 3437994.6 | BA13: 3323459.5 | BB13: 3208924.3 | BC13: 1978971.1 | BD13: 1877797.6 | BE13: 1639990.4 | BF13: 1597355.2 | BG13: 1307774.7 | BH13: 1018890.4 | BI13: 987316.24 | BJ13: 955742.08 | BK13: 924167.92 | BL13: 892593.76
... A16: olmm_fleet_drop | B16: 0 | C16: 0 | D16: 0 | E16: 0 | F16: 1 | G16: 0 | H16: 0 | I16: 0 | J16: 0 | K16: 0 | L16: 0 | M16: 0 | N16: 0 | O16: 0 | P16: 0 | Q16: 0 | R16: 0 | S16: 0 | T16: 0 | U16: 1 | V16: 0 | W16: 0 | X16: 0 | Y16: 0 | Z16: 5 | AA16: 0 | AB16: 0 | AC16: 0 | AD16: 0 | AE16: 0 | AF16: 0 | AG16: 1 | AH16: 0 | AI16: 0 | AJ16: 0 | AK16: 0 | AL16: 0 | AM16: 0 | AN16: 0 | AO16: 0 | AP16: 0 | AQ16: 0 | AR16: 0 | AS16: 0 | AT16: 0 | AU16: 0 | AV16: 0 | AW16: 0 | AX16: 0 | AY16: 0 | AZ16: 0 | BA16: 0 | BB16: 0 | BC16: 1 | BD16: 0 | BE16: 0 | BF16: 0 | BG16: 0 | BH16: 0 | BI16: 0 | BJ16: 0 | BK16: 0 | BL16: 0

Sheet MOZ
A1: Value | B1: 2025/11/17 | C1: 2025/11/30 | D1: 2025/12/31 | E1: 2026/01/31 | F1: 2026/02/28 | G1: 2026/03/31 | H1: 2026/04/30 | I1: 2026/05/31 | J1: 2026/06/30 | K1: 2026/07/31 | L1: 2026/08/31 | M1: 2026/09/30 | N1: 2026/10/31 | O1: 2026/11/30 | P1: 2026/12/31 | Q1: 2027/01/31 | R1: 2027/02/28 | S1: 2027/03/31 | T1: 2027/04/30 | U1: 2027/05/31 | V1: 2027/06/30 | W1: 2027/07/31 | X1: 2027/08/31 | Y1: 2027/09/30 | Z1: 2027/10/31 | AA1: 2027/11/30 | AB1: 2027/12/31 | AC1: 2028/01/31 | AD1: 2028/02/29 | AE1: 2028/03/31 | AF1: 2028/04/30 | AG1: 2028/05/31 | AH1: 2028/06/30 | AI1: 2028/07/31 | AJ1: 2028/08/31 | AK1: 2028/09/30 | AL1: 2028/10/31 | AM1: 2028/11/30 | AN1: 2028/12/31 | AO1: 2029/01/31 | AP1: 2029/02/28 | AQ1: 2029/03/31 | AR1: 2029/04/30 | AS1: 2029/05/31 | AT1: 2029/06/30 | AU1: 2029/07/31 | AV1: 2029/08/31 | AW1: 2029/09/30 | AX1: 2029/10/31 | AY1: 2029/11/30 | AZ1: 2029/12/31 | BA1: 2030/01/31 | BB1: 2030/02/28 | BC1: 2030/03/31 | BD1: 2030/04/30 | BE1: 2030/05/31 | BF1: 2030/06/30 | BG1: 2030/07/31 | BH1: 2030/08/31 | BI1: 2030/09/30 | BJ1: 2030/10/31 | BK1: 2030/11/30 | BL1: 2030/12/31
A2: fml_count | B2: 257 | C2: 238 | D2: 237 | E2: 232 | F2: 231 | G2: 224 | H2: 222 | I2: 220 | J2: 218 | K2: 218 | L2: 208 | M2: 208 | N2: 205 | O2: 204 | P2: 203 | Q2: 203 | R2: 202 | S2: 202 | T2: 193 | U2: 181 | V2: 180 | W2: 153 | X2: 140 | Y2: 122 | Z2: 122 | AA2: 114 | AB2: 108 | AC2: 106 | AD2: 102 | AE2: 98 | AF2: 93 | AG2: 93 | AH2: 93 | AI2: 80 | AJ2: 68 | AK2: 67 | AL2: 62 | AM2: 58 | AN2: 57 | AO2: 57 | AP2: 57 | AQ2: 55 | AR2: 51 | AS2: 49 | AT2: 37 | AU2: 30 | AV2: 29 | AW2: 29 | AX2: 27 | AY2: 27 | AZ2: 25 | BA2: 23 | BB2: 23 | BC2: 22 | BD2: 22 | BE2: 22 | BF2: 17 | BG2: 7 | BH2: 7 | BI2: 0 | BJ2: 0 | BK2: 0 | BL2: 0
A3: olmm_count | B3: 36 | C3: 36 | D3: 34 | E3: 34 | F3: 33 | G3: 33 | H3: 32 | I3: 30 | J3: 30 | K3: 28 | L3: 28 | M3: 18 | N3: 18 | O3: 18 | P3: 18 | Q3: 18 | R3: 18 | S3: 18 | T3: 18 | U3: 16 | V3: 16 | W3: 16 | X3: 16 | Y3: 16 | Z3: 16 | AA3: 14 | AB3: 10 | AC3: 9 | AD3: 9 | AE3: 9 | AF3: 9 | AG3: 7 | AH3: 7 | AI3: 5 | AJ3: 4 | AK3: 1 | AL3: 1 | AM3: 1 | AN3: 1 | AO3: 0 | AP3: 0 | AQ3: 0 | AR3: 0 | AS3: 0 | AT3: 0 | AU3: 0 | AV3: 0 | AW3: 0 | AX3: 0 | AY3: 0 | AZ3: 0 | BA3: 0 | BB3: 0 | BC3: 0 | BD3: 0 | BE3: 0 | BF3: 0 | BG3: 0 | BH3: 0 | BI3: 0 | BJ3: 0 | BK3: 0 | BL3: 0
A4: pl_count | B4: 0 | C4: 0 | D4: 0 | E4: 0 | F4: 0 | G4: 0 | H4: 0 | I4: 0 | J4: 0 | K4: 0 | L4: 0 | M4: 0 | N4: 0 | O4: 0 | P4: 0 | Q4: 0 | R4: 0 | S4: 0 | T4: 0 | U4: 0 | V4: 0 | W4: 0 | X4: 0 | Y4: 0 | Z4: 0 | AA4: 0 | AB4: 0 | AC4: 0 | AD4: 0 | AE4: 0 | AF4: 0 | AG4: 0 | AH4: 0 | AI4: 0 | AJ4: 0 | AK4: 0 | AL4: 0 | AM4: 0 | AN4: 0 | AO4: 0 | AP4: 0 | AQ4: 0 | AR4: 0 | AS4: 0 | AT4: 0 | AU4: 0 | AV4: 0 | AW4: 0 | AX4: 0 | AY4: 0 | AZ4: 0 | BA4: 0 | BB4: 0 | BC4: 0 | BD4: 0 | BE4: 0 | BF4: 0 | BG4: 0 | BH4: 0 | BI4: 0 | BJ4: 0 | BK4: 0 | BL4: 0
A5: revenue_p_m | B5: 22807645 | C5: 21662615 | D5: 21266685 | E5: 20920125 | F5: 20662883 | G5: 20262628 | H5: 20017323 | I5: 19672711 | J5: 19447910 | K5: 19287649 | L5: 18708683 | M5: 17597523 | N5: 17363352 | O5: 17285512 | P5: 17231287 | Q5: 17231287 | R5: 17147141 | S5: 17147141 | T5: 16292494 | U5: 15185445 | V5: 15115097 | W5: 13828765 | X5: 13053370 | Y5: 11979650 | Z5: 11979650 | AA5: 11331219 | AB5: 10231818 | AC5: 10115686 | AD5: 9833919.4 | AE5: 9123181.8 | AF5: 8478120.2 | AG5: 8248958.4 | AH5: 8248958.4 | AI5: 7172329.4 | AJ5: 6184661.4 | AK5: 5776927.7 | AL5: 5461498.1 | AM5: 5160698.1 | AN5: 5119423 | AO5: 5041121.9 | AP5: 5041121.9 | AQ5: 4907550.9 | AR5: 4544621.1 | AS5: 4464979.4 | AT5: 3745783 | AU5: 3130131.2 | AV5: 3044825.8 | AW5: 3044825.8 | AX5: 2756367.7 | AY5: 2756367.7 | AZ5: 2514361.2 | BA5: 2344771.7 | BB5: 2344771.7 | BC5: 2304950.8 | BD5: 2304950.8 | BE5: 2304950.8 | BF5: 1993741.9 | BG5: 353701.25 | BH5: 353701.25 | BI5: 0 | BJ5: 0 | BK5: 0 | BL5: 0
A6: depreciation_p_m | B6: 9276224.4 | C6: 8861310.8 | D6: 8614082.7 | E6: 8478914.2 | F6: 8340043.6 | G6: 8190155.3 | H6: 8083625.9 | I6: 7931354.7 | J6: 7819080.3 | K6: 7745362.4 | L6: 7496120.1 | M6: 6983620.1 | N6: 6869273.8 | O6: 6840171.2 | P6: 6819368.6 | Q6: 6819368.6 | R6: 6783243.6 | S6: 6783243.6 | T6: 6395964.4 | U6: 5945152.9 | V6: 5919635.3 | W6: 5425613.9 | X6: 5135828.4 | Y6: 4757021.1 | Z6: 4757021.1 | AA6: 4491374.4 | AB6: 3975788.7 | AC6: 3934029.7 | AD6: 3798916.5 | AE6: 3420424.1 | AF6: 3064516.9 | AG6: 2957329.4 | AH6: 2957329.4 | AI6: 2523239.7 | AJ6: 2093755.2 | AK6: 1904541.8 | AL6: 1771265.5 | AM6: 1641969.1 | AN6: 1627865.8 | AO6: 1587214.6 | AP6: 1587214.6 | AQ6: 1538203.7 | AR6: 1391057.9 | AS6: 1364503.7 | AT6: 1090713 | AU6: 867671.76 | AV6: 836976.22 | AW6: 836976.22 | AX6: 704250.36 | AY6: 704250.36 | AZ6: 608270.96 | BA6: 543180.72 | BB6: 543180.72 | BC6: 529903.61 | BD6: 529903.61 | BE6: 529903.61 | BF6: 420991.29 | BG6: 111939.59 | BH6: 111939.59 | BI6: 0 | BJ6: 0 | BK6: 0 | BL6: 0
A7: interest_p_m | B7: 7012245.6 | C7: 6763848.8 | D7: 6660989.8 | E7: 6531138.5 | F7: 6445075.3 | G7: 6331742.7 | H7: 6241639.1 | I7: 6137534.9 | J7: 6067100.5 | K7: 5999982.9 | L7: 5827310.7 | M7: 5360697.5 | N7: 5308203.7 | O7: 5279651.6 | P7: 5260461.1 | Q7: 5260461.1 | R7: 5227570.6 | S7: 5227570.6 | T7: 4947052.4 | U7: 4565103.4 | V7: 4536686.7 | W7: 4081242.9 | X7: 3833767.2 | Y7: 3473170.7 | Z7: 3473170.7 | AA7: 3245148.1 | AB7: 2898459.5 | AC7: 2857118.6 | AD7: 2782254.9 | AE7: 2609806.1 | AF7: 2466411 | AG7: 2369422.3 | AH7: 2369422.3 | AI7: 2026196.6 | AJ7: 1727301.8 | AK7: 1564575.7 | AL7: 1474617.4 | AM7: 1387926.6 | AN7: 1374493.9 | AO7: 1345557.5 | AP7: 1345557.5 | AQ7: 1309473 | AR7: 1168331.5 | AS7: 1142885 | AT7: 905428.61 | AU7: 671937.01 | AV7: 639736.22 | AW7: 639736.22 | AX7: 538213.4 | AY7: 538213.4 | AZ7: 455655.4 | BA7: 404504.4 | BB7: 404504.4 | BC7: 391781.14 | BD7: 391781.14 | BE7: 391781.14 | BF7: 314057.58 | BG7: 112444.78 | BH7: 112444.78 | BI7: 0 | BJ7: 0 | BK7: 0 | BL7: 0
A8: admin_p_m | B8: 1800220.3 | C8: 1729073.7 | D8: 1702573.3 | E8: 1671184.5 | F8: 1648150.4 | G8: 1618094.6 | H8: 1595490.9 | I8: 1574874.3 | J8: 1556563.3 | K8: 1539362.5 | L8: 1483407.3 | M8: 1363824 | N8: 1342211.7 | O8: 1335503.4 | P8: 1330674.2 | Q8: 1330674.2 | R8: 1322245.1 | S8: 1322245.1 | T8: 1250830 | U8: 1151793.8 | V8: 1144852.2 | W8: 1028030.9 | X8: 965297.1 | Y8: 875274.28 | Z8: 875274.28 | AA8: 817870.92 | AB8: 735446.04 | AC8: 717978.85 | AD8: 705948.2 | AE8: 655395.91 | AF8: 604658.37 | AG8: 584650.05 | AH8: 584650.05 | AI8: 504464.85 | AJ8: 421673.54 | AK8: 386684.98 | AL8: 362438.2 | AM8: 339489.13 | AN8: 336600.13 | AO8: 330132.9 | AP8: 330132.9 | AQ8: 321470.94 | AR8: 291187.04 | AS8: 285725.4 | AT8: 232505.15 | AU8: 180467.98 | AV8: 173306.65 | AW8: 173306.65 | AX8: 147270.21 | AY8: 147270.21 | AZ8: 126501.12 | BA8: 113232.1 | BB8: 113232.1 | BC8: 110501.28 | BD8: 110501.28 | BE8: 110501.28 | BF8: 88078.18 | BG8: 27984.88 | BH8: 27984.88 | BI8: 0 | BJ8: 0 | BK8: 0 | BL8: 0
A9: maint_prov_p_m | B9: 87574402 | C9: 70819961 | D9: 70459961 | E9: 68648013 | F9: 68403985 | G9: 64560081 | H9: 63615053 | I9: 62415925 | J9: 61614032 | K9: 61614032 | L9: 57472490 | M9: 57472490 | N9: 55727210 | O9: 55166704 | P9: 54981631 | Q9: 54981631 | R9: 54712476 | S9: 54712476 | T9: 51469659 | U9: 46309197 | V9: 45989052 | W9: 39019045 | X9: 34795757 | Y9: 28620611 | Z9: 28620611 | AA9: 26540929 | AB9: 24292671 | AC9: 23855343 | AD9: 22419784 | AE9: 21392992 | AF9: 20356370 | AG9: 20356370 | AH9: 20356370 | AI9: 16253386 | AJ9: 12822859 | AK9: 12517337 | AL9: 11223226 | AM9: 10018382 | AN9: 9802382.1 | AO9: 9802382.1 | AP9: 9802382.1 | AQ9: 9401390.1 | AR9: 8657390.1 | AS9: 8303990.1 | AT9: 6418409.8 | AU9: 4871760.2 | AV9: 4670794 | AW9: 4670794 | AX9: 4336627.2 | AY9: 4336627.2 | AZ9: 3868627.2 | BA9: 3527377.2 | BB9: 3527377.2 | BC9: 3443677.2 | BD9: 3443677.2 | BE9: 3443677.2 | BF9: 2886277.8 | BG9: 223146 | BH9: 223146 | BI9: 0 | BJ9: 0 | BK9: 0 | BL9: 0
A10: maintenance_fund | B10: 52210783 | C10: 40157121 | D10: 39811387 | E10: 38900522 | F10: 38716146 | G10: 37622807 | H10: 37126130 | I10: 36512003 | J10: 35893972 | K10: 35893972 | L10: 34966946 | M10: 34966946 | N10: 34068295 | O10: 33755791 | P10: 33681510 | Q10: 33681510 | R10: 33594206 | S10: 33594206 | T10: 31774247 | U10: 29689035 | V10: 29471655 | W10: 27410156 | X10: 25332932 | Y10: 22386693 | Z10: 22386693 | AA10: 20307011 | AB10: 18944407 | AC10: 18638560 | AD10: 17498232 | AE10: 16909458 | AF10: 16244468 | AG10: 16244468 | AH10: 16244468 | AI10: 13203241 | AJ10: 11103649 | AK10: 10849831 | AL10: 10035945 | AM10: 9356894.7 | AN10: 9238473.5 | AO10: 9238473.5 | AP10: 9238473.5 | AQ10: 8861200.4 | AR10: 8249328.9 | AS10: 7934243.9 | AT10: 6232324 | AU10: 4731553.8 | AV10: 4530587.5 | AW10: 4530587.5 | AX10: 4270686.1 | AY10: 4270686.1 | AZ10: 3831728 | BA10: 3508127.4 | BB10: 3508127.4 | BC10: 3438595.1 | BD10: 3438595.1 | BE10: 3438595.1 | BF10: 2886277.8 | BG10: 223146 | BH10: 223146 | BI10: 0 | BJ10: 0 | BK10: 0 | BL10: 0
A11: other_fee_p_m | B11: 1141434.9 | C11: 1132094.9 | D11: 1127752.3 | E11: 1119707.3 | F11: 1117611 | G11: 1111661 | H11: 1108663.7 | I11: 1104155.9 | J11: 1102430.4 | K11: 1100205.7 | L11: 1091680.2 | M11: 1079217.2 | N11: 1076667.2 | O11: 1074867.2 | P11: 1070752.2 | Q11: 1070752.2 | R11: 1069902.2 | S11: 1069902.2 | T11: 1055987.2 | U11: 1033979.4 | V11: 1032129.4 | W11: 989000.9 | X11: 966369.9 | Y11: 936967.9 | Z11: 936967.9 | AA11: 926243.2 | AB11: 908214.8 | AC11: 905268.5 | AD11: 900471.4 | AE11: 893806.4 | AF11: 887556.4 | AG11: 882579.12 | AH11: 882579.12 | AI11: 857856.52 | AJ11: 809920.22 | AK11: 800430.22 | AL11: 782888.6 | AM11: 769218.6 | AN11: 767368.6 | AO11: 765122.3 | AP11: 765122.3 | AQ11: 761482.65 | AR11: 754324.05 | AS11: 750744.75 | AT11: 721208.6 | AU11: 708258.6 | AV11: 706408.6 | AW11: 706408.6 | AX11: 702768.95 | AY11: 702768.95 | AZ11: 699068.95 | BA11: 691489.65 | BB11: 691489.65 | BC11: 689700 | BD11: 689700 | BE11: 689700 | BF11: 680450 | BG11: 26950 | BH11: 26950 | BI11: 0 | BJ11: 0 | BK11: 0 | BL11: 0
A12: total_cost | B12: 6.2699128e+08 | C12: 5.904305e+08 | D12: 5.8134466e+08 | E12: 5.706102e+08 | F12: 5.6271277e+08 | G12: 5.5242851e+08 | H12: 5.4468552e+08 | I12: 5.3541437e+08 | J12: 5.2913632e+08 | K12: 5.2323888e+08 | L12: 5.0577538e+08 | M12: 4.6477538e+08 | N12: 4.573723e+08 | O12: 4.550723e+08 | P12: 4.5341659e+08 | Q12: 4.5341659e+08 | R12: 4.5052659e+08 | S12: 4.5052659e+08 | T12: 4.2606884e+08 | U12: 3.9216839e+08 | V12: 3.8978839e+08 | W12: 3.4975592e+08 | X12: 3.2833287e+08 | Y12: 2.9746787e+08 | Z12: 2.9746787e+08 | AA12: 2.777867e+08 | AB12: 2.4954729e+08 | AC12: 2.4607791e+08 | AD12: 2.3806958e+08 | AE12: 2.2156918e+08 | AF12: 2.0731164e+08 | AG12: 2.0045164e+08 | AH12: 2.0045164e+08 | AI12: 1.7295955e+08 | AJ12: 1.4457393e+08 | AK12: 1.3257784e+08 | AL12: 1.2426465e+08 | AM12: 1.1639639e+08 | AN12: 1.1540587e+08 | AO12: 1.1318853e+08 | AP12: 1.1318853e+08 | AQ12: 1.1021871e+08 | AR12: 99835656 | AS12: 97963092 | AT12: 79716136 | AU12: 61874802 | AV12: 59419486 | AW12: 59419486 | AX12: 50492703 | AY12: 50492703 | AZ12: 43371870 | BA12: 38822489 | BB12: 38822489 | BC12: 37886207 | BD12: 37886207 | BE12: 37886207 | BF12: 30198276 | BG12: 9594827.6 | BH12: 9594827.6 | BI12: 0 | BJ12: 0 | BK12: 0 | BL12: 0
A13: nbv | B13: 3.5565563e+08 | C13: 3.5132765e+08 | D13: 3.41205e+08 | E13: 3.2826898e+08 | F13: 3.1813396e+08 | G13: 3.0803619e+08 | H13: 2.9843636e+08 | I13: 2.8801936e+08 | J13: 2.7825621e+08 | K13: 2.6888905e+08 | L13: 2.5902511e+08 | M13: 2.4076649e+08 | N13: 2.3236481e+08 | O13: 2.249126e+08 | P13: 2.1739443e+08 | Q13: 2.1057507e+08 | R13: 2.030332e+08 | S13: 1.9624995e+08 | T13: 1.8395532e+08 | U13: 1.6921114e+08 | V13: 1.6241704e+08 | W13: 1.4598099e+08 | X13: 1.3322993e+08 | Y13: 1.16486e+08 | Z13: 1.1172898e+08 | AA13: 1.0016963e+08 | AB13: 90050955 | AC13: 85102228 | AD13: 79687572 | AE13: 74216985 | AF13: 70023530 | AG13: 65136826 | AH13: 62179496 | AI13: 54814643 | AJ13: 48473661 | AK13: 43646466 | AL13: 41377331 | AM13: 39495588 | AN13: 37709300 | AO13: 35815353 | AP13: 34228139 | AQ13: 32229206 | AR13: 29136691 | AS13: 27466322 | AT13: 23758710 | AU13: 18086353 | AV13: 16574402 | AW13: 15737426 | AX13: 13916993 | AY13: 13212743 | AZ13: 11146423 | BA13: 9861640.1 | BB13: 9318459.4 | BC13: 8635623.4 | BD13: 8105719.7 | BE13: 7575816.1 | BF13: 5892720.7 | BG13: 3102331.4 | BH13: 2990391.8 | BI13: 0 | BJ13: 0 | BK13: 0 | BL13: 0
... A16: olmm_fleet_drop | B16: 0 | C16: 0 | D16: 2 | E16: 0 | F16: 1 | G16: 0 | H16: 1 | I16: 2 | J16: 0 | K16: 2 | L16: 0 | M16: 10 | N16: 0 | O16: 0 | P16: 0 | Q16: 0 | R16: 0 | S16: 0 | T16: 0 | U16: 2 | V16: 0 | W16: 0 | X16: 0 | Y16: 0 | Z16: 0 | AA16: 2 | AB16: 4 | AC16: 1 | AD16: 0 | AE16: 0 | AF16: 0 | AG16: 2 | AH16: 0 | AI16: 2 | AJ16: 1 | AK16: 3 | AL16: 0 | AM16: 0 | AN16: 0 | AO16: 1 | AP16: 0 | AQ16: 0 | AR16: 0 | AS16: 0 | AT16: 0 | AU16: 0 | AV16: 0 | AW16: 0 | AX16: 0 | AY16: 0 | AZ16: 0 | BA16: 0 | BB16: 0 | BC16: 0 | BD16: 0 | BE16: 0 | BF16: 0 | BG16: 0 | BH16: 0 | BI16: 0 | BJ16: 0 | BK16: 0 | BL16: 0

Sheet NAM
A1: Value | B1: 2025/11/17 | C1: 2025/11/30 | D1: 2025/12/31 | E1: 2026/01/31 | F1: 2026/02/28 | G1: 2026/03/31 | H1: 2026/04/30 | I1: 2026/05/31 | J1: 2026/06/30 | K1: 2026/07/31 | L1: 2026/08/31 | M1: 2026/09/30 | N1: 2026/10/31 | O1: 2026/11/30 | P1: 2026/12/31 | Q1: 2027/01/31 | R1: 2027/02/28 | S1: 2027/03/31 | T1: 2027/04/30 | U1: 2027/05/31 | V1: 2027/06/30 | W1: 2027/07/31 | X1: 2027/08/31 | Y1: 2027/09/30 | Z1: 2027/10/31 | AA1: 2027/11/30 | AB1: 2027/12/31 | AC1: 2028/01/31 | AD1: 2028/02/29 | AE1: 2028/03/31 | AF1: 2028/04/30 | AG1: 2028/05/31 | AH1: 2028/06/30 | AI1: 2028/07/31 | AJ1: 2028/08/31 | AK1: 2028/09/30 | AL1: 2028/10/31 | AM1: 2028/11/30 | AN1: 2028/12/31 | AO1: 2029/01/31 | AP1: 2029/02/28 | AQ1: 2029/03/31 | AR1: 2029/04/30 | AS1: 2029/05/31 | AT1: 2029/06/30 | AU1: 2029/07/31 | AV1: 2029/08/31 | AW1: 2029/09/30 | AX1: 2029/10/31 | AY1: 2029/11/30 | AZ1: 2029/12/31 | BA1: 2030/01/31 | BB1: 2030/02/28 | BC1: 2030/03/31 | BD1: 2030/04/30 | BE1: 2030/05/31 | BF1: 2030/06/30 | BG1: 2030/07/31 | BH1: 2030/08/31 | BI1: 2030/09/30 | BJ1: 2030/10/31 | BK1: 2030/11/30 | BL1: 2030/12/31
A2: fml_count | B2: 1048 | C2: 977 | D2: 962 | E2: 955 | F2: 919 | G2: 898 | H2: 846 | I2: 830 | J2: 812 | K2: 789 | L2: 776 | M2: 760 | N2: 750 | O2: 735 | P2: 730 | Q2: 715 | R2: 693 | S2: 683 | T2: 670 | U2: 657 | V2: 648 | W2: 612 | X2: 595 | Y2: 580 | Z2: 566 | AA2: 528 | AB2: 507 | AC2: 500 | AD2: 476 | AE2: 455 | AF2: 436 | AG2: 420 | AH2: 407 | AI2: 391 | AJ2: 373 | AK2: 350 | AL2: 318 | AM2: 302 | AN2: 285 | AO2: 273 | AP2: 250 | AQ2: 245 | AR2: 231 | AS2: 219 | AT2: 197 | AU2: 186 | AV2: 170 | AW2: 155 | AX2: 142 | AY2: 127 | AZ2: 108 | BA2: 105 | BB2: 99 | BC2: 85 | BD2: 76 | BE2: 63 | BF2: 46 | BG2: 37 | BH2: 26 | BI2: 12 | BJ2: 5 | BK2: 2 | BL2: 0
A3: olmm_count | B3: 280 | C3: 276 | D3: 274 | E3: 274 | F3: 269 | G3: 265 | H3: 260 | I3: 256 | J3: 247 | K3: 244 | L3: 237 | M3: 229 | N3: 228 | O3: 227 | P3: 223 | Q3: 220 | R3: 217 | S3: 214 | T3: 209 | U3: 195 | V3: 194 | W3: 187 | X3: 183 | Y3: 178 | Z3: 172 | AA3: 168 | AB3: 165 | AC3: 162 | AD3: 157 | AE3: 148 | AF3: 142 | AG3: 140 | AH3: 135 | AI3: 126 | AJ3: 122 | AK3: 118 | AL3: 114 | AM3: 111 | AN3: 108 | AO3: 103 | AP3: 96 | AQ3: 90 | AR3: 83 | AS3: 80 | AT3: 70 | AU3: 54 | AV3: 52 | AW3: 44 | AX3: 41 | AY3: 32 | AZ3: 24 | BA3: 20 | BB3: 18 | BC3: 15 | BD3: 14 | BE3: 13 | BF3: 10 | BG3: 10 | BH3: 7 | BI3: 6 | BJ3: 0 | BK3: 0 | BL3: 0
A4: pl_count | B4: 0 | C4: 0 | D4: 0 | E4: 0 | F4: 0 | G4: 0 | H4: 0 | I4: 0 | J4: 0 | K4: 0 | L4: 0 | M4: 0 | N4: 0 | O4: 0 | P4: 0 | Q4: 0 | R4: 0 | S4: 0 | T4: 0 | U4: 0 | V4: 0 | W4: 0 | X4: 0 | Y4: 0 | Z4: 0 | AA4: 0 | AB4: 0 | AC4: 0 | AD4: 0 | AE4: 0 | AF4: 0 | AG4: 0 | AH4: 0 | AI4: 0 | AJ4: 0 | AK4: 0 | AL4: 0 | AM4: 0 | AN4: 0 | AO4: 0 | AP4: 0 | AQ4: 0 | AR4: 0 | AS4: 0 | AT4: 0 | AU4: 0 | AV4: 0 | AW4: 0 | AX4: 0 | AY4: 0 | AZ4: 0 | BA4: 0 | BB4: 0 | BC4: 0 | BD4: 0 | BE4: 0 | BF4: 0 | BG4: 0 | BH4: 0 | BI4: 0 | BJ4: 0 | BK4: 0 | BL4: 0
A5: revenue_p_m | B5: 16784081 | C5: 16138262 | D5: 15959344 | E5: 15891805 | F5: 15534345 | G5: 15304676 | H5: 14625995 | I5: 14451584 | J5: 14115394 | K5: 13894805 | L5: 13697938 | M5: 13474250 | N5: 13305326 | O5: 13108676 | P5: 12995256 | Q5: 12821364 | R5: 12565575 | S5: 12400063 | T5: 12160668 | U5: 11852564 | V5: 11702989 | W5: 11086356 | X5: 10849631 | Y5: 10609082 | Z5: 10103275 | AA5: 9564674.8 | AB5: 9255341.5 | AC5: 9115049.4 | AD5: 8772588.3 | AE5: 8350960.6 | AF5: 8005491.5 | AG5: 7738594.5 | AH5: 7516281.5 | AI5: 7194861.7 | AJ5: 6882810.9 | AK5: 6451065.9 | AL5: 6092233.8 | AM5: 5756109 | AN5: 5495895.8 | AO5: 5301101.3 | AP5: 4953582.8 | AQ5: 4772589 | AR5: 4489185.3 | AS5: 4252767.3 | AT5: 3856961.8 | AU5: 3457534.5 | AV5: 3229013.4 | AW5: 2715517.7 | AX5: 2477485.2 | AY5: 2047979.4 | AZ5: 1575128.1 | BA5: 1495327 | BB5: 1402119.8 | BC5: 1226858.9 | BD5: 1119099 | BE5: 967212.03 | BF5: 751260.22 | BG5: 645843.75 | BH5: 444306.95 | BI5: 228846.23 | BJ5: 64063.45 | BK5: 29382.51 | BL5: 0
A6: depreciation_p_m | B6: 8646793 | C6: 8398159.5 | D6: 8321944.2 | E6: 8286449.5 | F6: 8133276.1 | G6: 8025638.3 | H6: 7729096.9 | I6: 7641447 | J6: 7442071.6 | K6: 7341325.2 | L6: 7231019.3 | M6: 7125854.6 | N6: 7033508.8 | O6: 6937063.3 | P6: 6875814.1 | Q6: 6788043.1 | R6: 6656590.8 | S6: 6563402.8 | T6: 6431102.8 | U6: 6259174.6 | V6: 6175405.1 | W6: 5846465.8 | X6: 5720868.9 | Y6: 5589594.1 | Z6: 5257118.5 | AA6: 4989171.7 | AB6: 4839976.2 | AC6: 4757919.9 | AD6: 4574358.4 | AE6: 4334947.2 | AF6: 4161881.4 | AG6: 4028263.4 | AH6: 3911749.8 | AI6: 3722214.4 | AJ6: 3562650.9 | AK6: 3351163.1 | AL6: 3171334.9 | AM6: 3015922.3 | AN6: 2885272.8 | AO6: 2782355.2 | AP6: 2599194.2 | AQ6: 2492351.6 | AR6: 2340599.5 | AS6: 2225813.2 | AT6: 2024874.7 | AU6: 1776199.2 | AV6: 1659365.5 | AW6: 1360726.6 | AX6: 1233373.9 | AY6: 1012962.6 | AZ6: 766920.12 | BA6: 725364.12 | BB6: 677925.92 | BC6: 594679.63 | BD6: 546545.16 | BE6: 477005.91 | BF6: 370702.97 | BG6: 323854.68 | BH6: 220348.14 | BI6: 119595.64 | BJ6: 29864.14 | BK6: 13895.77 | BL6: 0
A7: interest_p_m | B7: 3843722.6 | C7: 3706643.4 | D7: 3671907.6 | E7: 3659231.2 | F7: 3577655.1 | G7: 3531161.4 | H7: 3396357.9 | I7: 3361466.7 | J7: 3296550.7 | K7: 3247824.7 | L7: 3205037.6 | M7: 3154756 | N7: 3120901.9 | O7: 3080224.4 | P7: 3054561.2 | Q7: 3013080.3 | R7: 2949921.4 | S7: 2914379.8 | T7: 2859808 | U7: 2800452 | V7: 2770330.6 | W7: 2627901.7 | X7: 2576876 | Y7: 2524043.6 | Z7: 2430183.6 | AA7: 2302187.1 | AB7: 2227883.2 | AC7: 2198803.4 | AD7: 2117049.2 | AE7: 2027321.4 | AF7: 1950092.3 | AG7: 1889959 | AH7: 1840694.1 | AI7: 1770181.8 | AJ7: 1691974.5 | AK7: 1590796.2 | AL7: 1507665.5 | AM7: 1413607.4 | AN7: 1347501.8 | AO7: 1299215.2 | AP7: 1211528.4 | AQ7: 1169788.2 | AR7: 1095561.9 | AS7: 1035752.9 | AT7: 939833.26 | AU7: 857348.41 | AV7: 801185.67 | AW7: 685773.37 | AX7: 628275.12 | AY7: 525047.26 | AZ7: 411738.01 | BA7: 390917.4 | BB7: 367741.03 | BC7: 326217.01 | BD7: 297800.69 | BE7: 256779.05 | BF7: 198824.72 | BG7: 168041.72 | BH7: 115375.98 | BI7: 59743.92 | BJ7: 20199.82 | BK7: 9097.94 | BL7: 0
A8: admin_p_m | B8: 1435123.1 | C8: 1363023.1 | D8: 1341653.3 | E8: 1334092 | F8: 1299709.9 | G8: 1272455.1 | H8: 1209399.1 | I8: 1190292.9 | J8: 1162105.9 | K8: 1145777.8 | L8: 1127471.2 | M8: 1107170.3 | N8: 1093454.2 | O8: 1078156.8 | P8: 1068647.7 | Q8: 1055323.5 | R8: 1033040.5 | S8: 1020242.3 | T8: 999448.13 | U8: 974973.61 | V8: 964394.18 | W8: 919186.18 | X8: 900105.97 | Y8: 879834.25 | Z8: 838314.38 | AA8: 794925.11 | AB8: 773843.41 | AC8: 763206.3 | AD8: 735151.7 | AE8: 700120.73 | AF8: 670813.24 | AG8: 649060.26 | AH8: 629751.62 | AI8: 600650.53 | AJ8: 572438.74 | AK8: 538565.51 | AL8: 511308.45 | AM8: 485644.22 | AN8: 463769.65 | AO8: 445507.37 | AP8: 417419.13 | AQ8: 397413.34 | AR8: 371578.81 | AS8: 352520.66 | AT8: 323593.05 | AU8: 285584.83 | AV8: 268067.92 | AW8: 217277.87 | AX8: 198185.67 | AY8: 163986.31 | AZ8: 126249.19 | BA8: 118913.4 | BB8: 110859.53 | BC8: 95212.35 | BD8: 86956.58 | BE8: 77261.75 | BF8: 60742.23 | BG8: 52916.66 | BH8: 34347.4 | BI8: 16002.87 | BJ8: 2059.15 | BK8: 820 | BL8: 0
A9: maint_prov_p_m | B9: 48659668 | C9: 41519621 | D9: 40373624 | E9: 39815837 | F9: 37636830 | G9: 35775662 | H9: 31650266 | I9: 30632914 | J9: 29260433 | K9: 27951984 | L9: 27360773 | M9: 26388841 | N9: 25738201 | O9: 25005884 | P9: 24711585 | Q9: 24026878 | R9: 23052560 | S9: 22602989 | T9: 21885922 | U9: 20946076 | V9: 20557283 | W9: 19268529 | X9: 18615259 | Y9: 18103610 | Z9: 17482872 | AA9: 15657131 | AB9: 14679701 | AC9: 14423255 | AD9: 13563432 | AE9: 12866093 | AF9: 12183737 | AG9: 11622156 | AH9: 11270250 | AI9: 11042902 | AJ9: 10405811 | AK9: 9096606.9 | AL9: 8436536.6 | AM9: 7401444.6 | AN9: 6773678.7 | AO9: 6371357.3 | AP9: 5687320.4 | AQ9: 5524893.1 | AR9: 5133332.3 | AS9: 4673951.9 | AT9: 4405323.5 | AU9: 4228683.4 | AV9: 3795167.4 | AW9: 3366851.4 | AX9: 3127456 | AY9: 2355188.4 | AZ9: 1581944 | BA9: 1462025.4 | BB9: 1307266.6 | BC9: 1028186.5 | BD9: 868040.56 | BE9: 662787.18 | BF9: 451547.57 | BG9: 339384.73 | BH9: 251445.53 | BI9: 178554.25 | BJ9: 128021.74 | BK9: 63417.72 | BL9: 0
A10: maintenance_fund | B10: 27252230 | C10: 25187531 | D10: 24503853 | E10: 24122414 | F10: 23118387 | G10: 21963381 | H10: 19820159 | I10: 19173252 | J10: 18402414 | K10: 17690819 | L10: 17391039 | M10: 16896365 | N10: 16529356 | O10: 16322131 | P10: 16136081 | Q10: 15653576 | R10: 15191475 | S10: 14936512 | T10: 14462312 | U10: 13973874 | V10: 13712059 | W10: 13045661 | X10: 12717869 | Y10: 12355520 | Z10: 11931840 | AA10: 11535225 | AB10: 10888496 | AC10: 10703734 | AD10: 10108770 | AE10: 9609019.8 | AF10: 9061697.9 | AG10: 8548455.7 | AH10: 8233029.1 | AI10: 8036604.1 | AJ10: 7513636.7 | AK10: 6888336.7 | AL10: 6406115.2 | AM10: 6197090.7 | AN10: 5694574 | AO10: 5408727.5 | AP10: 4899653.9 | AQ10: 4741988.4 | AR10: 4446634.9 | AS10: 4078063.2 | AT10: 3818682.1 | AU10: 3652731.5 | AV10: 3240944 | AW10: 2859535.7 | AX10: 2688986.1 | AY10: 2077951.6 | AZ10: 1380139.3 | BA10: 1304980.7 | BB10: 1182062.1 | BC10: 917494.28 | BD10: 790256.65 | BE10: 587737.93 | BF10: 381749.93 | BG10: 279719.27 | BH10: 192188.07 | BI10: 119296.79 | BJ10: 85094.72 | BK10: 63209.03 | BL10: 0
A11: other_fee_p_m | B11: 755827.59 | C11: 722254.03 | D11: 714186.95 | E11: 711701.95 | F11: 692762.93 | G11: 682902.93 | H11: 647872.93 | I11: 638142.93 | J11: 627285.93 | K11: 615042.63 | L11: 607776.72 | M11: 594131.72 | N11: 590323.67 | O11: 574413.14 | P11: 570720.78 | Q11: 562575.78 | R11: 549934.81 | S11: 539824.81 | T11: 530079.81 | U11: 508990.81 | V11: 504840.81 | W11: 472273.25 | X11: 460839.25 | Y11: 450244.82 | Z11: 435434.82 | AA11: 411514.82 | AB11: 398739.82 | AC11: 394140.82 | AD11: 379723.82 | AE11: 367508.82 | AF11: 354288.82 | AG11: 344789.82 | AH11: 336849.82 | AI11: 325983.77 | AJ11: 314414.77 | AK11: 290014.77 | AL11: 270924.75 | AM11: 254419.87 | AN11: 238751.28 | AO11: 229284.64 | AP11: 214554.64 | AQ11: 207857.64 | AR11: 198897.06 | AS11: 186427.06 | AT11: 153402.79 | AU11: 141023.79 | AV11: 130002.79 | AW11: 115065.79 | AX11: 107710.79 | AY11: 89345.45 | AZ11: 71065.45 | BA11: 68431.41 | BB11: 65176.41 | BC11: 57046.41 | BD11: 50551.41 | BE11: 43176.41 | BF11: 32106.41 | BG11: 27111.41 | BH11: 19551.41 | BI11: 8720.41 | BJ11: 2890 | BK11: 1150 | BL11: 0
A12: total_cost | B12: 6.6768169e+08 | C12: 6.4012164e+08 | D12: 6.3262952e+08 | E12: 6.2963509e+08 | F12: 6.1412265e+08 | G12: 6.0530999e+08 | H12: 5.7966182e+08 | I12: 5.7219625e+08 | J12: 5.5972911e+08 | K12: 5.5109274e+08 | L12: 5.4331154e+08 | M12: 5.3449302e+08 | N12: 5.2843116e+08 | O12: 5.209674e+08 | P12: 5.1663532e+08 | Q12: 5.1004393e+08 | R12: 4.9986934e+08 | S12: 4.9343695e+08 | T12: 4.8412473e+08 | U12: 4.7406845e+08 | V12: 4.6914745e+08 | W12: 4.4742552e+08 | X12: 4.3871999e+08 | Y12: 4.3018162e+08 | Z12: 4.1347492e+08 | AA12: 3.9288725e+08 | AB12: 3.8047883e+08 | AC12: 3.7548173e+08 | AD12: 3.6239872e+08 | AE12: 3.4726431e+08 | AF12: 3.3475019e+08 | AG12: 3.2488961e+08 | AH12: 3.1658614e+08 | AI12: 3.0453013e+08 | AJ12: 2.9159171e+08 | AK12: 2.7456998e+08 | AL12: 2.6069371e+08 | AM12: 2.4608559e+08 | AN12: 2.3457678e+08 | AO12: 2.2609534e+08 | AP12: 2.1105077e+08 | AQ12: 2.0350988e+08 | AR12: 1.9123533e+08 | AS12: 1.8107807e+08 | AT12: 1.6504732e+08 | AU12: 1.4965351e+08 | AV12: 1.3963246e+08 | AW12: 1.1856352e+08 | AX12: 1.0839391e+08 | AY12: 90046443 | AZ12: 69996663 | BA12: 66291907 | BB12: 62245764 | BC12: 55126555 | BD12: 50482528 | BE12: 43525663 | BF12: 33429408 | BG12: 28530435 | BH12: 19627678 | BI12: 10611807 | BJ12: 3311162.7 | BK12: 1472952.8 | BL12: 0
A13: nbv | B13: 4.692547e+08 | C13: 4.5874388e+08 | D13: 4.477611e+08 | E13: 4.3872441e+08 | F13: 4.2415461e+08 | G13: 4.133506e+08 | H13: 3.9465863e+08 | I13: 3.8436798e+08 | J13: 3.7351681e+08 | K13: 3.6264719e+08 | L13: 3.5286276e+08 | M13: 3.4249312e+08 | N13: 3.3345472e+08 | O13: 3.2402109e+08 | P13: 3.1553165e+08 | Q13: 3.0589716e+08 | R13: 2.9515069e+08 | S13: 2.8664321e+08 | T13: 2.7693808e+08 | U13: 2.6792361e+08 | V13: 2.6000165e+08 | W13: 2.4403903e+08 | X13: 2.3538242e+08 | Y13: 2.2667207e+08 | Z13: 2.1748434e+08 | AA13: 2.0497286e+08 | AB13: 1.9500765e+08 | AC13: 1.8866334e+08 | AD13: 1.7934909e+08 | AE13: 1.7052704e+08 | AF13: 1.6154564e+08 | AG13: 1.5368818e+08 | AH13: 1.4668512e+08 | AI13: 1.3885397e+08 | AJ13: 1.3059437e+08 | AK13: 1.2093618e+08 | AL13: 1.124964e+08 | AM13: 1.0343382e+08 | AN13: 96394298 | AO13: 91027794 | AP13: 83409610 | AQ13: 78869689 | AR13: 72467931 | AS13: 66660832 | AT13: 59060393 | AU13: 54345354 | AV13: 49467808 | AW13: 44228608 | AX13: 39620128 | AY13: 33694218 | AZ13: 27648753 | BA13: 25817594 | BB13: 23889005 | BC13: 21063297 | BD13: 18823081 | BE13: 15697038 | BF13: 11854276 | BG13: 9536970.1 | BH13: 6499795.3 | BI13: 3221725.4 | BJ13: 1194585.6 | BK13: 464390.02 | BL13: 0
... A16: olmm_fleet_drop | B16: 0 | C16: 4 | D16: 2 | E16: 0 | F16: 5 | G16: 4 | H16: 5 | I16: 4 | J16: 9 | K16: 3 | L16: 7 | M16: 8 | N16: 1 | O16: 1 | P16: 4 | Q16: 3 | R16: 3 | S16: 3 | T16: 5 | U16: 14 | V16: 1 | W16: 7 | X16: 4 | Y16: 5 | Z16: 6 | AA16: 4 | AB16: 3 | AC16: 3 | AD16: 5 | AE16: 9 | AF16: 6 | AG16: 2 | AH16: 5 | AI16: 9 | AJ16: 4 | AK16: 4 | AL16: 4 | AM16: 3 | AN16: 3 | AO16: 5 | AP16: 7 | AQ16: 6 | AR16: 7 | AS16: 3 | AT16: 10 | AU16: 16 | AV16: 2 | AW16: 8 | AX16: 3 | AY16: 9 | AZ16: 8 | BA16: 4 | BB16: 2 | BC16: 3 | BD16: 1 | BE16: 1 | BF16: 3 | BG16: 0 | BH16: 3 | BI16: 1 | BJ16: 6 | BK16: 0 | BL16: 0

Sheet Inland
A1: Value | B1: 2025/11/17 | C1: 2025/11/30 | D1: 2025/12/31 | E1: 2026/01/31 | F1: 2026/02/28 | G1: 2026/03/31 | H1: 2026/04/30 | I1: 2026/05/31 | J1: 2026/06/30 | K1: 2026/07/31 | L1: 2026/08/31 | M1: 2026/09/30 | N1: 2026/10/31 | O1: 2026/11/30 | P1: 2026/12/31 | Q1: 2027/01/31 | R1: 2027/02/28 | S1: 2027/03/31 | T1: 2027/04/30 | U1: 2027/05/31 | V1: 2027/06/30 | W1: 2027/07/31 | X1: 2027/08/31 | Y1: 2027/09/30 | Z1: 2027/10/31 | AA1: 2027/11/30 | AB1: 2027/12/31 | AC1: 2028/01/31 | AD1: 2028/02/29 | AE1: 2028/03/31 | AF1: 2028/04/30 | AG1: 2028/05/31 | AH1: 2028/06/30 | AI1: 2028/07/31 | AJ1: 2028/08/31 | AK1: 2028/09/30 | AL1: 2028/10/31 | AM1: 2028/11/30 | AN1: 2028/12/31 | AO1: 2029/01/31 | AP1: 2029/02/28 | AQ1: 2029/03/31 | AR1: 2029/04/30 | AS1: 2029/05/31 | AT1: 2029/06/30 | AU1: 2029/07/31 | AV1: 2029/08/31 | AW1: 2029/09/30 | AX1: 2029/10/31 | AY1: 2029/11/30 | AZ1: 2029/12/31 | BA1: 2030/01/31 | BB1: 2030/02/28 | BC1: 2030/03/31 | BD1: 2030/04/30 | BE1: 2030/05/31 | BF1: 2030/06/30 | BG1: 2030/07/31 | BH1: 2030/08/31 | BI1: 2030/09/30 | BJ1: 2030/10/31 | BK1: 2030/11/30 | BL1: 2030/12/31
A2: fml_count | B2: 7653 | C2: 6789 | D2: 6603 | E2: 6395 | F2: 6202 | G2: 6008 | H2: 5858 | I2: 5667 | J2: 5374 | K2: 5163 | L2: 4994 | M2: 4717 | N2: 4530 | O2: 4327 | P2: 4221 | Q2: 4078 | R2: 3918 | S2: 3734 | T2: 3582 | U2: 3407 | V2: 3128 | W2: 2958 | X2: 2785 | Y2: 2582 | Z2: 2423 | AA2: 2297 | AB2: 2181 | AC2: 2105 | AD2: 2018 | AE2: 1903 | AF2: 1809 | AG2: 1708 | AH2: 1567 | AI2: 1480 | AJ2: 1373 | AK2: 1257 | AL2: 1110 | AM2: 1033 | AN2: 966 | AO2: 929 | AP2: 896 | AQ2: 846 | AR2: 787 | AS2: 731 | AT2: 679 | AU2: 560 | AV2: 442 | AW2: 386 | AX2: 345 | AY2: 303 | AZ2: 279 | BA2: 261 | BB2: 242 | BC2: 220 | BD2: 195 | BE2: 172 | BF2: 142 | BG2: 97 | BH2: 55 | BI2: 28 | BJ2: 9 | BK2: 9 | BL2: 9
A3: olmm_count | B3: 1748 | C3: 1700 | D3: 1683 | E3: 1680 | F3: 1668 | G3: 1642 | H3: 1606 | I3: 1593 | J3: 1581 | K3: 1545 | L3: 1508 | M3: 1464 | N3: 1417 | O3: 1388 | P3: 1368 | Q3: 1361 | R3: 1338 | S3: 1310 | T3: 1221 | U3: 1208 | V3: 1183 | W3: 1168 | X3: 1148 | Y3: 1130 | Z3: 1110 | AA3: 1087 | AB3: 1081 | AC3: 1044 | AD3: 1008 | AE3: 975 | AF3: 948 | AG3: 892 | AH3: 796 | AI3: 720 | AJ3: 539 | AK3: 472 | AL3: 340 | AM3: 334 | AN3: 324 | AO3: 323 | AP3: 319 | AQ3: 305 | AR3: 276 | AS3: 263 | AT3: 254 | AU3: 215 | AV3: 188 | AW3: 186 | AX3: 164 | AY3: 161 | AZ3: 146 | BA3: 142 | BB3: 129 | BC3: 124 | BD3: 121 | BE3: 51 | BF3: 18 | BG3: 18 | BH3: 17 | BI3: 16 | BJ3: 15 | BK3: 15 | BL3: 15
A4: pl_count | B4: 1 | C4: 1 | D4: 1 | E4: 1 | F4: 1 | G4: 1 | H4: 1 | I4: 1 | J4: 0 | K4: 0 | L4: 0 | M4: 0 | N4: 0 | O4: 0 | P4: 0 | Q4: 0 | R4: 0 | S4: 0 | T4: 0 | U4: 0 | V4: 0 | W4: 0 | X4: 0 | Y4: 0 | Z4: 0 | AA4: 0 | AB4: 0 | AC4: 0 | AD4: 0 | AE4: 0 | AF4: 0 | AG4: 0 | AH4: 0 | AI4: 0 | AJ4: 0 | AK4: 0 | AL4: 0 | AM4: 0 | AN4: 0 | AO4: 0 | AP4: 0 | AQ4: 0 | AR4: 0 | AS4: 0 | AT4: 0 | AU4: 0 | AV4: 0 | AW4: 0 | AX4: 0 | AY4: 0 | AZ4: 0 | BA4: 0 | BB4: 0 | BC4: 0 | BD4: 0 | BE4: 0 | BF4: 0 | BG4: 0 | BH4: 0 | BI4: 0 | BJ4: 0 | BK4: 0 | BL4: 0
A5: revenue_p_m | B5: 1.0546975e+08 | C5: 96030610 | D5: 93751568 | E5: 91535497 | F5: 89801240 | G5: 87600099 | H5: 85499849 | I5: 83332882 | J5: 80493843 | K5: 77276184 | L5: 74149555 | M5: 71169028 | N5: 68546569 | O5: 66161964 | P5: 64683921 | Q5: 63200901 | R5: 61258429 | S5: 58924233 | T5: 56572635 | U5: 54332389 | V5: 51532710 | W5: 48918009 | X5: 45883269 | Y5: 43282910 | Z5: 40705334 | AA5: 38159907 | AB5: 36586402 | AC5: 35252992 | AD5: 33949391 | AE5: 31871612 | AF5: 30278288 | AG5: 28001682 | AH5: 25560464 | AI5: 23943850 | AJ5: 21861132 | AK5: 19483756 | AL5: 17036957 | AM5: 15673170 | AN5: 14778582 | AO5: 14278866 | AP5: 13818510 | AQ5: 13050777 | AR5: 11800129 | AS5: 10947060 | AT5: 10247808 | AU5: 8644514.8 | AV5: 7086092.7 | AW5: 6407616.1 | AX5: 5153832.7 | AY5: 4732951.7 | AZ5: 4427222.8 | BA5: 4144637.6 | BB5: 3802976.3 | BC5: 3529285 | BD5: 3161604.9 | BE5: 2314544.3 | BF5: 1599817.6 | BG5: 1197027.5 | BH5: 740215.36 | BI5: 444767.21 | BJ5: 262341.68 | BK5: 262341.68 | BL5: 262341.68
A6: depreciation_p_m | B6: 51416043 | C6: 47272500 | D6: 46174117 | E6: 45252773 | F6: 44448468 | G6: 43446137 | H6: 42358400 | I6: 41373622 | J6: 40052216 | K6: 38460888 | L6: 36720871 | M6: 35325764 | N6: 33975082 | O6: 32869223 | P6: 32133861 | Q6: 31469592 | R6: 30495300 | S6: 29358081 | T6: 28094302 | U6: 27025086 | V6: 25783508 | W6: 24462011 | X6: 22921539 | Y6: 21684518 | Z6: 20349531 | AA6: 19169408 | AB6: 18369408 | AC6: 17732091 | AD6: 17070679 | AE6: 16160857 | AF6: 15268878 | AG6: 13967025 | AH6: 12758322 | AI6: 11958296 | AJ6: 10852724 | AK6: 9483045 | AL6: 8247213.8 | AM6: 7620507.1 | AN6: 7210387.1 | AO6: 6991652.8 | AP6: 6774289.6 | AQ6: 6416869 | AR6: 5777766.7 | AS6: 5370095.1 | AT6: 5028236.1 | AU6: 4255140.5 | AV6: 3495705.3 | AW6: 3192887.5 | AX6: 2417560.8 | AY6: 2253190.1 | AZ6: 2103152.3 | BA6: 1986424.3 | BB6: 1807637.5 | BC6: 1671102.6 | BD6: 1492314.5 | BE6: 1048814.2 | BF6: 657096.55 | BG6: 494452.8 | BH6: 301430.24 | BI6: 188631.97 | BJ6: 107894.37 | BK6: 107894.37 | BL6: 107894.37
A7: interest_p_m | B7: 24544371 | C7: 22944289 | D7: 22518100 | E7: 22155634 | F7: 21790992 | G7: 21350713 | H7: 20864911 | I7: 20383362 | J7: 19720164 | K7: 19053635 | L7: 18363598 | M7: 17664539 | N7: 17057414 | O7: 16526052 | P7: 16181353 | Q7: 15826027 | R7: 15363706 | S7: 14800133 | T7: 14304806 | U7: 13772127 | V7: 13150560 | W7: 12564408 | X7: 11823408 | Y7: 11215359 | Z7: 10640728 | AA7: 9979408.8 | AB7: 9586974.3 | AC7: 9207661.3 | AD7: 8878443.2 | AE7: 8376814.9 | AF7: 7974441.8 | AG7: 7408414.6 | AH7: 6807522.8 | AI7: 6371719.8 | AJ7: 5866427.9 | AK7: 5299078 | AL7: 4714671.2 | AM7: 4353675.6 | AN7: 4092757.4 | AO7: 3953054.8 | AP7: 3825029.7 | AQ7: 3606022.8 | AR7: 3255200 | AS7: 3004120.1 | AT7: 2804988.4 | AU7: 2339552.5 | AV7: 1922147.6 | AW7: 1749383.9 | AX7: 1457932.7 | AY7: 1322130.2 | AZ7: 1238006.9 | BA7: 1155884.2 | BB7: 1064189.9 | BC7: 987210.35 | BD7: 883498.8 | BE7: 680535.88 | BF7: 493525.07 | BG7: 369729.93 | BH7: 231803.2 | BI7: 141503.82 | BJ7: 84127.02 | BK7: 84127.02 | BL7: 84127.02
A8: admin_p_m | B8: 6084594.9 | C8: 5528055.6 | D8: 5407186.7 | E8: 5284117.6 | F8: 5170706.3 | G8: 5024557.6 | H8: 4903747.1 | I8: 4771300 | J8: 4604619.2 | K8: 4411672 | L8: 4258656.5 | M8: 4088382.4 | N8: 3936169.1 | O8: 3770079.7 | P8: 3685202.4 | Q8: 3603629.5 | R8: 3497231.4 | S8: 3370153.7 | T8: 3249499.5 | U8: 3105905.1 | V8: 2961013.3 | W8: 2819672.4 | X8: 2641671.6 | Y8: 2528300.1 | Z8: 2392326.3 | AA8: 2252219 | AB8: 2168769.3 | AC8: 2091656.8 | AD8: 2013337.7 | AE8: 1896700.9 | AF8: 1805977.3 | AG8: 1705282 | AH8: 1575169.7 | AI8: 1469343.9 | AJ8: 1355378.3 | AK8: 1235913.8 | AL8: 1112022.7 | AM8: 1031574.5 | AN8: 974417.61 | AO8: 942860.49 | AP8: 918075.85 | AQ8: 868661.63 | AR8: 789317.85 | AS8: 742179.68 | AT8: 695644.05 | AU8: 595487.78 | AV8: 494046.94 | AW8: 459848.16 | AX8: 399401.92 | AY8: 371011.89 | AZ8: 350808.35 | BA8: 331651.47 | BB8: 307844.42 | BC8: 295715.44 | BD8: 274033.11 | BE8: 164803.02 | BF8: 122469.31 | BG8: 102754.51 | BH8: 72740.07 | BI8: 51992.98 | BJ8: 41579.06 | BK8: 41579.06 | BL8: 41579.06
A9: maint_prov_p_m | B9: 4.251329e+08 | C9: 3.3715012e+08 | D9: 3.2053528e+08 | E9: 3.0216461e+08 | F9: 2.8957661e+08 | G9: 2.7460813e+08 | H9: 2.6392476e+08 | I9: 2.5083272e+08 | J9: 2.337463e+08 | K9: 2.16803e+08 | L9: 205140529 | M9: 1.8986743e+08 | N9: 1.7819096e+08 | O9: 1.6593275e+08 | P9: 1.6017946e+08 | Q9: 1.532978e+08 | R9: 1.4564699e+08 | S9: 1.3631088e+08 | T9: 1.2910947e+08 | U9: 1.1935802e+08 | V9: 1.0680921e+08 | W9: 96465410 | X9: 87647876 | Y9: 79907622 | Z9: 73418919 | AA9: 63849802 | AB9: 59838603 | AC9: 56694853 | AD9: 53891788 | AE9: 46250060 | AF9: 43397603 | AG9: 40345507 | AH9: 35745974 | AI9: 33499681 | AJ9: 30754175 | AK9: 28436244 | AL9: 25515983 | AM9: 20284196 | AN9: 18269396 | AO9: 16939304 | AP9: 15948420 | AQ9: 14708120 | AR9: 13144121 | AS9: 11655364 | AT9: 10639088 | AU9: 8127953.4 | AV9: 5889574.3 | AW9: 5118102.5 | AX9: 4427919.1 | AY9: 3556540.3 | AZ9: 3098126.8 | BA9: 2511843.7 | BB9: 2142283.6 | BC9: 1840474.3 | BD9: 1521359.6 | BE9: 1253870.5 | BF9: 926277.96 | BG9: 599015.83 | BH9: 333886.3 | BI9: 173187.17 | BJ9: 79091.21 | BK9: 79091.21 | BL9: 79091.21
A10: maintenance_fund | B10: 2.5828006e+08 | C10: 2.200253e+08 | D10: 2.1229257e+08 | E10: 2.0227293e+08 | F10: 1.9593234e+08 | G10: 1.8782521e+08 | H10: 1.8245093e+08 | I10: 1.7554018e+08 | J10: 1.6634845e+08 | K10: 1.5813004e+08 | L10: 1.5185363e+08 | M10: 1.4271709e+08 | N10: 1.3512129e+08 | O10: 1.2746195e+08 | P10: 1.2395867e+08 | Q10: 1.1975031e+08 | R10: 1.1467425e+08 | S10: 1.0842791e+08 | T10: 1.0339462e+08 | U10: 96890008 | V10: 87286914 | W10: 79530663 | X10: 73414875 | Y10: 67768228 | Z10: 63182177 | AA10: 55545775 | AB10: 52386763 | AC10: 49696185 | AD10: 47209135 | AE10: 41029164 | AF10: 38555489 | AG10: 35815181 | AH10: 32085236 | AI10: 30137880 | AJ10: 27762221 | AK10: 25640242 | AL10: 23092805 | AM10: 18495345 | AN10: 16948983 | AO10: 15745483 | AP10: 14999656 | AQ10: 13810665 | AR10: 12465664 | AS10: 11162806 | AT10: 10198030 | AU10: 7812310.2 | AV10: 5648044 | AW10: 4920399.1 | AX10: 4249472.5 | AY10: 3432495.7 | AZ10: 2992415.8 | BA10: 2439116.6 | BB10: 2080355.9 | BC10: 1785226.1 | BD10: 1505222.6 | BE10: 1238672.5 | BF10: 916415.48 | BG10: 594014.05 | BH10: 330796.94 | BI10: 171350.38 | BJ10: 79091.21 | BK10: 79091.21 | BL10: 79091.21
A11: other_fee_p_m | B11: 4678316.7 | C11: 4163712.3 | D11: 4049175.2 | E11: 3862055.4 | F11: 3778365 | G11: 3682987.7 | H11: 3605085.1 | I11: 3506015.7 | J11: 3366401.2 | K11: 3238232.8 | L11: 3148228.8 | M11: 2951819.7 | N11: 2845542.7 | O11: 2724916 | P11: 2668468.2 | Q11: 2579988.5 | R11: 2485916.6 | S11: 2387018 | T11: 2270189.7 | U11: 2185644.9 | V11: 2058629.6 | W11: 1977203.9 | X11: 1865513.2 | Y11: 1702362.3 | Z11: 1601259.2 | AA11: 1533038.1 | AB11: 1459329.3 | AC11: 1412398.7 | AD11: 1362696.3 | AE11: 1303835.3 | AF11: 1260454.2 | AG11: 1200170.3 | AH11: 1108211.9 | AI11: 1048081.2 | AJ11: 959400.44 | AK11: 883386.02 | AL11: 736769.97 | AM11: 690637.12 | AN11: 649167.25 | AO11: 633556.71 | AP11: 616548.01 | AQ11: 585485.7 | AR11: 552851.88 | AS11: 522041.88 | AT11: 493176.79 | AU11: 425901.94 | AV11: 354052.39 | AW11: 311887.06 | AX11: 271802.05 | AY11: 247729.96 | AZ11: 228350.84 | BA11: 218797.97 | BB11: 204118.3 | BC11: 191339.27 | BD11: 172735.67 | BE11: 121535.97 | BF11: 85582.97 | BG11: 57381.81 | BH11: 37440.07 | BI11: 16355.78 | BJ11: 9965.95 | BK11: 9965.95 | BL11: 9965.95
A12: total_cost | B12: 3.852902e+09 | C12: 3.5583466e+09 | D12: 3.4808016e+09 | E12: 3.4078541e+09 | F12: 3.3442961e+09 | G12: 3.2686661e+09 | H12: 3.194339e+09 | I12: 3.1182414e+09 | J12: 3.0131024e+09 | K12: 2.9050733e+09 | L12: 2.7975766e+09 | M12: 2.6894164e+09 | N12: 2.5949459e+09 | O12: 2.5066236e+09 | P12: 2.4537399e+09 | Q12: 2.4006896e+09 | R12: 2.3322479e+09 | S12: 2.2505813e+09 | T12: 2.1746703e+09 | U12: 2.0972034e+09 | V12: 2.0045947e+09 | W12: 1.9141702e+09 | X12: 1.8049306e+09 | Y12: 1.7144054e+09 | Z12: 1.6270818e+09 | AA12: 1.530053e+09 | AB12: 1.4715159e+09 | AC12: 1.4185319e+09 | AD12: 1.3700833e+09 | AE12: 1.2975495e+09 | AF12: 1.2353863e+09 | AG12: 1.1509139e+09 | AH12: 1.0613109e+09 | AI12: 9.9732549e+08 | AJ12: 9.1932475e+08 | AK12: 8.2998774e+08 | AL12: 7.3911866e+08 | AM12: 6.8444858e+08 | AN12: 6.4605465e+08 | AO12: 6.2551417e+08 | AP12: 6.0582475e+08 | AQ12: 5.7340225e+08 | AR12: 5.2072426e+08 | AS12: 4.8242235e+08 | AT12: 4.5243395e+08 | AU12: 3.814386e+08 | AV12: 3.1103053e+08 | AW12: 2.8413258e+08 | AX12: 2.3370369e+08 | AY12: 2.1285688e+08 | AZ12: 1.9936075e+08 | BA12: 1.8729151e+08 | BB12: 1.720445e+08 | BC12: 1.5954566e+08 | BD12: 1.428998e+08 | BE12: 1.0640922e+08 | BF12: 74234505 | BG12: 55163862 | BH12: 34558424 | BI12: 21536009 | BJ12: 13014846 | BK12: 13014846 | BL12: 13014846
A13: nbv | B13: 2.6971545e+09 | C13: 2.5820195e+09 | D13: 2.503091e+09 | E13: 2.4248647e+09 | F13: 2.3494322e+09 | G13: 2.2726806e+09 | H13: 2.1965232e+09 | I13: 2.117849e+09 | J13: 2.0255099e+09 | K13: 1.9366247e+09 | L13: 1.8560644e+09 | M13: 1.7678684e+09 | N13: 1.692366e+09 | O13: 1.6196931e+09 | P13: 1.5635083e+09 | Q13: 1.5040117e+09 | R13: 1.4398335e+09 | S13: 1.3702895e+09 | T13: 1.3098402e+09 | U13: 1.2458771e+09 | V13: 1.1740884e+09 | W13: 1.1102566e+09 | X13: 1.0355798e+09 | Y13: 9.7048398e+08 | Z13: 9.128122e+08 | AA13: 8.4344333e+08 | AB13: 7.9919162e+08 | AC13: 7.5595856e+08 | AD13: 7.1712983e+08 | AE13: 6.6693075e+08 | AF13: 6.2835155e+08 | AG13: 5.8100462e+08 | AH13: 5.30187e+08 | AI13: 4.8983126e+08 | AJ13: 4.4935931e+08 | AK13: 4.0641435e+08 | AL13: 3.6374656e+08 | AM13: 3.3469756e+08 | AN13: 3.0928234e+08 | AO13: 2.9286758e+08 | AP13: 2.7795779e+08 | AQ13: 2.5705857e+08 | AR13: 2.2984005e+08 | AS13: 2.0842515e+08 | AT13: 1.9058473e+08 | AU13: 1.5718851e+08 | AV13: 1.2853068e+08 | AW13: 1.1363848e+08 | AX13: 98367663 | AY13: 86063361 | AZ13: 79383781 | BA13: 72092205 | BB13: 65699906 | BC13: 59652379 | BD13: 52217771 | BE13: 44386373 | BF13: 35402093 | BG13: 25400511 | BH13: 15864432 | BI13: 9350698.9 | BJ13: 5546285.7 | BK13: 5438391.3 | BL13: 5330496.9
... A16: olmm_fleet_drop | B16: 0 | C16: 48 | D16: 17 | E16: 3 | F16: 12 | G16: 26 | H16: 36 | I16: 13 | J16: 12 | K16: 36 | L16: 37 | M16: 44 | N16: 47 | O16: 29 | P16: 20 | Q16: 7 | R16: 23 | S16: 28 | T16: 89 | U16: 13 | V16: 25 | W16: 15 | X16: 20 | Y16: 18 | Z16: 20 | AA16: 23 | AB16: 6 | AC16: 37 | AD16: 36 | AE16: 33 | AF16: 27 | AG16: 56 | AH16: 96 | AI16: 76 | AJ16: 181 | AK16: 67 | AL16: 132 | AM16: 6 | AN16: 10 | AO16: 1 | AP16: 4 | AQ16: 14 | AR16: 29 | AS16: 13 | AT16: 9 | AU16: 39 | AV16: 27 | AW16: 2 | AX16: 22 | AY16: 3 | AZ16: 15 | BA16: 4 | BB16: 13 | BC16: 5 | BD16: 3 | BE16: 70 | BF16: 33 | BG16: 0 | BH16: 1 | BI16: 1 | BJ16: 1 | BK16: 0 | BL16: 0

Sheet Central & Commercial
A1: Value | B1: 2025/11/17 | C1: 2025/11/30 | D1: 2025/12/31 | E1: 2026/01/31 | F1: 2026/02/28 | G1: 2026/03/31 | H1: 2026/04/30 | I1: 2026/05/31 | J1: 2026/06/30 | K1: 2026/07/31 | L1: 2026/08/31 | M1: 2026/09/30 | N1: 2026/10/31 | O1: 2026/11/30 | P1: 2026/12/31 | Q1: 2027/01/31 | R1: 2027/02/28 | S1: 2027/03/31 | T1: 2027/04/30 | U1: 2027/05/31 | V1: 2027/06/30 | W1: 2027/07/31 | X1: 2027/08/31 | Y1: 2027/09/30 | Z1: 2027/10/31 | AA1: 2027/11/30 | AB1: 2027/12/31 | AC1: 2028/01/31 | AD1: 2028/02/29 | AE1: 2028/03/31 | AF1: 2028/04/30 | AG1: 2028/05/31 | AH1: 2028/06/30 | AI1: 2028/07/31 | AJ1: 2028/08/31 | AK1: 2028/09/30 | AL1: 2028/10/31 | AM1: 2028/11/30 | AN1: 2028/12/31 | AO1: 2029/01/31 | AP1: 2029/02/28 | AQ1: 2029/03/31 | AR1: 2029/04/30 | AS1: 2029/05/31 | AT1: 2029/06/30 | AU1: 2029/07/31 | AV1: 2029/08/31 | AW1: 2029/09/30 | AX1: 2029/10/31 | AY1: 2029/11/30 | AZ1: 2029/12/31 | BA1: 2030/01/31 | BB1: 2030/02/28 | BC1: 2030/03/31 | BD1: 2030/04/30 | BE1: 2030/05/31 | BF1: 2030/06/30 | BG1: 2030/07/31 | BH1: 2030/08/31 | BI1: 2030/09/30 | BJ1: 2030/10/31 | BK1: 2030/11/30 | BL1: 2030/12/31
A2: fml_count | B2: 497 | C2: 458 | D2: 454 | E2: 444 | F2: 438 | G2: 426 | H2: 420 | I2: 409 | J2: 403 | K2: 398 | L2: 392 | M2: 382 | N2: 377 | O2: 370 | P2: 363 | Q2: 358 | R2: 356 | S2: 349 | T2: 341 | U2: 317 | V2: 305 | W2: 299 | X2: 293 | Y2: 250 | Z2: 239 | AA2: 201 | AB2: 182 | AC2: 167 | AD2: 165 | AE2: 161 | AF2: 157 | AG2: 155 | AH2: 147 | AI2: 138 | AJ2: 132 | AK2: 118 | AL2: 117 | AM2: 108 | AN2: 105 | AO2: 104 | AP2: 103 | AQ2: 99 | AR2: 86 | AS2: 74 | AT2: 71 | AU2: 61 | AV2: 58 | AW2: 54 | AX2: 50 | AY2: 49 | AZ2: 44 | BA2: 37 | BB2: 36 | BC2: 33 | BD2: 29 | BE2: 22 | BF2: 14 | BG2: 13 | BH2: 7 | BI2: 3 | BJ2: 0 | BK2: 0 | BL2: 0
A3: olmm_count | B3: 287 | C3: 286 | D3: 286 | E3: 284 | F3: 284 | G3: 284 | H3: 279 | I3: 279 | J3: 279 | K3: 274 | L3: 250 | M3: 247 | N3: 247 | O3: 236 | P3: 236 | Q3: 235 | R3: 229 | S3: 212 | T3: 212 | U3: 199 | V3: 194 | W3: 193 | X3: 185 | Y3: 179 | Z3: 172 | AA3: 164 | AB3: 159 | AC3: 156 | AD3: 153 | AE3: 134 | AF3: 131 | AG3: 119 | AH3: 118 | AI3: 117 | AJ3: 108 | AK3: 82 | AL3: 76 | AM3: 68 | AN3: 68 | AO3: 60 | AP3: 57 | AQ3: 54 | AR3: 39 | AS3: 38 | AT3: 34 | AU3: 30 | AV3: 28 | AW3: 23 | AX3: 21 | AY3: 18 | AZ3: 11 | BA3: 11 | BB3: 11 | BC3: 11 | BD3: 11 | BE3: 11 | BF3: 9 | BG3: 7 | BH3: 7 | BI3: 5 | BJ3: 4 | BK3: 3 | BL3: 3
A4: pl_count | B4: 0 | C4: 0 | D4: 0 | E4: 0 | F4: 0 | G4: 0 | H4: 0 | I4: 0 | J4: 0 | K4: 0 | L4: 0 | M4: 0 | N4: 0 | O4: 0 | P4: 0 | Q4: 0 | R4: 0 | S4: 0 | T4: 0 | U4: 0 | V4: 0 | W4: 0 | X4: 0 | Y4: 0 | Z4: 0 | AA4: 0 | AB4: 0 | AC4: 0 | AD4: 0 | AE4: 0 | AF4: 0 | AG4: 0 | AH4: 0 | AI4: 0 | AJ4: 0 | AK4: 0 | AL4: 0 | AM4: 0 | AN4: 0 | AO4: 0 | AP4: 0 | AQ4: 0 | AR4: 0 | AS4: 0 | AT4: 0 | AU4: 0 | AV4: 0 | AW4: 0 | AX4: 0 | AY4: 0 | AZ4: 0 | BA4: 0 | BB4: 0 | BC4: 0 | BD4: 0 | BE4: 0 | BF4: 0 | BG4: 0 | BH4: 0 | BI4: 0 | BJ4: 0 | BK4: 0 | BL4: 0
A5: revenue_p_m | B5: 15289625 | C5: 14825090 | D5: 14765783 | E5: 14648978 | F5: 14588663 | G5: 14431742 | H5: 14305136 | I5: 14163222 | J5: 14098749 | K5: 13711850 | L5: 13099417 | M5: 12838695 | N5: 12801561 | O5: 12312828 | P5: 12181525 | Q5: 12082399 | R5: 11945079 | S5: 11537968 | T5: 11421454 | U5: 9541718 | V5: 9144792 | W5: 9019495.4 | X5: 8606673.2 | Y5: 8081290 | Z5: 7744776.2 | AA5: 6621190.2 | AB5: 6346051.7 | AC5: 6174692.8 | AD5: 6109262.4 | AE5: 5592620.3 | AF5: 5444517.6 | AG5: 5339902.1 | AH5: 5203773.2 | AI5: 5066256.7 | AJ5: 4703925.6 | AK5: 4062938.8 | AL5: 3800750.7 | AM5: 3570119.8 | AN5: 3433020 | AO5: 3090363.7 | AP5: 3027456.3 | AQ5: 2947489 | AR5: 2371546.3 | AS5: 1694561.3 | AT5: 1606222.7 | AU5: 1382616.6 | AV5: 1314914.7 | AW5: 1201163.9 | AX5: 994316.64 | AY5: 937940.83 | AZ5: 744569.56 | BA5: 655532.03 | BB5: 649562.18 | BC5: 600339.23 | BD5: 552770.83 | BE5: 481472.88 | BF5: 367756.07 | BG5: 301488.25 | BH5: 231164.09 | BI5: 165436.22 | BJ5: 120746.32 | BK5: 93739.45 | BL5: 93739.45
A6: depreciation_p_m | B6: 8322684.1 | C6: 8109495.3 | D6: 8086478.3 | E6: 8033318.8 | F6: 8005207.8 | G6: 7933329.7 | H6: 7881435.3 | I6: 7815536.1 | J6: 7788699.4 | K6: 7511415.9 | L6: 7234691.8 | M6: 7072521.9 | N6: 7059174 | O6: 6718430.7 | P6: 6649041 | Q6: 6588875.1 | R6: 6514363.4 | S6: 6268886.3 | T6: 6222197.5 | U6: 5223907.8 | V6: 4989848.8 | W6: 4927676.1 | X6: 4675110.4 | Y6: 4394554 | Z6: 4201467.6 | AA6: 3640946.7 | AB6: 3501875.2 | AC6: 3420883.7 | AD6: 3388271.7 | AE6: 3051324.8 | AF6: 2965417.5 | AG6: 2904552.3 | AH6: 2827251.8 | AI6: 2769064.6 | AJ6: 2574442 | AK6: 2175261.9 | AL6: 2019076.8 | AM6: 1900243.5 | AN6: 1833350.7 | AO6: 1620429.8 | AP6: 1578451.9 | AQ6: 1540959.2 | AR6: 1229154.8 | AS6: 869241.56 | AT6: 815995.09 | AU6: 702353.27 | AV6: 664991.49 | AW6: 603800.35 | AX6: 475496.89 | AY6: 447251.45 | AZ6: 337930.97 | BA6: 299303.07 | BB6: 297341.97 | BC6: 278079.34 | BD6: 258775.08 | BE6: 234372.96 | BF6: 185660.85 | BG6: 152682.37 | BH6: 122480.27 | BI6: 88618.24 | BJ6: 66722.81 | BK6: 52333.93 | BL6: 52333.93
A7: interest_p_m | B7: 3915212.9 | C7: 3832874.7 | D7: 3820388.5 | E7: 3787833.5 | F7: 3770635.1 | G7: 3732194.8 | H7: 3709446.9 | I7: 3669163.8 | J7: 3655212.8 | K7: 3585934.5 | L7: 3341290.6 | M7: 3295017.2 | N7: 3284588.5 | O7: 3198011.8 | P7: 3177445.5 | Q7: 3157751.1 | R7: 3112022.3 | S7: 2992965.1 | T7: 2970298.2 | U7: 2486857.1 | V7: 2400704 | W7: 2364223.6 | X7: 2250704.2 | Y7: 2125748.8 | Z7: 2032914.3 | AA7: 1728925.9 | AB7: 1652798.2 | AC7: 1611092 | AD7: 1592357.9 | AE7: 1463580.9 | AF7: 1419252 | AG7: 1388299.1 | AH7: 1349297.8 | AI7: 1311256.6 | AJ7: 1217196.3 | AK7: 1057173.4 | AL7: 974840.24 | AM7: 909235.22 | AN7: 875850.8 | AO7: 786518.68 | AP7: 772543.53 | AQ7: 748938.87 | AR7: 616365.17 | AS7: 469872.43 | AT7: 449601.28 | AU7: 395111.5 | AV7: 379943.4 | AW7: 348605.12 | AX7: 297398.75 | AY7: 279044.9 | AZ7: 224151.32 | BA7: 200662.75 | BB7: 198794.44 | BC7: 184325.19 | BD7: 170889.6 | BE7: 147055.41 | BF7: 115225.56 | BG7: 93575.35 | BH7: 74482.81 | BI7: 55227.23 | BJ7: 40468.5 | BK7: 30810.51 | BL7: 30810.51
A8: admin_p_m | B8: 1088677.3 | C8: 1057224 | D8: 1053458.1 | E8: 1045411.3 | F8: 1043136.7 | G8: 1029536.5 | H8: 1003379.5 | I8: 993961.25 | J8: 985559.71 | K8: 965776.04 | L8: 904003.96 | M8: 886798.33 | N8: 884177.36 | O8: 844443.21 | P8: 838681.84 | Q8: 833240.27 | R8: 822403.03 | S8: 792940.97 | T8: 783548.37 | U8: 657046.65 | V8: 637527.44 | W8: 627011.14 | X8: 596341.55 | Y8: 569763.06 | Z8: 547765.99 | AA8: 465445.5 | AB8: 449289.74 | AC8: 440392.95 | AD8: 435808.76 | AE8: 398631.19 | AF8: 389789.39 | AG8: 381242.93 | AH8: 372288.24 | AI8: 362932.57 | AJ8: 335007.39 | AK8: 289886.94 | AL8: 270071.04 | AM8: 253102.07 | AN8: 242486.03 | AO8: 215556.88 | AP8: 211971.88 | AQ8: 206049.51 | AR8: 167133.02 | AS8: 119132.16 | AT8: 115311.34 | AU8: 101121.37 | AV8: 95480.74 | AW8: 87633.6 | AX8: 73919.4 | AY8: 68448.88 | AZ8: 52154.95 | BA8: 48803.66 | BB8: 48563.68 | BC8: 45396.13 | BD8: 42602.96 | BE8: 37585.53 | BF8: 31484.65 | BG8: 24858.78 | BH8: 21576.24 | BI8: 16743.04 | BJ8: 13135.01 | BK8: 10175.01 | BL8: 10175.01
A9: maint_prov_p_m | B9: 30161056 | C9: 25939837 | D9: 25612608 | E9: 25114081 | F9: 24776961 | G9: 23881881 | H9: 23557706 | I9: 23146926 | J9: 22823901 | K9: 22408205 | L9: 21917308 | M9: 21262330 | N9: 21087846 | O9: 20590274 | P9: 20165484 | Q9: 19901943 | R9: 19851332 | S9: 19700313 | T9: 19036266 | U9: 14097758 | V9: 13098034 | W9: 12794525 | X9: 12507183 | Y9: 11156595 | Z9: 10824606 | AA9: 7462852.6 | AB9: 6901414.2 | AC9: 6475702 | AD9: 6352277.3 | AE9: 6257501.8 | AF9: 6176267.8 | AG9: 6109059.6 | AH9: 5980069.8 | AI9: 5510399.9 | AJ9: 4860613.5 | AK9: 4573361.3 | AL9: 4525146.3 | AM9: 4054653.5 | AN9: 3474283 | AO9: 3355284.7 | AP9: 3296180.7 | AQ9: 3186375.9 | AR9: 2452509.9 | AS9: 1319895 | AT9: 1221325.6 | AU9: 1078150.2 | AV9: 958102.65 | AW9: 826197.34 | AX9: 707040.74 | AY9: 664848.74 | AZ9: 584139.14 | BA9: 405227.21 | BB9: 390857.21 | BC9: 309319.36 | BD9: 245670.04 | BE9: 162463.54 | BF9: 72819.34 | BG9: 53978.04 | BH9: 12055.6 | BI9: 2510.4 | BJ9: 0 | BK9: 0 | BL9: 0
A10: maintenance_fund | B10: 17978753 | C10: 16001196 | D10: 15880306 | E10: 15970168 | F10: 15887918 | G10: 15336650 | H10: 15277301 | I10: 14977577 | J10: 14838472 | K10: 14722109 | L10: 14700986 | M10: 14361726 | N10: 14264209 | O10: 14000743 | P10: 13728954 | Q10: 13642548 | R10: 13592436 | S10: 13482024 | T10: 13154463 | U10: 10133428 | V10: 9508004.1 | W10: 9379159.1 | X10: 9190111.2 | Y10: 7995457 | Z10: 7731770.8 | AA10: 5159301.2 | AB10: 4771706.2 | AC10: 4363681.1 | AD10: 4252441.7 | AE10: 4175323.7 | AF10: 4095231.7 | AG10: 4030132.1 | AH10: 3910403.4 | AI10: 3510397.3 | AJ10: 3056405.8 | AK10: 2808645 | AL10: 2782094.5 | AM10: 2384300.8 | AN10: 2258781.4 | AO10: 2189841.2 | AP10: 2141940.9 | AQ10: 2032136.2 | AR10: 1532347.6 | AS10: 1247666.9 | AT10: 1171099.6 | AU10: 1040571.4 | AV10: 936094.57 | AW10: 815784.36 | AX10: 696627.76 | AY10: 657318.21 | AZ10: 576970.97 | BA10: 398806.08 | BB10: 384867.98 | BC10: 309319.36 | BD10: 245670.04 | BE10: 162463.54 | BF10: 72819.34 | BG10: 53978.04 | BH10: 12055.6 | BI10: 2510.4 | BJ10: 0 | BK10: 0 | BL10: 0
A11: other_fee_p_m | B11: 343391.32 | C11: 315326.57 | D11: 312072.05 | E11: 305680.27 | F11: 302532 | G11: 297824.98 | H11: 282962.12 | I11: 279742.99 | J11: 278398.46 | K11: 275363.86 | L11: 262644.04 | M11: 256254.54 | N11: 254873.98 | O11: 250410.93 | P11: 245673.39 | Q11: 243255.13 | R11: 239104.73 | S11: 232770.98 | T11: 226106.58 | U11: 214777.97 | V11: 208591.67 | W11: 203690.91 | X11: 197640.87 | Y11: 181259.11 | Z11: 176262.79 | AA11: 161538.81 | AB11: 153877.5 | AC11: 148970.16 | AD11: 147174.03 | AE11: 141718.89 | AF11: 139550.2 | AG11: 135826.88 | AH11: 133263.97 | AI11: 128129.22 | AJ11: 124639.39 | AK11: 110820.53 | AL11: 108895.2 | AM11: 101942.74 | AN11: 100962.26 | AO11: 98072.25 | AP11: 97218.94 | AQ11: 94720 | AR11: 83714.03 | AS11: 78904.03 | AT11: 75299.05 | AU11: 57194.2 | AV11: 55397.54 | AW11: 50194.9 | AX11: 46336.46 | AY11: 45546.46 | AZ11: 41153.98 | BA11: 34060.71 | BB11: 33597.25 | BC11: 30802.68 | BD11: 27860.06 | BE11: 22904 | BF11: 13276.27 | BG11: 12031.27 | BH11: 5456.27 | BI11: 2337.31 | BJ11: 420 | BK11: 420 | BL11: 420
A12: total_cost | B12: 6.0553788e+08 | C12: 5.8841566e+08 | D12: 5.8665918e+08 | E12: 5.8189656e+08 | F12: 5.7955205e+08 | G12: 5.7383768e+08 | H12: 5.6897436e+08 | I12: 5.6360967e+08 | J12: 5.6120099e+08 | K12: 5.4941419e+08 | L12: 5.1521256e+08 | M12: 5.0677311e+08 | N12: 5.0538362e+08 | O12: 4.8952032e+08 | P12: 4.8636041e+08 | Q12: 4.8330056e+08 | R12: 4.7705328e+08 | S12: 4.5955161e+08 | T12: 4.558409e+08 | U12: 3.8577492e+08 | V12: 3.7127097e+08 | W12: 3.6613154e+08 | X12: 3.4924266e+08 | Y12: 3.3044541e+08 | Z12: 3.1672753e+08 | AA12: 2.7254493e+08 | AB12: 2.614488e+08 | AC12: 2.5527399e+08 | AD12: 2.5253273e+08 | AE12: 2.3187939e+08 | AF12: 2.2530881e+08 | AG12: 2.2040042e+08 | AH12: 2.146828e+08 | AI12: 2.0924081e+08 | AJ12: 1.9501576e+08 | AK12: 1.6908713e+08 | AL12: 1.5664644e+08 | AM12: 1.4640686e+08 | AN12: 1.4110883e+08 | AO12: 1.2692521e+08 | AP12: 1.2444516e+08 | AQ12: 1.2094048e+08 | AR12: 99503799 | AS12: 75513340 | AT12: 71936352 | AU12: 63344888 | AV12: 60743764 | AW12: 55502692 | AX12: 46544539 | AY12: 43829277 | AZ12: 35301511 | BA12: 31303925 | BB12: 31015948 | BC12: 28827599 | BD12: 26741210 | BE12: 23349577 | BF12: 18234531 | BG12: 14921592 | BH12: 11783798 | BI12: 8788239.6 | BJ12: 6567505.2 | BK12: 5087505.2 | BL12: 5087505.2
A13: nbv | B13: 4.3566602e+08 | C13: 4.3000464e+08 | D13: 4.207068e+08 | E13: 4.0996329e+08 | F13: 4.0053127e+08 | G13: 3.895045e+08 | H13: 3.8006846e+08 | I13: 3.6896482e+08 | J13: 3.5984182e+08 | K13: 3.5037405e+08 | L13: 3.2155743e+08 | M13: 3.1193849e+08 | N13: 3.0398724e+08 | O13: 2.940765e+08 | P13: 2.8605914e+08 | Q13: 2.780757e+08 | R13: 2.6866188e+08 | S13: 2.5558404e+08 | T13: 2.4788655e+08 | U13: 2.1168354e+08 | V13: 2.0258889e+08 | W13: 1.9507228e+08 | X13: 1.8491444e+08 | Y13: 1.7262247e+08 | Z13: 1.6294275e+08 | AA13: 1.3966266e+08 | AB13: 1.3121871e+08 | AC13: 1.250539e+08 | AD13: 1.2039056e+08 | AE13: 1.1144201e+08 | AF13: 1.0530285e+08 | AG13: 1.0085572e+08 | AH13: 95238599 | AI13: 89668736 | AJ13: 82329594 | AK13: 73485313 | AL13: 66426110 | AM13: 60890007 | AN13: 57688853 | AO13: 51849949 | AP13: 49924957 | AQ13: 46754894 | AR13: 38962292 | AS13: 32163407 | AT13: 30414151 | AU13: 26926696 | AV13: 25687488 | AW13: 23470072 | AX13: 21210133 | AY13: 19723740 | AZ13: 16446836 | BA13: 14436699 | BB13: 13967085 | BC13: 12635437 | BD13: 11414387 | BE13: 9216088 | BF13: 6753204.2 | BG13: 5541332.7 | BH13: 4058334.3 | BI13: 2952375.8 | BJ13: 1934853.5 | BK13: 1424130.1 | BL13: 1371796.1
... A16: olmm_fleet_drop | B16: 0 | C16: 1 | D16: 0 | E16: 2 | F16: 0 | G16: 0 | H16: 5 | I16: 0 | J16: 0 | K16: 5 | L16: 24 | M16: 3 | N16: 0 | O16: 11 | P16: 0 | Q16: 1 | R16: 6 | S16: 17 | T16: 0 | U16: 13 | V16: 5 | W16: 1 | X16: 8 | Y16: 6 | Z16: 7 | AA16: 8 | AB16: 5 | AC16: 3 | AD16: 3 | AE16: 19 | AF16: 3 | AG16: 12 | AH16: 1 | AI16: 1 | AJ16: 9 | AK16: 26 | AL16: 6 | AM16: 8 | AN16: 0 | AO16: 8 | AP16: 3 | AQ16: 3 | AR16: 15 | AS16: 1 | AT16: 4 | AU16: 4 | AV16: 2 | AW16: 5 | AX16: 2 | AY16: 3 | AZ16: 7 | BA16: 0 | BB16: 0 | BC16: 0 | BD16: 0 | BE16: 0 | BF16: 2 | BG16: 2 | BH16: 0 | BI16: 2 | BJ16: 1 | BK16: 1 | BL16: 0

Sheet Calculations
Q1: Column | BG1: 2 | BO1: =BG1+2 -> 4 | BW1: =BO1+1 -> 5 | CE1: =BW1+1 -> 6 | CM1: =CE1+1 -> 7
D2: Replacements | R2: Period 1 | U2: Period 2 | X2: Period 3 | AA2: Period 4 | AI2: Feb | AQ2: Mar | AY2: Apr | BG2: May | BO2: Jun | BW2: Jul | CE2: Aug | CM2: Sep
A3: Region | B3: Company Code | C3: Budget Split | D3: fleet ratio | E3: rental ratio | F3: Revenue Budget | G3: Fleet Budget | H3: Fleet Contracted | I3: Fleet New | J3: Fleet Forecast | K3: Revenue YTD | L3: Revenue Contracted | M3: Revenue New | N3: Revenue Forecast | O3: Revenue Gap | P3: Revenue Risk | Q3: Budget Contribution | R3: Fleet | S3: Revenue | T3: FX | U3: Fleet | V3: Revenue | W3: FX | X3: Fleet | Y3: Revenue | Z3: FX | AA3: Fleet | AB3: Revenue (month) | AC3: FX | AD3: Avg Revenue | AE3: Dropped Fleet | AF3: Replacement Fleet | AG3: Replacement Revenue | AH3: Replacement Revenue Full Year | AI3: Fleet | AJ3: Revenue (month) | AK3: FX | AL3: Avg Revenue | AM3: Dropped Fleet | AN3: Replacement Fleet | AO3: Replacement Revenue | AP3: Replacement Revenue Full Year | AS3: FX | AY3: Fleet | AZ3: Revenue (month) | BA3: FX | BB3: Avg Revenue | BC3: Dropped Fleet | BD3: Replacement Fleet | BE3: Replacement Revenue | BF3: Replacement Revenue Full Year | BG3: Fleet | BH3: Revenue (month) | BI3: FX | BJ3: Avg Revenue | BK3: Dropped Fleet | BL3: Replacement Fleet | BM3: Replacement Revenue | BN3: Replacement Revenue Full Year | BO3: Fleet | BP3: Revenue (month) | BQ3: FX | BR3: Avg Revenue | BS3: Dropped Fleet | BT3: Replacement Fleet | BU3: Replacement Revenue | BV3: Replacement Revenue Full Year | BW3: Fleet | BX3: Revenue (month) | BY3: FX | BZ3: Avg Revenue | CA3: Dropped Fleet | CB3: Replacement Fleet | CC3: Replacement Revenue | CD3: Replacement Revenue Full Year | CE3: Fleet | CF3: Revenue (month) | CG3: FX | CH3: Avg Revenue | CI3: Dropped Fleet | CJ3: Replacement Fleet | CK3: Replacement Revenue | CL3: Replacement Revenue Full Year | CM3: Fleet | CN3: Revenue (month) | CO3: FX | CP3: Avg Revenue | CQ3: Dropped Fleet | CR3: Replacement Fleet | CS3: Replacement Revenue | CT3: Replacement Revenue Full Year | CW3: Full Year Estimate Current | CX3: X 6 | CY3: H1 Estimate
A4: Botswana | B4: BOT | D4: -0.22 | E4: 0.23 | F4: 103018848 | G4: 595 | H4: =CM4 -> 355 | I4: =AF4+AN4+AV4+BD4+BL4+BT4+CB4+CJ4+CR4 -> 25.74 | J4: =H4+INT(I4) -> 380 | K4: -38757901 | L4: =AB4+AJ4+AR4+AZ4+BH4+BP4+BX4+CF4+CN4 -> -29232202 | M4: =AH4+AP4+AX4+BF4+BN4+BV4+CD4+CL4+CT4 -> -851250.51 | N4: =K4+L4+M4 -> -68841354 | O4: =N4+F4 -> 34177494 | P4: =-N4/F4 -> 0.66824038 | Q4: =F4/F23 -> 0.038700632 | R4: 516 | S4: 6178000 | T4: 1.3225308 | W4: 1.3250834 | Z4: 1.3413375 | AC4: 1.3486482 | AK4: =AC4 -> 1.3486482 | AS4: 1.3413019 | BA4: 1.3487419 | BG4: {=INDIRECT(ADDRESS(2,BG$1,,,B4))+INDIRECT(ADDRESS(3,BG$1,,,B4))} -> 480 | BH4: {=-INDIRECT(ADDRESS(5,BG$1,,,B4))*BI4} -> -6853029.8 | BI4: =BA4 -> 1.3487419 | BJ4: =BH4/BG$4 -> -14277.145 | BK4: {=INDIRECT(ADDRESS(15,BG$1,,,B4))+INDIRECT(ADDRESS(16,BG$1,,,B4))} -> 0 | BL4: =BK4*(1+$D4) -> 0 | BM4: =BJ4*(1+$E4)*BL4 -> 0 | BN4: =BM4*5 -> 0 | BO4: {=INDIRECT(ADDRESS(2,BO$1,,,B4))+INDIRECT(ADDRESS(3,BO$1,,,B4))} -> 381 | BP4: {=-INDIRECT(ADDRESS(5,BO$1,,,B4))*BQ4} -> -5685235.7 | BQ4: =BI4 -> 1.3487419 | BR4: =BP4/BO$4 -> -14921.879 | BS4: {=INDIRECT(ADDRESS(15,BO$1,,,B4))+INDIRECT(ADDRESS(16,BO$1,,,B4))} -> 7 | BT4: =BS4*(1+$D4) -> 5.46 | BU4: =BR4*(1+$E4)*BT4 -> -100212.35 | BV4: =BU4*4 -> -400849.41 | BW4: {=INDIRECT(ADDRESS(2,BW$1,,,B4))+INDIRECT(ADDRESS(3,BW$1,,,B4))} -> 380 | BX4: {=-INDIRECT(ADDRESS(5,BW$1,,,B4))*BY4} -> -5667027.5 | BY4: =BQ4 -> 1.3487419 | BZ4: =BX4/BW$4 -> -14913.23 | CA4: {=INDIRECT(ADDRESS(15,BW$1,,,B4))+INDIRECT(ADDRESS(16,BW$1,,,B4))} -> 1 | CB4: =CA4*(1+$D4) -> 0.78 | CC4: =BZ4*(1+$E4)*CB4 -> -14307.753 | CD4: =CC4*3 -> -42923.259 | CE4: {=INDIRECT(ADDRESS(2,CE$1,,,B4))+INDIRECT(ADDRESS(3,CE$1,,,B4))} -> 377 | CF4: {=-INDIRECT(ADDRESS(5,CE$1,,,B4))*CG4} -> -5615603 | CG4: =BY4 -> 1.3487419 | CH4: =CF4/CE$4 -> -14895.499 | CI4: {=INDIRECT(ADDRESS(15,CE$1,,,B4))+INDIRECT(ADDRESS(16,CE$1,,,B4))} -> 3 | CJ4: =CI4*(1+$D4) -> 2.34 | CK4: =CH4*(1+$E4)*CJ4 -> -42872.224 | CL4: =CK4*2 -> -85744.448 | CM4: {=INDIRECT(ADDRESS(2,CM$1,,,B4))+INDIRECT(ADDRESS(3,CM$1,,,B4))} -> 355 | CN4: {=-INDIRECT(ADDRESS(5,CM$1,,,B4))*CO4} -> -5411306 | CO4: =CG4 -> 1.3487419 | CP4: =CN4/CM$4 -> -15243.115 | CQ4: {=INDIRECT(ADDRESS(15,CM$1,,,B4))+INDIRECT(ADDRESS(16,CM$1,,,B4))} -> 22 | CR4: =CQ4*(1+$D4) -> 17.16 | CS4: =CP4*(1+$E4)*CR4 -> -321733.39 | CT4: =CS4*1 -> -321733.39 | CW4: =AZ4 -> 0 | CX4: =CW4*6 -> 0 | CY4: =K4 -> -38757901
A6: Ghana | F6: 70915007 | G6: 280 | H6: =H7+H8 -> 121 | I6: =I7+I8 -> 0 | J6: =J7+J8 -> 121 | K6: -14671768 | L6: =L7+L8 -> -15240723 | M6: =M7+M8 -> #DIV/0! | N6: =K6+L6+M6 -> #DIV/0! | O6: =N6+F6 -> #DIV/0! | P6: =-N6/F6 -> #DIV/0! | Q6: =F6/$F$23 -> 0.026640325 | R6: 193 | S6: 2954389 | CY6: =K6 -> -14671768
A7: Ghana | B7: GHA | D7: -1 | E7: 0 | H7: =CM7 -> 0 | I7: =AF7+AN7+AV7+BD7+BL7+BT7+CB7+CJ7+CR7 -> 0 | J7: =H7+INT(I7) -> 0 | L7: =AB7+AJ7+AR7+AZ7+BH7+BP7+BX7+CF7+CN7 -> -40689.643 | M7: =AH7+AP7+AX7+BF7+BN7+BV7+CD7+CL7+CT7 -> #DIV/0! | T7: 17.451466 | W7: 17.870771 | Z7: 18.463523 | AC7: 18.770692 | AK7: =AC7 -> 18.770692 | AS7: 18.481078 | BA7: 18.50059 | BG7: {=INDIRECT(ADDRESS(2,BG$1,,,B7))+INDIRECT(ADDRESS(3,BG$1,,,B7))} -> 5 | BH7: {=-INDIRECT(ADDRESS(5,BG$1,,,B7))*BI7} -> -40689.643 | BI7: =BA7 -> 18.50059 | BJ7: =BH7/BG7 -> -8137.9286 | BK7: {=INDIRECT(ADDRESS(15,BG$1,,,B7))+INDIRECT(ADDRESS(16,BG$1,,,B7))} -> 0 | BL7: =BK7*(1+$D7) -> 0 | BM7: =BJ7*(1+$E7)*BL7 -> 0 | BN7: =BM7*5 -> 0 | BO7: {=INDIRECT(ADDRESS(2,BO$1,,,B7))+INDIRECT(ADDRESS(3,BO$1,,,B7))} -> 0 | BP7: {=-INDIRECT(ADDRESS(5,BO$1,,,B7))*BQ7} -> 0 | BQ7: =BI7 -> 18.50059 | BR7: =BP7/BO7 -> #DIV/0! | BS7: {=INDIRECT(ADDRESS(15,BO$1,,,B7))+INDIRECT(ADDRESS(16,BO$1,,,B7))} -> 4 | BT7: =BS7*(1+$D7) -> 0 | BU7: =BR7*(1+$E7)*BT7 -> #DIV/0! | BV7: =BU7*4 -> #DIV/0! | BW7: {=INDIRECT(ADDRESS(2,BW$1,,,B7))+INDIRECT(ADDRESS(3,BW$1,,,B7))} -> 0 | BX7: {=-INDIRECT(ADDRESS(5,BW$1,,,B7))*BY7} -> 0 | BY7: =BQ7 -> 18.50059 | BZ7: =BX7/BW7 -> #DIV/0! | CA7: {=INDIRECT(ADDRESS(15,BW$1,,,B7))+INDIRECT(ADDRESS(16,BW$1,,,B7))} -> 0 | CB7: =CA7*(1+$D7) -> 0 | CC7: =BZ7*(1+$E7)*CB7 -> #DIV/0! | CD7: =CC7*3 -> #DIV/0! | CE7: {=INDIRECT(ADDRESS(2,CE$1,,,B7))+INDIRECT(ADDRESS(3,CE$1,,,B7))} -> 0 | CF7: {=-INDIRECT(ADDRESS(5,CE$1,,,B7))*CG7} -> 0 | CG7: =BY7 -> 18.50059 | CH7: =CF7/CE7 -> #DIV/0! | CI7: {=INDIRECT(ADDRESS(15,CE$1,,,B7))+INDIRECT(ADDRESS(16,CE$1,,,B7))} -> 0 | CJ7: =CI7*(1+$D7) -> 0 | CK7: =CH7*(1+$E7)*CJ7 -> #DIV/0! | CL7: =CK7*2 -> #DIV/0! | CM7: {=INDIRECT(ADDRESS(2,CM$1,,,B7))+INDIRECT(ADDRESS(3,CM$1,,,B7))} -> 0 | CN7: {=-INDIRECT(ADDRESS(5,CM$1,,,B7))*CO7} -> 0 | CO7: =CG7 -> 18.50059 | CP7: =CN7/CM7 -> #DIV/0! | CQ7: {=INDIRECT(ADDRESS(15,CM$1,,,B7))+INDIRECT(ADDRESS(16,CM$1,,,B7))} -> 0 | CR7: =CQ7*(1+$D7) -> 0 | CS7: =CP7*(1+$E7)*CR7 -> #DIV/0! | CT7: =CS7*1 -> #DIV/0! | CW7: =AZ7 -> 0 | CX7: =CW7*6 -> 0
A8: Ghana | B8: GHC | D8: -1 | E8: 0 | H8: =CM8 -> 121 | I8: =AF8+AN8+AV8+BD8+BL8+BT8+CB8+CJ8+CR8 -> 0 | J8: =H8+INT(I8) -> 121 | L8: =AB8+AJ8+AR8+AZ8+BH8+BP8+BX8+CF8+CN8 -> -15200033 | M8: =AH8+AP8+AX8+BF8+BN8+BV8+CD8+CL8+CT8 -> 0 | T8: 1.089343 | W8: 1.1308812 | Z8: 1.2286845 | AC8: 1.2493831 | AK8: =AC8 -> 1.2493831 | AS8: 1.1919491 | BA8: 1.251073 | BG8: {=INDIRECT(ADDRESS(2,BG$1,,,B8))+INDIRECT(ADDRESS(3,BG$1,,,B8))} -> 156 | BH8: {=-INDIRECT(ADDRESS(5,BG$1,,,B8))*BI8} -> -3229798.8 | BI8: =BA8 -> 1.251073 | BJ8: =BH8/BG8 -> -20703.839 | BK8: {=INDIRECT(ADDRESS(15,BG$1,,,B8))+INDIRECT(ADDRESS(16,BG$1,,,B8))} -> 0 | BL8: =BK8*(1+$D8) -> 0 | BM8: =BJ8*(1+$E8)*BL8 -> 0 | BN8: =BM8*5 -> 0 | BO8: {=INDIRECT(ADDRESS(2,BO$1,,,B8))+INDIRECT(ADDRESS(3,BO$1,,,B8))} -> 134 | BP8: {=-INDIRECT(ADDRESS(5,BO$1,,,B8))*BQ8} -> -3037029.4 | BQ8: =BI8 -> 1.251073 | BR8: =BP8/BO8 -> -22664.399 | BS8: {=INDIRECT(ADDRESS(15,BO$1,,,B8))+INDIRECT(ADDRESS(16,BO$1,,,B8))} -> 1 | BT8: =BS8*(1+$D8) -> 0 | BU8: =BR8*(1+$E8)*BT8 -> 0 | BV8: =BU8*4 -> 0 | BW8: {=INDIRECT(ADDRESS(2,BW$1,,,B8))+INDIRECT(ADDRESS(3,BW$1,,,B8))} -> 133 | BX8: {=-INDIRECT(ADDRESS(5,BW$1,,,B8))*BY8} -> -3030890.6 | BY8: =BQ8 -> 1.251073 | BZ8: =BX8/BW8 -> -22788.651 | CA8: {=INDIRECT(ADDRESS(15,BW$1,,,B8))+INDIRECT(ADDRESS(16,BW$1,,,B8))} -> 1 | CB8: =CA8*(1+$D8) -> 0 | CC8: =BZ8*(1+$E8)*CB8 -> 0 | CD8: =CC8*3 -> 0 | CE8: {=INDIRECT(ADDRESS(2,CE$1,,,B8))+INDIRECT(ADDRESS(3,CE$1,,,B8))} -> 130 | CF8: {=-INDIRECT(ADDRESS(5,CE$1,,,B8))*CG8} -> -2998061.8 | CG8: =BY8 -> 1.251073 | CH8: =CF8/CE8 -> -23062.013 | CI8: {=INDIRECT(ADDRESS(15,CE$1,,,B8))+INDIRECT(ADDRESS(16,CE$1,,,B8))} -> 3 | CJ8: =CI8*(1+$D8) -> 0 | CK8: =CH8*(1+$E8)*CJ8 -> 0 | CL8: =CK8*2 -> 0 | CM8: {=INDIRECT(ADDRESS(2,CM$1,,,B8))+INDIRECT(ADDRESS(3,CM$1,,,B8))} -> 121 | CN8: {=-INDIRECT(ADDRESS(5,CM$1,,,B8))*CO8} -> -2904252.9 | CO8: =CG8 -> 1.251073 | CP8: =CN8/CM8 -> -24002.09 | CQ8: {=INDIRECT(ADDRESS(15,CM$1,,,B8))+INDIRECT(ADDRESS(16,CM$1,,,B8))} -> 9 | CR8: =CQ8*(1+$D8) -> 0 | CS8: =CP8*(1+$E8)*CR8 -> 0 | CT8: =CS8*1 -> 0 | CW8: =AZ8 -> 0 | CX8: =CW8*6 -> 0
A10: Mozambique | B10: MOZ | D10: 0.01 | E10: =29%/2 -> 0.145 | F10: 113726588 | G10: 408 | H10: =CM10 -> 257 | I10: =AF10+AN10+AV10+BD10+BL10+BT10+CB10+CJ10+CR10 -> 17.17 | J10: =H10+INT(I10) -> 274 | K10: -44528051 | L10: =AB10+AJ10+AR10+AZ10+BH10+BP10+BX10+CF10+CN10 -> -30631654 | M10: =AH10+AP10+AX10+BF10+BN10+BV10+CD10+CL10+CT10 -> -998767.45 | N10: =K10+L10+M10 -> -76158472 | O10: =N10+F10 -> 37568116 | P10: =-N10/F10 -> 0.66966286 | Q10: =F10/$F$23 -> 0.042723161 | R10: 334 | S10: 6168000 | T10: 0.27312914 | W10: 0.27964626 | Z10: 0.28892745 | AC10: 0.29372343 | AK10: =AC10 -> 0.29372343 | AS10: 0.28919622 | BA10: =AS10 -> 0.28919622 | BG10: {=INDIRECT(ADDRESS(2,BG$1,,,B10))+INDIRECT(ADDRESS(3,BG$1,,,B10))} -> 293 | BH10: {=-INDIRECT(ADDRESS(5,BG$1,,,B10))*BI10} -> -6595884.6 | BI10: =BA10 -> 0.28919622 | BJ10: =BH10/BG10 -> -22511.552 | BK10: {=INDIRECT(ADDRESS(15,BG$1,,,B10))+INDIRECT(ADDRESS(16,BG$1,,,B10))} -> 0 | BL10: =BK10*(1+$D10) -> 0 | BM10: =BJ10*(1+$E10)*BL10 -> 0 | BN10: =BM10*5 -> 0 | BO10: {=INDIRECT(ADDRESS(2,BO$1,,,B10))+INDIRECT(ADDRESS(3,BO$1,,,B10))} -> 271 | BP10: {=-INDIRECT(ADDRESS(5,BO$1,,,B10))*BQ10} -> -6150244.9 | BQ10: =BI10 -> 0.28919622 | BR10: =BP10/BO10 -> -22694.631 | BS10: {=INDIRECT(ADDRESS(15,BO$1,,,B10))+INDIRECT(ADDRESS(16,BO$1,,,B10))} -> 3 | BT10: =BS10*(1+$D10) -> 3.03 | BU10: =BR10*(1+$E10)*BT10 -> -78735.617 | BV10: =BU10*4 -> -314942.47 | BW10: {=INDIRECT(ADDRESS(2,BW$1,,,B10))+INDIRECT(ADDRESS(3,BW$1,,,B10))} -> 266 | BX10: {=-INDIRECT(ADDRESS(5,BW$1,,,B10))*BY10} -> -6050021 | BY10: =BQ10 -> 0.28919622 | BZ10: =BX10/BW10 -> -22744.44 | CA10: {=INDIRECT(ADDRESS(15,BW$1,,,B10))+INDIRECT(ADDRESS(16,BW$1,,,B10))} -> 5 | CB10: =CA10*(1+$D10) -> 5.05 | CC10: =BZ10*(1+$E10)*CB10 -> -131514.04 | CD10: =CC10*3 -> -394542.11 | CE10: {=INDIRECT(ADDRESS(2,CE$1,,,B10))+INDIRECT(ADDRESS(3,CE$1,,,B10))} -> 264 | CF10: {=-INDIRECT(ADDRESS(5,CE$1,,,B10))*CG10} -> -5975627.8 | CG10: =BY10 -> 0.28919622 | CH10: =CF10/CE10 -> -22634.954 | CI10: {=INDIRECT(ADDRESS(15,CE$1,,,B10))+INDIRECT(ADDRESS(16,CE$1,,,B10))} -> 2 | CJ10: =CI10*(1+$D10) -> 2.02 | CK10: =CH10*(1+$E10)*CJ10 -> -52352.384 | CL10: =CK10*2 -> -104704.77 | CM10: {=INDIRECT(ADDRESS(2,CM$1,,,B10))+INDIRECT(ADDRESS(3,CM$1,,,B10))} -> 257 | CN10: {=-INDIRECT(ADDRESS(5,CM$1,,,B10))*CO10} -> -5859875.5 | CO10: =CG10 -> 0.28919622 | CP10: =CN10/CM10 -> -22801.072 | CQ10: {=INDIRECT(ADDRESS(15,CM$1,,,B10))+INDIRECT(ADDRESS(16,CM$1,,,B10))} -> 7 | CR10: =CQ10*(1+$D10) -> 7.07 | CS10: =CP10*(1+$E10)*CR10 -> -184578.1 | CT10: =CS10*1 -> -184578.1 | CW10: =AZ10 -> 0 | CX10: =CW10*6 -> 0 | CY10: =K10 -> -44528051
A11: Namibia | B11: NAM | D11: 0.03 | E11: =37%/2 -> 0.185 | F11: 199243565 | G11: 1471 | H11: =CM11 -> 1163 | I11: =AF11+AN11+AV11+BD11+BL11+BT11+CB11+CJ11+CR11 -> 92.7 | J11: =H11+INT(I11) -> 1255 | K11: -88937124 | L11: =AB11+AJ11+AR11+AZ11+BH11+BP11+BX11+CF11+CN11 -> -79474250 | M11: =AH11+AP11+AX11+BF11+BN11+BV11+CD11+CL11+CT11 -> -3113371.2 | N11: =K11+L11+M11 -> -1.7152474e+08 | O11: =N11+F11 -> 27718820 | P11: =-N11/F11 -> 0.86087972 | Q11: =F11/$F$23 -> 0.074848943 | R11: 1321 | S11: 15116000 | Z11: 1 | AC11: =Z11 -> 1 | AK11: =AC11 -> 1 | AS11: =AK11 -> 1 | BA11: =AS11 -> 1 | BG11: {=INDIRECT(ADDRESS(2,BG$1,,,B11))+INDIRECT(ADDRESS(3,BG$1,,,B11))} -> 1328 | BH11: {=-INDIRECT(ADDRESS(5,BG$1,,,B11))*BI11} -> -16784081 | BI11: =BA11 -> 1 | BJ11: =BH11/BG11 -> -12638.615 | BK11: {=INDIRECT(ADDRESS(15,BG$1,,,B11))+INDIRECT(ADDRESS(16,BG$1,,,B11))} -> 0 | BL11: =BK11*(1+$D11) -> 0 | BM11: =BJ11*(1+$E11)*BL11 -> 0 | BN11: =BM11*5 -> 0 | BO11: {=INDIRECT(ADDRESS(2,BO$1,,,B11))+INDIRECT(ADDRESS(3,BO$1,,,B11))} -> 1236 | BP11: {=-INDIRECT(ADDRESS(5,BO$1,,,B11))*BQ11} -> -15959344 | BQ11: =BI11 -> 1 | BR11: =BP11/BO11 -> -12912.091 | BS11: {=INDIRECT(ADDRESS(15,BO$1,,,B11))+INDIRECT(ADDRESS(16,BO$1,,,B11))} -> 17 | BT11: =BS11*(1+$D11) -> 17.51 | BU11: =BR11*(1+$E11)*BT11 -> -267917.49 | BV11: =BU11*4 -> -1071670 | BW11: {=INDIRECT(ADDRESS(2,BW$1,,,B11))+INDIRECT(ADDRESS(3,BW$1,,,B11))} -> 1229 | BX11: {=-INDIRECT(ADDRESS(5,BW$1,,,B11))*BY11} -> -15891805 | BY11: =BQ11 -> 1 | BZ11: =BX11/BW11 -> -12930.679 | CA11: {=INDIRECT(ADDRESS(15,BW$1,,,B11))+INDIRECT(ADDRESS(16,BW$1,,,B11))} -> 7 | CB11: =CA11*(1+$D11) -> 7.21 | CC11: =BZ11*(1+$E11)*CB11 -> -110477.78 | CD11: =CC11*3 -> -331433.35 | CE11: {=INDIRECT(ADDRESS(2,CE$1,,,B11))+INDIRECT(ADDRESS(3,CE$1,,,B11))} -> 1188 | CF11: {=-INDIRECT(ADDRESS(5,CE$1,,,B11))*CG11} -> -15534345 | CG11: =BY11 -> 1 | CH11: =CF11/CE11 -> -13076.048 | CI11: {=INDIRECT(ADDRESS(15,CE$1,,,B11))+INDIRECT(ADDRESS(16,CE$1,,,B11))} -> 41 | CJ11: =CI11*(1+$D11) -> 42.23 | CK11: =CH11*(1+$E11)*CJ11 -> -654358.77 | CL11: =CK11*2 -> -1308717.5 | CM11: {=INDIRECT(ADDRESS(2,CM$1,,,B11))+INDIRECT(ADDRESS(3,CM$1,,,B11))} -> 1163 | CN11: {=-INDIRECT(ADDRESS(5,CM$1,,,B11))*CO11} -> -15304676 | CO11: =CG11 -> 1 | CP11: =CN11/CM11 -> -13159.652 | CQ11: {=INDIRECT(ADDRESS(15,CM$1,,,B11))+INDIRECT(ADDRESS(16,CM$1,,,B11))} -> 25 | CR11: =CQ11*(1+$D11) -> 25.75 | CS11: =CP11*(1+$E11)*CR11 -> -401550.34 | CT11: =CS11*1 -> -401550.34 | CW11: =AZ11 -> 0 | CX11: =CW11*6 -> 0 | CY11: =K11 -> -88937124
A12: Lesotho | B12: LES | D12: 0.09 | E12: =76%/2 -> 0.38 | F12: 24454461 | G12: 179 | H12: =CM12 -> 161 | I12: =AF12+AN12+AV12+BD12+BL12+BT12+CB12+CJ12+CR12 -> 14.17 | J12: =H12+INT(I12) -> 175 | K12: -13748321 | L12: =AB12+AJ12+AR12+AZ12+BH12+BP12+BX12+CF12+CN12 -> -13993090 | M12: =AH12+AP12+AX12+BF12+BN12+BV12+CD12+CL12+CT12 -> -875087.79 | N12: =K12+L12+M12 -> -28616498 | O12: =N12+F12 -> -4162037.5 | P12: =-N12/F12 -> 1.1701954 | Q12: =F12/$F$23 -> 0.0091866985 | R12: 182 | S12: 2365000 | Z12: 1 | AC12: =Z12 -> 1 | AK12: =AC12 -> 1 | AS12: =AK12 -> 1 | BA12: =AS12 -> 1 | BG12: {=INDIRECT(ADDRESS(2,BG$1,,,B12))+INDIRECT(ADDRESS(3,BG$1,,,B12))} -> 190 | BH12: {=-INDIRECT(ADDRESS(5,BG$1,,,B12))*BI12} -> -2983657.9 | BI12: =BA12 -> 1 | BJ12: =BH12/BG12 -> -15703.462 | BK12: {=INDIRECT(ADDRESS(15,BG$1,,,B12))+INDIRECT(ADDRESS(16,BG$1,,,B12))} -> 0 | BL12: =BK12*(1+$D12) -> 0 | BM12: =BJ12*(1+$E12)*BL12 -> 0 | BN12: =BM12*5 -> 0 | BO12: {=INDIRECT(ADDRESS(2,BO$1,,,B12))+INDIRECT(ADDRESS(3,BO$1,,,B12))} -> 172 | BP12: {=-INDIRECT(ADDRESS(5,BO$1,,,B12))*BQ12} -> -2821250.9 | BQ12: =BI12 -> 1 | BR12: =BP12/BO12 -> -16402.622 | BS12: {=INDIRECT(ADDRESS(15,BO$1,,,B12))+INDIRECT(ADDRESS(16,BO$1,,,B12))} -> 2 | BT12: =BS12*(1+$D12) -> 2.18 | BU12: =BR12*(1+$E12)*BT12 -> -49345.647 | BV12: =BU12*4 -> -197382.59 | BW12: {=INDIRECT(ADDRESS(2,BW$1,,,B12))+INDIRECT(ADDRESS(3,BW$1,,,B12))} -> 165 | BX12: {=-INDIRECT(ADDRESS(5,BW$1,,,B12))*BY12} -> -2749320.5 | BY12: =BQ12 -> 1 | BZ12: =BX12/BW12 -> -16662.548 | CA12: {=INDIRECT(ADDRESS(15,BW$1,,,B12))+INDIRECT(ADDRESS(16,BW$1,,,B12))} -> 7 | CB12: =CA12*(1+$D12) -> 7.63 | CC12: =BZ12*(1+$E12)*CB12 -> -175446.64 | CD12: =CC12*3 -> -526339.91 | CE12: {=INDIRECT(ADDRESS(2,CE$1,,,B12))+INDIRECT(ADDRESS(3,CE$1,,,B12))} -> 163 | CF12: {=-INDIRECT(ADDRESS(5,CE$1,,,B12))*CG12} -> -2728690.6 | CG12: =BY12 -> 1 | CH12: =CF12/CE12 -> -16740.433 | CI12: {=INDIRECT(ADDRESS(15,CE$1,,,B12))+INDIRECT(ADDRESS(16,CE$1,,,B12))} -> 2 | CJ12: =CI12*(1+$D12) -> 2.18 | CK12: =CH12*(1+$E12)*CJ12 -> -50361.918 | CL12: =CK12*2 -> -100723.84 | CM12: {=INDIRECT(ADDRESS(2,CM$1,,,B12))+INDIRECT(ADDRESS(3,CM$1,,,B12))} -> 161 | CN12: {=-INDIRECT(ADDRESS(5,CM$1,,,B12))*CO12} -> -2710170.1 | CO12: =CG12 -> 1 | CP12: =CN12/CM12 -> -16833.354 | CQ12: {=INDIRECT(ADDRESS(15,CM$1,,,B12))+INDIRECT(ADDRESS(16,CM$1,,,B12))} -> 2 | CR12: =CQ12*(1+$D12) -> 2.18 | CS12: =CP12*(1+$E12)*CR12 -> -50641.463 | CT12: =CS12*1 -> -50641.463 | CW12: =AZ12 -> 0 | CX12: =CW12*6 -> 0 | CY12: =K12 -> -13748321
A14: Central & Commercial | B14: RSA | C14: =F14/SUM($F$14:$F$17) -> 0.085749986 | D14: 0.09 | E14: =29%/2 -> 0.145 | F14: 170565897 | G14: 669 | H14: =CM14 -> 710 | I14: =AF14+AN14+AV14+BD14+BL14+BT14+CB14+CJ14+CR14 -> 37.06 | J14: =H14+INT(I14) -> 747 | K14: -89936593 | L14: =AB14+AJ14+AR14+AZ14+BH14+BP14+BX14+CF14+CN14 -> -73724792 | M14: =AH14+AP14+AX14+BF14+BN14+BV14+CD14+CL14+CT14 -> -1909576.2 | N14: =K14+L14+M14 -> -1.6557096e+08 | O14: =N14+F14 -> 4994935.6 | P14: =-N14/F14 -> 0.97071551 | Q14: =F14/$F$23 -> 0.064075731 | R14: 688 | S14: 10303289 | Z14: 1 | AC14: =Z14 -> 1 | AK14: =AC14 -> 1 | AS14: =AK14 -> 1 | BA14: =AS14 -> 1 | BG14: {=INDIRECT(ADDRESS(2,BG$1,,,A14))+INDIRECT(ADDRESS(3,BG$1,,,A14))} -> 784 | BH14: {=-INDIRECT(ADDRESS(5,BG$1,,,A14))*BI14} -> -15289625 | BI14: =BA14 -> 1 | BJ14: =BH14/BG14 -> -19502.073 | BK14: {=INDIRECT(ADDRESS(15,BG$1,,,A14))+INDIRECT(ADDRESS(16,BG$1,,,A14))} -> 0 | BL14: =BK14*(1+$D14) -> 0 | BM14: =BJ14*(1+$E14)*BL14 -> 0 | BN14: =BM14*5 -> 0 | BO14: {=INDIRECT(ADDRESS(2,BO$1,,,A14))+INDIRECT(ADDRESS(3,BO$1,,,A14))} -> 740 | BP14: {=-INDIRECT(ADDRESS(5,BO$1,,,A14))*BQ14} -> -14765783 | BQ14: =BI14 -> 1 | BR14: =BP14/BO14 -> -19953.761 | BS14: {=INDIRECT(ADDRESS(15,BO$1,,,A14))+INDIRECT(ADDRESS(16,BO$1,,,A14))} -> 4 | BT14: =BS14*(1+$D14) -> 4.36 | BU14: =BR14*(1+$E14)*BT14 -> -99613.168 | BV14: =BU14*4 -> -398452.67 | BW14: {=INDIRECT(ADDRESS(2,BW$1,,,A14))+INDIRECT(ADDRESS(3,BW$1,,,A14))} -> 728 | BX14: {=-INDIRECT(ADDRESS(5,BW$1,,,A14))*BY14} -> -14648978 | BY14: =BQ14 -> 1 | BZ14: =BX14/BW14 -> -20122.223 | CA14: {=INDIRECT(ADDRESS(15,BW$1,,,A14))+INDIRECT(ADDRESS(16,BW$1,,,A14))} -> 12 | CB14: =CA14*(1+$D14) -> 13.08 | CC14: =BZ14*(1+$E14)*CB14 -> -301362.48 | CD14: =CC14*3 -> -904087.44 | CE14: {=INDIRECT(ADDRESS(2,CE$1,,,A14))+INDIRECT(ADDRESS(3,CE$1,,,A14))} -> 722 | CF14: {=-INDIRECT(ADDRESS(5,CE$1,,,A14))*CG14} -> -14588663 | CG14: =BY14 -> 1 | CH14: =CF14/CE14 -> -20205.904 | CI14: {=INDIRECT(ADDRESS(15,CE$1,,,A14))+INDIRECT(ADDRESS(16,CE$1,,,A14))} -> 6 | CJ14: =CI14*(1+$D14) -> 6.54 | CK14: =CH14*(1+$E14)*CJ14 -> -151307.87 | CL14: =CK14*2 -> -302615.74 | CM14: {=INDIRECT(ADDRESS(2,CM$1,,,A14))+INDIRECT(ADDRESS(3,CM$1,,,A14))} -> 710 | CN14: {=-INDIRECT(ADDRESS(5,CM$1,,,A14))*CO14} -> -14431742 | CO14: =CG14 -> 1 | CP14: =CN14/CM14 -> -20326.398 | CQ14: {=INDIRECT(ADDRESS(15,CM$1,,,A14))+INDIRECT(ADDRESS(16,CM$1,,,A14))} -> 12 | CR14: =CQ14*(1+$D14) -> 13.08 | CS14: =CP14*(1+$E14)*CR14 -> -304420.33 | CT14: =CS14*1 -> -304420.33 | CW14: =AZ14 -> 0 | CX14: =CW14*6 -> 0 | CY14: =K14 -> -89936593
A15: Inland | B15: RSA | C15: =F15/SUM($F$14:$F$17) -> 0.63886682 | D15: 0.09 | E15: =29%/2 -> 0.145 | F15: 1270774464 | G15: 10490 | H15: =CM15 -> 7650 | I15: =AF15+AN15+AV15+BD15+BL15+BT15+CB15+CJ15+CR15 -> 914.51 | J15: =H15+INT(I15) -> 8564 | K15: -6.7005848e+08 | L15: =AB15+AJ15+AR15+AZ15+BH15+BP15+BX15+CF15+CN15 -> -4.6815815e+08 | M15: =AH15+AP15+AX15+BF15+BN15+BV15+CD15+CL15+CT15 -> -29404517 | N15: =K15+L15+M15 -> -1.1676212e+09 | O15: =N15+F15 -> 1.0315331e+08 | P15: =-N15/F15 -> 0.91882642 | Q15: =F15/$F$23 -> 0.47738619 | R15: 9348 | S15: 76763043 | Z15: 1 | AC15: =Z15 -> 1 | AK15: =AC15 -> 1 | AS15: =AK15 -> 1 | BA15: =AS15 -> 1 | BG15: {=INDIRECT(ADDRESS(2,BG$1,,,A15))+INDIRECT(ADDRESS(3,BG$1,,,A15))} -> 9401 | BH15: {=-INDIRECT(ADDRESS(5,BG$1,,,A15))*BI15} -> -1.0546975e+08 | BI15: =BA15 -> 1 | BJ15: =BH15/BG15 -> -11218.992 | BK15: {=INDIRECT(ADDRESS(15,BG$1,,,A15))+INDIRECT(ADDRESS(16,BG$1,,,A15))} -> 0 | BL15: =BK15*(1+$D15) -> 0 | BM15: =BJ15*(1+$E15)*BL15 -> 0 | BN15: =BM15*5 -> 0 | BO15: {=INDIRECT(ADDRESS(2,BO$1,,,A15))+INDIRECT(ADDRESS(3,BO$1,,,A15))} -> 8286 | BP15: {=-INDIRECT(ADDRESS(5,BO$1,,,A15))*BQ15} -> -93751568 | BQ15: =BI15 -> 1 | BR15: =BP15/BO15 -> -11314.454 | BS15: {=INDIRECT(ADDRESS(15,BO$1,,,A15))+INDIRECT(ADDRESS(16,BO$1,,,A15))} -> 203 | BT15: =BS15*(1+$D15) -> 221.27 | BU15: =BR15*(1+$E15)*BT15 -> -2866564 | BV15: =BU15*4 -> -11466256 | BW15: {=INDIRECT(ADDRESS(2,BW$1,,,A15))+INDIRECT(ADDRESS(3,BW$1,,,A15))} -> 8075 | BX15: {=-INDIRECT(ADDRESS(5,BW$1,,,A15))*BY15} -> -91535497 | BY15: =BQ15 -> 1 | BZ15: =BX15/BW15 -> -11335.665 | CA15: {=INDIRECT(ADDRESS(15,BW$1,,,A15))+INDIRECT(ADDRESS(16,BW$1,,,A15))} -> 211 | CB15: =CA15*(1+$D15) -> 229.99 | CC15: =BZ15*(1+$E15)*CB15 -> -2985117.7 | CD15: =CC15*3 -> -8955353 | CE15: {=INDIRECT(ADDRESS(2,CE$1,,,A15))+INDIRECT(ADDRESS(3,CE$1,,,A15))} -> 7870 | CF15: {=-INDIRECT(ADDRESS(5,CE$1,,,A15))*CG15} -> -89801240 | CG15: =BY15 -> 1 | CH15: =CF15/CE15 -> -11410.577 | CI15: {=INDIRECT(ADDRESS(15,CE$1,,,A15))+INDIRECT(ADDRESS(16,CE$1,,,A15))} -> 205 | CJ15: =CI15*(1+$D15) -> 223.45 | CK15: =CH15*(1+$E15)*CJ15 -> -2919398.9 | CL15: =CK15*2 -> -5838797.9 | CM15: {=INDIRECT(ADDRESS(2,CM$1,,,A15))+INDIRECT(ADDRESS(3,CM$1,,,A15))} -> 7650 | CN15: {=-INDIRECT(ADDRESS(5,CM$1,,,A15))*CO15} -> -87600099 | CO15: =CG15 -> 1 | CP15: =CN15/CM15 -> -11450.993 | CQ15: {=INDIRECT(ADDRESS(15,CM$1,,,A15))+INDIRECT(ADDRESS(16,CM$1,,,A15))} -> 220 | CR15: =CQ15*(1+$D15) -> 239.8 | CS15: =CP15*(1+$E15)*CR15 -> -3144110.7 | CT15: =CS15*1 -> -3144110.7 | CW15: =AZ15 -> 0 | CX15: =CW15*6 -> 0 | CY15: =K15 -> -6.7005848e+08
A16: Coastal | B16: RSA | C16: =F16/SUM($F$14:$F$17) -> 0.21321726 | D16: 0.09 | E16: =29%/2 -> 0.145 | F16: 424111943 | G16: 3564 | H16: =CM16 -> 2501 | I16: =AF16+AN16+AV16+BD16+BL16+BT16+CB16+CJ16+CR16 -> 391.31 | J16: =H16+INT(I16) -> 2892 | K16: -2.2362726e+08 | L16: =AB16+AJ16+AR16+AZ16+BH16+BP16+BX16+CF16+CN16 -> -1.5909499e+08 | M16: =AH16+AP16+AX16+BF16+BN16+BV16+CD16+CL16+CT16 -> -12616260 | N16: =K16+L16+M16 -> -3.9533851e+08 | O16: =N16+F16 -> 28773435 | P16: =-N16/F16 -> 0.93215604 | Q16: =F16/$F$23 -> 0.15932425 | R16: 3043 | S16: 25619120 | Z16: 1 | AC16: =Z16 -> 1 | AK16: =AC16 -> 1 | AS16: =AK16 -> 1 | BA16: =AS16 -> 1 | BG16: {=INDIRECT(ADDRESS(2,BG$1,,,A16))+INDIRECT(ADDRESS(3,BG$1,,,A16))} -> 3142 | BH16: {=-INDIRECT(ADDRESS(5,BG$1,,,A16))*BI16} -> -36061930 | BI16: =BA16 -> 1 | BJ16: =BH16/BG16 -> -11477.381 | BK16: {=INDIRECT(ADDRESS(15,BG$1,,,A16))+INDIRECT(ADDRESS(16,BG$1,,,A16))} -> 0 | BL16: =BK16*(1+$D16) -> 0 | BM16: =BJ16*(1+$E16)*BL16 -> 0 | BN16: =BM16*5 -> 0 | BO16: {=INDIRECT(ADDRESS(2,BO$1,,,A16))+INDIRECT(ADDRESS(3,BO$1,,,A16))} -> 2785 | BP16: {=-INDIRECT(ADDRESS(5,BO$1,,,A16))*BQ16} -> -32142524 | BQ16: =BI16 -> 1 | BR16: =BP16/BO16 -> -11541.301 | BS16: {=INDIRECT(ADDRESS(15,BO$1,,,A16))+INDIRECT(ADDRESS(16,BO$1,,,A16))} -> 75 | BT16: =BS16*(1+$D16) -> 81.75 | BU16: =BR16*(1+$E16)*BT16 -> -1080309.1 | BV16: =BU16*4 -> -4321236.3 | BW16: {=INDIRECT(ADDRESS(2,BW$1,,,A16))+INDIRECT(ADDRESS(3,BW$1,,,A16))} -> 2679 | BX16: {=-INDIRECT(ADDRESS(5,BW$1,,,A16))*BY16} -> -31181889 | BY16: =BQ16 -> 1 | BZ16: =BX16/BW16 -> -11639.376 | CA16: {=INDIRECT(ADDRESS(15,BW$1,,,A16))+INDIRECT(ADDRESS(16,BW$1,,,A16))} -> 106 | CB16: =CA16*(1+$D16) -> 115.54 | CC16: =BZ16*(1+$E16)*CB16 -> -1539811.5 | CD16: =CC16*3 -> -4619434.5 | CE16: {=INDIRECT(ADDRESS(2,CE$1,,,A16))+INDIRECT(ADDRESS(3,CE$1,,,A16))} -> 2605 | CF16: {=-INDIRECT(ADDRESS(5,CE$1,,,A16))*CG16} -> -30345711 | CG16: =BY16 -> 1 | CH16: =CF16/CE16 -> -11649.025 | CI16: {=INDIRECT(ADDRESS(15,CE$1,,,A16))+INDIRECT(ADDRESS(16,CE$1,,,A16))} -> 74 | CJ16: =CI16*(1+$D16) -> 80.66 | CK16: =CH16*(1+$E16)*CJ16 -> -1075853.9 | CL16: =CK16*2 -> -2151707.8 | CM16: {=INDIRECT(ADDRESS(2,CM$1,,,A16))+INDIRECT(ADDRESS(3,CM$1,,,A16))} -> 2501 | CN16: {=-INDIRECT(ADDRESS(5,CM$1,,,A16))*CO16} -> -29362939 | CO16: =CG16 -> 1 | CP16: =CN16/CM16 -> -11740.479 | CQ16: {=INDIRECT(ADDRESS(15,CM$1,,,A16))+INDIRECT(ADDRESS(16,CM$1,,,A16))} -> 104 | CR16: =CQ16*(1+$D16) -> 113.36 | CS16: =CP16*(1+$E16)*CR16 -> -1523881.3 | CT16: =CS16*1 -> -1523881.3 | CW16: =AZ16 -> 0 | CX16: =CW16*6 -> 0 | CY16: =K16 -> -2.2362726e+08
A17: Public Sector | B17: RSA | C17: =F17/SUM($F$14:$F$17) -> 0.062165938 | D17: 0.09 | E17: =29%/2 -> 0.145 | F17: 123654702 | G17: 1101 | H17: =CM17 -> #REF! | I17: =AF17+AN17+AV17+BD17+BL17+BT17+CB17+CJ17+CR17 -> #REF! | J17: =H17+INT(I17) -> #REF! | K17: -65201092 | L17: =AB17+AJ17+AR17+AZ17+BH17+BP17+BX17+CF17+CN17 -> #REF! | M17: =AH17+AP17+AX17+BF17+BN17+BV17+CD17+CL17+CT17 -> #REF! | N17: =K17+L17+M17 -> #REF! | O17: =N17+F17 -> #REF! | P17: =-N17/F17 -> #REF! | Q17: =F17/$F$23 -> 0.046452811 | R17: 275 | S17: 7469548 | Z17: 1 | AC17: =Z17 -> 1 | AK17: =AC17 -> 1 | AS17: =AK17 -> 1 | BA17: =AS17 -> 1 | BG17: {=INDIRECT(ADDRESS(2,BG$1,,,A17))+INDIRECT(ADDRESS(3,BG$1,,,A17))} -> #REF! | BH17: {=-INDIRECT(ADDRESS(5,BG$1,,,A17))*BI17} -> #REF! | BI17: =BA17 -> 1 | BJ17: =BH17/BG17 -> #REF! | BK17: {=INDIRECT(ADDRESS(15,BG$1,,,A17))+INDIRECT(ADDRESS(16,BG$1,,,A17))} -> #REF! | BL17: =BK17*(1+$D17) -> #REF! | BM17: =BJ17*(1+$E17)*BL17 -> #REF! | BN17: =BM17*5 -> #REF! | BO17: {=INDIRECT(ADDRESS(2,BO$1,,,A17))+INDIRECT(ADDRESS(3,BO$1,,,A17))} -> #REF! | BP17: {=-INDIRECT(ADDRESS(5,BO$1,,,A17))*BQ17} -> #REF! | BQ17: =BI17 -> 1 | BR17: =BP17/BO17 -> #REF! | BS17: {=INDIRECT(ADDRESS(15,BO$1,,,A17))+INDIRECT(ADDRESS(16,BO$1,,,A17))} -> #REF! | BT17: =BS17*(1+$D17) -> #REF! | BU17: =BR17*(1+$E17)*BT17 -> #REF! | BV17: =BU17*4 -> #REF! | BW17: {=INDIRECT(ADDRESS(2,BW$1,,,A17))+INDIRECT(ADDRESS(3,BW$1,,,A17))} -> #REF! | BX17: {=-INDIRECT(ADDRESS(5,BW$1,,,A17))*BY17} -> #REF! | BY17: =BQ17 -> 1 | BZ17: =BX17/BW17 -> #REF! | CA17: {=INDIRECT(ADDRESS(15,BW$1,,,A17))+INDIRECT(ADDRESS(16,BW$1,,,A17))} -> #REF! | CB17: =CA17*(1+$D17) -> #REF! | CC17: =BZ17*(1+$E17)*CB17 -> #REF! | CD17: =CC17*3 -> #REF! | CE17: {=INDIRECT(ADDRESS(2,CE$1,,,A17))+INDIRECT(ADDRESS(3,CE$1,,,A17))} -> #REF! | CF17: {=-INDIRECT(ADDRESS(5,CE$1,,,A17))*CG17} -> #REF! | CG17: =BY17 -> 1 | CH17: =CF17/CE17 -> #REF! | CI17: {=INDIRECT(ADDRESS(15,CE$1,,,A17))+INDIRECT(ADDRESS(16,CE$1,,,A17))} -> #REF! | CJ17: =CI17*(1+$D17) -> #REF! | CK17: =CH17*(1+$E17)*CJ17 -> #REF! | CL17: =CK17*2 -> #REF! | CM17: {=INDIRECT(ADDRESS(2,CM$1,,,A17))+INDIRECT(ADDRESS(3,CM$1,,,A17))} -> #REF! | CN17: {=-INDIRECT(ADDRESS(5,CM$1,,,A17))*CO17} -> #REF! | CO17: =CG17 -> 1 | CP17: =CN17/CM17 -> #REF! | CQ17: {=INDIRECT(ADDRESS(15,CM$1,,,A17))+INDIRECT(ADDRESS(16,CM$1,,,A17))} -> #REF! | CR17: =CQ17*(1+$D17) -> #REF! | CS17: =CP17*(1+$E17)*CR17 -> #REF! | CT17: =CS17*1 -> #REF! | CW17: =AZ17 -> 0 | CX17: =CW17*6 -> 0 | CY17: =K17 -> -65201092
A19: Zambia | F19: 161476790 | G19: 482 | H19: =H20+H21 -> 542 | I19: =I20+I21 -> 60.025 | J19: =J20+J21 -> 602 | K19: -93381608 | L19: =L20+L21 -> -83024191 | M19: =M20+M21 -> -4849841.3 | N19: =K19+L19+M19 -> -1.8125564e+08 | O19: =N19+F19 -> -19778851 | P19: =-N19/F19 -> 1.1224873 | Q19: =F19/$F$23 -> 0.060661267 | R19: 490 | S19: 13709000 | CY19: =K19 -> -93381608
A20: Zambia | B20: ZAM | D20: =143%/2 -> 0.715 | E20: =38%/2 -> 0.19 | H20: =CM20 -> 509 | I20: =AF20+AN20+AV20+BD20+BL20+BT20+CB20+CJ20+CR20 -> 60.025 | J20: =H20+INT(I20) -> 569 | L20: =AB20+AJ20+AR20+AZ20+BH20+BP20+BX20+CF20+CN20 -> -80246677 | M20: =AH20+AP20+AX20+BF20+BN20+BV20+CD20+CL20+CT20 -> -4849841.3 | T20: 17.451466 | W20: 17.870771 | Z20: 18.463523 | AC20: 18.770692 | AK20: =AC20 -> 18.770692 | AS20: 18.481078 | BA20: 18.50059 | BG20: {=INDIRECT(ADDRESS(2,BG$1,,,B20))+INDIRECT(ADDRESS(3,BG$1,,,B20))} -> 579 | BH20: {=-INDIRECT(ADDRESS(5,BG$1,,,B20))*BI20} -> -17140349 | BI20: =BA20 -> 18.50059 | BJ20: =BH20/BG20 -> -29603.366 | BK20: {=INDIRECT(ADDRESS(15,BG$1,,,B20))+INDIRECT(ADDRESS(16,BG$1,,,B20))} -> 0 | BL20: =BK20*(1+$D20) -> 0 | BM20: =BJ20*(1+$E20)*BL20 -> 0 | BN20: =BM20*5 -> 0 | BO20: {=INDIRECT(ADDRESS(2,BO$1,,,B20))+INDIRECT(ADDRESS(3,BO$1,,,B20))} -> 537 | BP20: {=-INDIRECT(ADDRESS(5,BO$1,,,B20))*BQ20} -> -16130786 | BQ20: =BI20 -> 18.50059 | BR20: =BP20/BO20 -> -30038.707 | BS20: {=INDIRECT(ADDRESS(15,BO$1,,,B20))+INDIRECT(ADDRESS(16,BO$1,,,B20))} -> 7 | BT20: =BS20*(1+$D20) -> 12.005 | BU20: =BR20*(1+$E20)*BT20 -> -429131.47 | BV20: =BU20*4 -> -1716525.9 | BW20: {=INDIRECT(ADDRESS(2,BW$1,,,B20))+INDIRECT(ADDRESS(3,BW$1,,,B20))} -> 530 | BX20: {=-INDIRECT(ADDRESS(5,BW$1,,,B20))*BY20} -> -15908249 | BY20: =BQ20 -> 18.50059 | BZ20: =BX20/BW20 -> -30015.564 | CA20: {=INDIRECT(ADDRESS(15,BW$1,,,B20))+INDIRECT(ADDRESS(16,BW$1,,,B20))} -> 7 | CB20: =CA20*(1+$D20) -> 12.005 | CC20: =BZ20*(1+$E20)*CB20 -> -428800.84 | CD20: =CC20*3 -> -1286402.5 | CE20: {=INDIRECT(ADDRESS(2,CE$1,,,B20))+INDIRECT(ADDRESS(3,CE$1,,,B20))} -> 521 | CF20: {=-INDIRECT(ADDRESS(5,CE$1,,,B20))*CG20} -> -15723713 | CG20: =BY20 -> 18.50059 | CH20: =CF20/CE20 -> -30179.871 | CI20: {=INDIRECT(ADDRESS(15,CE$1,,,B20))+INDIRECT(ADDRESS(16,CE$1,,,B20))} -> 9 | CJ20: =CI20*(1+$D20) -> 15.435 | CK20: =CH20*(1+$E20)*CJ20 -> -554333.31 | CL20: =CK20*2 -> -1108666.6 | CM20: {=INDIRECT(ADDRESS(2,CM$1,,,B20))+INDIRECT(ADDRESS(3,CM$1,,,B20))} -> 509 | CN20: {=-INDIRECT(ADDRESS(5,CM$1,,,B20))*CO20} -> -15343580 | CO20: =CG20 -> 18.50059 | CP20: =CN20/CM20 -> -30144.558 | CQ20: {=INDIRECT(ADDRESS(15,CM$1,,,B20))+INDIRECT(ADDRESS(16,CM$1,,,B20))} -> 12 | CR20: =CQ20*(1+$D20) -> 20.58 | CS20: =CP20*(1+$E20)*CR20 -> -738246.26 | CT20: =CS20*1 -> -738246.26 | CW20: =AZ20 -> 0 | CX20: =CW20*6 -> 0
A21: Zambia | B21: ZMK | D21: =143%/2 -> 0.715 | E21: =38%/2 -> 0.19 | H21: =CM21 -> 33 | I21: =AF21+AN21+AV21+BD21+BL21+BT21+CB21+CJ21+CR21 -> 0 | J21: =H21+INT(I21) -> 33 | L21: =AB21+AJ21+AR21+AZ21+BH21+BP21+BX21+CF21+CN21 -> -2777514.9 | M21: =AH21+AP21+AX21+BF21+BN21+BV21+CD21+CL21+CT21 -> 0 | T21: 0.65676752 | Z21: 0.67450186 | AC21: 0.67136598 | AK21: =AC21 -> 0.67136598 | AS21: 0.65293729 | BA21: 0.66258142 | BG21: {=INDIRECT(ADDRESS(2,BG$1,,,B21))+INDIRECT(ADDRESS(3,BG$1,,,B21))} -> 33 | BH21: {=-INDIRECT(ADDRESS(5,BG$1,,,B21))*BI21} -> -555502.97 | BI21: =BA21 -> 0.66258142 | BJ21: =BH21/BG21 -> -16833.423 | BK21: {=INDIRECT(ADDRESS(15,BG$1,,,B21))+INDIRECT(ADDRESS(16,BG$1,,,B21))} -> 0 | BL21: =BK21*(1+$D21) -> 0 | BM21: =BJ21*(1+$E21)*BL21 -> 0 | BN21: =BM21*5 -> 0 | BO21: {=INDIRECT(ADDRESS(2,BO$1,,,B21))+INDIRECT(ADDRESS(3,BO$1,,,B21))} -> 33 | BP21: {=-INDIRECT(ADDRESS(5,BO$1,,,B21))*BQ21} -> -555502.97 | BQ21: =BI21 -> 0.66258142 | BR21: =BP21/BO21 -> -16833.423 | BS21: {=INDIRECT(ADDRESS(15,BO$1,,,B21))+INDIRECT(ADDRESS(16,BO$1,,,B21))} -> 0 | BT21: =BS21*(1+$D21) -> 0 | BU21: =BR21*(1+$E21)*BT21 -> 0 | BV21: =BU21*4 -> 0 | BW21: {=INDIRECT(ADDRESS(2,BW$1,,,B21))+INDIRECT(ADDRESS(3,BW$1,,,B21))} -> 33 | BX21: {=-INDIRECT(ADDRESS(5,BW$1,,,B21))*BY21} -> -555502.97 | BY21: =BQ21 -> 0.66258142 | BZ21: =BX21/BW21 -> -16833.423 | CA21: {=INDIRECT(ADDRESS(15,BW$1,,,B21))+INDIRECT(ADDRESS(16,BW$1,,,B21))} -> 0 | CB21: =CA21*(1+$D21) -> 0 | CC21: =BZ21*(1+$E21)*CB21 -> 0 | CD21: =CC21*3 -> 0 | CE21: {=INDIRECT(ADDRESS(2,CE$1,,,B21))+INDIRECT(ADDRESS(3,CE$1,,,B21))} -> 33 | CF21: {=-INDIRECT(ADDRESS(5,CE$1,,,B21))*CG21} -> -555502.97 | CG21: =BY21 -> 0.66258142 | CH21: =CF21/CE21 -> -16833.423 | CI21: {=INDIRECT(ADDRESS(15,CE$1,,,B21))+INDIRECT(ADDRESS(16,CE$1,,,B21))} -> 0 | CJ21: =CI21*(1+$D21) -> 0 | CK21: =CH21*(1+$E21)*CJ21 -> 0 | CL21: =CK21*2 -> 0 | CM21: {=INDIRECT(ADDRESS(2,CM$1,,,B21))+INDIRECT(ADDRESS(3,CM$1,,,B21))} -> 33 | CN21: {=-INDIRECT(ADDRESS(5,CM$1,,,B21))*CO21} -> -555502.97 | CO21: =CG21 -> 0.66258142 | CP21: =CN21/CM21 -> -16833.423 | CQ21: {=INDIRECT(ADDRESS(15,CM$1,,,B21))+INDIRECT(ADDRESS(16,CM$1,,,B21))} -> 0 | CR21: =CQ21*(1+$D21) -> 0 | CS21: =CP21*(1+$E21)*CR21 -> 0 | CT21: =CS21*1 -> 0 | CW21: =AZ21 -> 0 | CX21: =CW21*6 -> 0
CL22: 2
F23: =SUM(F4:F21) -> 2661942265 | K23: =-SUM(K4:K21) -> 1.3428482e+09 | N23: =-SUM(N4:N21) -> #DIV/0! | Q23: =SUM(Q4:Q21) -> 1
K24: =K23/F23 -> 0.5044618 | N24: =N23/F23 -> #DIV/0! | CX24: =SUM(CX4:CX21) -> 0 | CY24: =SUM(CY4:CY21) -> -1.3428482e+09 | CZ24: =SUM(CX24:CY24) -> -1.3428482e+09
B26: RSA | K26: =SUM(K14:K17) -> -1.0488234e+09
A28: iLease | B28: iLease | D28: 0.09 | E28: 0.29 | K28: =[1]Breakdown!$R$14 -> -295896.75

Sheet Sheet1
C4: Inland | D4: Coastal | E4: Namibia | F4: Zambia | G4: Central & Commercial | H4: Mozambique | I4: Botswana | J4: Ghana | K4: Public Sector | L4: Lesotho
C5: 1.5176873e+09 | D5: 5.8892194e+08 | E5: 2.2733804e+08 | F5: 1.8853358e+08 | G5: 1.275311e+08 | H5: 68987995 | I5: 93921956 | J5: 84460351 | K5: 57750145 | L5: 35801642

Sheet Coastal
A1: Value | B1: 2025/11/17 | C1: 2025/11/30 | D1: 2025/12/31 | E1: 2026/01/31 | F1: 2026/02/28 | G1: 2026/03/31 | H1: 2026/04/30 | I1: 2026/05/31 | J1: 2026/06/30 | K1: 2026/07/31 | L1: 2026/08/31 | M1: 2026/09/30 | N1: 2026/10/31 | O1: 2026/11/30 | P1: 2026/12/31 | Q1: 2027/01/31 | R1: 2027/02/28 | S1: 2027/03/31 | T1: 2027/04/30 | U1: 2027/05/31 | V1: 2027/06/30 | W1: 2027/07/31 | X1: 2027/08/31 | Y1: 2027/09/30 | Z1: 2027/10/31 | AA1: 2027/11/30 | AB1: 2027/12/31 | AC1: 2028/01/31 | AD1: 2028/02/29 | AE1: 2028/03/31 | AF1: 2028/04/30 | AG1: 2028/05/31 | AH1: 2028/06/30 | AI1: 2028/07/31 | AJ1: 2028/08/31 | AK1: 2028/09/30 | AL1: 2028/10/31 | AM1: 2028/11/30 | AN1: 2028/12/31 | AO1: 2029/01/31 | AP1: 2029/02/28 | AQ1: 2029/03/31 | AR1: 2029/04/30 | AS1: 2029/05/31 | AT1: 2029/06/30 | AU1: 2029/07/31 | AV1: 2029/08/31 | AW1: 2029/09/30 | AX1: 2029/10/31 | AY1: 2029/11/30 | AZ1: 2029/12/31 | BA1: 2030/01/31 | BB1: 2030/02/28 | BC1: 2030/03/31 | BD1: 2030/04/30 | BE1: 2030/05/31 | BF1: 2030/06/30 | BG1: 2030/07/31 | BH1: 2030/08/31 | BI1: 2030/09/30 | BJ1: 2030/10/31 | BK1: 2030/11/30 | BL1: 2030/12/31
A2: fml_count | B2: 2881 | C2: 2632 | D2: 2562 | E2: 2459 | F2: 2388 | G2: 2286 | H2: 2217 | I2: 2119 | J2: 2051 | K2: 1965 | L2: 1904 | M2: 1823 | N2: 1741 | O2: 1668 | P2: 1613 | Q2: 1556 | R2: 1503 | S2: 1452 | T2: 1396 | U2: 1349 | V2: 1282 | W2: 1221 | X2: 1141 | Y2: 1080 | Z2: 1011 | AA2: 969 | AB2: 929 | AC2: 893 | AD2: 867 | AE2: 827 | AF2: 775 | AG2: 734 | AH2: 654 | AI2: 590 | AJ2: 535 | AK2: 483 | AL2: 444 | AM2: 410 | AN2: 388 | AO2: 372 | AP2: 361 | AQ2: 339 | AR2: 319 | AS2: 306 | AT2: 285 | AU2: 271 | AV2: 246 | AW2: 226 | AX2: 188 | AY2: 152 | AZ2: 143 | BA2: 129 | BB2: 120 | BC2: 107 | BD2: 94 | BE2: 77 | BF2: 71 | BG2: 54 | BH2: 34 | BI2: 14 | BJ2: 1 | BK2: 1 | BL2: 1
A3: olmm_count | B3: 261 | C3: 228 | D3: 223 | E3: 220 | F3: 217 | G3: 215 | H3: 214 | I3: 214 | J3: 212 | K3: 209 | L3: 203 | M3: 199 | N3: 198 | O3: 194 | P3: 193 | Q3: 192 | R3: 192 | S3: 187 | T3: 187 | U3: 183 | V3: 182 | W3: 174 | X3: 170 | Y3: 162 | Z3: 152 | AA3: 145 | AB3: 137 | AC3: 137 | AD3: 133 | AE3: 126 | AF3: 124 | AG3: 124 | AH3: 124 | AI3: 106 | AJ3: 76 | AK3: 74 | AL3: 71 | AM3: 70 | AN3: 65 | AO3: 64 | AP3: 60 | AQ3: 58 | AR3: 49 | AS3: 49 | AT3: 31 | AU3: 27 | AV3: 24 | AW3: 22 | AX3: 19 | AY3: 12 | AZ3: 11 | BA3: 11 | BB3: 11 | BC3: 10 | BD3: 6 | BE3: 6 | BF3: 4 | BG3: 4 | BH3: 3 | BI3: 0 | BJ3: 0 | BK3: 0 | BL3: 0
A4: pl_count | B4: 0 | C4: 0 | D4: 0 | E4: 0 | F4: 0 | G4: 0 | H4: 0 | I4: 0 | J4: 0 | K4: 0 | L4: 0 | M4: 0 | N4: 0 | O4: 0 | P4: 0 | Q4: 0 | R4: 0 | S4: 0 | T4: 0 | U4: 0 | V4: 0 | W4: 0 | X4: 0 | Y4: 0 | Z4: 0 | AA4: 0 | AB4: 0 | AC4: 0 | AD4: 0 | AE4: 0 | AF4: 0 | AG4: 0 | AH4: 0 | AI4: 0 | AJ4: 0 | AK4: 0 | AL4: 0 | AM4: 0 | AN4: 0 | AO4: 0 | AP4: 0 | AQ4: 0 | AR4: 0 | AS4: 0 | AT4: 0 | AU4: 0 | AV4: 0 | AW4: 0 | AX4: 0 | AY4: 0 | AZ4: 0 | BA4: 0 | BB4: 0 | BC4: 0 | BD4: 0 | BE4: 0 | BF4: 0 | BG4: 0 | BH4: 0 | BI4: 0 | BJ4: 0 | BK4: 0 | BL4: 0
A5: revenue_p_m | B5: 36061930 | C5: 33082839 | D5: 32142524 | E5: 31181889 | F5: 30345711 | G5: 29362939 | H5: 28611786 | I5: 27625885 | J5: 26926776 | K5: 25859169 | L5: 25063300 | M5: 24086503 | N5: 23053629 | O5: 21972577 | P5: 21411828 | Q5: 20677346 | R5: 20128710 | S5: 19453017 | T5: 18879268 | U5: 18207134 | V5: 17487788 | W5: 16802731 | X5: 15813516 | Y5: 15044805 | Z5: 14187478 | AA5: 13627835 | AB5: 13084453 | AC5: 12654060 | AD5: 12345427 | AE5: 11765923 | AF5: 11031887 | AG5: 10596178 | AH5: 9643632.3 | AI5: 8769630.4 | AJ5: 7953162.5 | AK5: 7383519.5 | AL5: 6881624.7 | AM5: 6475984.4 | AN5: 6093890.2 | AO5: 5902986 | AP5: 5574913.3 | AQ5: 5232541.4 | AR5: 4930996.9 | AS5: 4813756.1 | AT5: 4417225.6 | AU5: 4168084.1 | AV5: 3933561.6 | AW5: 3663759.8 | AX5: 3094972.5 | AY5: 2261993.7 | AZ5: 2143196.8 | BA5: 2021146.1 | BB5: 1927906.9 | BC5: 1689825.6 | BD5: 1337312.2 | BE5: 1146751 | BF5: 1078940.8 | BG5: 919030.87 | BH5: 577944.97 | BI5: 226361.77 | BJ5: 20732.6 | BK5: 20732.6 | BL5: 20732.6
A6: depreciation_p_m | B6: 15557761 | C6: 14192955 | D6: 13761786 | E6: 13356959 | F6: 13010132 | G6: 12597135 | H6: 12296358 | I6: 11905224 | J6: 11609722 | K6: 11116415 | L6: 10771677 | M6: 10368483 | N6: 9927185.9 | O6: 9499474 | P6: 9260661.1 | Q6: 8939940.9 | R6: 8707843.6 | S6: 8430844.9 | T6: 8198805.8 | U6: 7930443.8 | V6: 7636049.4 | W6: 7335922.4 | X6: 6916964.6 | Y6: 6570661.2 | Z6: 6197157.8 | AA6: 5952174.5 | AB6: 5715975 | AC6: 5536616.9 | AD6: 5404755.9 | AE6: 5155379.4 | AF6: 4831070.5 | AG6: 4647540.4 | AH6: 4263536.7 | AI6: 3874547.5 | AJ6: 3524726.6 | AK6: 3274185.1 | AL6: 3078257.5 | AM6: 2887315.9 | AN6: 2697987.1 | AO6: 2624672.3 | AP6: 2444255 | AQ6: 2291205.2 | AR6: 2144014.8 | AS6: 2099922.7 | AT6: 1889910.8 | AU6: 1764433.9 | AV6: 1666231 | AW6: 1538816.3 | AX6: 1298525.3 | AY6: 947904.52 | AZ6: 894158.68 | BA6: 845497.02 | BB6: 807770.62 | BC6: 715347.27 | BD6: 535053.85 | BE6: 455543.68 | BF6: 427209.75 | BG6: 365925.55 | BH6: 229695.73 | BI6: 85040.7 | BJ6: 9595.63 | BK6: 9595.63 | BL6: 9595.63
A7: interest_p_m | B7: 9493757.9 | C7: 8821856.3 | D7: 8625812.1 | E7: 8428238.8 | F7: 8231344.9 | G7: 8005503.6 | H7: 7827256.4 | I7: 7584910.6 | J7: 7416294.5 | K7: 7154906 | L7: 6977845.5 | M7: 6714993.5 | N7: 6431954.2 | O7: 6172260.5 | P7: 6012246.3 | Q7: 5827482.6 | R7: 5679482.4 | S7: 5521293.8 | T7: 5376848.5 | U7: 5203879.5 | V7: 5012624.7 | W7: 4816410.6 | X7: 4527817.3 | Y7: 4307664.6 | Z7: 4087395.7 | AA7: 3939472.2 | AB7: 3798964.6 | AC7: 3689406.3 | AD7: 3596761.4 | AE7: 3439280.5 | AF7: 3252257 | AG7: 3128251.6 | AH7: 2812414.8 | AI7: 2545116.6 | AJ7: 2277292.2 | AK7: 2116358.5 | AL7: 1978468.9 | AM7: 1860500.1 | AN7: 1747379.2 | AO7: 1683225.3 | AP7: 1586443.4 | AQ7: 1485566.5 | AR7: 1393616 | AS7: 1356496.2 | AT7: 1252527.8 | AU7: 1181023.7 | AV7: 1110824.1 | AW7: 1034765.8 | AX7: 882361.93 | AY7: 659898.9 | AZ7: 624111.27 | BA7: 588005.02 | BB7: 563901.41 | BC7: 508224.37 | BD7: 393347.75 | BE7: 327684.06 | BF7: 304486.24 | BG7: 251532.84 | BH7: 160952.53 | BI7: 59097.82 | BJ7: 4359.75 | BK7: 4359.75 | BL7: 4359.75
A8: admin_p_m | B8: 2372533 | C8: 2129240.1 | D8: 2075837.2 | E8: 2000386.1 | F8: 1944090.6 | G8: 1867239.3 | H8: 1810511 | I8: 1736306.3 | J8: 1681394.3 | K8: 1607889.9 | L8: 1556572.3 | M8: 1479323.4 | N8: 1409131.2 | O8: 1336156.4 | P8: 1294251.8 | Q8: 1248996.2 | R8: 1212293.6 | S8: 1171211.6 | T8: 1135826.7 | U8: 1089945.9 | V8: 1047612.9 | W8: 1001932.3 | X8: 945125.05 | Y8: 889872.56 | Z8: 833823.62 | AA8: 801392.18 | AB8: 770269.5 | AC8: 747136.05 | AD8: 726640.29 | AE8: 687142.96 | AF8: 645728.82 | AG8: 615754.05 | AH8: 580956.29 | AI8: 539195.44 | AJ8: 495746.05 | AK8: 460174.47 | AL8: 422000.33 | AM8: 401930.24 | AN8: 376121.89 | AO8: 363836.25 | AP8: 339542.14 | AQ8: 309547.23 | AR8: 289819.36 | AS8: 281922.2 | AT8: 251451.37 | AU8: 231690.48 | AV8: 216235.15 | AW8: 197002.76 | AX8: 173598.38 | AY8: 141305.29 | AZ8: 132134.27 | BA8: 124413.11 | BB8: 119104.21 | BC8: 108025.22 | BD8: 76253.83 | BE8: 60198.15 | BF8: 54298.19 | BG8: 46184.59 | BH8: 29647.19 | BI8: 9207.35 | BJ8: 1612.18 | BK8: 1612.18 | BL8: 1612.18
A9: maint_prov_p_m | B9: 1.60234e+08 | C9: 1.3598408e+08 | D9: 1.3066213e+08 | E9: 1.2332277e+08 | F9: 1.1810245e+08 | G9: 1.1163895e+08 | H9: 1.0689369e+08 | I9: 1.0006904e+08 | J9: 95628431 | K9: 90200005 | L9: 85411121 | M9: 79196458 | N9: 74286959 | O9: 66302019 | P9: 63363116 | Q9: 59755860 | R9: 57177744 | S9: 54286012 | T9: 51932035 | U9: 49856115 | V9: 46303265 | W9: 44205408 | X9: 37990649 | Y9: 35328649 | Z9: 32250615 | AA9: 29983854 | AB9: 28480544 | AC9: 26793904 | AD9: 25842386 | AE9: 24190120 | AF9: 22264511 | AG9: 21336954 | AH9: 20070876 | AI9: 18792185 | AJ9: 15980965 | AK9: 14568941 | AL9: 11749143 | AM9: 10316667 | AN9: 9769579.8 | AO9: 9429804.9 | AP9: 9102478 | AQ9: 8590104.7 | AR9: 8143226.5 | AS9: 7878599.6 | AT9: 7544216.6 | AU9: 7290665.2 | AV9: 7067451.1 | AW9: 6805991.4 | AX9: 5152068.9 | AY9: 2332273.4 | AZ9: 2169310.3 | BA9: 1741086.1 | BB9: 1441928.7 | BC9: 1150733.2 | BD9: 1004815.7 | BE9: 846406.92 | BF9: 801913.24 | BG9: 685818.12 | BH9: 373960.44 | BI9: 179754.22 | BJ9: 83880.54 | BK9: 83880.54 | BL9: 83880.54
A10: maintenance_fund | B10: 78938053 | C10: 69690424 | D10: 67791557 | E10: 64561953 | F10: 62483442 | G10: 59258292 | H10: 56816527 | I10: 53778462 | J10: 51641485 | K10: 49300420 | L10: 47523296 | M10: 44685946 | N10: 42314862 | O10: 40769492 | P10: 39327722 | Q10: 37643750 | R10: 36064268 | S10: 34030355 | T10: 32625096 | U10: 31212720 | V10: 29104531 | W10: 27685743 | X10: 25633292 | Y10: 23985212 | Z10: 21999495 | AA10: 20869908 | AB10: 19674002 | AC10: 18530229 | AD10: 17816378 | AE10: 16537991 | AF10: 15295543 | AG10: 14517043 | AH10: 13388005 | AI10: 12382075 | AJ10: 11319871 | AK10: 10429764 | AL10: 9446049 | AM10: 8370755.8 | AN10: 7972633.7 | AO10: 7690144.5 | AP10: 7482503.3 | AQ10: 7007372.5 | AR10: 6684393.3 | AS10: 6466596.5 | AT10: 6170397 | AU10: 5935163.5 | AV10: 5720180.2 | AW10: 5491418.6 | AX10: 4150092.8 | AY10: 1961573.5 | AZ10: 1829701.7 | BA10: 1683825 | BB10: 1424172.3 | BC10: 1132976.8 | BD10: 992446.05 | BE10: 834415.5 | BF10: 789921.82 | BG10: 673826.7 | BH10: 371377.58 | BI10: 177171.36 | BJ10: 81297.68 | BK10: 81297.68 | BL10: 81297.68
A11: other_fee_p_m | B11: 1829676.3 | C11: 1733802.1 | D11: 1705774.4 | E11: 1649198.2 | F11: 1579019.7 | G11: 1507906.8 | H11: 1453151.9 | I11: 1402926.7 | J11: 1375728.4 | K11: 1323719.5 | L11: 1287867.4 | M11: 1252768.8 | N11: 1191144.6 | O11: 1127493.2 | P11: 1106252.1 | Q11: 1079040.9 | R11: 1060169.7 | S11: 992593.41 | T11: 935070.97 | U11: 862432.08 | V11: 834141.46 | W11: 800015.76 | X11: 756603.58 | Y11: 719284.31 | Z11: 678788.19 | AA11: 647069.15 | AB11: 604161.46 | AC11: 576188.56 | AD11: 559938.98 | AE11: 514921.18 | AF11: 469934.06 | AG11: 448782.45 | AH11: 343264.21 | AI11: 287038.6 | AJ11: 253613.32 | AK11: 237028.38 | AL11: 220133.82 | AM11: 208497.69 | AN11: 195222.69 | AO11: 176659.91 | AP11: 171860.57 | AQ11: 152701.14 | AR11: 143571.15 | AS11: 136620.2 | AT11: 120511.9 | AU11: 115252.94 | AV11: 103690.8 | AW11: 95184.12 | AX11: 78731.36 | AY11: 62551.4 | AZ11: 58621.24 | BA11: 52556.78 | BB11: 47736.29 | BC11: 42473.08 | BD11: 36705.34 | BE11: 31731.76 | BF11: 29840.61 | BG11: 18163.26 | BH11: 11814.61 | BI11: 4951.44 | BJ11: 505.01 | BK11: 505.01 | BL11: 505.01
A12: total_cost | B12: 1.3882377e+09 | C12: 1.2798702e+09 | D12: 1.2493307e+09 | E12: 1.2153497e+09 | F12: 1.18605e+09 | G12: 1.1515135e+09 | H12: 1.1252254e+09 | I12: 1.0888964e+09 | J12: 1.0636847e+09 | K12: 1.0248448e+09 | L12: 9.9784718e+08 | M12: 9.6116391e+08 | N12: 9.224789e+08 | O12: 8.8487091e+08 | P12: 8.6272007e+08 | Q12: 8.3717138e+08 | R12: 8.1688587e+08 | S12: 7.9436703e+08 | T12: 7.7436267e+08 | U12: 7.5115938e+08 | V12: 7.2460855e+08 | W12: 6.977536e+08 | X12: 6.5642659e+08 | Y12: 6.2527359e+08 | Z12: 5.9323268e+08 | AA12: 5.7220992e+08 | AB12: 5.5272706e+08 | AC12: 5.3691808e+08 | AD12: 5.2401565e+08 | AE12: 5.019789e+08 | AF12: 4.7470027e+08 | AG12: 4.5771929e+08 | AH12: 4.1507925e+08 | AI12: 3.7756793e+08 | AJ12: 3.4016077e+08 | AK12: 3.1710187e+08 | AL12: 2.9728162e+08 | AM12: 2.7863773e+08 | AN12: 2.6163201e+08 | AO12: 2.5291862e+08 | AP12: 2.376445e+08 | AQ12: 2.2308108e+08 | AR12: 2.0952263e+08 | AS12: 2.043406e+08 | AT12: 1.8837361e+08 | AU12: 1.7780432e+08 | AV12: 1.6795789e+08 | AW12: 1.5676084e+08 | AX12: 1.3337418e+08 | AY12: 98799557 | AZ12: 93428743 | BA12: 87637516 | BB12: 83893853 | BC12: 75429261 | BD12: 58268129 | BE12: 48873893 | BF12: 45631133 | BG12: 37616956 | BH12: 23968978 | BI12: 8929200.2 | BJ12: 806093.48 | BK12: 806093.48 | BL12: 806093.48
A13: nbv | B13: 1.0253164e+09 | C13: 9.7217275e+08 | D13: 9.4167693e+08 | E13: 9.1030274e+08 | F13: 8.810119e+08 | G13: 8.4941025e+08 | H13: 8.2252669e+08 | I13: 7.8990999e+08 | J13: 7.649016e+08 | K13: 7.3404573e+08 | L13: 7.100324e+08 | M13: 6.7945214e+08 | N13: 6.465822e+08 | O13: 6.1778319e+08 | P13: 5.9620401e+08 | Q13: 5.7303302e+08 | R13: 5.5251839e+08 | S13: 5.3228995e+08 | T13: 5.1305603e+08 | U13: 4.9194028e+08 | V13: 4.6925444e+08 | W13: 4.4697794e+08 | X13: 4.1786031e+08 | Y13: 3.9454996e+08 | Z13: 3.7229821e+08 | AA13: 3.5626916e+08 | AB13: 3.4071443e+08 | AC13: 3.2728099e+08 | AD13: 3.1517825e+08 | AE13: 2.9901777e+08 | AF13: 2.8102245e+08 | AG13: 2.6670642e+08 | AH13: 2.3471443e+08 | AI13: 2.1020163e+08 | AJ13: 1.8677178e+08 | AK13: 1.7172048e+08 | AL13: 1.5952025e+08 | AM13: 1.4869062e+08 | AN13: 1.3849033e+08 | AO13: 1.308244e+08 | AP13: 1.2330335e+08 | AQ13: 1.1446465e+08 | AR13: 1.0615103e+08 | AS13: 1.0122651e+08 | AT13: 93581456 | AU13: 87408917 | AV13: 80646460 | AW13: 74295904 | AX13: 63148512 | AY13: 48407863 | AZ13: 45229562 | BA13: 41857790 | BB13: 39706182 | BC13: 35647043 | BD13: 28394720 | BE13: 23182141 | BF13: 21158340 | BG13: 16367678 | BH13: 10445109 | BI13: 3787722.6 | BJ13: 76825.6 | BK13: 67229.97 | BL13: 57634.34
... A16: olmm_fleet_drop | B16: 0 | C16: 33 | D16: 5 | E16: 3 | F16: 3 | G16: 2 | H16: 1 | I16: 0 | J16: 2 | K16: 3 | L16: 6 | M16: 4 | N16: 1 | O16: 4 | P16: 1 | Q16: 1 | R16: 0 | S16: 5 | T16: 0 | U16: 4 | V16: 1 | W16: 8 | X16: 4 | Y16: 8 | Z16: 10 | AA16: 7 | AB16: 8 | AC16: 0 | AD16: 4 | AE16: 7 | AF16: 2 | AG16: 0 | AH16: 0 | AI16: 18 | AJ16: 30 | AK16: 2 | AL16: 3 | AM16: 1 | AN16: 5 | AO16: 1 | AP16: 4 | AQ16: 2 | AR16: 9 | AS16: 0 | AT16: 18 | AU16: 4 | AV16: 3 | AW16: 2 | AX16: 3 | AY16: 7 | AZ16: 1 | BA16: 0 | BB16: 0 | BC16: 1 | BD16: 4 | BE16: 0 | BF16: 2 | BG16: 0 | BH16: 1 | BI16: 3 | BJ16: 0 | BK16: 0 | BL16: 0

Sheet Public Sector_x000a_
A1: Value | B1: 2025/11/17 | C1: 2025/11/30 | D1: 2025/12/31 | E1: 2026/01/31 | F1: 2026/02/28 | G1: 2026/03/31 | H1: 2026/04/30 | I1: 2026/05/31 | J1: 2026/06/30 | K1: 2026/07/31 | L1: 2026/08/31 | M1: 2026/09/30 | N1: 2026/10/31 | O1: 2026/11/30 | P1: 2026/12/31 | Q1: 2027/01/31 | R1: 2027/02/28 | S1: 2027/03/31 | T1: 2027/04/30 | U1: 2027/05/31 | V1: 2027/06/30 | W1: 2027/07/31 | X1: 2027/08/31 | Y1: 2027/09/30 | Z1: 2027/10/31 | AA1: 2027/11/30 | AB1: 2027/12/31 | AC1: 2028/01/31 | AD1: 2028/02/29 | AE1: 2028/03/31 | AF1: 2028/04/30 | AG1: 2028/05/31 | AH1: 2028/06/30 | AI1: 2028/07/31 | AJ1: 2028/08/31 | AK1: 2028/09/30 | AL1: 2028/10/31 | AM1: 2028/11/30 | AN1: 2028/12/31 | AO1: 2029/01/31 | AP1: 2029/02/28 | AQ1: 2029/03/31 | AR1: 2029/04/30 | AS1: 2029/05/31 | AT1: 2029/06/30 | AU1: 2029/07/31 | AV1: 2029/08/31 | AW1: 2029/09/30 | AX1: 2029/10/31 | AY1: 2029/11/30 | AZ1: 2029/12/31 | BA1: 2030/01/31 | BB1: 2030/02/28 | BC1: 2030/03/31 | BD1: 2030/04/30 | BE1: 2030/05/31 | BF1: 2030/06/30 | BG1: 2030/07/31 | BH1: 2030/08/31 | BI1: 2030/09/30 | BJ1: 2030/10/31 | BK1: 2030/11/30 | BL1: 2030/12/31
A2: fml_count | B2: 314 | C2: 279 | D2: 274 | E2: 274 | F2: 274 | G2: 273 | H2: 268 | I2: 266 | J2: 259 | K2: 259 | L2: 254 | M2: 246 | N2: 240 | O2: 226 | P2: 186 | Q2: 174 | R2: 145 | S2: 145 | T2: 138 | U2: 125 | V2: 108 | W2: 107 | X2: 103 | Y2: 97 | Z2: 97 | AA2: 86 | AB2: 86 | AC2: 62 | AD2: 60 | AE2: 59 | AF2: 57 | AG2: 57 | AH2: 57 | AI2: 55 | AJ2: 54 | AK2: 52 | AL2: 52 | AM2: 51 | AN2: 51 | AO2: 51 | AP2: 51 | AQ2: 50 | AR2: 50 | AS2: 49 | AT2: 49 | AU2: 48 | AV2: 48 | AW2: 48 | AX2: 48 | AY2: 48 | AZ2: 48 | BA2: 48 | BB2: 48 | BC2: 47 | BD2: 47 | BE2: 34 | BF2: 34 | BG2: 18 | BH2: 7 | BI2: 3 | BJ2: 0 | BK2: 0 | BL2: 0
A3: olmm_count | B3: 110 | C3: 110 | D3: 110 | E3: 110 | F3: 110 | G3: 110 | H3: 110 | I3: 110 | J3: 110 | K3: 110 | L3: 110 | M3: 110 | N3: 110 | O3: 110 | P3: 110 | Q3: 110 | R3: 110 | S3: 110 | T3: 110 | U3: 110 | V3: 110 | W3: 110 | X3: 110 | Y3: 110 | Z3: 109 | AA3: 61 | AB3: 42 | AC3: 26 | AD3: 18 | AE3: 18 | AF3: 17 | AG3: 17 | AH3: 17 | AI3: 17 | AJ3: 17 | AK3: 17 | AL3: 17 | AM3: 17 | AN3: 17 | AO3: 17 | AP3: 17 | AQ3: 17 | AR3: 17 | AS3: 17 | AT3: 13 | AU3: 7 | AV3: 7 | AW3: 7 | AX3: 7 | AY3: 7 | AZ3: 7 | BA3: 7 | BB3: 7 | BC3: 7 | BD3: 7 | BE3: 7 | BF3: 7 | BG3: 7 | BH3: 5 | BI3: 5 | BJ3: 0 | BK3: 0 | BL3: 0
A4: pl_count | B4: 0 | C4: 0 | D4: 0 | E4: 0 | F4: 0 | G4: 0 | H4: 0 | I4: 0 | J4: 0 | K4: 0 | L4: 0 | M4: 0 | N4: 0 | O4: 0 | P4: 0 | Q4: 0 | R4: 0 | S4: 0 | T4: 0 | U4: 0 | V4: 0 | W4: 0 | X4: 0 | Y4: 0 | Z4: 0 | AA4: 0 | AB4: 0 | AC4: 0 | AD4: 0 | AE4: 0 | AF4: 0 | AG4: 0 | AH4: 0 | AI4: 0 | AJ4: 0 | AK4: 0 | AL4: 0 | AM4: 0 | AN4: 0 | AO4: 0 | AP4: 0 | AQ4: 0 | AR4: 0 | AS4: 0 | AT4: 0 | AU4: 0 | AV4: 0 | AW4: 0 | AX4: 0 | AY4: 0 | AZ4: 0 | BA4: 0 | BB4: 0 | BC4: 0 | BD4: 0 | BE4: 0 | BF4: 0 | BG4: 0 | BH4: 0 | BI4: 0 | BJ4: 0 | BK4: 0 | BL4: 0
A5: revenue_p_m | B5: 7049966 | C5: 6551310.2 | D5: 6420226 | E5: 6420226 | F5: 6420226 | G5: 6341819 | H5: 6282865.5 | I5: 6257564.9 | J5: 6213476.4 | K5: 6213476.4 | L5: 6156716.5 | M5: 6062334 | N5: 5997300.1 | O5: 5842132.9 | P5: 5483241.4 | Q5: 5388713.7 | R5: 5029625.1 | S5: 5029625.1 | T5: 4974806.6 | U5: 4814135.5 | V5: 4708468.6 | W5: 4702200.1 | X5: 4636753.8 | Y5: 4599418.4 | Z5: 4489992.5 | AA5: 3701987.5 | AB5: 3117244.7 | AC5: 2186503 | AD5: 2023010.2 | AE5: 2011053.6 | AF5: 1813085.3 | AG5: 1813085.3 | AH5: 1813085.3 | AI5: 1784969.9 | AJ5: 1771500.9 | AK5: 1742274.3 | AL5: 1742274.3 | AM5: 1734265.9 | AN5: 1734265.9 | AO5: 1734265.9 | AP5: 1734265.9 | AQ5: 1725783.2 | AR5: 1725783.2 | AS5: 1717953.4 | AT5: 1685331.4 | AU5: 1627900.8 | AV5: 1627900.8 | AW5: 1627900.8 | AX5: 1627900.8 | AY5: 1627900.8 | AZ5: 1627900.8 | BA5: 1627900.8 | BB5: 1627900.8 | BC5: 1609569 | BD5: 1609569 | BE5: 1529103.2 | BF5: 1529103.2 | BG5: 1077261.5 | BH5: 511622.63 | BI5: 334192.55 | BJ5: 0 | BK5: 0 | BL5: 0
A6: depreciation_p_m | B6: 3388650.3 | C6: 3183662 | D6: 3119800.8 | E6: 3119800.8 | F6: 3119800.8 | G6: 3075171.9 | H6: 3049257.6 | I6: 3038749.1 | J6: 3021586.4 | K6: 3021586.4 | L6: 2996909.4 | M6: 2953847.7 | N6: 2929303.7 | O6: 2860935.2 | P6: 2731247.4 | Q6: 2697817.6 | R6: 2563117.8 | S6: 2563117.8 | T6: 2543826.2 | U6: 2477693.6 | V6: 2442786.2 | W6: 2440444.9 | X6: 2414347.4 | Y6: 2401661.5 | Z6: 2346858.7 | AA6: 1938834.9 | AB6: 1563643.3 | AC6: 1101186.2 | AD6: 1009890.2 | AE6: 1004986.9 | AF6: 878906.23 | AG6: 878906.23 | AH6: 878906.23 | AI6: 871447.77 | AJ6: 865915.45 | AK6: 852816.41 | AL6: 852816.41 | AM6: 849813.42 | AN6: 849813.42 | AO6: 849813.42 | AP6: 849813.42 | AQ6: 846858.44 | AR6: 846858.44 | AS6: 844234.15 | AT6: 825317.51 | AU6: 793983.3 | AV6: 793983.3 | AW6: 793983.3 | AX6: 793983.3 | AY6: 793983.3 | AZ6: 793983.3 | BA6: 793983.3 | BB6: 793983.3 | BC6: 785655.3 | BD6: 785655.3 | BE6: 758858.75 | BF6: 758858.75 | BG6: 530012.77 | BH6: 251486.88 | BI6: 165777.86 | BJ6: 0 | BK6: 0 | BL6: 0
A7: interest_p_m | B7: 2213008.6 | C7: 2091347.6 | D7: 2065873.8 | E7: 2065873.8 | F7: 2065873.8 | G7: 2052564.1 | H7: 2032300.9 | I7: 2022702.9 | J7: 2009723 | K7: 2009723 | L7: 1992097.4 | M7: 1963392.2 | N7: 1937965.3 | O7: 1890167.4 | P7: 1793842 | Q7: 1761361.9 | R7: 1657957.5 | S7: 1657957.5 | T7: 1640033.5 | U7: 1589796.2 | V7: 1550725.2 | W7: 1548760 | X7: 1531292.5 | Y7: 1518189.8 | Z7: 1485538.8 | AA7: 1217307.7 | AB7: 1072523.2 | AC7: 729347.8 | AD7: 673716.1 | AE7: 669466.96 | AF7: 610424.49 | AG7: 610424.49 | AH7: 610424.49 | AI7: 602928.35 | AJ7: 598013.95 | AK7: 588382.21 | AL7: 588382.21 | AM7: 585848.59 | AN7: 585848.59 | AO7: 585848.59 | AP7: 585848.59 | AQ7: 583277.52 | AR7: 583277.52 | AS7: 580655.73 | AT7: 570498.37 | AU7: 552691.82 | AV7: 552691.82 | AW7: 552691.82 | AX7: 552691.82 | AY7: 552691.82 | AZ7: 552691.82 | BA7: 552691.82 | BB7: 552691.82 | BC7: 545619.1 | BD7: 545619.1 | BE7: 518411.48 | BF7: 518411.48 | BG7: 357620.6 | BH7: 166121.09 | BI7: 105832.33 | BJ7: 0 | BK7: 0 | BL7: 0
A8: admin_p_m | B8: 344051.75 | C8: 326133.69 | D8: 318953.4 | E8: 318953.4 | F8: 318953.4 | G8: 314761.61 | H8: 309650.61 | I8: 307983.14 | J8: 304650.56 | K8: 304650.56 | L8: 300430.52 | M8: 292507.44 | N8: 286669.03 | O8: 273796.73 | P8: 265012.43 | Q8: 258929.3 | R8: 243540.19 | S8: 243540.19 | T8: 238870.55 | U8: 228798.06 | V8: 218854.49 | W8: 218348.06 | X8: 213940.22 | Y8: 210572.22 | Z8: 210542.78 | AA8: 180121.16 | AB8: 161470.19 | AC8: 90019.79 | AD8: 79970.17 | AE8: 79497.72 | AF8: 78453.95 | AG8: 78453.95 | AH8: 78453.95 | AI8: 76608.83 | AJ8: 75300.66 | AK8: 72574.24 | AL8: 72574.24 | AM8: 71904.73 | AN8: 71904.73 | AO8: 71904.73 | AP8: 71904.73 | AQ8: 71228.32 | AR8: 71228.32 | AS8: 70590.84 | AT8: 67602.84 | AU8: 62444.02 | AV8: 62444.02 | AW8: 62444.02 | AX8: 62444.02 | AY8: 62444.02 | AZ8: 62444.02 | BA8: 62444.02 | BB8: 62444.02 | BC8: 60525.56 | BD8: 60525.56 | BE8: 53291 | BF8: 53291 | BG8: 44387.21 | BH8: 25519.99 | BI8: 22015.23 | BJ8: 0 | BK8: 0 | BL8: 0
A9: maint_prov_p_m | B9: 11157226 | C9: 7886475.4 | D9: 7547265.1 | E9: 7547265.1 | F9: 7547265.1 | G9: 7477371.1 | H9: 7300981.1 | I9: 7171862.6 | J9: 6876188.3 | K9: 6876188.3 | L9: 6595062.3 | M9: 6172350.3 | N9: 5917249 | O9: 5254291.9 | P9: 4435114.4 | Q9: 4153001 | R9: 3284301.1 | S9: 3284301.1 | T9: 2966062.3 | U9: 2523687.6 | V9: 1843511.9 | W9: 1813553.3 | X9: 1745653.9 | Y9: 1524726.4 | Z9: 1524726.4 | AA9: 1323198.8 | AB9: 1323198.8 | AC9: 922998.55 | AD9: 896483.35 | AE9: 889070.35 | AF9: 867220.97 | AG9: 867220.97 | AH9: 867220.97 | AI9: 849335.97 | AJ9: 817345.55 | AK9: 736869.35 | AL9: 736869.35 | AM9: 718627.1 | AN9: 718627.1 | AO9: 718627.1 | AP9: 718627.1 | AQ9: 703881.1 | AR9: 703881.1 | AS9: 692882.35 | AT9: 692882.35 | AU9: 683666.1 | AV9: 683666.1 | AW9: 683666.1 | AX9: 683666.1 | AY9: 683666.1 | AZ9: 683666.1 | BA9: 683666.1 | BB9: 683666.1 | BC9: 679268.7 | BD9: 679268.7 | BE9: 601567.41 | BF9: 601567.41 | BG9: 351594.61 | BH9: 126363.88 | BI9: 46795.96 | BJ9: 0 | BK9: 0 | BL9: 0
A10: maintenance_fund | B10: 6444005.2 | C10: 5648770.3 | D10: 5480805.9 | E10: 5480805.9 | F10: 5480805.9 | G10: 5598817.7 | H10: 5423232.7 | I10: 5354431.5 | J10: 5119310.8 | K10: 5119310.8 | L10: 4918105.5 | M10: 4594974.7 | N10: 4431746.4 | O10: 3996060 | P10: 3545423.5 | Q10: 3395673.8 | R10: 2645367.2 | S10: 2645367.2 | T10: 2498440.1 | U10: 2255351.7 | V10: 1602127.2 | W10: 1572168.6 | X10: 1504269.1 | Y10: 1401602.3 | Z10: 1401602.3 | AA10: 1259375.5 | AB10: 1259375.5 | AC10: 869030.43 | AD10: 853709.33 | AE10: 846296.33 | AF10: 827980.75 | AG10: 827980.75 | AH10: 827980.75 | AI10: 810095.75 | AJ10: 808361.44 | AK10: 736869.35 | AL10: 736869.35 | AM10: 718627.1 | AN10: 718627.1 | AO10: 718627.1 | AP10: 718627.1 | AQ10: 703881.1 | AR10: 703881.1 | AS10: 692882.35 | AT10: 692882.35 | AU10: 683666.1 | AV10: 683666.1 | AW10: 683666.1 | AX10: 683666.1 | AY10: 683666.1 | AZ10: 683666.1 | BA10: 683666.1 | BB10: 683666.1 | BC10: 679268.7 | BD10: 679268.7 | BE10: 601567.41 | BF10: 601567.41 | BG10: 351594.61 | BH10: 126363.88 | BI10: 46795.96 | BJ10: 0 | BK10: 0 | BL10: 0
A11: other_fee_p_m | B11: 573371.48 | C11: 497011.93 | D11: 471865.46 | E11: 471865.46 | F11: 471865.46 | G11: 457706.95 | H11: 455731.95 | I11: 455167.61 | J11: 451761.49 | K11: 451761.49 | L11: 448288.46 | M11: 444539.9 | N11: 442209.97 | O11: 436204.97 | P11: 341501.29 | Q11: 328277.57 | R11: 257079.75 | S11: 257079.75 | T11: 254412.33 | U11: 236467.67 | V11: 233644.2 | W11: 233258.53 | X11: 220568.49 | Y11: 219280.7 | Z11: 197337.97 | AA11: 131169.89 | AB11: 85054.09 | AC11: 68256.15 | AD11: 64392.15 | AE11: 63913.78 | AF11: 55233.66 | AG11: 55233.66 | AH11: 55233.66 | AI11: 47918.99 | AJ11: 47658.96 | AK11: 46870.2 | AL11: 46870.2 | AM11: 46471.2 | AN11: 46471.2 | AO11: 46471.2 | AP11: 46471.2 | AQ11: 46034.2 | AR11: 46034.2 | AS11: 45659.2 | AT11: 45099.2 | AU11: 43811.45 | AV11: 43811.45 | AW11: 43811.45 | AX11: 43811.45 | AY11: 43811.45 | AZ11: 43811.45 | BA11: 43811.45 | BB11: 43811.45 | BC11: 43287.43 | BD11: 43287.43 | BE11: 36811.19 | BF11: 36811.19 | BG11: 33504.67 | BH11: 18574.05 | BI11: 17169.15 | BJ11: 0 | BK11: 0 | BL11: 0
A12: total_cost | B12: 2.8348862e+08 | C12: 2.6722773e+08 | D12: 2.6350835e+08 | E12: 2.6350835e+08 | F12: 2.6350835e+08 | G12: 2.6141245e+08 | H12: 2.5885694e+08 | I12: 2.5759916e+08 | J12: 2.5589209e+08 | K12: 2.5589209e+08 | L12: 2.5363e+08 | M12: 2.4987748e+08 | N12: 2.4670996e+08 | O12: 2.4053389e+08 | P12: 2.2653895e+08 | Q12: 2.2229357e+08 | R12: 2.0881909e+08 | S12: 2.0881909e+08 | T12: 2.0652659e+08 | U12: 1.9991507e+08 | V12: 1.9494323e+08 | W12: 1.9469002e+08 | X12: 1.9248608e+08 | Y12: 1.9080206e+08 | Z12: 1.8726856e+08 | AA12: 1.5750238e+08 | AB12: 1.3754235e+08 | AC12: 99259016 | AD12: 93024621 | AE12: 92509212 | AF12: 86196290 | AG12: 86196290 | AH12: 86196290 | AI12: 85273722 | AJ12: 84619636 | AK12: 83256418 | AL12: 83256418 | AM12: 82921661 | AN12: 82921661 | AO12: 82921661 | AP12: 82921661 | AQ12: 82583452 | AR12: 82583452 | AS12: 82264711 | AT12: 80770711 | AU12: 78191298 | AV12: 78191298 | AW12: 78191298 | AX12: 78191298 | AY12: 78191298 | AZ12: 78191298 | BA12: 78191298 | BB12: 78191298 | BC12: 77232063 | BD12: 77232063 | BE12: 73614761 | BF12: 73614761 | BG12: 50736725 | BH12: 23541755 | BI12: 14966188 | BJ12: 0 | BK12: 0 | BL12: 0
A13: nbv | B13: 2.3492864e+08 | C13: 2.2742121e+08 | D13: 2.2281717e+08 | E13: 2.1969736e+08 | F13: 2.1657756e+08 | G13: 2.1296851e+08 | H13: 2.0824483e+08 | I13: 2.0448067e+08 | J13: 2.0054717e+08 | K13: 1.9752559e+08 | L13: 1.9331297e+08 | M13: 1.8828522e+08 | N13: 1.8325398e+08 | O13: 1.7663585e+08 | P13: 1.6449798e+08 | Q13: 1.5903259e+08 | R13: 1.4793706e+08 | S13: 1.4537394e+08 | T13: 1.4140118e+08 | U13: 1.3508832e+08 | V13: 1.2948613e+08 | W13: 1.2690017e+08 | X13: 1.2298684e+08 | Y13: 1.1955423e+08 | Z13: 1.1553717e+08 | AA13: 97973503 | AB13: 89460805 | AC13: 66241213 | AD13: 62184434 | AE13: 60811139 | AF13: 57906052 | AG13: 57027146 | AH13: 56148239 | AI13: 54611663 | AJ13: 53384875 | AK13: 51941684 | AL13: 51088867 | AM13: 50045437 | AN13: 49195623 | AO13: 48345810 | AP13: 47495996 | AQ13: 46446859 | AR13: 45600000 | AS13: 44560367 | AT13: 43111215 | AU13: 41210526 | AV13: 40416543 | AW13: 39622559 | AX13: 38828576 | AY13: 38034593 | AZ13: 37240609 | BA13: 36446626 | BB13: 35652643 | BC13: 34399105 | BD13: 33613449 | BE13: 30795896 | BF13: 30037037 | BG13: 20130901 | BH13: 8965622.5 | BI13: 5281111.9 | BJ13: 0 | BK13: 0 | BL13: 0
... A16: olmm_fleet_drop | B16: 0 | C16: 0 | D16: 0 | E16: 0 | F16: 0 | G16: 0 | H16: 0 | I16: 0 | J16: 0 | K16: 0 | L16: 0 | M16: 0 | N16: 0 | O16: 0 | P16: 0 | Q16: 0 | R16: 0 | S16: 0 | T16: 0 | U16: 0 | V16: 0 | W16: 0 | X16: 0 | Y16: 0 | Z16: 1 | AA16: 48 | AB16: 19 | AC16: 16 | AD16: 8 | AE16: 0 | AF16: 1 | AG16: 0 | AH16: 0 | AI16: 0 | AJ16: 0 | AK16: 0 | AL16: 0 | AM16: 0 | AN16: 0 | AO16: 0 | AP16: 0 | AQ16: 0 | AR16: 0 | AS16: 0 | AT16: 4 | AU16: 6 | AV16: 0 | AW16: 0 | AX16: 0 | AY16: 0 | AZ16: 0 | BA16: 0 | BB16: 0 | BC16: 0 | BD16: 0 | BE16: 0 | BF16: 0 | BG16: 0 | BH16: 2 | BI16: 0 | BJ16: 5 | BK16: 0 | BL16: 0

Sheet Legal
A1: Value | B1: 2025/11/17 | C1: 2025/11/30 | D1: 2025/12/31 | E1: 2026/01/31 | F1: 2026/02/28 | G1: 2026/03/31 | H1: 2026/04/30 | I1: 2026/05/31 | J1: 2026/06/30 | K1: 2026/07/31 | L1: 2026/08/31 | M1: 2026/09/30 | N1: 2026/10/31 | O1: 2026/11/30 | P1: 2026/12/31 | Q1: 2027/01/31 | R1: 2027/02/28 | S1: 2027/03/31 | T1: 2027/04/30 | U1: 2027/05/31 | V1: 2027/06/30 | W1: 2027/07/31 | X1: 2027/08/31 | Y1: 2027/09/30 | Z1: 2027/10/31 | AA1: 2027/11/30 | AB1: 2027/12/31 | AC1: 2028/01/31 | AD1: 2028/02/29 | AE1: 2028/03/31 | AF1: 2028/04/30 | AG1: 2028/05/31 | AH1: 2028/06/30 | AI1: 2028/07/31 | AJ1: 2028/08/31 | AK1: 2028/09/30 | AL1: 2028/10/31 | AM1: 2028/11/30 | AN1: 2028/12/31 | AO1: 2029/01/31 | AP1: 2029/02/28 | AQ1: 2029/03/31 | AR1: 2029/04/30 | AS1: 2029/05/31 | AT1: 2029/06/30 | AU1: 2029/07/31 | AV1: 2029/08/31 | AW1: 2029/09/30 | AX1: 2029/10/31 | AY1: 2029/11/30 | AZ1: 2029/12/31 | BA1: 2030/01/31 | BB1: 2030/02/28 | BC1: 2030/03/31 | BD1: 2030/04/30 | BE1: 2030/05/31 | BF1: 2030/06/30 | BG1: 2030/07/31 | BH1: 2030/08/31 | BI1: 2030/09/30 | BJ1: 2030/10/31 | BK1: 2030/11/30 | BL1: 2030/12/31
A2: fml_count | B2: 21 | C2: 16 | D2: 16 | E2: 16 | F2: 16 | G2: 16 | H2: 16 | I2: 15 | J2: 13 | K2: 13 | L2: 13 | M2: 13 | N2: 13 | O2: 13 | P2: 13 | Q2: 13 | R2: 13 | S2: 13 | T2: 13 | U2: 12 | V2: 12 | W2: 12 | X2: 12 | Y2: 12 | Z2: 11 | AA2: 9 | AB2: 9 | AC2: 9 | AD2: 9 | AE2: 9 | AF2: 6 | AG2: 6 | AH2: 6 | AI2: 6 | AJ2: 6 | AK2: 5 | AL2: 0 | AM2: 0 | AN2: 0 | AO2: 0 | AP2: 0 | AQ2: 0 | AR2: 0 | AS2: 0 | AT2: 0 | AU2: 0 | AV2: 0 | AW2: 0 | AX2: 0 | AY2: 0 | AZ2: 0 | BA2: 0 | BB2: 0 | BC2: 0 | BD2: 0 | BE2: 0 | BF2: 0 | BG2: 0 | BH2: 0 | BI2: 0 | BJ2: 0 | BK2: 0 | BL2: 0
A3: olmm_count | B3: 13 | C3: 13 | D3: 13 | E3: 13 | F3: 13 | G3: 13 | H3: 13 | I3: 13 | J3: 13 | K3: 13 | L3: 13 | M3: 13 | N3: 13 | O3: 13 | P3: 13 | Q3: 13 | R3: 13 | S3: 13 | T3: 13 | U3: 13 | V3: 13 | W3: 12 | X3: 12 | Y3: 12 | Z3: 12 | AA3: 12 | AB3: 12 | AC3: 12 | AD3: 12 | AE3: 11 | AF3: 11 | AG3: 11 | AH3: 8 | AI3: 8 | AJ3: 7 | AK3: 7 | AL3: 0 | AM3: 0 | AN3: 0 | AO3: 0 | AP3: 0 | AQ3: 0 | AR3: 0 | AS3: 0 | AT3: 0 | AU3: 0 | AV3: 0 | AW3: 0 | AX3: 0 | AY3: 0 | AZ3: 0 | BA3: 0 | BB3: 0 | BC3: 0 | BD3: 0 | BE3: 0 | BF3: 0 | BG3: 0 | BH3: 0 | BI3: 0 | BJ3: 0 | BK3: 0 | BL3: 0
A4: pl_count | B4: 1 | C4: 1 | D4: 1 | E4: 1 | F4: 1 | G4: 1 | H4: 1 | I4: 1 | J4: 1 | K4: 1 | L4: 1 | M4: 1 | N4: 1 | O4: 1 | P4: 1 | Q4: 1 | R4: 1 | S4: 1 | T4: 1 | U4: 1 | V4: 0 | W4: 0 | X4: 0 | Y4: 0 | Z4: 0 | AA4: 0 | AB4: 0 | AC4: 0 | AD4: 0 | AE4: 0 | AF4: 0 | AG4: 0 | AH4: 0 | AI4: 0 | AJ4: 0 | AK4: 0 | AL4: 0 | AM4: 0 | AN4: 0 | AO4: 0 | AP4: 0 | AQ4: 0 | AR4: 0 | AS4: 0 | AT4: 0 | AU4: 0 | AV4: 0 | AW4: 0 | AX4: 0 | AY4: 0 | AZ4: 0 | BA4: 0 | BB4: 0 | BC4: 0 | BD4: 0 | BE4: 0 | BF4: 0 | BG4: 0 | BH4: 0 | BI4: 0 | BJ4: 0 | BK4: 0 | BL4: 0
A5: revenue_p_m | B5: 1143088.2 | C5: 1077239.1 | D5: 1077239.1 | E5: 1077239.1 | F5: 1077239.1 | G5: 1077239.1 | H5: 1077239.1 | I5: 1070873.8 | J5: 1050622 | K5: 1050622 | L5: 1050622 | M5: 1050622 | N5: 1050622 | O5: 1050622 | P5: 1050622 | Q5: 1050622 | R5: 1050622 | S5: 1050622 | T5: 1050622 | U5: 1001804.7 | V5: 971277.04 | W5: 939150.44 | X5: 939150.44 | Y5: 939150.44 | Z5: 898985.5 | AA5: 810905.26 | AB5: 810905.26 | AC5: 810905.26 | AD5: 810905.26 | AE5: 775833.83 | AF5: 634142.82 | AG5: 634142.82 | AH5: 540308.78 | AI5: 540308.78 | AJ5: 503443.03 | AK5: 446026.66 | AL5: 0 | AM5: 0 | AN5: 0 | AO5: 0 | AP5: 0 | AQ5: 0 | AR5: 0 | AS5: 0 | AT5: 0 | AU5: 0 | AV5: 0 | AW5: 0 | AX5: 0 | AY5: 0 | AZ5: 0 | BA5: 0 | BB5: 0 | BC5: 0 | BD5: 0 | BE5: 0 | BF5: 0 | BG5: 0 | BH5: 0 | BI5: 0 | BJ5: 0 | BK5: 0 | BL5: 0
A6: depreciation_p_m | B6: 538429.12 | C6: 508756.44 | D6: 508756.44 | E6: 508756.44 | F6: 508756.44 | G6: 508756.44 | H6: 508756.44 | I6: 506146.12 | J6: 498876.03 | K6: 498876.03 | L6: 498876.03 | M6: 498876.03 | N6: 498876.03 | O6: 498876.03 | P6: 498876.03 | Q6: 498876.03 | R6: 498876.03 | S6: 498876.03 | T6: 498876.03 | U6: 480907.23 | V6: 464959.31 | W6: 446297.21 | X6: 446297.21 | Y6: 446297.21 | Z6: 427987.89 | AA6: 389855.83 | AB6: 389855.83 | AC6: 389855.83 | AD6: 389855.83 | AE6: 366777 | AF6: 311091.68 | AG6: 311091.68 | AH6: 257261.3 | AI6: 257261.3 | AJ6: 234654.33 | AK6: 208590.27 | AL6: 0 | AM6: 0 | AN6: 0 | AO6: 0 | AP6: 0 | AQ6: 0 | AR6: 0 | AS6: 0 | AT6: 0 | AU6: 0 | AV6: 0 | AW6: 0 | AX6: 0 | AY6: 0 | AZ6: 0 | BA6: 0 | BB6: 0 | BC6: 0 | BD6: 0 | BE6: 0 | BF6: 0 | BG6: 0 | BH6: 0 | BI6: 0 | BJ6: 0 | BK6: 0 | BL6: 0
A7: interest_p_m | B7: 336435.15 | C7: 319299.91 | D7: 319299.91 | E7: 319299.91 | F7: 319299.91 | G7: 319299.91 | H7: 319299.91 | I7: 318056.02 | J7: 312204.94 | K7: 312204.94 | L7: 312204.94 | M7: 312204.94 | N7: 312204.94 | O7: 312204.94 | P7: 312204.94 | Q7: 312204.94 | R7: 312204.94 | S7: 312204.94 | T7: 312204.94 | U7: 300214.64 | V7: 293519.01 | W7: 283079.88 | X7: 283079.88 | Y7: 283079.88 | Z7: 270003.57 | AA7: 244040.01 | AB7: 244040.01 | AC7: 244040.01 | AD7: 244040.01 | AE7: 234669.41 | AF7: 194139.27 | AG7: 194139.27 | AH7: 163498.29 | AI7: 163498.29 | AJ7: 153901.51 | AK7: 138195.71 | AL7: 0 | AM7: 0 | AN7: 0 | AO7: 0 | AP7: 0 | AQ7: 0 | AR7: 0 | AS7: 0 | AT7: 0 | AU7: 0 | AV7: 0 | AW7: 0 | AX7: 0 | AY7: 0 | AZ7: 0 | BA7: 0 | BB7: 0 | BC7: 0 | BD7: 0 | BE7: 0 | BF7: 0 | BG7: 0 | BH7: 0 | BI7: 0 | BJ7: 0 | BK7: 0 | BL7: 0
A8: admin_p_m | B8: 89535.3 | C8: 86290.88 | D8: 86290.88 | E8: 86290.88 | F8: 86290.88 | G8: 86290.88 | H8: 86290.88 | I8: 85864.37 | J8: 84197.19 | K8: 84197.19 | L8: 84197.19 | M8: 84197.19 | N8: 84197.19 | O8: 84197.19 | P8: 84197.19 | Q8: 84197.19 | R8: 84197.19 | S8: 84197.19 | T8: 84197.19 | U8: 80592.6 | V8: 78614.61 | W8: 75729.24 | X8: 75729.24 | Y8: 75729.24 | Z8: 74152.47 | AA8: 70998.93 | AB8: 70998.93 | AC8: 70998.93 | AD8: 70998.93 | AE8: 68746.93 | AF8: 57185.53 | AG8: 57185.53 | AH8: 47886.85 | AI8: 47886.85 | AJ8: 43594.85 | AK8: 39127.08 | AL8: 0 | AM8: 0 | AN8: 0 | AO8: 0 | AP8: 0 | AQ8: 0 | AR8: 0 | AS8: 0 | AT8: 0 | AU8: 0 | AV8: 0 | AW8: 0 | AX8: 0 | AY8: 0 | AZ8: 0 | BA8: 0 | BB8: 0 | BC8: 0 | BD8: 0 | BE8: 0 | BF8: 0 | BG8: 0 | BH8: 0 | BI8: 0 | BJ8: 0 | BK8: 0 | BL8: 0
A9: maint_prov_p_m | B9: 7167449.7 | C9: 6183536 | D9: 6183536 | E9: 6183536 | F9: 6183536 | G9: 6183536 | H9: 6183536 | I9: 6103862 | J9: 5957945.9 | K9: 5957945.9 | L9: 5957945.9 | M9: 5957945.9 | N9: 5957945.9 | O9: 5957945.9 | P9: 5957945.9 | Q9: 5957945.9 | R9: 5957945.9 | S9: 5957945.9 | T9: 5957945.9 | U9: 5345059.6 | V9: 5259965 | W9: 5259965 | X9: 5259965 | Y9: 5259965 | Z9: 4663159.8 | AA9: 3430993.4 | AB9: 3430993.4 | AC9: 3430993.4 | AD9: 3430993.4 | AE9: 3430993.4 | AF9: 2013933.7 | AG9: 2013933.7 | AH9: 2013933.7 | AI9: 2013933.7 | AJ9: 2013933.7 | AK9: 1866111.3 | AL9: 0 | AM9: 0 | AN9: 0 | AO9: 0 | AP9: 0 | AQ9: 0 | AR9: 0 | AS9: 0 | AT9: 0 | AU9: 0 | AV9: 0 | AW9: 0 | AX9: 0 | AY9: 0 | AZ9: 0 | BA9: 0 | BB9: 0 | BC9: 0 | BD9: 0 | BE9: 0 | BF9: 0 | BG9: 0 | BH9: 0 | BI9: 0 | BJ9: 0 | BK9: 0 | BL9: 0
A10: maintenance_fund | B10: 3833860.1 | C10: 3055732.4 | D10: 3055732.4 | E10: 3055732.4 | F10: 3055732.4 | G10: 3055732.4 | H10: 3055732.4 | I10: 3025502.8 | J10: 2913747 | K10: 2913747 | L10: 2913747 | M10: 2913747 | N10: 2913747 | O10: 2913747 | P10: 2913747 | Q10: 2913747 | R10: 2913747 | S10: 2913747 | T10: 2913747 | U10: 2668292.8 | V10: 2595366.9 | W10: 2595366.9 | X10: 2595366.9 | Y10: 2595366.9 | Z10: 2355904.8 | AA10: 1828071.6 | AB10: 1828071.6 | AC10: 1828071.6 | AD10: 1828071.6 | AE10: 1828071.6 | AF10: 1068754.4 | AG10: 1068754.4 | AH10: 1068754.4 | AI10: 1068754.4 | AJ10: 1068754.4 | AK10: 936108.41 | AL10: 0 | AM10: 0 | AN10: 0 | AO10: 0 | AP10: 0 | AQ10: 0 | AR10: 0 | AS10: 0 | AT10: 0 | AU10: 0 | AV10: 0 | AW10: 0 | AX10: 0 | AY10: 0 | AZ10: 0 | BA10: 0 | BB10: 0 | BC10: 0 | BD10: 0 | BE10: 0 | BF10: 0 | BG10: 0 | BH10: 0 | BI10: 0 | BJ10: 0 | BK10: 0 | BL10: 0
A11: other_fee_p_m | B11: 15664.88 | C11: 14343.73 | D11: 14343.73 | E11: 14343.73 | F11: 14343.73 | G11: 14343.73 | H11: 14343.73 | I11: 14156.14 | J11: 13780.96 | K11: 13780.96 | L11: 13780.96 | M11: 13780.96 | N11: 13780.96 | O11: 13780.96 | P11: 13780.96 | Q11: 13780.96 | R11: 13780.96 | S11: 13780.96 | T11: 13780.96 | U11: 13119.91 | V11: 9555.07 | W11: 9415.07 | X11: 9415.07 | Y11: 9415.07 | Z11: 8756.53 | AA11: 7439.45 | AB11: 7439.45 | AC11: 7439.45 | AD11: 7439.45 | AE11: 7069.45 | AF11: 5086.3 | AG11: 5086.3 | AH11: 5022.3 | AI11: 5022.3 | AJ11: 4652.3 | AK11: 4032.3 | AL11: 0 | AM11: 0 | AN11: 0 | AO11: 0 | AP11: 0 | AQ11: 0 | AR11: 0 | AS11: 0 | AT11: 0 | AU11: 0 | AV11: 0 | AW11: 0 | AX11: 0 | AY11: 0 | AZ11: 0 | BA11: 0 | BB11: 0 | BC11: 0 | BD11: 0 | BE11: 0 | BF11: 0 | BG11: 0 | BH11: 0 | BI11: 0 | BJ11: 0 | BK11: 0 | BL11: 0
A12: total_cost | B12: 48338284 | C12: 45651380 | D12: 45651380 | E12: 45651380 | F12: 45651380 | G12: 45651380 | H12: 45651380 | I12: 45438121 | J12: 44624528 | K12: 44624528 | L12: 44624528 | M12: 44624528 | N12: 44624528 | O12: 44624528 | P12: 44624528 | Q12: 44624528 | R12: 44624528 | S12: 44624528 | T12: 44624528 | U12: 42822230 | V12: 41852246 | W12: 40988396 | X12: 40988396 | Y12: 40988396 | Z12: 39120265 | AA12: 35384002 | AB12: 35384002 | AC12: 35384002 | AD12: 35384002 | AE12: 33768002 | AF12: 28017298 | AG12: 28017298 | AH12: 23378624 | AI12: 23378624 | AJ12: 21742624 | AK12: 19508739 | AL12: 0 | AM12: 0 | AN12: 0 | AO12: 0 | AP12: 0 | AQ12: 0 | AR12: 0 | AS12: 0 | AT12: 0 | AU12: 0 | AV12: 0 | AW12: 0 | AX12: 0 | AY12: 0 | AZ12: 0 | BA12: 0 | BB12: 0 | BC12: 0 | BD12: 0 | BE12: 0 | BF12: 0 | BG12: 0 | BH12: 0 | BI12: 0 | BJ12: 0 | BK12: 0 | BL12: 0
A13: nbv | B13: 32968629 | C13: 32432882 | D13: 31924126 | E13: 31415369 | F13: 30906613 | G13: 30397856 | H13: 29889100 | I13: 29289770 | J13: 28360158 | K13: 27861282 | L13: 27362406 | M13: 26863530 | N13: 26364654 | O13: 25865778 | P13: 25366902 | Q13: 24868026 | R13: 24369150 | S13: 23870274 | T13: 23371398 | U13: 22130383 | V13: 21237714 | W13: 20397577 | X13: 19951279 | Y13: 19504982 | Z13: 18294262 | AA13: 16417934 | AB13: 16028078 | AC13: 15638223 | AD13: 15248367 | AE13: 14497422 | AF13: 11698980 | AG13: 11387889 | AH13: 9649143.3 | AI13: 9391882 | AJ13: 8774003.5 | AK13: 7530475 | AL13: 0 | AM13: 0 | AN13: 0 | AO13: 0 | AP13: 0 | AQ13: 0 | AR13: 0 | AS13: 0 | AT13: 0 | AU13: 0 | AV13: 0 | AW13: 0 | AX13: 0 | AY13: 0 | AZ13: 0 | BA13: 0 | BB13: 0 | BC13: 0 | BD13: 0 | BE13: 0 | BF13: 0 | BG13: 0 | BH13: 0 | BI13: 0 | BJ13: 0 | BK13: 0 | BL13: 0
... A16: olmm_fleet_drop | B16: 0 | C16: 0 | D16: 0 | E16: 0 | F16: 0 | G16: 0 | H16: 0 | I16: 0 | J16: 0 | K16: 0 | L16: 0 | M16: 0 | N16: 0 | O16: 0 | P16: 0 | Q16: 0 | R16: 0 | S16: 0 | T16: 0 | U16: 0 | V16: 0 | W16: 1 | X16: 0 | Y16: 0 | Z16: 0 | AA16: 0 | AB16: 0 | AC16: 0 | AD16: 0 | AE16: 1 | AF16: 0 | AG16: 0 | AH16: 3 | AI16: 0 | AJ16: 1 | AK16: 0 | AL16: 7 | AM16: 0 | AN16: 0 | AO16: 0 | AP16: 0 | AQ16: 0 | AR16: 0 | AS16: 0 | AT16: 0 | AU16: 0 | AV16: 0 | AW16: 0 | AX16: 0 | AY16: 0 | AZ16: 0 | BA16: 0 | BB16: 0 | BC16: 0 | BD16: 0 | BE16: 0 | BF16: 0 | BG16: 0 | BH16: 0 | BI16: 0 | BJ16: 0 | BK16: 0 | BL16: 0

Sheet Company Cars
A1: Value | B1: 2025/11/17 | C1: 2025/11/30 | D1: 2025/12/31 | E1: 2026/01/31 | F1: 2026/02/28 | G1: 2026/03/31 | H1: 2026/04/30 | I1: 2026/05/31 | J1: 2026/06/30 | K1: 2026/07/31 | L1: 2026/08/31 | M1: 2026/09/30 | N1: 2026/10/31 | O1: 2026/11/30 | P1: 2026/12/31 | Q1: 2027/01/31 | R1: 2027/02/28 | S1: 2027/03/31 | T1: 2027/04/30 | U1: 2027/05/31 | V1: 2027/06/30 | W1: 2027/07/31 | X1: 2027/08/31 | Y1: 2027/09/30 | Z1: 2027/10/31 | AA1: 2027/11/30 | AB1: 2027/12/31 | AC1: 2028/01/31 | AD1: 2028/02/29 | AE1: 2028/03/31 | AF1: 2028/04/30 | AG1: 2028/05/31 | AH1: 2028/06/30 | AI1: 2028/07/31 | AJ1: 2028/08/31 | AK1: 2028/09/30 | AL1: 2028/10/31 | AM1: 2028/11/30 | AN1: 2028/12/31 | AO1: 2029/01/31 | AP1: 2029/02/28 | AQ1: 2029/03/31 | AR1: 2029/04/30 | AS1: 2029/05/31 | AT1: 2029/06/30 | AU1: 2029/07/31 | AV1: 2029/08/31 | AW1: 2029/09/30 | AX1: 2029/10/31 | AY1: 2029/11/30 | AZ1: 2029/12/31 | BA1: 2030/01/31 | BB1: 2030/02/28 | BC1: 2030/03/31 | BD1: 2030/04/30 | BE1: 2030/05/31 | BF1: 2030/06/30 | BG1: 2030/07/31 | BH1: 2030/08/31 | BI1: 2030/09/30 | BJ1: 2030/10/31 | BK1: 2030/11/30 | BL1: 2030/12/31
A2: fml_count | B2: 2 | C2: 2 | D2: 2 | E2: 2 | F2: 2 | G2: 1 | H2: 1 | I2: 1 | J2: 1 | K2: 1 | L2: 1 | M2: 1 | N2: 1 | O2: 1 | P2: 1 | Q2: 1 | R2: 1 | S2: 1 | T2: 1 | U2: 1 | V2: 1 | W2: 1 | X2: 1 | Y2: 1 | Z2: 1 | AA2: 1 | AB2: 1 | AC2: 1 | AD2: 1 | AE2: 1 | AF2: 1 | AG2: 0 | AH2: 0 | AI2: 0 | AJ2: 0 | AK2: 0 | AL2: 0 | AM2: 0 | AN2: 0 | AO2: 0 | AP2: 0 | AQ2: 0 | AR2: 0 | AS2: 0 | AT2: 0 | AU2: 0 | AV2: 0 | AW2: 0 | AX2: 0 | AY2: 0 | AZ2: 0 | BA2: 0 | BB2: 0 | BC2: 0 | BD2: 0 | BE2: 0 | BF2: 0 | BG2: 0 | BH2: 0 | BI2: 0 | BJ2: 0 | BK2: 0 | BL2: 0
A3: olmm_count | B3: 478 | C3: 478 | D3: 478 | E3: 478 | F3: 478 | G3: 478 | H3: 478 | I3: 478 | J3: 475 | K3: 309 | L3: 17 | M3: 1 | N3: 0 | O3: 0 | P3: 0 | Q3: 0 | R3: 0 | S3: 0 | T3: 0 | U3: 0 | V3: 0 | W3: 0 | X3: 0 | Y3: 0 | Z3: 0 | AA3: 0 | AB3: 0 | AC3: 0 | AD3: 0 | AE3: 0 | AF3: 0 | AG3: 0 | AH3: 0 | AI3: 0 | AJ3: 0 | AK3: 0 | AL3: 0 | AM3: 0 | AN3: 0 | AO3: 0 | AP3: 0 | AQ3: 0 | AR3: 0 | AS3: 0 | AT3: 0 | AU3: 0 | AV3: 0 | AW3: 0 | AX3: 0 | AY3: 0 | AZ3: 0 | BA3: 0 | BB3: 0 | BC3: 0 | BD3: 0 | BE3: 0 | BF3: 0 | BG3: 0 | BH3: 0 | BI3: 0 | BJ3: 0 | BK3: 0 | BL3: 0
A4: pl_count | B4: 0 | C4: 0 | D4: 0 | E4: 0 | F4: 0 | G4: 0 | H4: 0 | I4: 0 | J4: 0 | K4: 0 | L4: 0 | M4: 0 | N4: 0 | O4: 0 | P4: 0 | Q4: 0 | R4: 0 | S4: 0 | T4: 0 | U4: 0 | V4: 0 | W4: 0 | X4: 0 | Y4: 0 | Z4: 0 | AA4: 0 | AB4: 0 | AC4: 0 | AD4: 0 | AE4: 0 | AF4: 0 | AG4: 0 | AH4: 0 | AI4: 0 | AJ4: 0 | AK4: 0 | AL4: 0 | AM4: 0 | AN4: 0 | AO4: 0 | AP4: 0 | AQ4: 0 | AR4: 0 | AS4: 0 | AT4: 0 | AU4: 0 | AV4: 0 | AW4: 0 | AX4: 0 | AY4: 0 | AZ4: 0 | BA4: 0 | BB4: 0 | BC4: 0 | BD4: 0 | BE4: 0 | BF4: 0 | BG4: 0 | BH4: 0 | BI4: 0 | BJ4: 0 | BK4: 0 | BL4: 0
A5: revenue_p_m | B5: 2148560.7 | C5: 2148560.7 | D5: 2148560.7 | E5: 2148560.7 | F5: 2148560.7 | G5: 2143214.6 | H5: 2143214.6 | I5: 2143214.6 | J5: 2130250.6 | K5: 1358450.4 | L5: 81445.36 | M5: 12304.93 | N5: 7984.75 | O5: 7984.75 | P5: 7984.75 | Q5: 7984.75 | R5: 7984.75 | S5: 7984.75 | T5: 7984.75 | U5: 7984.75 | V5: 7984.75 | W5: 7984.75 | X5: 7984.75 | Y5: 7984.75 | Z5: 7984.75 | AA5: 7984.75 | AB5: 7984.75 | AC5: 7984.75 | AD5: 7984.75 | AE5: 7984.75 | AF5: 7984.75 | AG5: 0 | AH5: 0 | AI5: 0 | AJ5: 0 | AK5: 0 | AL5: 0 | AM5: 0 | AN5: 0 | AO5: 0 | AP5: 0 | AQ5: 0 | AR5: 0 | AS5: 0 | AT5: 0 | AU5: 0 | AV5: 0 | AW5: 0 | AX5: 0 | AY5: 0 | AZ5: 0 | BA5: 0 | BB5: 0 | BC5: 0 | BD5: 0 | BE5: 0 | BF5: 0 | BG5: 0 | BH5: 0 | BI5: 0 | BJ5: 0 | BK5: 0 | BL5: 0
A6: depreciation_p_m | B6: 1175756.9 | C6: 1175756.9 | D6: 1175756.9 | E6: 1175756.9 | F6: 1175756.9 | G6: 1173402 | H6: 1173402 | I6: 1173402 | J6: 1166120.1 | K6: 753226.95 | L6: 44202.15 | M6: 5365.51 | N6: 2938.22 | O6: 2938.22 | P6: 2938.22 | Q6: 2938.22 | R6: 2938.22 | S6: 2938.22 | T6: 2938.22 | U6: 2938.22 | V6: 2938.22 | W6: 2938.22 | X6: 2938.22 | Y6: 2938.22 | Z6: 2938.22 | AA6: 2938.22 | AB6: 2938.22 | AC6: 2938.22 | AD6: 2938.22 | AE6: 2938.22 | AF6: 2938.22 | AG6: 0 | AH6: 0 | AI6: 0 | AJ6: 0 | AK6: 0 | AL6: 0 | AM6: 0 | AN6: 0 | AO6: 0 | AP6: 0 | AQ6: 0 | AR6: 0 | AS6: 0 | AT6: 0 | AU6: 0 | AV6: 0 | AW6: 0 | AX6: 0 | AY6: 0 | AZ6: 0 | BA6: 0 | BB6: 0 | BC6: 0 | BD6: 0 | BE6: 0 | BF6: 0 | BG6: 0 | BH6: 0 | BI6: 0 | BJ6: 0 | BK6: 0 | BL6: 0
A7: interest_p_m | B7: 830171.69 | C7: 830171.69 | D7: 830171.69 | E7: 830171.69 | F7: 830171.69 | G7: 828875.59 | H7: 828875.59 | I7: 828875.59 | J7: 824063.41 | K7: 513292.89 | L7: 29989.15 | M7: 4324.19 | N7: 2720.13 | O7: 2720.13 | P7: 2720.13 | Q7: 2720.13 | R7: 2720.13 | S7: 2720.13 | T7: 2720.13 | U7: 2720.13 | V7: 2720.13 | W7: 2720.13 | X7: 2720.13 | Y7: 2720.13 | Z7: 2720.13 | AA7: 2720.13 | AB7: 2720.13 | AC7: 2720.13 | AD7: 2720.13 | AE7: 2720.13 | AF7: 2720.13 | AG7: 0 | AH7: 0 | AI7: 0 | AJ7: 0 | AK7: 0 | AL7: 0 | AM7: 0 | AN7: 0 | AO7: 0 | AP7: 0 | AQ7: 0 | AR7: 0 | AS7: 0 | AT7: 0 | AU7: 0 | AV7: 0 | AW7: 0 | AX7: 0 | AY7: 0 | AZ7: 0 | BA7: 0 | BB7: 0 | BC7: 0 | BD7: 0 | BE7: 0 | BF7: 0 | BG7: 0 | BH7: 0 | BI7: 0 | BJ7: 0 | BK7: 0 | BL7: 0
A8: admin_p_m | B8: 72377.72 | C8: 72377.72 | D8: 72377.72 | E8: 72377.72 | F8: 72377.72 | G8: 72367.72 | H8: 72367.72 | I8: 72367.72 | J8: 71917.72 | K8: 47021.23 | L8: 3224.74 | M8: 825.91 | N8: 677.08 | O8: 677.08 | P8: 677.08 | Q8: 677.08 | R8: 677.08 | S8: 677.08 | T8: 677.08 | U8: 677.08 | V8: 677.08 | W8: 677.08 | X8: 677.08 | Y8: 677.08 | Z8: 677.08 | AA8: 677.08 | AB8: 677.08 | AC8: 677.08 | AD8: 677.08 | AE8: 677.08 | AF8: 677.08 | AG8: 0 | AH8: 0 | AI8: 0 | AJ8: 0 | AK8: 0 | AL8: 0 | AM8: 0 | AN8: 0 | AO8: 0 | AP8: 0 | AQ8: 0 | AR8: 0 | AS8: 0 | AT8: 0 | AU8: 0 | AV8: 0 | AW8: 0 | AX8: 0 | AY8: 0 | AZ8: 0 | BA8: 0 | BB8: 0 | BC8: 0 | BD8: 0 | BE8: 0 | BF8: 0 | BG8: 0 | BH8: 0 | BI8: 0 | BJ8: 0 | BK8: 0 | BL8: 0
A9: maint_prov_p_m | B9: 44111.8 | C9: 44111.8 | D9: 44111.8 | E9: 44111.8 | F9: 44111.8 | G9: 7087.8 | H9: 7087.8 | I9: 7087.8 | J9: 7087.8 | K9: 7087.8 | L9: 7087.8 | M9: 7087.8 | N9: 7087.8 | O9: 7087.8 | P9: 7087.8 | Q9: 7087.8 | R9: 7087.8 | S9: 7087.8 | T9: 7087.8 | U9: 7087.8 | V9: 7087.8 | W9: 7087.8 | X9: 7087.8 | Y9: 7087.8 | Z9: 7087.8 | AA9: 7087.8 | AB9: 7087.8 | AC9: 7087.8 | AD9: 7087.8 | AE9: 7087.8 | AF9: 7087.8 | AG9: 0 | AH9: 0 | AI9: 0 | AJ9: 0 | AK9: 0 | AL9: 0 | AM9: 0 | AN9: 0 | AO9: 0 | AP9: 0 | AQ9: 0 | AR9: 0 | AS9: 0 | AT9: 0 | AU9: 0 | AV9: 0 | AW9: 0 | AX9: 0 | AY9: 0 | AZ9: 0 | BA9: 0 | BB9: 0 | BC9: 0 | BD9: 0 | BE9: 0 | BF9: 0 | BG9: 0 | BH9: 0 | BI9: 0 | BJ9: 0 | BK9: 0 | BL9: 0
A10: maintenance_fund | B10: 28641.65 | C10: 28641.65 | D10: 28641.65 | E10: 28641.65 | F10: 28641.65 | G10: 7087.8 | H10: 7087.8 | I10: 7087.8 | J10: 7087.8 | K10: 7087.8 | L10: 7087.8 | M10: 7087.8 | N10: 7087.8 | O10: 7087.8 | P10: 7087.8 | Q10: 7087.8 | R10: 7087.8 | S10: 7087.8 | T10: 7087.8 | U10: 7087.8 | V10: 7087.8 | W10: 7087.8 | X10: 7087.8 | Y10: 7087.8 | Z10: 7087.8 | AA10: 7087.8 | AB10: 7087.8 | AC10: 7087.8 | AD10: 7087.8 | AE10: 7087.8 | AF10: 7087.8 | AG10: 0 | AH10: 0 | AI10: 0 | AJ10: 0 | AK10: 0 | AL10: 0 | AM10: 0 | AN10: 0 | AO10: 0 | AP10: 0 | AQ10: 0 | AR10: 0 | AS10: 0 | AT10: 0 | AU10: 0 | AV10: 0 | AW10: 0 | AX10: 0 | AY10: 0 | AZ10: 0 | BA10: 0 | BB10: 0 | BC10: 0 | BD10: 0 | BE10: 0 | BF10: 0 | BG10: 0 | BH10: 0 | BI10: 0 | BJ10: 0 | BK10: 0 | BL10: 0
A11: other_fee_p_m | B11: 67916.08 | C11: 67916.08 | D11: 67916.08 | E11: 67916.08 | F11: 67916.08 | G11: 67388.02 | H11: 67388.02 | I11: 67388.02 | J11: 66968.02 | K11: 43728.02 | L11: 2848.02 | M11: 608.02 | N11: 468.02 | O11: 468.02 | P11: 468.02 | Q11: 468.02 | R11: 468.02 | S11: 468.02 | T11: 468.02 | U11: 468.02 | V11: 468.02 | W11: 468.02 | X11: 468.02 | Y11: 468.02 | Z11: 468.02 | AA11: 468.02 | AB11: 468.02 | AC11: 468.02 | AD11: 468.02 | AE11: 468.02 | AF11: 468.02 | AG11: 0 | AH11: 0 | AI11: 0 | AJ11: 0 | AK11: 0 | AL11: 0 | AM11: 0 | AN11: 0 | AO11: 0 | AP11: 0 | AQ11: 0 | AR11: 0 | AS11: 0 | AT11: 0 | AU11: 0 | AV11: 0 | AW11: 0 | AX11: 0 | AY11: 0 | AZ11: 0 | BA11: 0 | BB11: 0 | BC11: 0 | BD11: 0 | BE11: 0 | BF11: 0 | BG11: 0 | BH11: 0 | BI11: 0 | BJ11: 0 | BK11: 0 | BL11: 0
A12: total_cost | B12: 1.0361999e+08 | C12: 1.0361999e+08 | D12: 1.0361999e+08 | E12: 1.0361999e+08 | F12: 1.0361999e+08 | G12: 1.0337755e+08 | H12: 1.0337755e+08 | I12: 1.0337755e+08 | J12: 1.0277486e+08 | K12: 64163723 | L12: 3753799.5 | M12: 539441.39 | N12: 338544.01 | O12: 338544.01 | P12: 338544.01 | Q12: 338544.01 | R12: 338544.01 | S12: 338544.01 | T12: 338544.01 | U12: 338544.01 | V12: 338544.01 | W12: 338544.01 | X12: 338544.01 | Y12: 338544.01 | Z12: 338544.01 | AA12: 338544.01 | AB12: 338544.01 | AC12: 338544.01 | AD12: 338544.01 | AE12: 338544.01 | AF12: 338544.01 | AG12: 0 | AH12: 0 | AI12: 0 | AJ12: 0 | AK12: 0 | AL12: 0 | AM12: 0 | AN12: 0 | AO12: 0 | AP12: 0 | AQ12: 0 | AR12: 0 | AS12: 0 | AT12: 0 | AU12: 0 | AV12: 0 | AW12: 0 | AX12: 0 | AY12: 0 | AZ12: 0 | BA12: 0 | BB12: 0 | BC12: 0 | BD12: 0 | BE12: 0 | BF12: 0 | BG12: 0 | BH12: 0 | BI12: 0 | BJ12: 0 | BK12: 0 | BL12: 0
A13: nbv | B13: 1.0015324e+08 | C13: 1.0015324e+08 | D13: 98977479 | E13: 97801722 | F13: 96625966 | G13: 95290191 | H13: 94116789 | I13: 92943387 | J13: 91254676 | K13: 56192752 | L13: 3261188.4 | M13: 468667.9 | N13: 291532.49 | O13: 288594.27 | P13: 285656.05 | Q13: 282717.83 | R13: 279779.61 | S13: 276841.39 | T13: 273903.17 | U13: 270964.95 | V13: 268026.73 | W13: 265088.51 | X13: 262150.29 | Y13: 259212.07 | Z13: 256273.85 | AA13: 253335.63 | AB13: 250397.41 | AC13: 247459.19 | AD13: 244520.97 | AE13: 241582.75 | AF13: 238644.53 | AG13: 0 | AH13: 0 | AI13: 0 | AJ13: 0 | AK13: 0 | AL13: 0 | AM13: 0 | AN13: 0 | AO13: 0 | AP13: 0 | AQ13: 0 | AR13: 0 | AS13: 0 | AT13: 0 | AU13: 0 | AV13: 0 | AW13: 0 | AX13: 0 | AY13: 0 | AZ13: 0 | BA13: 0 | BB13: 0 | BC13: 0 | BD13: 0 | BE13: 0 | BF13: 0 | BG13: 0 | BH13: 0 | BI13: 0 | BJ13: 0 | BK13: 0 | BL13: 0
... A16: olmm_fleet_drop | B16: 0 | C16: 0 | D16: 0 | E16: 0 | F16: 0 | G16: 0 | H16: 0 | I16: 0 | J16: 3 | K16: 166 | L16: 292 | M16: 16 | N16: 1 | O16: 0 | P16: 0 | Q16: 0 | R16: 0 | S16: 0 | T16: 0 | U16: 0 | V16: 0 | W16: 0 | X16: 0 | Y16: 0 | Z16: 0 | AA16: 0 | AB16: 0 | AC16: 0 | AD16: 0 | AE16: 0 | AF16: 0 | AG16: 0 | AH16: 0 | AI16: 0 | AJ16: 0 | AK16: 0 | AL16: 0 | AM16: 0 | AN16: 0 | AO16: 0 | AP16: 0 | AQ16: 0 | AR16: 0 | AS16: 0 | AT16: 0 | AU16: 0 | AV16: 0 | AW16: 0 | AX16: 0 | AY16: 0 | AZ16: 0 | BA16: 0 | BB16: 0 | BC16: 0 | BD16: 0 | BE16: 0 | BF16: 0 | BG16: 0 | BH16: 0 | BI16: 0 | BJ16: 0 | BK16: 0 | BL16: 0

Sheet iLease
A1: Value | B1: 2025/11/17 | C1: 2025/11/30 | D1: 2025/12/31 | E1: 2026/01/31 | F1: 2026/02/28 | G1: 2026/03/31 | H1: 2026/04/30 | I1: 2026/05/31 | J1: 2026/06/30 | K1: 2026/07/31 | L1: 2026/08/31 | M1: 2026/09/30 | N1: 2026/10/31 | O1: 2026/11/30 | P1: 2026/12/31 | Q1: 2027/01/31 | R1: 2027/02/28 | S1: 2027/03/31 | T1: 2027/04/30 | U1: 2027/05/31 | V1: 2027/06/30 | W1: 2027/07/31 | X1: 2027/08/31 | Y1: 2027/09/30 | Z1: 2027/10/31 | AA1: 2027/11/30 | AB1: 2027/12/31 | AC1: 2028/01/31 | AD1: 2028/02/29 | AE1: 2028/03/31 | AF1: 2028/04/30 | AG1: 2028/05/31 | AH1: 2028/06/30 | AI1: 2028/07/31 | AJ1: 2028/08/31 | AK1: 2028/09/30 | AL1: 2028/10/31 | AM1: 2028/11/30 | AN1: 2028/12/31 | AO1: 2029/01/31 | AP1: 2029/02/28 | AQ1: 2029/03/31 | AR1: 2029/04/30 | AS1: 2029/05/31 | AT1: 2029/06/30 | AU1: 2029/07/31 | AV1: 2029/08/31 | AW1: 2029/09/30 | AX1: 2029/10/31 | AY1: 2029/11/30 | AZ1: 2029/12/31 | BA1: 2030/01/31 | BB1: 2030/02/28 | BC1: 2030/03/31 | BD1: 2030/04/30 | BE1: 2030/05/31 | BF1: 2030/06/30 | BG1: 2030/07/31 | BH1: 2030/08/31 | BI1: 2030/09/30 | BJ1: 2030/10/31 | BK1: 2030/11/30 | BL1: 2030/12/31
A2: fml_count | B2: 0 | C2: 0 | D2: 0 | E2: 0 | F2: 0 | G2: 0 | H2: 0 | I2: 0 | J2: 0 | K2: 0 | L2: 0 | M2: 0 | N2: 0 | O2: 0 | P2: 0 | Q2: 0 | R2: 0 | S2: 0 | T2: 0 | U2: 0 | V2: 0 | W2: 0 | X2: 0 | Y2: 0 | Z2: 0 | AA2: 0 | AB2: 0 | AC2: 0 | AD2: 0 | AE2: 0 | AF2: 0 | AG2: 0 | AH2: 0 | AI2: 0 | AJ2: 0 | AK2: 0 | AL2: 0 | AM2: 0 | AN2: 0 | AO2: 0 | AP2: 0 | AQ2: 0 | AR2: 0 | AS2: 0 | AT2: 0 | AU2: 0 | AV2: 0 | AW2: 0 | AX2: 0 | AY2: 0 | AZ2: 0 | BA2: 0 | BB2: 0 | BC2: 0 | BD2: 0 | BE2: 0 | BF2: 0 | BG2: 0 | BH2: 0 | BI2: 0 | BJ2: 0 | BK2: 0 | BL2: 0
A3: olmm_count | B3: 0 | C3: 0 | D3: 0 | E3: 0 | F3: 0 | G3: 0 | H3: 0 | I3: 0 | J3: 0 | K3: 0 | L3: 0 | M3: 0 | N3: 0 | O3: 0 | P3: 0 | Q3: 0 | R3: 0 | S3: 0 | T3: 0 | U3: 0 | V3: 0 | W3: 0 | X3: 0 | Y3: 0 | Z3: 0 | AA3: 0 | AB3: 0 | AC3: 0 | AD3: 0 | AE3: 0 | AF3: 0 | AG3: 0 | AH3: 0 | AI3: 0 | AJ3: 0 | AK3: 0 | AL3: 0 | AM3: 0 | AN3: 0 | AO3: 0 | AP3: 0 | AQ3: 0 | AR3: 0 | AS3: 0 | AT3: 0 | AU3: 0 | AV3: 0 | AW3: 0 | AX3: 0 | AY3: 0 | AZ3: 0 | BA3: 0 | BB3: 0 | BC3: 0 | BD3: 0 | BE3: 0 | BF3: 0 | BG3: 0 | BH3: 0 | BI3: 0 | BJ3: 0 | BK3: 0 | BL3: 0
A4: pl_count | B4: 15 | C4: 15 | D4: 15 | E4: 15 | F4: 15 | G4: 15 | H4: 15 | I4: 15 | J4: 15 | K4: 15 | L4: 15 | M4: 14 | N4: 14 | O4: 14 | P4: 14 | Q4: 14 | R4: 14 | S4: 14 | T4: 14 | U4: 14 | V4: 14 | W4: 14 | X4: 14 | Y4: 14 | Z4: 14 | AA4: 14 | AB4: 14 | AC4: 14 | AD4: 12 | AE4: 12 | AF4: 11 | AG4: 10 | AH4: 10 | AI4: 10 | AJ4: 10 | AK4: 10 | AL4: 10 | AM4: 10 | AN4: 10 | AO4: 10 | AP4: 10 | AQ4: 10 | AR4: 10 | AS4: 10 | AT4: 10 | AU4: 10 | AV4: 10 | AW4: 10 | AX4: 10 | AY4: 9 | AZ4: 9 | BA4: 9 | BB4: 8 | BC4: 7 | BD4: 4 | BE4: 4 | BF4: 4 | BG4: 2 | BH4: 2 | BI4: 2 | BJ4: 2 | BK4: 2 | BL4: 2
A5: revenue_p_m | B5: 218881.46 | C5: 218881.46 | D5: 218881.46 | E5: 218881.46 | F5: 218881.46 | G5: 218881.46 | H5: 218881.46 | I5: 218881.46 | J5: 218881.46 | K5: 218881.46 | L5: 218881.46 | M5: 207065.31 | N5: 207065.31 | O5: 207065.31 | P5: 207065.31 | Q5: 207065.31 | R5: 207065.31 | S5: 207065.31 | T5: 207065.31 | U5: 207065.31 | V5: 207065.31 | W5: 207065.31 | X5: 207065.31 | Y5: 207065.31 | Z5: 207065.31 | AA5: 207065.31 | AB5: 207065.31 | AC5: 207065.31 | AD5: 187366.98 | AE5: 187366.98 | AF5: 174268.52 | AG5: 165567.22 | AH5: 165567.22 | AI5: 165567.22 | AJ5: 165567.22 | AK5: 165567.22 | AL5: 165567.22 | AM5: 165567.22 | AN5: 165567.22 | AO5: 165567.22 | AP5: 165567.22 | AQ5: 165567.22 | AR5: 165567.22 | AS5: 165567.22 | AT5: 165567.22 | AU5: 165567.22 | AV5: 165567.22 | AW5: 165567.22 | AX5: 165567.22 | AY5: 154048.29 | AZ5: 154048.29 | BA5: 154048.29 | BB5: 133181.75 | BC5: 122099.93 | BD5: 62249.4 | BE5: 62249.4 | BF5: 62249.4 | BG5: 31983.96 | BH5: 31983.96 | BI5: 31983.96 | BJ5: 31983.96 | BK5: 31983.96 | BL5: 31983.96
A6: depreciation_p_m | B6: 79502.8 | C6: 79502.8 | D6: 79502.8 | E6: 79502.8 | F6: 79502.8 | G6: 79502.8 | H6: 79502.8 | I6: 79502.8 | J6: 79502.8 | K6: 79502.8 | L6: 79502.8 | M6: 75453.3 | N6: 75453.3 | O6: 75453.3 | P6: 75453.3 | Q6: 75453.3 | R6: 75453.3 | S6: 75453.3 | T6: 75453.3 | U6: 75453.3 | V6: 75453.3 | W6: 75453.3 | X6: 75453.3 | Y6: 75453.3 | Z6: 75453.3 | AA6: 75453.3 | AB6: 75453.3 | AC6: 75453.3 | AD6: 67094.79 | AE6: 67094.79 | AF6: 62604.58 | AG6: 60193.39 | AH6: 60193.39 | AI6: 60193.39 | AJ6: 60193.39 | AK6: 60193.39 | AL6: 60193.39 | AM6: 60193.39 | AN6: 60193.39 | AO6: 60193.39 | AP6: 60193.39 | AQ6: 60193.39 | AR6: 60193.39 | AS6: 60193.39 | AT6: 60193.39 | AU6: 60193.39 | AV6: 60193.39 | AW6: 60193.39 | AX6: 60193.39 | AY6: 56909.74 | AZ6: 56909.74 | BA6: 56909.74 | BB6: 50166.85 | BC6: 47113.37 | BD6: 21853.9 | BE6: 21853.9 | BF6: 21853.9 | BG6: 11656.82 | BH6: 11656.82 | BI6: 11656.82 | BJ6: 11656.82 | BK6: 11656.82 | BL6: 11656.82
A7: interest_p_m | B7: 68253.96 | C7: 68253.96 | D7: 68253.96 | E7: 68253.96 | F7: 68253.96 | G7: 68253.96 | H7: 68253.96 | I7: 68253.96 | J7: 68253.96 | K7: 68253.96 | L7: 68253.96 | M7: 65359.08 | N7: 65359.08 | O7: 65359.08 | P7: 65359.08 | Q7: 65359.08 | R7: 65359.08 | S7: 65359.08 | T7: 65359.08 | U7: 65359.08 | V7: 65359.08 | W7: 65359.08 | X7: 65359.08 | Y7: 65359.08 | Z7: 65359.08 | AA7: 65359.08 | AB7: 65359.08 | AC7: 65359.08 | AD7: 60155.18 | AE7: 60155.18 | AF7: 55789.65 | AG7: 53013.9 | AH7: 53013.9 | AI7: 53013.9 | AJ7: 53013.9 | AK7: 53013.9 | AL7: 53013.9 | AM7: 53013.9 | AN7: 53013.9 | AO7: 53013.9 | AP7: 53013.9 | AQ7: 53013.9 | AR7: 53013.9 | AS7: 53013.9 | AT7: 53013.9 | AU7: 53013.9 | AV7: 53013.9 | AW7: 53013.9 | AX7: 53013.9 | AY7: 49216.39 | AZ7: 49216.39 | BA7: 49216.39 | BB7: 41281.61 | BC7: 37454.13 | BD7: 19895.39 | BE7: 19895.39 | BF7: 19895.39 | BG7: 10040.58 | BH7: 10040.58 | BI7: 10040.58 | BJ7: 10040.58 | BK7: 10040.58 | BL7: 10040.58
A8: admin_p_m | B8: 18569.44 | C8: 18569.44 | D8: 18569.44 | E8: 18569.44 | F8: 18569.44 | G8: 18569.44 | H8: 18569.44 | I8: 18569.44 | J8: 18569.44 | K8: 18569.44 | L8: 18569.44 | M8: 17849.51 | N8: 17849.51 | O8: 17849.51 | P8: 17849.51 | Q8: 17849.51 | R8: 17849.51 | S8: 17849.51 | T8: 17849.51 | U8: 17849.51 | V8: 17849.51 | W8: 17849.51 | X8: 17849.51 | Y8: 17849.51 | Z8: 17849.51 | AA8: 17849.51 | AB8: 17849.51 | AC8: 17849.51 | AD8: 16423.27 | AE8: 16423.27 | AF8: 15302.17 | AG8: 14630.58 | AH8: 14630.58 | AI8: 14630.58 | AJ8: 14630.58 | AK8: 14630.58 | AL8: 14630.58 | AM8: 14630.58 | AN8: 14630.58 | AO8: 14630.58 | AP8: 14630.58 | AQ8: 14630.58 | AR8: 14630.58 | AS8: 14630.58 | AT8: 14630.58 | AU8: 14630.58 | AV8: 14630.58 | AW8: 14630.58 | AX8: 14630.58 | AY8: 13646.24 | AZ8: 13646.24 | BA8: 13646.24 | BB8: 11594.48 | BC8: 10615.38 | BD8: 5523.47 | BE8: 5523.47 | BF8: 5523.47 | BG8: 2876.35 | BH8: 2876.35 | BI8: 2876.35 | BJ8: 2876.35 | BK8: 2876.35 | BL8: 2876.35
A9: maint_prov_p_m | B9: 125201.04 | C9: 125201.04 | D9: 125201.04 | E9: 125201.04 | F9: 125201.04 | G9: 125201.04 | H9: 125201.04 | I9: 125201.04 | J9: 125201.04 | K9: 125201.04 | L9: 125201.04 | M9: 120514.62 | N9: 120514.62 | O9: 120514.62 | P9: 120514.62 | Q9: 120514.62 | R9: 120514.62 | S9: 120514.62 | T9: 120514.62 | U9: 120514.62 | V9: 120514.62 | W9: 120514.62 | X9: 120514.62 | Y9: 120514.62 | Z9: 120514.62 | AA9: 120514.62 | AB9: 120514.62 | AC9: 120514.62 | AD9: 86609.6 | AE9: 86609.6 | AF9: 73138.6 | AG9: 70027.6 | AH9: 70027.6 | AI9: 70027.6 | AJ9: 70027.6 | AK9: 70027.6 | AL9: 70027.6 | AM9: 70027.6 | AN9: 70027.6 | AO9: 70027.6 | AP9: 70027.6 | AQ9: 70027.6 | AR9: 70027.6 | AS9: 70027.6 | AT9: 70027.6 | AU9: 70027.6 | AV9: 70027.6 | AW9: 70027.6 | AX9: 70027.6 | AY9: 58264.96 | AZ9: 58264.96 | BA9: 58264.96 | BB9: 47653.96 | BC9: 41198.62 | BD9: 14566.62 | BE9: 14566.62 | BF9: 14566.62 | BG9: 3884.02 | BH9: 3884.02 | BI9: 3884.02 | BJ9: 3884.02 | BK9: 3884.02 | BL9: 3884.02
A10: maintenance_fund | B10: 119042.44 | C10: 119042.44 | D10: 119042.44 | E10: 119042.44 | F10: 119042.44 | G10: 119042.44 | H10: 119042.44 | I10: 119042.44 | J10: 119042.44 | K10: 119042.44 | L10: 119042.44 | M10: 114356.02 | N10: 114356.02 | O10: 114356.02 | P10: 114356.02 | Q10: 114356.02 | R10: 114356.02 | S10: 114356.02 | T10: 114356.02 | U10: 114356.02 | V10: 114356.02 | W10: 114356.02 | X10: 114356.02 | Y10: 114356.02 | Z10: 114356.02 | AA10: 114356.02 | AB10: 114356.02 | AC10: 114356.02 | AD10: 86609.6 | AE10: 86609.6 | AF10: 73138.6 | AG10: 70027.6 | AH10: 70027.6 | AI10: 70027.6 | AJ10: 70027.6 | AK10: 70027.6 | AL10: 70027.6 | AM10: 70027.6 | AN10: 70027.6 | AO10: 70027.6 | AP10: 70027.6 | AQ10: 70027.6 | AR10: 70027.6 | AS10: 70027.6 | AT10: 70027.6 | AU10: 70027.6 | AV10: 70027.6 | AW10: 70027.6 | AX10: 70027.6 | AY10: 58264.96 | AZ10: 58264.96 | BA10: 58264.96 | BB10: 47653.96 | BC10: 41198.62 | BD10: 14566.62 | BE10: 14566.62 | BF10: 14566.62 | BG10: 3884.02 | BH10: 3884.02 | BI10: 3884.02 | BJ10: 3884.02 | BK10: 3884.02 | BL10: 3884.02
A11: other_fee_p_m | B11: 37052.96 | C11: 37052.96 | D11: 37052.96 | E11: 37052.96 | F11: 37052.96 | G11: 37052.96 | H11: 37052.96 | I11: 37052.96 | J11: 37052.96 | K11: 37052.96 | L11: 37052.96 | M11: 34463.26 | N11: 34463.26 | O11: 34463.26 | P11: 34463.26 | Q11: 34463.26 | R11: 34463.26 | S11: 34463.26 | T11: 34463.26 | U11: 34463.26 | V11: 34463.26 | W11: 34463.26 | X11: 34463.26 | Y11: 34463.26 | Z11: 34463.26 | AA11: 34463.26 | AB11: 34463.26 | AC11: 34463.26 | AD11: 31854.2 | AE11: 31854.2 | AF11: 29441.58 | AG11: 27117.31 | AH11: 27117.31 | AI11: 27117.31 | AJ11: 27117.31 | AK11: 27117.31 | AL11: 27117.31 | AM11: 27117.31 | AN11: 27117.31 | AO11: 27117.31 | AP11: 27117.31 | AQ11: 27117.31 | AR11: 27117.31 | AS11: 27117.31 | AT11: 27117.31 | AU11: 27117.31 | AV11: 27117.31 | AW11: 27117.31 | AX11: 27117.31 | AY11: 24644.1 | AZ11: 24644.1 | BA11: 24644.1 | BB11: 21685.99 | BC11: 19181.49 | BD11: 10570.08 | BE11: 10570.08 | BF11: 10570.08 | BG11: 5468.2 | BH11: 5468.2 | BI11: 5468.2 | BJ11: 5468.2 | BK11: 5468.2 | BL11: 5468.2
A12: total_cost | B12: 9255386.7 | C12: 9255386.7 | D12: 9255386.7 | E12: 9255386.7 | F12: 9255386.7 | G12: 9255386.7 | H12: 9255386.7 | I12: 9255386.7 | J12: 9255386.7 | K12: 9255386.7 | L12: 9255386.7 | M12: 8924778 | N12: 8924778 | O12: 8924778 | P12: 8924778 | Q12: 8924778 | R12: 8924778 | S12: 8924778 | T12: 8924778 | U12: 8924778 | V12: 8924778 | W12: 8924778 | X12: 8924778 | Y12: 8924778 | Z12: 8924778 | AA12: 8924778 | AB12: 8924778 | AC12: 8924778 | AD12: 8211655.4 | AE12: 8211655.4 | AF12: 7651103.2 | AG12: 7315307.6 | AH12: 7315307.6 | AI12: 7315307.6 | AJ12: 7315307.6 | AK12: 7315307.6 | AL12: 7315307.6 | AM12: 7315307.6 | AN12: 7315307.6 | AO12: 7315307.6 | AP12: 7315307.6 | AQ12: 7315307.6 | AR12: 7315307.6 | AS12: 7315307.6 | AT12: 7315307.6 | AU12: 7315307.6 | AV12: 7315307.6 | AW12: 7315307.6 | AX12: 7315307.6 | AY12: 6823136.3 | AZ12: 6823136.3 | BA12: 6823136.3 | BB12: 5797256.3 | BC12: 5307703.7 | BD12: 2761738.5 | BE12: 2761738.5 | BF12: 2761738.5 | BG12: 1438177.5 | BH12: 1438177.5 | BI12: 1438177.5 | BJ12: 1438177.5 | BK12: 1438177.5 | BL12: 1438177.5
A13: nbv | B13: 8716058.1 | C13: 8716058.1 | D13: 8636555.3 | E13: 8557052.5 | F13: 8477549.7 | G13: 8398046.9 | H13: 8318544.1 | I13: 8239041.3 | J13: 8159538.5 | K13: 8080035.7 | L13: 8000532.9 | M13: 7639015.4 | N13: 7563562.1 | O13: 7488108.8 | P13: 7412655.5 | Q13: 7337202.2 | R13: 7261748.9 | S13: 7186295.6 | T13: 7110842.3 | U13: 7035389 | V13: 6959935.7 | W13: 6884482.4 | X13: 6809029.1 | Y13: 6733575.8 | Z13: 6658122.5 | AA13: 6582669.2 | AB13: 6507215.9 | AC13: 6431762.6 | AD13: 5970228.3 | AE13: 5903133.5 | AF13: 5486526.4 | AG13: 5172517.8 | AH13: 5112324.4 | AI13: 5052131 | AJ13: 4991937.6 | AK13: 4931744.3 | AL13: 4871550.9 | AM13: 4811357.5 | AN13: 4751164.1 | AO13: 4690970.7 | AP13: 4630777.3 | AQ13: 4570583.9 | AR13: 4510390.5 | AS13: 4450197.1 | AT13: 4390003.7 | AU13: 4329810.4 | AV13: 4269617 | AW13: 4209423.6 | AX13: 4149230.2 | AY13: 3790600.8 | AZ13: 3733691.1 | BA13: 3676781.4 | BB13: 2991822.1 | BC13: 2635311.5 | BD13: 1557801.1 | BE13: 1535947.2 | BF13: 1514093.3 | BG13: 773738.77 | BH13: 762081.95 | BI13: 750425.13 | BJ13: 738768.31 | BK13: 727111.49 | BL13: 715454.67
... A16: olmm_fleet_drop | B16: 0 | C16: 0 | D16: 0 | E16: 0 | F16: 0 | G16: 0 | H16: 0 | I16: 0 | J16: 0 | K16: 0 | L16: 0 | M16: 0 | N16: 0 | O16: 0 | P16: 0 | Q16: 0 | R16: 0 | S16: 0 | T16: 0 | U16: 0 | V16: 0 | W16: 0 | X16: 0 | Y16: 0 | Z16: 0 | AA16: 0 | AB16: 0 | AC16: 0 | AD16: 0 | AE16: 0 | AF16: 0 | AG16: 0 | AH16: 0 | AI16: 0 | AJ16: 0 | AK16: 0 | AL16: 0 | AM16: 0 | AN16: 0 | AO16: 0 | AP16: 0 | AQ16: 0 | AR16: 0 | AS16: 0 | AT16: 0 | AU16: 0 | AV16: 0 | AW16: 0 | AX16: 0 | AY16: 0 | AZ16: 0 | BA16: 0 | BB16: 0 | BC16: 0 | BD16: 0 | BE16: 0 | BF16: 0 | BG16: 0 | BH16: 0 | BI16: 0 | BJ16: 0 | BK16: 0 | BL16: 0

Sheet ZAM
A1: Value | B1: 2025/11/17 | C1: 2025/11/30 | D1: 2025/12/31 | E1: 2026/01/31 | F1: 2026/02/28 | G1: 2026/03/31 | H1: 2026/04/30 | I1: 2026/05/31 | J1: 2026/06/30 | K1: 2026/07/31 | L1: 2026/08/31 | M1: 2026/09/30 | N1: 2026/10/31 | O1: 2026/11/30 | P1: 2026/12/31 | Q1: 2027/01/31 | R1: 2027/02/28 | S1: 2027/03/31 | T1: 2027/04/30 | U1: 2027/05/31 | V1: 2027/06/30 | W1: 2027/07/31 | X1: 2027/08/31 | Y1: 2027/09/30 | Z1: 2027/10/31 | AA1: 2027/11/30 | AB1: 2027/12/31 | AC1: 2028/01/31 | AD1: 2028/02/29 | AE1: 2028/03/31 | AF1: 2028/04/30 | AG1: 2028/05/31 | AH1: 2028/06/30 | AI1: 2028/07/31 | AJ1: 2028/08/31 | AK1: 2028/09/30 | AL1: 2028/10/31 | AM1: 2028/11/30 | AN1: 2028/12/31 | AO1: 2029/01/31 | AP1: 2029/02/28 | AQ1: 2029/03/31 | AR1: 2029/04/30 | AS1: 2029/05/31 | AT1: 2029/06/30 | AU1: 2029/07/31 | AV1: 2029/08/31 | AW1: 2029/09/30 | AX1: 2029/10/31 | AY1: 2029/11/30 | AZ1: 2029/12/31 | BA1: 2030/01/31 | BB1: 2030/02/28 | BC1: 2030/03/31 | BD1: 2030/04/30 | BE1: 2030/05/31 | BF1: 2030/06/30 | BG1: 2030/07/31 | BH1: 2030/08/31 | BI1: 2030/09/30 | BJ1: 2030/10/31 | BK1: 2030/11/30 | BL1: 2030/12/31
A2: fml_count | B2: 549 | C2: 514 | D2: 507 | E2: 500 | F2: 491 | G2: 479 | H2: 469 | I2: 463 | J2: 460 | K2: 444 | L2: 435 | M2: 422 | N2: 404 | O2: 384 | P2: 362 | Q2: 353 | R2: 345 | S2: 336 | T2: 316 | U2: 315 | V2: 302 | W2: 280 | X2: 266 | Y2: 247 | Z2: 233 | AA2: 222 | AB2: 216 | AC2: 206 | AD2: 199 | AE2: 187 | AF2: 187 | AG2: 179 | AH2: 162 | AI2: 154 | AJ2: 141 | AK2: 125 | AL2: 117 | AM2: 116 | AN2: 116 | AO2: 113 | AP2: 107 | AQ2: 93 | AR2: 79 | AS2: 75 | AT2: 64 | AU2: 59 | AV2: 48 | AW2: 36 | AX2: 34 | AY2: 29 | AZ2: 29 | BA2: 29 | BB2: 29 | BC2: 24 | BD2: 23 | BE2: 22 | BF2: 22 | BG2: 19 | BH2: 7 | BI2: 1 | BJ2: 0 | BK2: 0 | BL2: 0
A3: olmm_count | B3: 30 | C3: 30 | D3: 30 | E3: 30 | F3: 30 | G3: 30 | H3: 30 | I3: 30 | J3: 30 | K3: 30 | L3: 30 | M3: 30 | N3: 30 | O3: 30 | P3: 30 | Q3: 30 | R3: 30 | S3: 30 | T3: 30 | U3: 30 | V3: 30 | W3: 30 | X3: 30 | Y3: 30 | Z3: 30 | AA3: 30 | AB3: 30 | AC3: 30 | AD3: 30 | AE3: 15 | AF3: 15 | AG3: 15 | AH3: 15 | AI3: 15 | AJ3: 15 | AK3: 15 | AL3: 15 | AM3: 5 | AN3: 5 | AO3: 5 | AP3: 5 | AQ3: 5 | AR3: 5 | AS3: 5 | AT3: 5 | AU3: 0 | AV3: 0 | AW3: 0 | AX3: 0 | AY3: 0 | AZ3: 0 | BA3: 0 | BB3: 0 | BC3: 0 | BD3: 0 | BE3: 0 | BF3: 0 | BG3: 0 | BH3: 0 | BI3: 0 | BJ3: 0 | BK3: 0 | BL3: 0
A4: pl_count | B4: 0 | C4: 0 | D4: 0 | E4: 0 | F4: 0 | G4: 0 | H4: 0 | I4: 0 | J4: 0 | K4: 0 | L4: 0 | M4: 0 | N4: 0 | O4: 0 | P4: 0 | Q4: 0 | R4: 0 | S4: 0 | T4: 0 | U4: 0 | V4: 0 | W4: 0 | X4: 0 | Y4: 0 | Z4: 0 | AA4: 0 | AB4: 0 | AC4: 0 | AD4: 0 | AE4: 0 | AF4: 0 | AG4: 0 | AH4: 0 | AI4: 0 | AJ4: 0 | AK4: 0 | AL4: 0 | AM4: 0 | AN4: 0 | AO4: 0 | AP4: 0 | AQ4: 0 | AR4: 0 | AS4: 0 | AT4: 0 | AU4: 0 | AV4: 0 | AW4: 0 | AX4: 0 | AY4: 0 | AZ4: 0 | BA4: 0 | BB4: 0 | BC4: 0 | BD4: 0 | BE4: 0 | BF4: 0 | BG4: 0 | BH4: 0 | BI4: 0 | BJ4: 0 | BK4: 0 | BL4: 0
A5: revenue_p_m | B5: 926475.8 | C5: 881756.16 | D5: 871906.56 | E5: 859877.91 | F5: 849903.31 | G5: 829356.25 | H5: 815229.18 | I5: 805190.11 | J5: 798463.82 | K5: 771626.27 | L5: 755874.71 | M5: 733076.3 | N5: 706171.73 | O5: 680472.34 | P5: 641623.24 | Q5: 623416.89 | R5: 609092.04 | S5: 596094.95 | T5: 565645.43 | U5: 564253.95 | V5: 542869.34 | W5: 505966.05 | X5: 483300.95 | Y5: 445892.43 | Z5: 424482.06 | AA5: 405786.77 | AB5: 393135.99 | AC5: 374012.96 | AD5: 361178.04 | AE5: 322815.76 | AF5: 322815.76 | AG5: 310690.43 | AH5: 283055.03 | AI5: 269231.96 | AJ5: 241694.8 | AK5: 221484.91 | AL5: 212087.12 | AM5: 201517.95 | AN5: 201517.95 | AO5: 196653.75 | AP5: 187794 | AQ5: 163881.44 | AR5: 140094.84 | AS5: 133444.48 | AT5: 115189.9 | AU5: 97644.6 | AV5: 78963.26 | AW5: 57946.62 | AX5: 55089.31 | AY5: 47146.34 | AZ5: 47146.34 | BA5: 47146.34 | BB5: 47146.34 | BC5: 42152.34 | BD5: 40375.94 | BE5: 37995.81 | BF5: 37995.81 | BG5: 32153.02 | BH5: 9873.29 | BI5: 1246.24 | BJ5: 0 | BK5: 0 | BL5: 0
