Workbook

Sheet BOT
A1: Value | B1: 2025/06/06 | C1: 2025/06/30 | D1: 2025/07/31 | E1: 2025/08/31 | F1: 2025/09/30 | G1: 2025/10/31 | H1: 2025/11/30 | I1: 2025/12/31 | J1: 2026/01/31 | K1: 2026/02/28 | L1: 2026/03/31 | M1: 2026/04/30 | N1: 2026/05/31 | O1: 2026/06/30 | P1: 2026/07/31 | Q1: 2026/08/31 | R1: 2026/09/30 | S1: 2026/10/31 | T1: 2026/11/30 | U1: 2026/12/31 | V1: 2027/01/31 | W1: 2027/02/28 | X1: 2027/03/31 | Y1: 2027/04/30 | Z1: 2027/05/31 | AA1: 2027/06/30 | AB1: 2027/07/31 | AC1: 2027/08/31 | AD1: 2027/09/30 | AE1: 2027/10/31 | AF1: 2027/11/30 | AG1: 2027/12/31 | AH1: 2028/01/31 | AI1: 2028/02/29 | AJ1: 2028/03/31 | AK1: 2028/04/30 | AL1: 2028/05/31 | AM1: 2028/06/30 | AN1: 2028/07/31 | AO1: 2028/08/31 | AP1: 2028/09/30 | AQ1: 2028/10/31 | AR1: 2028/11/30 | AS1: 2028/12/31 | AT1: 2029/01/31 | AU1: 2029/02/28 | AV1: 2029/03/31 | AW1: 2029/04/30 | AX1: 2029/05/31 | AY1: 2029/06/30 | AZ1: 2029/07/31 | BA1: 2029/08/31 | BB1: 2029/09/30 | BC1: 2029/10/31 | BD1: 2029/11/30 | BE1: 2029/12/31 | BF1: 2030/01/31 | BG1: 2030/02/28 | BH1: 2030/03/31 | BI1: 2030/04/30 | BJ1: 2030/05/31 | BK1: 2030/06/30 | BL1: 2030/07/31
A2: fml_count | B2: 475 | C2: 381 | D2: 377 | E2: 367 | F2: 362 | G2: 361 | H2: 340 | I2: 334 | J2: 333 | K2: 331 | L2: 310 | M2: 297 | N2: 266 | O2: 255 | P2: 244 | Q2: 234 | R2: 217 | S2: 211 | T2: 201 | U2: 192 | V2: 185 | W2: 180 | X2: 171 | Y2: 166 | Z2: 160 | AA2: 158 | AB2: 152 | AC2: 142 | AD2: 139 | AE2: 128 | AF2: 126 | AG2: 125 | AH2: 125 | AI2: 121 | AJ2: 114 | AK2: 87 | AL2: 69 | AM2: 67 | AN2: 62 | AO2: 59 | AP2: 52 | AQ2: 48 | AR2: 40 | AS2: 40 | AT2: 37 | AU2: 33 | AV2: 30 | AW2: 29 | AX2: 26 | AY2: 25 | AZ2: 23 | BA2: 22 | BB2: 21 | BC2: 19 | BD2: 14 | BE2: 12 | BF2: 11 | BG2: 9 | BH2: 8 | BI2: 4 | BJ2: 0 | BK2: 0 | BL2: 0
A3: olmm_count | B3: 24 | C3: 20 | D3: 20 | E3: 20 | F3: 19 | G3: 18 | H3: 17 | I3: 16 | J3: 16 | K3: 16 | L3: 15 | M3: 14 | N3: 14 | O3: 14 | P3: 14 | Q3: 14 | R3: 13 | S3: 13 | T3: 13 | U3: 13 | V3: 13 | W3: 12 | X3: 11 | Y3: 10 | Z3: 9 | AA3: 8 | AB3: 8 | AC3: 6 | AD3: 6 | AE3: 6 | AF3: 6 | AG3: 5 | AH3: 5 | AI3: 5 | AJ3: 4 | AK3: 4 | AL3: 4 | AM3: 4 | AN3: 3 | AO3: 2 | AP3: 2 | AQ3: 2 | AR3: 2 | AS3: 2 | AT3: 2 | AU3: 2 | AV3: 2 | AW3: 2 | AX3: 2 | AY3: 2 | AZ3: 2 | BA3: 2 | BB3: 1 | BC3: 1 | BD3: 1 | BE3: 1 | BF3: 1 | BG3: 0 | BH3: 0 | BI3: 0 | BJ3: 0 | BK3: 0 | BL3: 0
A4: pl_count | B4: 0 | C4: 0 | D4: 0 | E4: 0 | F4: 0 | G4: 0 | H4: 0 | I4: 0 | J4: 0 | K4: 0 | L4: 0 | M4: 0 | N4: 0 | O4: 0 | P4: 0 | Q4: 0 | R4: 0 | S4: 0 | T4: 0 | U4: 0 | V4: 0 | W4: 0 | X4: 0 | Y4: 0 | Z4: 0 | AA4: 0 | AB4: 0 | AC4: 0 | AD4: 0 | AE4: 0 | AF4: 0 | AG4: 0 | AH4: 0 | AI4: 0 | AJ4: 0 | AK4: 0 | AL4: 0 | AM4: 0 | AN4: 0 | AO4: 0 | AP4: 0 | AQ4: 0 | AR4: 0 | AS4: 0 | AT4: 0 | AU4: 0 | AV4: 0 | AW4: 0 | AX4: 0 | AY4: 0 | AZ4: 0 | BA4: 0 | BB4: 0 | BC4: 0 | BD4: 0 | BE4: 0 | BF4: 0 | BG4: 0 | BH4: 0 | BI4: 0 | BJ4: 0 | BK4: 0 | BL4: 0
A5: revenue_p_m | B5: 4962187.6 | C5: 4172192.8 | D5: 4125217.5 | E5: 3985602.6 | F5: 3908387.9 | G5: 3881528.1 | H5: 3719033.9 | I5: 3675761.8 | J5: 3662318.8 | K5: 3644039.8 | L5: 3493851.7 | M5: 3368205.8 | N5: 3098877.1 | O5: 2964392.4 | P5: 2858410.3 | Q5: 2763297.3 | R5: 2568700.6 | S5: 2477895.6 | T5: 2347004.5 | U5: 2239170.5 | V5: 2150987.5 | W5: 2065239.3 | X5: 1966785.6 | Y5: 1902066.5 | Z5: 1810962.2 | AA5: 1777110.1 | AB5: 1674406.2 | AC5: 1588462 | AD5: 1540260.1 | AE5: 1421304.5 | AF5: 1403328.1 | AG5: 1382263.9 | AH5: 1382263.9 | AI5: 1332494.2 | AJ5: 1246150.6 | AK5: 1075462.7 | AL5: 884121.3 | AM5: 872779.83 | AN5: 810616.81 | AO5: 733333.36 | AP5: 665338.36 | AQ5: 594758.88 | AR5: 513115.45 | AS5: 513115.45 | AT5: 452820.35 | AU5: 414001.8 | AV5: 364513.69 | AW5: 352715.13 | AX5: 327538.32 | AY5: 320510.12 | AZ5: 310494.33 | BA5: 298305.72 | BB5: 265106.21 | BC5: 242757.47 | BD5: 189192.61 | BE5: 170847.19 | BF5: 164578.86 | BG5: 138315.89 | BH5: 100642.59 | BI5: 45172.83 | BJ5: 0 | BK5: 0 | BL5: 0
A6: depreciation_p_m | B6: 2668122.3 | C6: 2267367.5 | D6: 2240025.9 | E6: 2161712 | F6: 2113937.3 | G6: 2096871.8 | H6: 1998904.2 | I6: 1976975.3 | J6: 1972099.1 | K6: 1962244.3 | L6: 1877055.8 | M6: 1802993.2 | N6: 1654241.2 | O6: 1584406.1 | P6: 1525881 | Q6: 1475919.4 | R6: 1365854.4 | S6: 1312184.2 | T6: 1236623.3 | U6: 1177073.8 | V6: 1127379.5 | W6: 1079275.6 | X6: 1033510.3 | Y6: 1008357.8 | Z6: 956569.88 | AA6: 935638.39 | AB6: 874437.52 | AC6: 830868.74 | AD6: 801981.73 | AE6: 737504.41 | AF6: 726584.72 | AG6: 714367.96 | AH6: 714367.96 | AI6: 685113.89 | AJ6: 634796.55 | AK6: 547650.34 | AL6: 448118.92 | AM6: 443221.76 | AN6: 408766.49 | AO6: 381348.41 | AP6: 345824.59 | AQ6: 314089.43 | AR6: 274346.69 | AS6: 274346.69 | AT6: 240760.03 | AU6: 219325.95 | AV6: 201073.57 | AW6: 194339.66 | AX6: 182179.67 | AY6: 178766.57 | AZ6: 173781.54 | BA6: 167495.58 | BB6: 147114.84 | BC6: 134897.2 | BD6: 106340.69 | BE6: 95868.84 | BF6: 92341.94 | BG6: 76745.71 | BH6: 55748.98 | BI6: 21780.23 | BJ6: 0 | BK6: 0 | BL6: 0
A7: interest_p_m | B7: 737545.95 | C7: 630685.61 | D7: 624938.06 | E7: 608178.83 | F7: 599924.16 | G7: 596784.9 | H7: 571897.16 | I7: 565384.11 | J7: 565193.46 | K7: 563069.12 | L7: 549646.93 | M7: 529829.86 | N7: 481913.7 | O7: 457477 | P7: 442866.58 | Q7: 425863.73 | R7: 389616.41 | S7: 379259.43 | T7: 361778.06 | U7: 347544.89 | V7: 334127.25 | W7: 324155.18 | X7: 312378.19 | Y7: 307073.52 | Z7: 292330.98 | AA7: 287618.74 | AB7: 273551.73 | AC7: 257511.38 | AD7: 250787.29 | AE7: 228906.93 | AF7: 225897.55 | AG7: 221656.11 | AH7: 221656.11 | AI7: 212789.07 | AJ7: 196808.58 | AK7: 170126.36 | AL7: 138547.94 | AM7: 136694.47 | AN7: 127259.41 | AO7: 118748.68 | AP7: 108896.41 | AQ7: 99144.85 | AR7: 85384.27 | AS7: 85384.27 | AT7: 77282.52 | AU7: 70519.11 | AV7: 64063 | AW7: 61523.04 | AX7: 57945.05 | AY7: 56127.53 | AZ7: 54727.51 | BA7: 52450.71 | BB7: 46247.63 | BC7: 41092.95 | BD7: 32788.33 | BE7: 29722.41 | BF7: 28697.35 | BG7: 23906.3 | BH7: 17315.74 | BI7: 7583.79 | BJ7: 0 | BK7: 0 | BL7: 0
A8: admin_p_m | B8: 471769.89 | C8: 407200.32 | D8: 404891.14 | E8: 394934.45 | F8: 389695.44 | G8: 387529.38 | H8: 373654.46 | I8: 368888.01 | J8: 367816.9 | K8: 366871.95 | L8: 359023.84 | M8: 349029.63 | N8: 318668.02 | O8: 303351.43 | P8: 296065.83 | Q8: 286005.1 | R8: 262360.39 | S8: 253998.26 | T8: 243835.2 | U8: 236874.14 | V8: 227901.47 | W8: 221129.61 | X8: 209242.1 | Y8: 201067.91 | Z8: 191185.12 | AA8: 188022.56 | AB8: 179459.59 | AC8: 170025.13 | AD8: 165931.18 | AE8: 153502.01 | AF8: 151691.17 | AG8: 148915.78 | AH8: 148915.78 | AI8: 143610.51 | AJ8: 133288.95 | AK8: 114871.01 | AL8: 93729.6 | AM8: 92700.11 | AN8: 86071.82 | AO8: 79874.15 | AP8: 73525.22 | AQ8: 67105.88 | AR8: 57917.9 | AS8: 57917.9 | AT8: 52136.59 | AU8: 48078.1 | AV8: 43428.66 | AW8: 41985.68 | AX8: 39533.64 | AY8: 38609.18 | AZ8: 37739.58 | BA8: 36426.36 | BB8: 32140.8 | BC8: 29225.96 | BD8: 23186.16 | BE8: 21269.45 | BF8: 20623.95 | BG8: 17200.02 | BH8: 12278.2 | BI8: 6155.44 | BJ8: 0 | BK8: 0 | BL8: 0
A9: maint_prov_p_m | B9: 22977696 | C9: 12435450 | D9: 12223543 | E9: 11431551 | F9: 11117320 | G9: 11048284 | H9: 10307242 | I9: 10068142 | J9: 10000577 | K9: 9890029.1 | L9: 9165476.9 | M9: 8572543.4 | N9: 7821197.3 | O9: 7330808.8 | P9: 6855876.3 | Q9: 6562705 | R9: 6094363.4 | S9: 5823487.8 | T9: 5456953.2 | U9: 5147949.1 | V9: 4897613 | W9: 4700357.8 | X9: 4237782.8 | Y9: 3924317.4 | Z9: 3677687.4 | AA9: 3532245.8 | AB9: 3284596.1 | AC9: 2901091.6 | AD9: 2805662.5 | AE9: 2528706.5 | AF9: 2490140.5 | AG9: 2457639.7 | AH9: 2457639.7 | AI9: 2333189.3 | AJ9: 2255127.7 | AK9: 2119626.6 | AL9: 1657802.6 | AM9: 1566906.3 | AN9: 1425989.9 | AO9: 1209185.2 | AP9: 1030103.7 | AQ9: 867737.94 | AR9: 644683.09 | AS9: 644683.09 | AT9: 503415.48 | AU9: 380671.47 | AV9: 287506.86 | AW9: 272181.21 | AX9: 232819.28 | AY9: 215053.18 | AZ9: 184597.14 | BA9: 159818.21 | BB9: 139927.04 | BC9: 124323 | BD9: 66731.69 | BE9: 49592.61 | BF9: 46150.76 | BG9: 38830.34 | BH9: 23517.77 | BI9: 12696.95 | BJ9: 0 | BK9: 0 | BL9: 0
A10: maintenance_fund | B10: 13257588 | C10: 8080983.3 | D10: 7963378.7 | E10: 7576470.3 | F10: 7433785.8 | G10: 7405436.7 | H10: 7025375 | I10: 6874342.2 | J10: 6851788.3 | K10: 6830399.1 | L10: 6562993.2 | M10: 6384230.6 | N10: 5963135.9 | O10: 5586774.1 | P10: 5363876.2 | Q10: 5188050.7 | R10: 4855830.2 | S10: 4610476.6 | T10: 4337029.7 | U10: 4104176.6 | V10: 3896057.7 | W10: 3753724.4 | X10: 3463700 | Y10: 3240230.8 | Z10: 3044243.6 | AA10: 2918448.3 | AB10: 2699058.2 | AC10: 2365119.3 | AD10: 2278897.9 | AE10: 2132416 | AF10: 2093850 | AG10: 2061349.2 | AH10: 2061349.2 | AI10: 1949932.9 | AJ10: 1875079.4 | AK10: 1746762.3 | AL10: 1429138.4 | AM10: 1345966.4 | AN10: 1220899 | AO10: 1038555.2 | AP10: 862786.72 | AQ10: 707880.4 | AR10: 500573.64 | AS10: 500573.64 | AT10: 424783.76 | AU10: 345252.83 | AV10: 284101.44 | AW10: 268775.79 | AX10: 229413.86 | AY10: 211647.76 | AZ10: 181191.72 | BA10: 159818.21 | BB10: 139927.04 | BC10: 124323 | BD10: 66731.69 | BE10: 49592.61 | BF10: 46150.76 | BG10: 38830.34 | BH10: 23517.77 | BI10: 12696.95 | BJ10: 0 | BK10: 0 | BL10: 0
A11: other_fee_p_m | B11: 201610.65 | C11: 179272.35 | D11: 174288.46 | E11: 172803.7 | F11: 171651.83 | G11: 171205.33 | H11: 168398.86 | I11: 167193.14 | J11: 167133.14 | K11: 167013.14 | L11: 164170.66 | M11: 163390.66 | N11: 151748.51 | O11: 146275.43 | P11: 145308.93 | Q11: 140651.81 | R11: 132877.86 | S11: 127240.21 | T11: 120023.22 | U11: 107289.47 | V11: 102814.81 | W11: 95902.29 | X11: 94995.79 | Y11: 91530.86 | Z11: 87237.95 | AA11: 87037.95 | AB11: 78823.3 | AC11: 78103.3 | AD11: 75088.87 | AE11: 68947.5 | AF11: 67609.11 | AG11: 67489.11 | AH11: 67489.11 | AI11: 66866.61 | AJ11: 64754.11 | AK11: 54191.93 | AL11: 47052.25 | AM11: 46932.25 | AN11: 45604.75 | AO11: 34648.19 | AP11: 32938.19 | AQ11: 28507.55 | AR11: 23125.95 | AS11: 23125.95 | AT11: 17007.07 | AU11: 16767.07 | AV11: 8414.19 | AW11: 8354.19 | AX11: 7101.62 | AY11: 7041.62 | AZ11: 6921.62 | BA11: 6861.62 | BB11: 6741.62 | BC11: 6561.62 | BD11: 4125.02 | BE11: 3682.52 | BF11: 3300.02 | BG11: 2475.02 | BH11: 2415.02 | BI11: 1530.02 | BJ11: 0 | BK11: 0 | BL11: 0
A12: total_cost | B12: 1.8097802e+08 | C12: 1.5321032e+08 | D12: 1.5194827e+08 | E12: 1.4798652e+08 | F12: 1.4591233e+08 | G12: 1.4513108e+08 | H12: 1.3901625e+08 | I12: 1.3717322e+08 | J12: 1.3674477e+08 | K12: 1.3624916e+08 | L12: 1.3210466e+08 | M12: 1.2750744e+08 | N12: 1.1722332e+08 | O12: 1.1210884e+08 | P12: 1.0825801e+08 | Q12: 1.0447934e+08 | R12: 96581095 | S12: 93837215 | T12: 89240027 | U12: 85863940 | V12: 82914238 | W12: 80525876 | X12: 76729938 | Y12: 74509768 | Z12: 71039290 | AA12: 69734215 | AB12: 66153890 | AC12: 62354725 | AD12: 60799103 | AE12: 56103638 | AF12: 55324298 | AG12: 54371410 | AH12: 54371410 | AI12: 52327657 | AJ12: 48690075 | AK12: 42704587 | AL12: 35549893 | AM12: 35035143 | AN12: 32344318 | AO12: 29930024 | AP12: 27246663 | AQ12: 24703133 | AR12: 21440250 | AS12: 21440250 | AT12: 19133082 | AU12: 17430516 | AV12: 15724376 | AW12: 15147183 | AX12: 14265238 | AY12: 13803005 | AZ12: 13422739 | BA12: 12897450 | BB12: 11309785 | BC12: 10143847 | BD12: 8053369.3 | BE12: 7271913.5 | BF12: 7004807.8 | BG12: 5729167.3 | BH12: 4252619 | BI12: 1773259.8 | BJ12: 0 | BK12: 0 | BL12: 0
A13: nbv | B13: 1.1214437e+08 | C13: 1.0511136e+08 | D13: 1.0237632e+08 | E13: 98605758 | F13: 95859915 | G13: 93562887 | H13: 89161929 | I13: 86476123 | J13: 84444582 | K13: 82279337 | L13: 79125103 | M13: 75552720 | N13: 68696729 | O13: 64516329 | P13: 61542210 | Q13: 58238919 | R13: 52997014 | S13: 50923658 | T13: 47804519 | U13: 45305156 | V13: 42994852 | W13: 41079028 | X13: 38951942 | Y13: 37524987 | Z13: 35534347 | AA13: 34415056 | AB13: 32736576 | AC13: 30459593 | AD13: 29293862 | AE13: 26399583 | AF13: 25461884 | AG13: 24445072 | AH13: 23730704 | AI13: 22449052 | AJ13: 20298934 | AK13: 16875186 | AL13: 13709958 | AM13: 13063489 | AN13: 12015113 | AO13: 11176423 | AP13: 10052884 | AQ13: 9159043.9 | AR13: 7808893.9 | AS13: 7534547.2 | AT13: 6955467.4 | AU13: 6299129.5 | AV13: 5565394.4 | AW13: 5191162.5 | AX13: 4764551.4 | AY13: 4334182.6 | AZ13: 4072536.3 | BA13: 3750622.9 | BB13: 3254218.5 | BC13: 2668239.6 | BD13: 2127698.9 | BE13: 1868213.4 | BF13: 1713325.9 | BG13: 1326416.1 | BH13: 1011929.1 | BI13: 496230.26 | BJ13: 0 | BK13: 0 | BL13: 0
... A16: olmm_fleet_drop | B16: 0 | C16: 4 | D16: 0 | E16: 0 | F16: 1 | G16: 1 | H16: 1 | I16: 1 | J16: 0 | K16: 0 | L16: 1 | M16: 1 | N16: 0 | O16: 0 | P16: 0 | Q16: 0 | R16: 1 | S16: 0 | T16: 0 | U16: 0 | V16: 0 | W16: 1 | X16: 1 | Y16: 1 | Z16: 1 | AA16: 1 | AB16: 0 | AC16: 2 | AD16: 0 | AE16: 0 | AF16: 0 | AG16: 1 | AH16: 0 | AI16: 0 | AJ16: 1 | AK16: 0 | AL16: 0 | AM16: 0 | AN16: 1 | AO16: 1 | AP16: 0 | AQ16: 0 | AR16: 0 | AS16: 0 | AT16: 0 | AU16: 0 | AV16: 0 | AW16: 0 | AX16: 0 | AY16: 0 | AZ16: 0 | BA16: 0 | BB16: 1 | BC16: 0 | BD16: 0 | BE16: 0 | BF16: 0 | BG16: 1 | BH16: 0 | BI16: 0 | BJ16: 0 | BK16: 0 | BL16: 0

Sheet GHA
A1: Value | B1: 2025/06/06 | C1: 2025/06/30 | D1: 2025/07/31 | E1: 2025/08/31 | F1: 2025/09/30 | G1: 2025/10/31 | H1: 2025/11/30 | I1: 2025/12/31 | J1: 2026/01/31 | K1: 2026/02/28 | L1: 2026/03/31 | M1: 2026/04/30 | N1: 2026/05/31 | O1: 2026/06/30 | P1: 2026/07/31 | Q1: 2026/08/31 | R1: 2026/09/30 | S1: 2026/10/31 | T1: 2026/11/30 | U1: 2026/12/31 | V1: 2027/01/31 | W1: 2027/02/28 | X1: 2027/03/31 | Y1: 2027/04/30 | Z1: 2027/05/31 | AA1: 2027/06/30 | AB1: 2027/07/31 | AC1: 2027/08/31 | AD1: 2027/09/30 | AE1: 2027/10/31 | AF1: 2027/11/30 | AG1: 2027/12/31 | AH1: 2028/01/31 | AI1: 2028/02/29 | AJ1: 2028/03/31 | AK1: 2028/04/30 | AL1: 2028/05/31 | AM1: 2028/06/30 | AN1: 2028/07/31 | AO1: 2028/08/31 | AP1: 2028/09/30 | AQ1: 2028/10/31 | AR1: 2028/11/30 | AS1: 2028/12/31 | AT1: 2029/01/31 | AU1: 2029/02/28 | AV1: 2029/03/31 | AW1: 2029/04/30 | AX1: 2029/05/31 | AY1: 2029/06/30 | AZ1: 2029/07/31 | BA1: 2029/08/31 | BB1: 2029/09/30 | BC1: 2029/10/31 | BD1: 2029/11/30 | BE1: 2029/12/31 | BF1: 2030/01/31 | BG1: 2030/02/28 | BH1: 2030/03/31 | BI1: 2030/04/30 | BJ1: 2030/05/31 | BK1: 2030/06/30 | BL1: 2030/07/31
A2: fml_count | B2: 11 | C2: 11 | D2: 11 | E2: 10 | F2: 4 | G2: 4 | H2: 4 | I2: 0 | J2: 0 | K2: 0 | L2: 0 | M2: 0 | N2: 0 | O2: 0 | P2: 0 | Q2: 0 | R2: 0 | S2: 0 | T2: 0 | U2: 0 | V2: 0 | W2: 0 | X2: 0 | Y2: 0 | Z2: 0 | AA2: 0 | AB2: 0 | AC2: 0 | AD2: 0 | AE2: 0 | AF2: 0 | AG2: 0 | AH2: 0 | AI2: 0 | AJ2: 0 | AK2: 0 | AL2: 0 | AM2: 0 | AN2: 0 | AO2: 0 | AP2: 0 | AQ2: 0 | AR2: 0 | AS2: 0 | AT2: 0 | AU2: 0 | AV2: 0 | AW2: 0 | AX2: 0 | AY2: 0 | AZ2: 0 | BA2: 0 | BB2: 0 | BC2: 0 | BD2: 0 | BE2: 0 | BF2: 0 | BG2: 0 | BH2: 0 | BI2: 0 | BJ2: 0 | BK2: 0 | BL2: 0
A3: olmm_count | B3: 0 | C3: 0 | D3: 0 | E3: 0 | F3: 0 | G3: 0 | H3: 0 | I3: 0 | J3: 0 | K3: 0 | L3: 0 | M3: 0 | N3: 0 | O3: 0 | P3: 0 | Q3: 0 | R3: 0 | S3: 0 | T3: 0 | U3: 0 | V3: 0 | W3: 0 | X3: 0 | Y3: 0 | Z3: 0 | AA3: 0 | AB3: 0 | AC3: 0 | AD3: 0 | AE3: 0 | AF3: 0 | AG3: 0 | AH3: 0 | AI3: 0 | AJ3: 0 | AK3: 0 | AL3: 0 | AM3: 0 | AN3: 0 | AO3: 0 | AP3: 0 | AQ3: 0 | AR3: 0 | AS3: 0 | AT3: 0 | AU3: 0 | AV3: 0 | AW3: 0 | AX3: 0 | AY3: 0 | AZ3: 0 | BA3: 0 | BB3: 0 | BC3: 0 | BD3: 0 | BE3: 0 | BF3: 0 | BG3: 0 | BH3: 0 | BI3: 0 | BJ3: 0 | BK3: 0 | BL3: 0
A4: pl_count | B4: 0 | C4: 0 | D4: 0 | E4: 0 | F4: 0 | G4: 0 | H4: 0 | I4: 0 | J4: 0 | K4: 0 | L4: 0 | M4: 0 | N4: 0 | O4: 0 | P4: 0 | Q4: 0 | R4: 0 | S4: 0 | T4: 0 | U4: 0 | V4: 0 | W4: 0 | X4: 0 | Y4: 0 | Z4: 0 | AA4: 0 | AB4: 0 | AC4: 0 | AD4: 0 | AE4: 0 | AF4: 0 | AG4: 0 | AH4: 0 | AI4: 0 | AJ4: 0 | AK4: 0 | AL4: 0 | AM4: 0 | AN4: 0 | AO4: 0 | AP4: 0 | AQ4: 0 | AR4: 0 | AS4: 0 | AT4: 0 | AU4: 0 | AV4: 0 | AW4: 0 | AX4: 0 | AY4: 0 | AZ4: 0 | BA4: 0 | BB4: 0 | BC4: 0 | BD4: 0 | BE4: 0 | BF4: 0 | BG4: 0 | BH4: 0 | BI4: 0 | BJ4: 0 | BK4: 0 | BL4: 0
A5: revenue_p_m | B5: 8735.23 | C5: 8735.23 | D5: 8735.23 | E5: 8340.19 | F5: 1804.33 | G5: 1804.33 | H5: 1804.33 | I5: 0 | J5: 0 | K5: 0 | L5: 0 | M5: 0 | N5: 0 | O5: 0 | P5: 0 | Q5: 0 | R5: 0 | S5: 0 | T5: 0 | U5: 0 | V5: 0 | W5: 0 | X5: 0 | Y5: 0 | Z5: 0 | AA5: 0 | AB5: 0 | AC5: 0 | AD5: 0 | AE5: 0 | AF5: 0 | AG5: 0 | AH5: 0 | AI5: 0 | AJ5: 0 | AK5: 0 | AL5: 0 | AM5: 0 | AN5: 0 | AO5: 0 | AP5: 0 | AQ5: 0 | AR5: 0 | AS5: 0 | AT5: 0 | AU5: 0 | AV5: 0 | AW5: 0 | AX5: 0 | AY5: 0 | AZ5: 0 | BA5: 0 | BB5: 0 | BC5: 0 | BD5: 0 | BE5: 0 | BF5: 0 | BG5: 0 | BH5: 0 | BI5: 0 | BJ5: 0 | BK5: 0 | BL5: 0
A6: depreciation_p_m | B6: 2927.43 | C6: 2927.43 | D6: 2927.43 | E6: 2860.57 | F6: 358.15 | G6: 358.15 | H6: 358.15 | I6: 0 | J6: 0 | K6: 0 | L6: 0 | M6: 0 | N6: 0 | O6: 0 | P6: 0 | Q6: 0 | R6: 0 | S6: 0 | T6: 0 | U6: 0 | V6: 0 | W6: 0 | X6: 0 | Y6: 0 | Z6: 0 | AA6: 0 | AB6: 0 | AC6: 0 | AD6: 0 | AE6: 0 | AF6: 0 | AG6: 0 | AH6: 0 | AI6: 0 | AJ6: 0 | AK6: 0 | AL6: 0 | AM6: 0 | AN6: 0 | AO6: 0 | AP6: 0 | AQ6: 0 | AR6: 0 | AS6: 0 | AT6: 0 | AU6: 0 | AV6: 0 | AW6: 0 | AX6: 0 | AY6: 0 | AZ6: 0 | BA6: 0 | BB6: 0 | BC6: 0 | BD6: 0 | BE6: 0 | BF6: 0 | BG6: 0 | BH6: 0 | BI6: 0 | BJ6: 0 | BK6: 0 | BL6: 0
A7: interest_p_m | B7: 1197.83 | C7: 1197.83 | D7: 1197.83 | E7: 1172.72 | F7: 316.52 | G7: 316.52 | H7: 316.52 | I7: 0 | J7: 0 | K7: 0 | L7: 0 | M7: 0 | N7: 0 | O7: 0 | P7: 0 | Q7: 0 | R7: 0 | S7: 0 | T7: 0 | U7: 0 | V7: 0 | W7: 0 | X7: 0 | Y7: 0 | Z7: 0 | AA7: 0 | AB7: 0 | AC7: 0 | AD7: 0 | AE7: 0 | AF7: 0 | AG7: 0 | AH7: 0 | AI7: 0 | AJ7: 0 | AK7: 0 | AL7: 0 | AM7: 0 | AN7: 0 | AO7: 0 | AP7: 0 | AQ7: 0 | AR7: 0 | AS7: 0 | AT7: 0 | AU7: 0 | AV7: 0 | AW7: 0 | AX7: 0 | AY7: 0 | AZ7: 0 | BA7: 0 | BB7: 0 | BC7: 0 | BD7: 0 | BE7: 0 | BF7: 0 | BG7: 0 | BH7: 0 | BI7: 0 | BJ7: 0 | BK7: 0 | BL7: 0
A8: admin_p_m | B8: 1129.54 | C8: 1129.54 | D8: 1129.54 | E8: 1049.54 | F8: 320 | G8: 320 | H8: 320 | I8: 0 | J8: 0 | K8: 0 | L8: 0 | M8: 0 | N8: 0 | O8: 0 | P8: 0 | Q8: 0 | R8: 0 | S8: 0 | T8: 0 | U8: 0 | V8: 0 | W8: 0 | X8: 0 | Y8: 0 | Z8: 0 | AA8: 0 | AB8: 0 | AC8: 0 | AD8: 0 | AE8: 0 | AF8: 0 | AG8: 0 | AH8: 0 | AI8: 0 | AJ8: 0 | AK8: 0 | AL8: 0 | AM8: 0 | AN8: 0 | AO8: 0 | AP8: 0 | AQ8: 0 | AR8: 0 | AS8: 0 | AT8: 0 | AU8: 0 | AV8: 0 | AW8: 0 | AX8: 0 | AY8: 0 | AZ8: 0 | BA8: 0 | BB8: 0 | BC8: 0 | BD8: 0 | BE8: 0 | BF8: 0 | BG8: 0 | BH8: 0 | BI8: 0 | BJ8: 0 | BK8: 0 | BL8: 0
A9: maint_prov_p_m | B9: 89467.93 | C9: 89467.93 | D9: 89467.93 | E9: 83784.47 | F9: 21412.67 | G9: 21412.67 | H9: 21412.67 | I9: 0 | J9: 0 | K9: 0 | L9: 0 | M9: 0 | N9: 0 | O9: 0 | P9: 0 | Q9: 0 | R9: 0 | S9: 0 | T9: 0 | U9: 0 | V9: 0 | W9: 0 | X9: 0 | Y9: 0 | Z9: 0 | AA9: 0 | AB9: 0 | AC9: 0 | AD9: 0 | AE9: 0 | AF9: 0 | AG9: 0 | AH9: 0 | AI9: 0 | AJ9: 0 | AK9: 0 | AL9: 0 | AM9: 0 | AN9: 0 | AO9: 0 | AP9: 0 | AQ9: 0 | AR9: 0 | AS9: 0 | AT9: 0 | AU9: 0 | AV9: 0 | AW9: 0 | AX9: 0 | AY9: 0 | AZ9: 0 | BA9: 0 | BB9: 0 | BC9: 0 | BD9: 0 | BE9: 0 | BF9: 0 | BG9: 0 | BH9: 0 | BI9: 0 | BJ9: 0 | BK9: 0 | BL9: 0
A10: maintenance_fund | B10: 50104 | C10: 50104 | D10: 50104 | E10: 46766.11 | F10: 5594.12 | G10: 5594.12 | H10: 5594.12 | I10: 0 | J10: 0 | K10: 0 | L10: 0 | M10: 0 | N10: 0 | O10: 0 | P10: 0 | Q10: 0 | R10: 0 | S10: 0 | T10: 0 | U10: 0 | V10: 0 | W10: 0 | X10: 0 | Y10: 0 | Z10: 0 | AA10: 0 | AB10: 0 | AC10: 0 | AD10: 0 | AE10: 0 | AF10: 0 | AG10: 0 | AH10: 0 | AI10: 0 | AJ10: 0 | AK10: 0 | AL10: 0 | AM10: 0 | AN10: 0 | AO10: 0 | AP10: 0 | AQ10: 0 | AR10: 0 | AS10: 0 | AT10: 0 | AU10: 0 | AV10: 0 | AW10: 0 | AX10: 0 | AY10: 0 | AZ10: 0 | BA10: 0 | BB10: 0 | BC10: 0 | BD10: 0 | BE10: 0 | BF10: 0 | BG10: 0 | BH10: 0 | BI10: 0 | BJ10: 0 | BK10: 0 | BL10: 0
A11: other_fee_p_m | B11: 2003.25 | C11: 2003.25 | D11: 2003.25 | E11: 1894.52 | F11: 434.84 | G11: 434.84 | H11: 434.84 | I11: 0 | J11: 0 | K11: 0 | L11: 0 | M11: 0 | N11: 0 | O11: 0 | P11: 0 | Q11: 0 | R11: 0 | S11: 0 | T11: 0 | U11: 0 | V11: 0 | W11: 0 | X11: 0 | Y11: 0 | Z11: 0 | AA11: 0 | AB11: 0 | AC11: 0 | AD11: 0 | AE11: 0 | AF11: 0 | AG11: 0 | AH11: 0 | AI11: 0 | AJ11: 0 | AK11: 0 | AL11: 0 | AM11: 0 | AN11: 0 | AO11: 0 | AP11: 0 | AQ11: 0 | AR11: 0 | AS11: 0 | AT11: 0 | AU11: 0 | AV11: 0 | AW11: 0 | AX11: 0 | AY11: 0 | AZ11: 0 | BA11: 0 | BB11: 0 | BC11: 0 | BD11: 0 | BE11: 0 | BF11: 0 | BG11: 0 | BH11: 0 | BI11: 0 | BJ11: 0 | BK11: 0 | BL11: 0
A12: total_cost | B12: 245056.84 | C12: 245056.84 | D12: 245056.84 | E12: 231755.14 | F12: 53197 | G12: 53197 | H12: 53197 | I12: 0 | J12: 0 | K12: 0 | L12: 0 | M12: 0 | N12: 0 | O12: 0 | P12: 0 | Q12: 0 | R12: 0 | S12: 0 | T12: 0 | U12: 0 | V12: 0 | W12: 0 | X12: 0 | Y12: 0 | Z12: 0 | AA12: 0 | AB12: 0 | AC12: 0 | AD12: 0 | AE12: 0 | AF12: 0 | AG12: 0 | AH12: 0 | AI12: 0 | AJ12: 0 | AK12: 0 | AL12: 0 | AM12: 0 | AN12: 0 | AO12: 0 | AP12: 0 | AQ12: 0 | AR12: 0 | AS12: 0 | AT12: 0 | AU12: 0 | AV12: 0 | AW12: 0 | AX12: 0 | AY12: 0 | AZ12: 0 | BA12: 0 | BB12: 0 | BC12: 0 | BD12: 0 | BE12: 0 | BF12: 0 | BG12: 0 | BH12: 0 | BI12: 0 | BJ12: 0 | BK12: 0 | BL12: 0
A13: nbv | B13: 87189.01 | C13: 87189.01 | D13: 84261.58 | E13: 79450.09 | F13: 15643.02 | G13: 15284.87 | H13: 14926.72 | I13: 0 | J13: 0 | K13: 0 | L13: 0 | M13: 0 | N13: 0 | O13: 0 | P13: 0 | Q13: 0 | R13: 0 | S13: 0 | T13: 0 | U13: 0 | V13: 0 | W13: 0 | X13: 0 | Y13: 0 | Z13: 0 | AA13: 0 | AB13: 0 | AC13: 0 | AD13: 0 | AE13: 0 | AF13: 0 | AG13: 0 | AH13: 0 | AI13: 0 | AJ13: 0 | AK13: 0 | AL13: 0 | AM13: 0 | AN13: 0 | AO13: 0 | AP13: 0 | AQ13: 0 | AR13: 0 | AS13: 0 | AT13: 0 | AU13: 0 | AV13: 0 | AW13: 0 | AX13: 0 | AY13: 0 | AZ13: 0 | BA13: 0 | BB13: 0 | BC13: 0 | BD13: 0 | BE13: 0 | BF13: 0 | BG13: 0 | BH13: 0 | BI13: 0 | BJ13: 0 | BK13: 0 | BL13: 0
... A16: olmm_fleet_drop | B16: 0 | C16: 0 | D16: 0 | E16: 0 | F16: 0 | G16: 0 | H16: 0 | I16: 0 | J16: 0 | K16: 0 | L16: 0 | M16: 0 | N16: 0 | O16: 0 | P16: 0 | Q16: 0 | R16: 0 | S16: 0 | T16: 0 | U16: 0 | V16: 0 | W16: 0 | X16: 0 | Y16: 0 | Z16: 0 | AA16: 0 | AB16: 0 | AC16: 0 | AD16: 0 | AE16: 0 | AF16: 0 | AG16: 0 | AH16: 0 | AI16: 0 | AJ16: 0 | AK16: 0 | AL16: 0 | AM16: 0 | AN16: 0 | AO16: 0 | AP16: 0 | AQ16: 0 | AR16: 0 | AS16: 0 | AT16: 0 | AU16: 0 | AV16: 0 | AW16: 0 | AX16: 0 | AY16: 0 | AZ16: 0 | BA16: 0 | BB16: 0 | BC16: 0 | BD16: 0 | BE16: 0 | BF16: 0 | BG16: 0 | BH16: 0 | BI16: 0 | BJ16: 0 | BK16: 0 | BL16: 0

Sheet GHC
A1: Value | B1: 2025/06/06 | C1: 2025/06/30 | D1: 2025/07/31 | E1: 2025/08/31 | F1: 2025/09/30 | G1: 2025/10/31 | H1: 2025/11/30 | I1: 2025/12/31 | J1: 2026/01/31 | K1: 2026/02/28 | L1: 2026/03/31 | M1: 2026/04/30 | N1: 2026/05/31 | O1: 2026/06/30 | P1: 2026/07/31 | Q1: 2026/08/31 | R1: 2026/09/30 | S1: 2026/10/31 | T1: 2026/11/30 | U1: 2026/12/31 | V1: 2027/01/31 | W1: 2027/02/28 | X1: 2027/03/31 | Y1: 2027/04/30 | Z1: 2027/05/31 | AA1: 2027/06/30 | AB1: 2027/07/31 | AC1: 2027/08/31 | AD1: 2027/09/30 | AE1: 2027/10/31 | AF1: 2027/11/30 | AG1: 2027/12/31 | AH1: 2028/01/31 | AI1: 2028/02/29 | AJ1: 2028/03/31 | AK1: 2028/04/30 | AL1: 2028/05/31 | AM1: 2028/06/30 | AN1: 2028/07/31 | AO1: 2028/08/31 | AP1: 2028/09/30 | AQ1: 2028/10/31 | AR1: 2028/11/30 | AS1: 2028/12/31 | AT1: 2029/01/31 | AU1: 2029/02/28 | AV1: 2029/03/31 | AW1: 2029/04/30 | AX1: 2029/05/31 | AY1: 2029/06/30 | AZ1: 2029/07/31 | BA1: 2029/08/31 | BB1: 2029/09/30 | BC1: 2029/10/31 | BD1: 2029/11/30 | BE1: 2029/12/31 | BF1: 2030/01/31 | BG1: 2030/02/28 | BH1: 2030/03/31 | BI1: 2030/04/30 | BJ1: 2030/05/31 | BK1: 2030/06/30 | BL1: 2030/07/31
A2: fml_count | B2: 163 | C2: 139 | D2: 137 | E2: 136 | F2: 135 | G2: 135 | H2: 135 | I2: 134 | J2: 133 | K2: 128 | L2: 120 | M2: 119 | N2: 107 | O2: 104 | P2: 103 | Q2: 67 | R2: 65 | S2: 65 | T2: 65 | U2: 65 | V2: 64 | W2: 63 | X2: 58 | Y2: 57 | Z2: 57 | AA2: 46 | AB2: 46 | AC2: 46 | AD2: 46 | AE2: 46 | AF2: 46 | AG2: 46 | AH2: 44 | AI2: 44 | AJ2: 44 | AK2: 44 | AL2: 44 | AM2: 44 | AN2: 43 | AO2: 43 | AP2: 42 | AQ2: 42 | AR2: 42 | AS2: 42 | AT2: 42 | AU2: 42 | AV2: 42 | AW2: 42 | AX2: 41 | AY2: 1 | AZ2: 1 | BA2: 1 | BB2: 0 | BC2: 0 | BD2: 0 | BE2: 0 | BF2: 0 | BG2: 0 | BH2: 0 | BI2: 0 | BJ2: 0 | BK2: 0 | BL2: 0
A3: olmm_count | B3: 0 | C3: 0 | D3: 0 | E3: 0 | F3: 0 | G3: 0 | H3: 0 | I3: 0 | J3: 0 | K3: 0 | L3: 0 | M3: 0 | N3: 0 | O3: 0 | P3: 0 | Q3: 0 | R3: 0 | S3: 0 | T3: 0 | U3: 0 | V3: 0 | W3: 0 | X3: 0 | Y3: 0 | Z3: 0 | AA3: 0 | AB3: 0 | AC3: 0 | AD3: 0 | AE3: 0 | AF3: 0 | AG3: 0 | AH3: 0 | AI3: 0 | AJ3: 0 | AK3: 0 | AL3: 0 | AM3: 0 | AN3: 0 | AO3: 0 | AP3: 0 | AQ3: 0 | AR3: 0 | AS3: 0 | AT3: 0 | AU3: 0 | AV3: 0 | AW3: 0 | AX3: 0 | AY3: 0 | AZ3: 0 | BA3: 0 | BB3: 0 | BC3: 0 | BD3: 0 | BE3: 0 | BF3: 0 | BG3: 0 | BH3: 0 | BI3: 0 | BJ3: 0 | BK3: 0 | BL3: 0
A4: pl_count | B4: 0 | C4: 0 | D4: 0 | E4: 0 | F4: 0 | G4: 0 | H4: 0 | I4: 0 | J4: 0 | K4: 0 | L4: 0 | M4: 0 | N4: 0 | O4: 0 | P4: 0 | Q4: 0 | R4: 0 | S4: 0 | T4: 0 | U4: 0 | V4: 0 | W4: 0 | X4: 0 | Y4: 0 | Z4: 0 | AA4: 0 | AB4: 0 | AC4: 0 | AD4: 0 | AE4: 0 | AF4: 0 | AG4: 0 | AH4: 0 | AI4: 0 | AJ4: 0 | AK4: 0 | AL4: 0 | AM4: 0 | AN4: 0 | AO4: 0 | AP4: 0 | AQ4: 0 | AR4: 0 | AS4: 0 | AT4: 0 | AU4: 0 | AV4: 0 | AW4: 0 | AX4: 0 | AY4: 0 | AZ4: 0 | BA4: 0 | BB4: 0 | BC4: 0 | BD4: 0 | BE4: 0 | BF4: 0 | BG4: 0 | BH4: 0 | BI4: 0 | BJ4: 0 | BK4: 0 | BL4: 0
A5: revenue_p_m | B5: 2648489 | C5: 2464196.9 | D5: 2456677.2 | E5: 2450630.3 | F5: 2439276.6 | G5: 2439276.6 | H5: 2439276.6 | I5: 2428596.8 | J5: 2423689.9 | K5: 2377064.3 | L5: 2310233.7 | M5: 2298084.8 | N5: 2187806.4 | O5: 2136713.9 | P5: 2128616 | Q5: 1770250.2 | R5: 1739046.3 | S5: 1739046.3 | T5: 1739046.3 | U5: 1739046.3 | V5: 1711860.9 | W5: 1700335.2 | X5: 1649701.6 | Y5: 1639720.3 | Z5: 1639720.3 | AA5: 1307002.4 | AB5: 1307002.4 | AC5: 1307002.4 | AD5: 1307002.4 | AE5: 1307002.4 | AF5: 1307002.4 | AG5: 1307002.4 | AH5: 1261301.6 | AI5: 1261301.6 | AJ5: 1261301.6 | AK5: 1261301.6 | AL5: 1261301.6 | AM5: 1261301.6 | AN5: 1242826.4 | AO5: 1242826.4 | AP5: 1222232.9 | AQ5: 1222232.9 | AR5: 1222232.9 | AS5: 1222232.9 | AT5: 1222232.9 | AU5: 1222232.9 | AV5: 1222232.9 | AW5: 1222232.9 | AX5: 1170874.2 | AY5: 53283.12 | AZ5: 53283.12 | BA5: 53283.12 | BB5: 0 | BC5: 0 | BD5: 0 | BE5: 0 | BF5: 0 | BG5: 0 | BH5: 0 | BI5: 0 | BJ5: 0 | BK5: 0 | BL5: 0
A6: depreciation_p_m | B6: 711918.8 | C6: 664816.9 | D6: 664816.9 | E6: 664259.79 | F6: 662888.39 | G6: 662888.39 | H6: 662888.39 | I6: 661902.26 | J6: 661324.82 | K6: 656122.09 | L6: 645828.81 | M6: 643623 | N6: 609016.92 | O6: 595603.6 | P6: 593708.86 | Q6: 527237.59 | R6: 519042.58 | S6: 519042.58 | T6: 519042.58 | U6: 519042.58 | V6: 512261.4 | W6: 508659.36 | X6: 495130.56 | Y6: 492127.29 | Z6: 492127.29 | AA6: 370437.75 | AB6: 370437.75 | AC6: 370437.75 | AD6: 370437.75 | AE6: 370437.75 | AF6: 370437.75 | AG6: 370437.75 | AH6: 358295.09 | AI6: 358295.09 | AJ6: 358295.09 | AK6: 358295.09 | AL6: 358295.09 | AM6: 358295.09 | AN6: 353041.51 | AO6: 353041.51 | AP6: 347492.57 | AQ6: 347492.57 | AR6: 347492.57 | AS6: 347492.57 | AT6: 347492.57 | AU6: 347492.57 | AV6: 347492.57 | AW6: 347492.57 | AX6: 332726.37 | AY6: 17606.19 | AZ6: 17606.19 | BA6: 17606.19 | BB6: 0 | BC6: 0 | BD6: 0 | BE6: 0 | BF6: 0 | BG6: 0 | BH6: 0 | BI6: 0 | BJ6: 0 | BK6: 0 | BL6: 0
A7: interest_p_m | B7: 812546.68 | C7: 795400.15 | D7: 794218.02 | E7: 794491.4 | F7: 792434.67 | G7: 792434.67 | H7: 792434.67 | I7: 791160.36 | J7: 789958.74 | K7: 783205.84 | L7: 763649.5 | M7: 760768.63 | N7: 732240.85 | O7: 711861.73 | P7: 708871.4 | Q7: 612349.69 | R7: 601957.72 | S7: 601957.72 | T7: 601957.72 | U7: 601957.72 | V7: 590185.74 | W7: 587066.81 | X7: 574022.85 | Y7: 571345.17 | Z7: 571345.17 | AA7: 464310.5 | AB7: 464310.5 | AC7: 464310.5 | AD7: 464310.5 | AE7: 464310.5 | AF7: 464310.5 | AG7: 464310.5 | AH7: 449171.74 | AI7: 449171.74 | AJ7: 449171.74 | AK7: 449171.74 | AL7: 449171.74 | AM7: 449171.74 | AN7: 442712.32 | AO7: 442712.32 | AP7: 435084.11 | AQ7: 435084.11 | AR7: 435084.11 | AS7: 435084.11 | AT7: 435084.11 | AU7: 435084.11 | AV7: 435084.11 | AW7: 435084.11 | AX7: 412867.42 | AY7: 23615.34 | AZ7: 23615.34 | BA7: 23615.34 | BB7: 0 | BC7: 0 | BD7: 0 | BE7: 0 | BF7: 0 | BG7: 0 | BH7: 0 | BI7: 0 | BJ7: 0 | BK7: 0 | BL7: 0
A8: admin_p_m | B8: 213363.24 | C8: 184478.92 | D8: 182845.42 | E8: 182133.53 | F8: 181111.15 | G8: 181111.15 | H8: 181111.15 | I8: 179143.96 | J8: 177894.13 | K8: 173074.48 | L8: 164649.03 | M8: 163195.96 | N8: 155134.61 | O8: 151750.05 | P8: 150648.85 | Q8: 108943.49 | R8: 105219.94 | S8: 105219.94 | T8: 105219.94 | U8: 105219.94 | V8: 102986.56 | W8: 101792.73 | X8: 97011.14 | Y8: 95691.57 | Z8: 95691.57 | AA8: 68504.51 | AB8: 68504.51 | AC8: 68504.51 | AD8: 68504.51 | AE8: 68504.51 | AF8: 68504.51 | AG8: 68504.51 | AH8: 64995.61 | AI8: 64995.61 | AJ8: 64995.61 | AK8: 64995.61 | AL8: 64995.61 | AM8: 64995.61 | AN8: 63594.85 | AO8: 63594.85 | AP8: 62533.85 | AQ8: 62533.85 | AR8: 62533.85 | AS8: 62533.85 | AT8: 62533.85 | AU8: 62533.85 | AV8: 62533.85 | AW8: 62533.85 | AX8: 58842.3 | AY8: 3619.07 | AZ8: 3619.07 | BA8: 3619.07 | BB8: 0 | BC8: 0 | BD8: 0 | BE8: 0 | BF8: 0 | BG8: 0 | BH8: 0 | BI8: 0 | BJ8: 0 | BK8: 0 | BL8: 0
A9: maint_prov_p_m | B9: 10083547 | C9: 7754269 | D9: 7622820.6 | E9: 7497335.1 | F9: 7426166.2 | G9: 7426166.2 | H9: 7426166.2 | I9: 7370039 | J9: 7271505.9 | K9: 6598221.2 | L9: 5902196.7 | M9: 5823477.4 | N9: 5191872.5 | O9: 5053904 | P9: 5035454 | Q9: 2648744.9 | R9: 2540937.3 | S9: 2540937.3 | T9: 2540937.3 | U9: 2540937.3 | V9: 2494870.5 | W9: 2437587.7 | X9: 2157796.9 | Y9: 2123868.8 | Z9: 2123868.8 | AA9: 1786208 | AB9: 1786208 | AC9: 1786208 | AD9: 1786208 | AE9: 1786208 | AF9: 1786208 | AG9: 1786208 | AH9: 1625088 | AI9: 1625088 | AJ9: 1625088 | AK9: 1625088 | AL9: 1625088 | AM9: 1625088 | AN9: 1576501.7 | AO9: 1576501.7 | AP9: 1548330.4 | AQ9: 1548330.4 | AR9: 1548330.4 | AS9: 1548330.4 | AT9: 1548330.4 | AU9: 1548330.4 | AV9: 1548330.4 | AW9: 1548330.4 | AX9: 1543434.4 | AY9: 70701.93 | AZ9: 70701.93 | BA9: 70701.93 | BB9: 0 | BC9: 0 | BD9: 0 | BE9: 0 | BF9: 0 | BG9: 0 | BH9: 0 | BI9: 0 | BJ9: 0 | BK9: 0 | BL9: 0
A10: maintenance_fund | B10: 5057825.7 | C10: 3704786.7 | D10: 3666380.7 | E10: 3615064.7 | F10: 3602028.9 | G10: 3602028.9 | H10: 3602028.9 | I10: 3591239.4 | J10: 3515106.5 | K10: 3371320.9 | L10: 3092610 | M10: 3033504.8 | N10: 2817811.8 | O10: 2758063.5 | P10: 2744143.6 | Q10: 1882781.5 | R10: 1855500.5 | S10: 1855500.5 | T10: 1855500.5 | U10: 1855500.5 | V10: 1823861.1 | W10: 1795684.4 | X10: 1762163 | Y10: 1757438.1 | Z10: 1757438.1 | AA10: 1540826.2 | AB10: 1540826.2 | AC10: 1540826.2 | AD10: 1540826.2 | AE10: 1540826.2 | AF10: 1540826.2 | AG10: 1540826.2 | AH10: 1433503.5 | AI10: 1433503.5 | AJ10: 1433503.5 | AK10: 1433503.5 | AL10: 1433503.5 | AM10: 1433503.5 | AN10: 1420212.3 | AO10: 1420212.3 | AP10: 1432083.1 | AQ10: 1432083.1 | AR10: 1432083.1 | AS10: 1432083.1 | AT10: 1432083.1 | AU10: 1432083.1 | AV10: 1432083.1 | AW10: 1432083.1 | AX10: 1427187.1 | AY10: 68281.91 | AZ10: 68281.91 | BA10: 68281.91 | BB10: 0 | BC10: 0 | BD10: 0 | BE10: 0 | BF10: 0 | BG10: 0 | BH10: 0 | BI10: 0 | BJ10: 0 | BK10: 0 | BL10: 0
A11: other_fee_p_m | B11: 489053.1 | C11: 463262.08 | D11: 461939.74 | E11: 461074.36 | F11: 459171.24 | G11: 459171.24 | H11: 459171.24 | I11: 457219.05 | J11: 457091.05 | K11: 452544.59 | L11: 447060.99 | M11: 444451.86 | N11: 426024.95 | O11: 416965.32 | P11: 415075.86 | Q11: 353246.17 | R11: 348247.31 | S11: 348247.31 | T11: 348247.31 | U11: 348247.31 | V11: 343308.95 | W11: 341130.2 | X11: 333531.97 | Y11: 331503.97 | Z11: 331503.97 | AA11: 267287.94 | AB11: 267287.94 | AC11: 267287.94 | AD11: 267287.94 | AE11: 267287.94 | AF11: 267287.94 | AG11: 267287.94 | AH11: 260433.48 | AI11: 260433.48 | AJ11: 260433.48 | AK11: 260433.48 | AL11: 260433.48 | AM11: 260433.48 | AN11: 257096.48 | AO11: 257096.48 | AP11: 253531.51 | AQ11: 253531.51 | AR11: 253531.51 | AS11: 253531.51 | AT11: 253531.51 | AU11: 253531.51 | AV11: 253531.51 | AW11: 253531.51 | AX11: 245295.26 | AY11: 586.75 | AZ11: 586.75 | BA11: 586.75 | BB11: 0 | BC11: 0 | BD11: 0 | BE11: 0 | BF11: 0 | BG11: 0 | BH11: 0 | BI11: 0 | BJ11: 0 | BK11: 0 | BL11: 0
A12: total_cost | B12: 59843147 | C12: 54954461 | D12: 54718417 | E12: 54616039 | F12: 54339324 | G12: 54339324 | H12: 54339324 | I12: 54033255 | J12: 53839760 | K12: 52955106 | L12: 51231636 | M12: 50906898 | N12: 48168954 | O12: 46864941 | P12: 46578883 | Q12: 37525396 | R12: 36797370 | S12: 36797370 | T12: 36797370 | U12: 36797370 | V12: 36142353 | W12: 35855833 | X12: 34732244 | Y12: 34478329 | Z12: 34478329 | AA12: 25214041 | AB12: 25214041 | AC12: 25214041 | AD12: 25214041 | AE12: 25214041 | AF12: 25214041 | AG12: 25214041 | AH12: 24371905 | AI12: 24371905 | AJ12: 24371905 | AK12: 24371905 | AL12: 24371905 | AM12: 24371905 | AN12: 23951675 | AO12: 23951675 | AP12: 23547275 | AQ12: 23547275 | AR12: 23547275 | AS12: 23547275 | AT12: 23547275 | AU12: 23547275 | AV12: 23547275 | AW12: 23547275 | AX12: 22439810 | AY12: 1240825 | AZ12: 1240825 | BA12: 1240825 | BB12: 0 | BC12: 0 | BD12: 0 | BE12: 0 | BF12: 0 | BG12: 0 | BH12: 0 | BI12: 0 | BJ12: 0 | BK12: 0 | BL12: 0
A13: nbv | B13: 36089298 | C13: 35101273 | D13: 34393459 | E13: 33717294 | F13: 32971035 | G13: 32308147 | H13: 31645259 | I13: 30904866 | J13: 30198053 | K13: 29344048 | L13: 28145645 | M13: 27407261 | N13: 26000359 | O13: 24896712 | P13: 24193551 | Q13: 21271759 | R13: 20550334 | S13: 20031291 | T13: 19512249 | U13: 18993206 | V13: 18204963 | W13: 17618701 | X13: 16819882 | Y13: 16256855 | Z13: 15764728 | AA13: 11935273 | AB13: 11564835 | AC13: 11194398 | AD13: 10823960 | AE13: 10453522 | AF13: 10083084 | AG13: 9712646.7 | AH13: 9107205.8 | AI13: 8748910.7 | AJ13: 8390615.6 | AK13: 8032320.6 | AL13: 7674025.5 | AM13: 7315730.4 | AN13: 6852419.6 | AO13: 6499378.1 | AP13: 6058006.7 | AQ13: 5710514.1 | AR13: 5363021.6 | AS13: 5015529 | AT13: 4668036.4 | AU13: 4320543.8 | AV13: 3973051.3 | AW13: 3625558.7 | AX13: 2879378.6 | AY13: 254878.36 | AZ13: 237272.17 | BA13: 219665.98 | BB13: 0 | BC13: 0 | BD13: 0 | BE13: 0 | BF13: 0 | BG13: 0 | BH13: 0 | BI13: 0 | BJ13: 0 | BK13: 0 | BL13: 0
... A16: olmm_fleet_drop | B16: 0 | C16: 0 | D16: 0 | E16: 0 | F16: 0 | G16: 0 | H16: 0 | I16: 0 | J16: 0 | K16: 0 | L16: 0 | M16: 0 | N16: 0 | O16: 0 | P16: 0 | Q16: 0 | R16: 0 | S16: 0 | T16: 0 | U16: 0 | V16: 0 | W16: 0 | X16: 0 | Y16: 0 | Z16: 0 | AA16: 0 | AB16: 0 | AC16: 0 | AD16: 0 | AE16: 0 | AF16: 0 | AG16: 0 | AH16: 0 | AI16: 0 | AJ16: 0 | AK16: 0 | AL16: 0 | AM16: 0 | AN16: 0 | AO16: 0 | AP16: 0 | AQ16: 0 | AR16: 0 | AS16: 0 | AT16: 0 | AU16: 0 | AV16: 0 | AW16: 0 | AX16: 0 | AY16: 0 | AZ16: 0 | BA16: 0 | BB16: 0 | BC16: 0 | BD16: 0 | BE16: 0 | BF16: 0 | BG16: 0 | BH16: 0 | BI16: 0 | BJ16: 0 | BK16: 0 | BL16: 0

Sheet MOZ
A1: Value | B1: 2025/06/06 | C1: 2025/06/30 | D1: 2025/07/31 | E1: 2025/08/31 | F1: 2025/09/30 | G1: 2025/10/31 | H1: 2025/11/30 | I1: 2025/12/31 | J1: 2026/01/31 | K1: 2026/02/28 | L1: 2026/03/31 | M1: 2026/04/30 | N1: 2026/05/31 | O1: 2026/06/30 | P1: 2026/07/31 | Q1: 2026/08/31 | R1: 2026/09/30 | S1: 2026/10/31 | T1: 2026/11/30 | U1: 2026/12/31 | V1: 2027/01/31 | W1: 2027/02/28 | X1: 2027/03/31 | Y1: 2027/04/30 | Z1: 2027/05/31 | AA1: 2027/06/30 | AB1: 2027/07/31 | AC1: 2027/08/31 | AD1: 2027/09/30 | AE1: 2027/10/31 | AF1: 2027/11/30 | AG1: 2027/12/31 | AH1: 2028/01/31 | AI1: 2028/02/29 | AJ1: 2028/03/31 | AK1: 2028/04/30 | AL1: 2028/05/31 | AM1: 2028/06/30 | AN1: 2028/07/31 | AO1: 2028/08/31 | AP1: 2028/09/30 | AQ1: 2028/10/31 | AR1: 2028/11/30 | AS1: 2028/12/31 | AT1: 2029/01/31 | AU1: 2029/02/28 | AV1: 2029/03/31 | AW1: 2029/04/30 | AX1: 2029/05/31 | AY1: 2029/06/30 | AZ1: 2029/07/31 | BA1: 2029/08/31 | BB1: 2029/09/30 | BC1: 2029/10/31 | BD1: 2029/11/30 | BE1: 2029/12/31 | BF1: 2030/01/31 | BG1: 2030/02/28 | BH1: 2030/03/31 | BI1: 2030/04/30 | BJ1: 2030/05/31 | BK1: 2030/06/30 | BL1: 2030/07/31
A2: fml_count | B2: 259 | C2: 224 | D2: 222 | E2: 222 | F2: 222 | G2: 215 | H2: 213 | I2: 212 | J2: 207 | K2: 206 | L2: 199 | M2: 197 | N2: 195 | O2: 193 | P2: 193 | Q2: 184 | R2: 184 | S2: 182 | T2: 181 | U2: 180 | V2: 180 | W2: 179 | X2: 179 | Y2: 170 | Z2: 157 | AA2: 156 | AB2: 129 | AC2: 116 | AD2: 98 | AE2: 98 | AF2: 90 | AG2: 84 | AH2: 82 | AI2: 78 | AJ2: 74 | AK2: 69 | AL2: 69 | AM2: 69 | AN2: 56 | AO2: 45 | AP2: 44 | AQ2: 39 | AR2: 35 | AS2: 34 | AT2: 34 | AU2: 34 | AV2: 32 | AW2: 28 | AX2: 26 | AY2: 15 | AZ2: 8 | BA2: 7 | BB2: 7 | BC2: 5 | BD2: 5 | BE2: 3 | BF2: 1 | BG2: 1 | BH2: 0 | BI2: 0 | BJ2: 0 | BK2: 0 | BL2: 0
A3: olmm_count | B3: 43 | C3: 41 | D3: 41 | E3: 40 | F3: 40 | G3: 40 | H3: 40 | I3: 38 | J3: 38 | K3: 37 | L3: 37 | M3: 36 | N3: 34 | O3: 34 | P3: 32 | Q3: 32 | R3: 22 | S3: 22 | T3: 22 | U3: 22 | V3: 22 | W3: 22 | X3: 22 | Y3: 22 | Z3: 20 | AA3: 20 | AB3: 20 | AC3: 20 | AD3: 20 | AE3: 20 | AF3: 18 | AG3: 14 | AH3: 13 | AI3: 13 | AJ3: 13 | AK3: 13 | AL3: 11 | AM3: 11 | AN3: 5 | AO3: 4 | AP3: 1 | AQ3: 1 | AR3: 1 | AS3: 1 | AT3: 0 | AU3: 0 | AV3: 0 | AW3: 0 | AX3: 0 | AY3: 0 | AZ3: 0 | BA3: 0 | BB3: 0 | BC3: 0 | BD3: 0 | BE3: 0 | BF3: 0 | BG3: 0 | BH3: 0 | BI3: 0 | BJ3: 0 | BK3: 0 | BL3: 0
A4: pl_count | B4: 0 | C4: 0 | D4: 0 | E4: 0 | F4: 0 | G4: 0 | H4: 0 | I4: 0 | J4: 0 | K4: 0 | L4: 0 | M4: 0 | N4: 0 | O4: 0 | P4: 0 | Q4: 0 | R4: 0 | S4: 0 | T4: 0 | U4: 0 | V4: 0 | W4: 0 | X4: 0 | Y4: 0 | Z4: 0 | AA4: 0 | AB4: 0 | AC4: 0 | AD4: 0 | AE4: 0 | AF4: 0 | AG4: 0 | AH4: 0 | AI4: 0 | AJ4: 0 | AK4: 0 | AL4: 0 | AM4: 0 | AN4: 0 | AO4: 0 | AP4: 0 | AQ4: 0 | AR4: 0 | AS4: 0 | AT4: 0 | AU4: 0 | AV4: 0 | AW4: 0 | AX4: 0 | AY4: 0 | AZ4: 0 | BA4: 0 | BB4: 0 | BC4: 0 | BD4: 0 | BE4: 0 | BF4: 0 | BG4: 0 | BH4: 0 | BI4: 0 | BJ4: 0 | BK4: 0 | BL4: 0
A5: revenue_p_m | B5: 22289797 | C5: 20132176 | D5: 20052084 | E5: 19951198 | F5: 19951198 | G5: 19323804 | H5: 19166127 | I5: 18770197 | J5: 18423636 | K5: 18166395 | L5: 17766140 | M5: 17520835 | N5: 17176223 | O5: 16951421 | P5: 16791160 | Q5: 16261947 | R5: 15150787 | S5: 15046075 | T5: 14968235 | U5: 14914010 | V5: 14914010 | W5: 14829864 | X5: 14829864 | Y5: 13975217 | Z5: 12761039 | AA5: 12690690 | AB5: 11404358 | AC5: 10628963 | AD5: 9555243.3 | AE5: 9555243.3 | AF5: 8906812.3 | AG5: 7825525 | AH5: 7709392.8 | AI5: 7427625.9 | AJ5: 6737289.7 | AK5: 6112159.4 | AL5: 5882997.7 | AM5: 5882997.7 | AN5: 4695630.8 | AO5: 3791164.5 | AP5: 3383430.8 | AQ5: 3068001.3 | AR5: 2767201.3 | AS5: 2725926.2 | AT5: 2647625.1 | AU5: 2647625.1 | AV5: 2514054.1 | AW5: 2151124.3 | AX5: 2071482.6 | AY5: 1440832.2 | AZ5: 825180.41 | BA5: 739875 | BB5: 739875 | BC5: 451416.89 | BD5: 451416.89 | BE5: 209410.4 | BF5: 39820.84 | BG5: 39820.84 | BH5: 0 | BI5: 0 | BJ5: 0 | BK5: 0 | BL5: 0
A6: depreciation_p_m | B6: 9376783.9 | C6: 8629957.5 | D6: 8594188.3 | E6: 8544108.2 | F6: 8544108.2 | G6: 8274468.4 | H6: 8220129.2 | I6: 7972901.1 | J6: 7837732.5 | K6: 7698862 | L6: 7548973.7 | M6: 7442444.2 | N6: 7290173 | O6: 7177898.7 | P6: 7104180.7 | Q6: 6870728.2 | R6: 6358228.2 | S6: 6316528.2 | T6: 6287425.5 | U6: 6266623 | V6: 6266623 | W6: 6230498 | X6: 6230498 | Y6: 5843218.7 | Z6: 5352893.9 | AA6: 5327376.3 | AB6: 4833354.9 | AC6: 4543569.3 | AD6: 4164762.1 | AE6: 4164762.1 | AF6: 3899115.4 | AG6: 3397160.9 | AH6: 3355401.9 | AI6: 3220288.7 | AJ6: 2856576.4 | AK6: 2514972.3 | AL6: 2407784.8 | AM6: 2407784.8 | AN6: 1919772.5 | AO6: 1528785.2 | AP6: 1339571.8 | AQ6: 1206295.4 | AR6: 1076999.1 | AS6: 1062895.7 | AT6: 1022244.5 | AU6: 1022244.5 | AV6: 973233.6 | AW6: 826087.81 | AX6: 799533.59 | AY6: 560809.36 | AZ6: 337768.15 | BA6: 307072.61 | BB6: 307072.61 | BC6: 174346.75 | BD6: 174346.75 | BE6: 78367.35 | BF6: 13277.11 | BG6: 13277.11 | BH6: 0 | BI6: 0 | BJ6: 0 | BK6: 0 | BL6: 0
A7: interest_p_m | B7: 7218517.1 | C7: 6699479.2 | D7: 6673716 | E7: 6634355.1 | F7: 6634355.1 | G7: 6422079.9 | H7: 6370103.1 | I7: 6267244.1 | J7: 6137392.8 | K7: 6051329.6 | L7: 5937997 | M7: 5847893.4 | N7: 5743789.1 | O7: 5673354.8 | P7: 5606237.2 | Q7: 5438090.6 | R7: 4971477.4 | S7: 4941442.6 | T7: 4912890.4 | U7: 4893700 | V7: 4893700 | W7: 4860809.4 | X7: 4860809.4 | Y7: 4580291.3 | Z7: 4154116.4 | AA7: 4125699.8 | AB7: 3670256 | AC7: 3422780.2 | AD7: 3062183.8 | AE7: 3062183.8 | AF7: 2834161.2 | AG7: 2490881.1 | AH7: 2449540.3 | AI7: 2374676.6 | AJ7: 2206516 | AK7: 2067415.7 | AL7: 1970427 | AM7: 1970427 | AN7: 1586471 | AO7: 1317800.8 | AP7: 1155074.6 | AQ7: 1065116.4 | AR7: 978425.59 | AS7: 964992.82 | AT7: 936056.45 | AU7: 936056.45 | AV7: 899972 | AW7: 758830.47 | AX7: 733383.95 | AY7: 513647.47 | AZ7: 280155.87 | BA7: 247955.08 | BB7: 247955.08 | BC7: 146432.26 | BD7: 146432.26 | BE7: 63874.26 | BF7: 12723.26 | BG7: 12723.26 | BH7: 0 | BI7: 0 | BJ7: 0 | BK7: 0 | BL7: 0
A8: admin_p_m | B8: 1839367.8 | C8: 1682511.1 | D8: 1675556 | E8: 1666207.7 | F8: 1666207.7 | G8: 1611276.1 | H8: 1599033.5 | I8: 1572533.1 | J8: 1541144.4 | K8: 1518110.2 | L8: 1488054.4 | M8: 1465450.7 | N8: 1444834.1 | O8: 1426523.1 | P8: 1409322.3 | Q8: 1363928.8 | R8: 1244345.5 | S8: 1236237.2 | T8: 1229528.8 | U8: 1224699.7 | V8: 1224699.7 | W8: 1216270.5 | X8: 1216270.5 | Y8: 1144855.5 | Z8: 1035822.4 | AA8: 1028880.8 | AB8: 912059.47 | AC8: 849325.67 | AD8: 759302.85 | AE8: 759302.85 | AF8: 701899.49 | AG8: 620548.3 | AH8: 603081.11 | AI8: 591050.46 | AJ8: 541831.41 | AK8: 492427.11 | AL8: 472418.79 | AM8: 472418.79 | AN8: 381133.95 | AO8: 305762.6 | AP8: 270774.04 | AQ8: 246527.26 | AR8: 223578.19 | AS8: 220689.19 | AT8: 214221.96 | AU8: 214221.96 | AV8: 205560 | AW8: 175276.1 | AX8: 169814.46 | AY8: 122003.87 | AZ8: 69966.7 | BA8: 62805.37 | BB8: 62805.37 | BC8: 36768.93 | BD8: 36768.93 | BE8: 15999.84 | BF8: 2730.82 | BG8: 2730.82 | BH8: 0 | BI8: 0 | BJ8: 0 | BK8: 0 | BL8: 0
A9: maint_prov_p_m | B9: 84693357 | C9: 60039265 | D9: 59457912 | E9: 59457912 | F9: 59457912 | G9: 55165131 | H9: 54202853 | I9: 53917853 | J9: 52316437 | K9: 52108295 | L9: 48769534 | M9: 47939862 | N9: 47056294 | O9: 46364683 | P9: 46364683 | Q9: 42859867 | R9: 42859867 | S9: 41817267 | T9: 41315147 | U9: 41156513 | V9: 41156513 | W9: 40916614 | X9: 40916614 | Y9: 38181393 | Z9: 33310473 | AA9: 33028441 | AB9: 26943019 | AC9: 23483578 | AD9: 18382887 | AE9: 18382887 | AF9: 16736373 | AG9: 15171481 | AH9: 14797247 | AI9: 13636500 | AJ9: 13122603 | AK9: 12529839 | AL9: 12529839 | AM9: 12529839 | AN9: 9398884.3 | AO9: 6605952.8 | AP9: 6357009.1 | AQ9: 5314930.9 | AR9: 4351055.7 | AS9: 4180055.7 | AT9: 4180055.7 | AU9: 4180055.7 | AV9: 3959933.7 | AW9: 3401933.7 | AX9: 3141533.7 | AY9: 1910418.2 | AZ9: 834427.56 | BA9: 700450.06 | BB9: 700450.06 | BC9: 488950 | BD9: 488950 | BE9: 215950 | BF9: 37200 | BG9: 37200 | BH9: 0 | BI9: 0 | BJ9: 0 | BK9: 0 | BL9: 0
A10: maintenance_fund | B10: 50705548 | C10: 34611111 | D10: 34649907 | E10: 34649907 | F10: 34649907 | G10: 32679527 | H10: 32066517 | I10: 31795783 | J10: 31001896 | K10: 30835568 | L10: 29641224 | M10: 29174366 | N10: 28599474 | O10: 28033519 | P10: 28033519 | Q10: 27186880 | R10: 27186880 | S10: 26839794 | T10: 26531028 | U10: 26467831 | V10: 26467831 | W10: 26409783 | X10: 26409783 | Y10: 24863614 | Z10: 22516401 | AA10: 22293117 | AB10: 19697585 | AC10: 17754831 | AD10: 14857474 | AE10: 14857474 | AF10: 13210960 | AG10: 12103104 | AH10: 11860351 | AI10: 10933263 | AJ10: 10506308 | AK10: 10004331 | AL10: 10004331 | AM10: 10004331 | AN10: 7403234.8 | AO10: 5620212.2 | AP10: 5422971.8 | AQ10: 4738960.7 | AR10: 4061848 | AS10: 3964995.7 | AT10: 3964995.7 | AU10: 3964995.7 | AV10: 3748952.6 | AW10: 3254074 | AX10: 3018527 | AY10: 1858772.5 | AZ10: 793581.91 | BA10: 659604.41 | BB10: 659604.41 | BC10: 475307.28 | BD10: 475307.28 | BE10: 215950 | BF10: 37200 | BG10: 37200 | BH10: 0 | BI10: 0 | BJ10: 0 | BK10: 0 | BL10: 0
A11: other_fee_p_m | B11: 506790.24 | C11: 454453.9 | D11: 452702.9 | E11: 450606.6 | F11: 450606.6 | G11: 444554.6 | H11: 442804.6 | I11: 438462 | J11: 430417 | K11: 428320.7 | L11: 422370.7 | M11: 419373.4 | N11: 414865.6 | O11: 413140.1 | P11: 410915.4 | Q11: 403265.4 | R11: 390802.4 | S11: 389102.4 | T11: 387302.4 | U11: 383187.4 | V11: 383187.4 | W11: 382337.4 | X11: 382337.4 | Y11: 368422.4 | Z11: 345564.6 | AA11: 343714.6 | AB11: 300586.1 | AC11: 277955.1 | AD11: 248553.1 | AE11: 248553.1 | AF11: 237828.4 | AG11: 219800 | AH11: 216853.7 | AI11: 212056.6 | AJ11: 205391.6 | AK11: 199141.6 | AL11: 194164.32 | AM11: 194164.32 | AN11: 164456.52 | AO11: 118370.22 | AP11: 108880.22 | AQ11: 91338.6 | AR11: 77668.6 | AS11: 75818.6 | AT11: 73572.3 | AU11: 73572.3 | AV11: 69932.65 | AW11: 62774.05 | AX11: 59194.75 | AY11: 31508.6 | AZ11: 18558.6 | BA11: 16708.6 | BB11: 16708.6 | BC11: 13068.95 | BD11: 13068.95 | BE11: 9368.95 | BF11: 1789.65 | BG11: 1789.65 | BH11: 0 | BI11: 0 | BJ11: 0 | BK11: 0 | BL11: 0
A12: total_cost | B12: 6.4451369e+08 | C12: 5.7621473e+08 | D12: 5.7383011e+08 | E12: 5.7062498e+08 | F12: 5.7062498e+08 | G12: 5.5180497e+08 | H12: 5.4761437e+08 | I12: 5.3852853e+08 | J12: 5.2779408e+08 | K12: 5.1989664e+08 | L12: 5.0961238e+08 | M12: 5.0186939e+08 | N12: 4.9259824e+08 | O12: 4.8632019e+08 | P12: 4.8042275e+08 | Q12: 4.6485925e+08 | R12: 4.2385925e+08 | S12: 4.2107925e+08 | T12: 4.1877925e+08 | U12: 4.1712354e+08 | V12: 4.1712354e+08 | W12: 4.1423354e+08 | X12: 4.1423354e+08 | Y12: 3.8977579e+08 | Z12: 3.5244784e+08 | AA12: 3.5006784e+08 | AB12: 3.1003536e+08 | AC12: 2.8861232e+08 | AD12: 2.5774732e+08 | AE12: 2.5774732e+08 | AF12: 2.3806615e+08 | AG12: 2.1018115e+08 | AH12: 2.0671177e+08 | AI12: 1.9870344e+08 | AJ12: 1.8264644e+08 | AK12: 1.688323e+08 | AL12: 1.619723e+08 | AM12: 1.619723e+08 | AN12: 1.3067461e+08 | AO12: 1.0483298e+08 | AP12: 92836893 | AQ12: 84523699 | AR12: 76655438 | AS12: 75664921 | AT12: 73447582 | AU12: 73447582 | AV12: 70477766 | AW12: 60094708 | AX12: 58222144 | AY12: 41829929 | AZ12: 23988595 | BA12: 21533279 | BB12: 21533279 | BC12: 12606496 | BD12: 12606496 | BE12: 5485662.9 | BF12: 936281.9 | BG12: 936281.9 | BH12: 0 | BI12: 0 | BJ12: 0 | BK12: 0 | BL12: 0
A13: nbv | B13: 3.7309269e+08 | C13: 3.6090936e+08 | D13: 3.5200518e+08 | E13: 3.4255962e+08 | F13: 3.3401552e+08 | G13: 3.2082446e+08 | H13: 3.1125084e+08 | I13: 3.0176937e+08 | J13: 2.8947453e+08 | K13: 2.7998069e+08 | L13: 2.7052411e+08 | M13: 2.6156546e+08 | N13: 2.5178964e+08 | O13: 2.4266767e+08 | P13: 2.3394169e+08 | Q13: 2.2528116e+08 | R13: 2.0764793e+08 | S13: 2.010117e+08 | T13: 1.9411223e+08 | U13: 1.8714682e+08 | V13: 1.8088019e+08 | W13: 1.7389107e+08 | X13: 1.6766057e+08 | Y13: 1.5591868e+08 | Z13: 1.4067055e+08 | AA13: 1.3446871e+08 | AB13: 1.1862492e+08 | AC13: 1.0646612e+08 | AD13: 90314450 | AE13: 86149688 | AF13: 75182596 | AG13: 65656180 | AH13: 61286081 | AI13: 56450053 | AJ13: 51572875 | AK13: 47957572 | AL13: 43620412 | AM13: 41212627 | AN13: 33827076 | AO13: 29247653 | AP13: 24985428 | AQ13: 23281263 | AR13: 21964490 | AS13: 20743172 | AT13: 19414195 | AU13: 18391951 | AV13: 16957988 | AW13: 14430443 | AX13: 13325045 | AY13: 10353954 | AZ13: 5211500.8 | BA13: 4229453.5 | BB13: 3922380.9 | BC13: 2631851.6 | BD13: 2457504.9 | BE13: 921088.63 | BF13: 166209.52 | BG13: 152932.41 | BH13: 0 | BI13: 0 | BJ13: 0 | BK13: 0 | BL13: 0
... A16: olmm_fleet_drop | B16: 0 | C16: 2 | D16: 0 | E16: 1 | F16: 0 | G16: 0 | H16: 0 | I16: 2 | J16: 0 | K16: 1 | L16: 0 | M16: 1 | N16: 2 | O16: 0 | P16: 2 | Q16: 0 | R16: 10 | S16: 0 | T16: 0 | U16: 0 | V16: 0 | W16: 0 | X16: 0 | Y16: 0 | Z16: 2 | AA16: 0 | AB16: 0 | AC16: 0 | AD16: 0 | AE16: 0 | AF16: 2 | AG16: 4 | AH16: 1 | AI16: 0 | AJ16: 0 | AK16: 0 | AL16: 2 | AM16: 0 | AN16: 6 | AO16: 1 | AP16: 3 | AQ16: 0 | AR16: 0 | AS16: 0 | AT16: 1 | AU16: 0 | AV16: 0 | AW16: 0 | AX16: 0 | AY16: 0 | AZ16: 0 | BA16: 0 | BB16: 0 | BC16: 0 | BD16: 0 | BE16: 0 | BF16: 0 | BG16: 0 | BH16: 0 | BI16: 0 | BJ16: 0 | BK16: 0 | BL16: 0

Sheet NAM
A1: Value | B1: 2025/06/06 | C1: 2025/06/30 | D1: 2025/07/31 | E1: 2025/08/31 | F1: 2025/09/30 | G1: 2025/10/31 | H1: 2025/11/30 | I1: 2025/12/31 | J1: 2026/01/31 | K1: 2026/02/28 | L1: 2026/03/31 | M1: 2026/04/30 | N1: 2026/05/31 | O1: 2026/06/30 | P1: 2026/07/31 | Q1: 2026/08/31 | R1: 2026/09/30 | S1: 2026/10/31 | T1: 2026/11/30 | U1: 2026/12/31 | V1: 2027/01/31 | W1: 2027/02/28 | X1: 2027/03/31 | Y1: 2027/04/30 | Z1: 2027/05/31 | AA1: 2027/06/30 | AB1: 2027/07/31 | AC1: 2027/08/31 | AD1: 2027/09/30 | AE1: 2027/10/31 | AF1: 2027/11/30 | AG1: 2027/12/31 | AH1: 2028/01/31 | AI1: 2028/02/29 | AJ1: 2028/03/31 | AK1: 2028/04/30 | AL1: 2028/05/31 | AM1: 2028/06/30 | AN1: 2028/07/31 | AO1: 2028/08/31 | AP1: 2028/09/30 | AQ1: 2028/10/31 | AR1: 2028/11/30 | AS1: 2028/12/31 | AT1: 2029/01/31 | AU1: 2029/02/28 | AV1: 2029/03/31 | AW1: 2029/04/30 | AX1: 2029/05/31 | AY1: 2029/06/30 | AZ1: 2029/07/31 | BA1: 2029/08/31 | BB1: 2029/09/30 | BC1: 2029/10/31 | BD1: 2029/11/30 | BE1: 2029/12/31 | BF1: 2030/01/31 | BG1: 2030/02/28 | BH1: 2030/03/31 | BI1: 2030/04/30 | BJ1: 2030/05/31 | BK1: 2030/06/30 | BL1: 2030/07/31
A2: fml_count | B2: 1042 | C2: 943 | D2: 893 | E2: 875 | F2: 856 | G2: 804 | H2: 783 | I2: 766 | J2: 758 | K2: 731 | L2: 717 | M2: 706 | N2: 697 | O2: 682 | P2: 661 | Q2: 649 | R2: 635 | S2: 627 | T2: 614 | U2: 610 | V2: 595 | W2: 572 | X2: 561 | Y2: 549 | Z2: 536 | AA2: 527 | AB2: 504 | AC2: 489 | AD2: 473 | AE2: 459 | AF2: 421 | AG2: 401 | AH2: 393 | AI2: 369 | AJ2: 348 | AK2: 328 | AL2: 314 | AM2: 309 | AN2: 300 | AO2: 282 | AP2: 265 | AQ2: 240 | AR2: 222 | AS2: 205 | AT2: 192 | AU2: 170 | AV2: 165 | AW2: 151 | AX2: 138 | AY2: 131 | AZ2: 125 | BA2: 113 | BB2: 102 | BC2: 96 | BD2: 81 | BE2: 61 | BF2: 59 | BG2: 53 | BH2: 39 | BI2: 30 | BJ2: 17 | BK2: 7 | BL2: 3
A3: olmm_count | B3: 270 | C3: 262 | D3: 261 | E3: 259 | F3: 259 | G3: 253 | H3: 250 | I3: 248 | J3: 247 | K3: 237 | L3: 232 | M3: 228 | N3: 226 | O3: 216 | P3: 213 | Q3: 208 | R3: 200 | S3: 199 | T3: 198 | U3: 194 | V3: 191 | W3: 188 | X3: 185 | Y3: 180 | Z3: 165 | AA3: 163 | AB3: 155 | AC3: 151 | AD3: 146 | AE3: 140 | AF3: 136 | AG3: 133 | AH3: 129 | AI3: 123 | AJ3: 113 | AK3: 107 | AL3: 104 | AM3: 100 | AN3: 96 | AO3: 92 | AP3: 88 | AQ3: 85 | AR3: 82 | AS3: 79 | AT3: 74 | AU3: 67 | AV3: 60 | AW3: 53 | AX3: 50 | AY3: 45 | AZ3: 40 | BA3: 38 | BB3: 30 | BC3: 27 | BD3: 18 | BE3: 10 | BF3: 6 | BG3: 5 | BH3: 2 | BI3: 1 | BJ3: 0 | BK3: 0 | BL3: 0
A4: pl_count | B4: 0 | C4: 0 | D4: 0 | E4: 0 | F4: 0 | G4: 0 | H4: 0 | I4: 0 | J4: 0 | K4: 0 | L4: 0 | M4: 0 | N4: 0 | O4: 0 | P4: 0 | Q4: 0 | R4: 0 | S4: 0 | T4: 0 | U4: 0 | V4: 0 | W4: 0 | X4: 0 | Y4: 0 | Z4: 0 | AA4: 0 | AB4: 0 | AC4: 0 | AD4: 0 | AE4: 0 | AF4: 0 | AG4: 0 | AH4: 0 | AI4: 0 | AJ4: 0 | AK4: 0 | AL4: 0 | AM4: 0 | AN4: 0 | AO4: 0 | AP4: 0 | AQ4: 0 | AR4: 0 | AS4: 0 | AT4: 0 | AU4: 0 | AV4: 0 | AW4: 0 | AX4: 0 | AY4: 0 | AZ4: 0 | BA4: 0 | BB4: 0 | BC4: 0 | BD4: 0 | BE4: 0 | BF4: 0 | BG4: 0 | BH4: 0 | BI4: 0 | BJ4: 0 | BK4: 0 | BL4: 0
A5: revenue_p_m | B5: 16127040 | C5: 15239223 | D5: 14717657 | E5: 14505775 | F5: 14321213 | G5: 13772766 | H5: 13517174 | I5: 13310992 | J5: 13167462 | K5: 12789063 | L5: 12598405 | M5: 12434826 | N5: 12325540 | O5: 11973744 | P5: 11768593 | Q5: 11589088 | R5: 11321743 | S5: 11177794 | T5: 11007944 | U5: 10914272 | V5: 10739297 | W5: 10474954 | X5: 10274019 | Y5: 10045501 | Z5: 9721704.3 | AA5: 9556281.3 | AB5: 9163771.4 | AC5: 8963679.5 | AD5: 8721353.2 | AE5: 8212815.9 | AF5: 7669016.6 | AG5: 7377795.7 | AH5: 7203636.6 | AI5: 6823360.5 | AJ5: 6393571.9 | AK5: 6026372.3 | AL5: 5766606.2 | AM5: 5666464.2 | AN5: 5520302.2 | AO5: 5208808.3 | AP5: 4863541.7 | AQ5: 4606219.7 | AR5: 4240707.8 | AS5: 3978452.2 | AT5: 3767338.7 | AU5: 3430065.6 | AV5: 3235107.9 | AW5: 2951011.1 | AX5: 2685508.5 | AY5: 2509123.3 | AZ5: 2384012.5 | BA5: 2223967.5 | BB5: 1776292.7 | BC5: 1643750.9 | BD5: 1217863.2 | BE5: 722253.11 | BF5: 656067.21 | BG5: 581968.53 | BH5: 405249.73 | BI5: 296662.07 | BJ5: 142642.7 | BK5: 63033.12 | BL5: 30708.41
A6: depreciation_p_m | B6: 8195520.9 | C6: 7809633.6 | D6: 7678876.3 | E6: 7567981.3 | F6: 7500487.5 | G6: 7268934.2 | H6: 7157705 | I6: 7059796.8 | J6: 6977621.9 | K6: 6782284.6 | L6: 6684578.8 | M6: 6597332.9 | N6: 6542129.5 | O6: 6325833.4 | P6: 6225785.6 | Q6: 6124803 | R6: 5976249.3 | S6: 5895284.6 | T6: 5803407.9 | U6: 5749418.3 | V6: 5661647.4 | W6: 5529025.8 | X6: 5416649.4 | Y6: 5287246.8 | Z6: 5106663.7 | AA6: 5012811.8 | AB6: 4802839.8 | AC6: 4695024.4 | AD6: 4564331.8 | AE6: 4232130.2 | AF6: 3964503.7 | AG6: 3814301.2 | AH6: 3713161.5 | AI6: 3505757.6 | AJ6: 3263870.9 | AK6: 3078966.8 | AL6: 2939999.4 | AM6: 2886283.7 | AN6: 2808502.7 | AO6: 2652921.1 | AP6: 2486868.8 | AQ6: 2362707.5 | AR6: 2193954.2 | AS6: 2062117.5 | AT6: 1952104.9 | AU6: 1773782.9 | AV6: 1658545.9 | AW6: 1507991.7 | AX6: 1377747.2 | AY6: 1289722 | AZ6: 1223615.5 | BA6: 1146728.9 | BB6: 885935.39 | BC6: 812479.94 | BD6: 591673.96 | BE6: 335097.08 | BF6: 300000.25 | BG6: 264957.93 | BH6: 181711.64 | BI6: 133689.06 | BJ6: 64456.26 | BK6: 27819.93 | BL6: 13602.56
A7: interest_p_m | B7: 3772599.2 | C7: 3565955.2 | D7: 3503221.7 | E7: 3451076.6 | F7: 3415099.8 | G7: 3300988.3 | H7: 3251919.6 | I7: 3208429.9 | J7: 3182781.8 | K7: 3089200.4 | L7: 3044340.1 | M7: 3002445.4 | N7: 2973020.8 | O7: 2901752 | P7: 2853375.3 | Q7: 2812042 | R7: 2750989.6 | S7: 2720941.5 | T7: 2682634.8 | U7: 2660009.1 | V7: 2617445.4 | W7: 2551409.7 | X7: 2507112.9 | Y7: 2452955.8 | Z7: 2388748.2 | AA7: 2354822.3 | AB7: 2259085.5 | AC7: 2212557.9 | AD7: 2158100.5 | AE7: 2061751.3 | AF7: 1930253.3 | AG7: 1855527.6 | AH7: 1816500.6 | AI7: 1725210.1 | AJ7: 1631133.7 | AK7: 1545279 | AL7: 1483413.9 | AM7: 1458685.6 | AN7: 1418154.7 | AO7: 1337446.3 | AP7: 1252823.6 | AQ7: 1184858.2 | AR7: 1081239.3 | AS7: 1012982.6 | AT7: 959096.04 | AU7: 870621.28 | AV7: 825067.56 | AW7: 748719.1 | AX7: 680895.09 | AY7: 636152.4 | AZ7: 603646.6 | BA7: 560856.41 | BB7: 456870.27 | BC7: 424715 | BD7: 318353.08 | BE7: 196450.7 | BF7: 179344.65 | BG7: 160017.23 | BH7: 117030.32 | BI7: 87664.5 | BJ7: 45230.45 | BK7: 21043.04 | BL7: 10483.77
A8: admin_p_m | B8: 1399193.8 | C8: 1312101.3 | D8: 1254974.2 | E8: 1237628.9 | F8: 1218909.1 | G8: 1158306 | H8: 1130609 | I8: 1107600.1 | J8: 1093005.2 | K8: 1058425.5 | L8: 1039380.5 | M8: 1025347.2 | N8: 1015800.3 | O8: 987635.18 | P8: 974223.26 | Q8: 958260.43 | R8: 935641.98 | S8: 924231.91 | T8: 911420.72 | U8: 903256.55 | V8: 889932.36 | W8: 867721.99 | X8: 852507.42 | Y8: 832993.63 | Z8: 806632.46 | AA8: 794438.65 | AB8: 762805.62 | AC8: 746814.82 | AD8: 726644.21 | AE8: 685200.27 | AF8: 641846 | AG8: 622734.36 | AH8: 608777.43 | AI8: 577171.65 | AJ8: 541355.75 | AK8: 510100.77 | AL8: 487521.11 | AM8: 477148.83 | AN8: 461051.02 | AO8: 433006.42 | AP8: 404718.81 | AQ8: 383802.46 | AR8: 356870.39 | AS8: 335189.51 | AT8: 316660.28 | AU8: 289245.08 | AV8: 267962 | AW8: 242353.63 | AX8: 220958.49 | AY8: 207668.93 | AZ8: 195176.63 | BA8: 183259.4 | BB8: 136503.33 | BC8: 125377.66 | BD8: 91386.3 | BE8: 53335.32 | BF8: 46394.53 | BG8: 40874.35 | BH8: 25227.17 | BI8: 16981.26 | BJ8: 6260 | BK8: 2555 | BL8: 1115
A9: maint_prov_p_m | B9: 47943650 | C9: 40485229 | D9: 35835238 | E9: 34590985 | F9: 32985793 | G9: 29256656 | H9: 27529092 | I9: 26550465 | J9: 25865058 | K9: 24095760 | L9: 23131235 | M9: 22595738 | N9: 22141198 | O9: 21281047 | P9: 20378141 | Q9: 19965092 | R9: 19362034 | S9: 18847277 | T9: 18332483 | U9: 18187441 | V9: 17618586 | W9: 16709954 | X9: 16278808 | Y9: 15757795 | Z9: 14974229 | AA9: 14690258 | AB9: 13712699 | AC9: 13305542 | AD9: 12804556 | AE9: 12300114 | AF9: 10853166 | AG9: 10022445 | AH9: 9820580.3 | AI9: 9134427.4 | AJ9: 8663301.8 | AK9: 8221355.5 | AL9: 7939579.5 | AM9: 7748511.4 | AN9: 7619724.9 | AO9: 7092117.1 | AP9: 6053301.7 | AQ9: 5576968.7 | AR9: 4671827.3 | AS9: 4192461.5 | AT9: 3826825.8 | AU9: 3297302.2 | AV9: 3160938.5 | AW9: 2882528.9 | AX9: 2539293.3 | AY9: 2467156.5 | AZ9: 2375091.2 | BA9: 2064755.5 | BB9: 1780105.8 | BC9: 1585520 | BD9: 1086776.9 | BE9: 612172.29 | BF9: 572219.26 | BG9: 473879.22 | BH9: 328366.26 | BI9: 250512.08 | BJ9: 166540 | BK9: 78827.17 | BL9: 35022.12
A10: maintenance_fund | B10: 25735541 | C10: 23606401 | D10: 22000094 | E10: 21803585 | F10: 21163977 | G10: 18858428 | H10: 18125853 | I10: 17476221 | J10: 16985727 | K10: 16049170 | L10: 15334028 | M10: 15193981 | N10: 14921197 | O10: 14375300 | P10: 13837438 | Q10: 13582798 | R10: 13247261 | S10: 12903937 | T10: 12671558 | U10: 12570998 | V10: 12122603 | W10: 11552049 | X10: 11255932 | Y10: 10860594 | Z10: 10371295 | AA10: 10173596 | AB10: 9650211.7 | AC10: 9449495.4 | AD10: 9082915.3 | AE10: 8723693.8 | AF10: 8451256.2 | AG10: 7804249.4 | AH10: 7640191.4 | AI10: 7173240.6 | AJ10: 6840379.2 | AK10: 6482773.3 | AL10: 6207513.7 | AM10: 6041273.6 | AN10: 5935267.1 | AO10: 5485055.8 | AP10: 4957042.5 | AQ10: 4576178.5 | AR10: 4093187.6 | AS10: 3686525.7 | AT10: 3402830.2 | AU10: 2969126.6 | AV10: 2837392.6 | AW10: 2609733.5 | AX10: 2308698 | AY10: 2236636.2 | AZ10: 2147725.8 | BA10: 1845529 | BB10: 1596100.3 | BC10: 1436018.3 | BD10: 987599.61 | BE10: 570377.95 | BF10: 530424.92 | BG10: 442968.35 | BH10: 297455.39 | BI10: 221169.18 | BJ10: 139291.76 | BK10: 53761.1 | BL10: 10853.45
A11: other_fee_p_m | B11: 717563.38 | C11: 667958.14 | D11: 644918.91 | E11: 636473.91 | F11: 627429.91 | G11: 593914.86 | H11: 577662.48 | I11: 570756.4 | J11: 567916.4 | K11: 553391.38 | L11: 545121.38 | M11: 538766.38 | N11: 533466.38 | O11: 523014.38 | P11: 512031.08 | Q11: 505545.17 | R11: 490135.17 | S11: 486685.17 | T11: 477148.27 | U11: 474030.91 | V11: 465885.91 | W11: 452389.94 | X11: 440959.94 | Y11: 431796.94 | Z11: 410407.94 | AA11: 405957.94 | AB11: 393615.63 | AC11: 383565.63 | AD11: 374005.63 | AE11: 359195.63 | AF11: 335275.63 | AG11: 323075.63 | AH11: 317381.63 | AI11: 302379.63 | AJ11: 289612.63 | AK11: 276092.63 | AL11: 268222.63 | AM11: 264402.63 | AN11: 259456.58 | AO11: 247318.58 | AP11: 228058.58 | AQ11: 212858.56 | AR11: 195203.68 | AS11: 180210.09 | AT11: 169893.45 | AU11: 155768.45 | AV11: 148496.45 | AW11: 139540.87 | AX11: 126513.87 | AY11: 104368.87 | AZ11: 99449.87 | BA11: 90213.87 | BB11: 77341.87 | BC11: 73544.38 | BD11: 55854.04 | BE11: 37004.04 | BF11: 34945 | BG11: 32020 | BH11: 23895 | BI11: 17400 | BJ11: 10025 | BK11: 4025 | BL11: 1725
A12: total_cost | B12: 6.3843719e+08 | C12: 6.0106623e+08 | D12: 5.8626665e+08 | E12: 5.7789935e+08 | F12: 5.7089583e+08 | G12: 5.4819186e+08 | H12: 5.3828152e+08 | I12: 5.3020977e+08 | J12: 5.2509984e+08 | K12: 5.0922165e+08 | L12: 5.0139748e+08 | M12: 4.9485184e+08 | N12: 4.8985131e+08 | O12: 4.7743178e+08 | P12: 4.6957935e+08 | Q12: 4.6257721e+08 | R12: 4.5268963e+08 | S12: 4.4762578e+08 | T12: 4.4139053e+08 | U12: 4.3765176e+08 | V12: 4.3106037e+08 | W12: 4.207063e+08 | X12: 4.1313086e+08 | Y12: 4.0433569e+08 | Z12: 3.9363256e+08 | AA12: 3.8814605e+08 | AB12: 3.7308774e+08 | AC12: 3.6538758e+08 | AD12: 3.5670143e+08 | AE12: 3.3999473e+08 | AF12: 3.1940706e+08 | AG12: 3.0740511e+08 | AH12: 3.0106043e+08 | AI12: 2.8669481e+08 | AJ12: 2.7127928e+08 | AK12: 2.5775225e+08 | AL12: 2.4801064e+08 | AM12: 2.4379578e+08 | AN12: 2.3720761e+08 | AO12: 2.2429551e+08 | AP12: 2.1016393e+08 | AQ12: 1.9922831e+08 | AR12: 1.8345679e+08 | AS12: 1.7196593e+08 | AT12: 1.6277834e+08 | AU12: 1.4804003e+08 | AV12: 1.4002522e+08 | AW12: 1.2775066e+08 | AX12: 1.1645484e+08 | AY12: 1.0898533e+08 | AZ12: 1.0337811e+08 | BA12: 96044913 | BB12: 77623904 | BC12: 71787981 | BD12: 53438433 | BE12: 32510680 | BF12: 29512066 | BG12: 26334619 | BH12: 19215410 | BI12: 14571383 | BJ12: 7614517.7 | BK12: 3475512 | BL12: 1724233.1
A13: nbv | B13: 4.4774043e+08 | C13: 4.3285189e+08 | D13: 4.1907173e+08 | E13: 4.0783722e+08 | F13: 3.973789e+08 | G13: 3.8026816e+08 | H13: 3.6941231e+08 | I13: 3.5928468e+08 | J13: 3.5115487e+08 | K13: 3.3834977e+08 | L13: 3.2907374e+08 | M13: 3.1975524e+08 | N13: 3.1122859e+08 | O13: 3.0167924e+08 | P13: 2.9219645e+08 | Q13: 2.8368786e+08 | R13: 2.7442183e+08 | S13: 2.6694817e+08 | T13: 2.5892364e+08 | U13: 2.5182378e+08 | V13: 2.4331568e+08 | W13: 2.3362005e+08 | X13: 2.2574684e+08 | Y13: 2.1733514e+08 | Z13: 2.0932832e+08 | AA13: 2.0246101e+08 | AB13: 1.9172415e+08 | AC13: 1.843839e+08 | AD13: 1.7678499e+08 | AE13: 1.6861813e+08 | AF13: 1.57123e+08 | AG13: 1.4845739e+08 | AH13: 1.4263479e+08 | AI13: 1.3421383e+08 | AJ13: 1.2634148e+08 | AK13: 1.1798775e+08 | AL13: 1.1159221e+08 | AM13: 1.0744897e+08 | AN13: 1.0216934e+08 | AO13: 94837231 | AP13: 87417787 | AQ13: 80779158 | AR13: 72167915 | AS13: 65975974 | AT13: 61181002 | AU13: 54505765 | AV13: 50768873 | AW13: 45184232 | AX13: 39983217 | AY13: 36449201 | AZ13: 33514112 | BA13: 29976810 | BB13: 26121410 | BC13: 23964332 | BD13: 18417616 | BE13: 12480262 | BF13: 11310842 | BG13: 10006935 | BH13: 7668570.5 | BI13: 5855533.2 | BJ13: 3142653.9 | BK13: 1544783.1 | BL13: 784811.4
... A16: olmm_fleet_drop | B16: 0 | C16: 8 | D16: 1 | E16: 2 | F16: 0 | G16: 6 | H16: 3 | I16: 2 | J16: 1 | K16: 10 | L16: 5 | M16: 4 | N16: 2 | O16: 10 | P16: 3 | Q16: 5 | R16: 8 | S16: 1 | T16: 1 | U16: 4 | V16: 3 | W16: 3 | X16: 3 | Y16: 5 | Z16: 15 | AA16: 2 | AB16: 8 | AC16: 4 | AD16: 5 | AE16: 6 | AF16: 4 | AG16: 3 | AH16: 4 | AI16: 6 | AJ16: 10 | AK16: 6 | AL16: 3 | AM16: 4 | AN16: 4 | AO16: 4 | AP16: 4 | AQ16: 3 | AR16: 3 | AS16: 3 | AT16: 5 | AU16: 7 | AV16: 7 | AW16: 7 | AX16: 3 | AY16: 5 | AZ16: 5 | BA16: 2 | BB16: 8 | BC16: 3 | BD16: 9 | BE16: 8 | BF16: 4 | BG16: 1 | BH16: 3 | BI16: 1 | BJ16: 1 | BK16: 0 | BL16: 0

Sheet LES
A1: Value | B1: 2025/06/06 | C1: 2025/06/30 | D1: 2025/07/31 | E1: 2025/08/31 | F1: 2025/09/30 | G1: 2025/10/31 | H1: 2025/11/30 | I1: 2025/12/31 | J1: 2026/01/31 | K1: 2026/02/28 | L1: 2026/03/31 | M1: 2026/04/30 | N1: 2026/05/31 | O1: 2026/06/30 | P1: 2026/07/31 | Q1: 2026/08/31 | R1: 2026/09/30 | S1: 2026/10/31 | T1: 2026/11/30 | U1: 2026/12/31 | V1: 2027/01/31 | W1: 2027/02/28 | X1: 2027/03/31 | Y1: 2027/04/30 | Z1: 2027/05/31 | AA1: 2027/06/30 | AB1: 2027/07/31 | AC1: 2027/08/31 | AD1: 2027/09/30 | AE1: 2027/10/31 | AF1: 2027/11/30 | AG1: 2027/12/31 | AH1: 2028/01/31 | AI1: 2028/02/29 | AJ1: 2028/03/31 | AK1: 2028/04/30 | AL1: 2028/05/31 | AM1: 2028/06/30 | AN1: 2028/07/31 | AO1: 2028/08/31 | AP1: 2028/09/30 | AQ1: 2028/10/31 | AR1: 2028/11/30 | AS1: 2028/12/31 | AT1: 2029/01/31 | AU1: 2029/02/28 | AV1: 2029/03/31 | AW1: 2029/04/30 | AX1: 2029/05/31 | AY1: 2029/06/30 | AZ1: 2029/07/31 | BA1: 2029/08/31 | BB1: 2029/09/30 | BC1: 2029/10/31 | BD1: 2029/11/30 | BE1: 2029/12/31 | BF1: 2030/01/31 | BG1: 2030/02/28 | BH1: 2030/03/31 | BI1: 2030/04/30 | BJ1: 2030/05/31 | BK1: 2030/06/30 | BL1: 2030/07/31
A2: fml_count | B2: 178 | C2: 170 | D2: 169 | E2: 162 | F2: 152 | G2: 152 | H2: 151 | I2: 148 | J2: 141 | K2: 140 | L2: 138 | M2: 135 | N2: 134 | O2: 134 | P2: 133 | Q2: 130 | R2: 126 | S2: 125 | T2: 125 | U2: 124 | V2: 122 | W2: 118 | X2: 118 | Y2: 114 | Z2: 109 | AA2: 108 | AB2: 106 | AC2: 104 | AD2: 90 | AE2: 80 | AF2: 79 | AG2: 79 | AH2: 74 | AI2: 68 | AJ2: 62 | AK2: 58 | AL2: 56 | AM2: 42 | AN2: 32 | AO2: 30 | AP2: 29 | AQ2: 25 | AR2: 25 | AS2: 24 | AT2: 18 | AU2: 18 | AV2: 18 | AW2: 16 | AX2: 13 | AY2: 10 | AZ2: 8 | BA2: 7 | BB2: 7 | BC2: 4 | BD2: 4 | BE2: 4 | BF2: 4 | BG2: 4 | BH2: 2 | BI2: 1 | BJ2: 0 | BK2: 0 | BL2: 0
A3: olmm_count | B3: 9 | C3: 9 | D3: 9 | E3: 9 | F3: 9 | G3: 9 | H3: 9 | I3: 9 | J3: 9 | K3: 8 | L3: 8 | M3: 8 | N3: 8 | O3: 8 | P3: 8 | Q3: 8 | R3: 8 | S3: 8 | T3: 8 | U3: 8 | V3: 8 | W3: 8 | X3: 8 | Y3: 8 | Z3: 7 | AA3: 7 | AB3: 7 | AC3: 7 | AD3: 7 | AE3: 2 | AF3: 2 | AG3: 2 | AH3: 2 | AI3: 2 | AJ3: 2 | AK3: 2 | AL3: 1 | AM3: 1 | AN3: 1 | AO3: 1 | AP3: 1 | AQ3: 1 | AR3: 1 | AS3: 1 | AT3: 1 | AU3: 1 | AV3: 1 | AW3: 1 | AX3: 1 | AY3: 1 | AZ3: 1 | BA3: 1 | BB3: 1 | BC3: 1 | BD3: 1 | BE3: 1 | BF3: 1 | BG3: 1 | BH3: 0 | BI3: 0 | BJ3: 0 | BK3: 0 | BL3: 0
A4: pl_count | B4: 0 | C4: 0 | D4: 0 | E4: 0 | F4: 0 | G4: 0 | H4: 0 | I4: 0 | J4: 0 | K4: 0 | L4: 0 | M4: 0 | N4: 0 | O4: 0 | P4: 0 | Q4: 0 | R4: 0 | S4: 0 | T4: 0 | U4: 0 | V4: 0 | W4: 0 | X4: 0 | Y4: 0 | Z4: 0 | AA4: 0 | AB4: 0 | AC4: 0 | AD4: 0 | AE4: 0 | AF4: 0 | AG4: 0 | AH4: 0 | AI4: 0 | AJ4: 0 | AK4: 0 | AL4: 0 | AM4: 0 | AN4: 0 | AO4: 0 | AP4: 0 | AQ4: 0 | AR4: 0 | AS4: 0 | AT4: 0 | AU4: 0 | AV4: 0 | AW4: 0 | AX4: 0 | AY4: 0 | AZ4: 0 | BA4: 0 | BB4: 0 | BC4: 0 | BD4: 0 | BE4: 0 | BF4: 0 | BG4: 0 | BH4: 0 | BI4: 0 | BJ4: 0 | BK4: 0 | BL4: 0
A5: revenue_p_m | B5: 2832160 | C5: 2773746.7 | D5: 2759874.6 | E5: 2709688.8 | F5: 2618570.2 | G5: 2618570.2 | H5: 2605630.6 | I5: 2555964.1 | J5: 2484266.1 | K5: 2463636.2 | L5: 2445115.7 | M5: 2417550.4 | N5: 2407052.3 | O5: 2407052.3 | P5: 2393892.1 | Q5: 2359434.9 | R5: 2320156 | S5: 2314962 | T5: 2314962 | U5: 2308784.6 | V5: 2274941.6 | W5: 2212006 | X5: 2212006 | Y5: 2162887.1 | Z5: 2051361.9 | AA5: 2041022.3 | AB5: 2014180.4 | AC5: 1996129.2 | AD5: 1390629.1 | AE5: 1050077 | AF5: 1033364.7 | AG5: 1033364.7 | AH5: 964178.44 | AI5: 895972.98 | AJ5: 822188.66 | AK5: 780572.74 | AL5: 723772.82 | AM5: 612902.66 | AN5: 510634.6 | AO5: 500910.94 | AP5: 488102.95 | AQ5: 433183.37 | AR5: 433183.37 | AS5: 420031.67 | AT5: 346412.8 | AU5: 346412.8 | AV5: 346412.8 | AW5: 301434.93 | AX5: 254432.35 | AY5: 213090.31 | AZ5: 190296.73 | BA5: 175324.01 | BB5: 175324.01 | BC5: 132263.5 | BD5: 132263.5 | BE5: 132263.5 | BF5: 132263.5 | BG5: 132263.5 | BH5: 15534.58 | BI5: 7767.29 | BJ5: 0 | BK5: 0 | BL5: 0
A6: depreciation_p_m | B6: 1335058.2 | C6: 1307065.2 | D6: 1301631.6 | E6: 1277865.4 | F6: 1232276.1 | G6: 1232276.1 | H6: 1228257.3 | I6: 1211855.6 | J6: 1180219.3 | K6: 1169041.2 | L6: 1161008.4 | M6: 1149841.6 | N6: 1145273.9 | O6: 1145273.9 | P6: 1140292.4 | Q6: 1121925.2 | R6: 1104997.7 | S6: 1102946 | T6: 1102946 | U6: 1100455.8 | V6: 1085670.7 | W6: 1058478.2 | X6: 1058478.2 | Y6: 1036345.6 | Z6: 979636.39 | AA6: 975933.22 | AB6: 963799.58 | AC6: 955841.36 | AD6: 627239.09 | AE6: 432053.88 | AF6: 424379.52 | AG6: 424379.52 | AH6: 399187.27 | AI6: 370350.14 | AJ6: 336641.52 | AK6: 319495.95 | AL6: 287177.06 | AM6: 245787.56 | AN6: 210407.11 | AO6: 206831.09 | AP6: 202240.66 | AQ6: 184173.73 | AR6: 184173.73 | AS6: 179727.8 | AT6: 149046.81 | AU6: 149046.81 | AV6: 149046.81 | AW6: 129447.29 | AX6: 111746.82 | AY6: 95949.89 | AZ6: 87639.07 | BA6: 81678.35 | BB6: 81678.35 | BC6: 64032.02 | BD6: 64032.02 | BE6: 64032.02 | BF6: 64032.02 | BG6: 64032.02 | BH6: 5800.58 | BI6: 2900.29 | BJ6: 0 | BK6: 0 | BL6: 0
A7: interest_p_m | B7: 669414.57 | C7: 656314.41 | D7: 652778.12 | E7: 644091.18 | F7: 626082.14 | G7: 626082.14 | H7: 622756.65 | I7: 617202.18 | J7: 599031.99 | K7: 593721.35 | L7: 589392.19 | M7: 584278.37 | N7: 581861.79 | O7: 581861.79 | P7: 577761.52 | Q7: 573353.97 | R7: 561570.08 | S7: 560522.81 | T7: 560522.81 | U7: 558933.27 | V7: 548652.77 | W7: 530148.27 | X7: 530148.27 | Y7: 516911.24 | Z7: 500017.1 | AA7: 498112.08 | AB7: 488716.58 | AC7: 481987.55 | AD7: 375649.7 | AE7: 288873.58 | AF7: 283889.82 | AG7: 283889.82 | AH7: 263925.18 | AI7: 240932.07 | AJ7: 220439.49 | AK7: 206346.64 | AL7: 196992.93 | AM7: 169449.17 | AN7: 138915.46 | AO7: 135708.58 | AP7: 132538.72 | AQ7: 116468.51 | AR7: 116468.51 | AS7: 113868.18 | AT7: 95400.65 | AU7: 95400.65 | AV7: 95400.65 | AW7: 83789.23 | AX7: 70613.83 | AY7: 58891.95 | AZ7: 51863.13 | BA7: 47607.5 | BB7: 47607.5 | BC7: 34350.38 | BD7: 34350.38 | BE7: 34350.38 | BF7: 34350.38 | BG7: 34350.38 | BH7: 2964.26 | BI7: 1482.13 | BJ7: 0 | BK7: 0 | BL7: 0
A8: admin_p_m | B8: 186639.61 | C8: 183142.2 | D8: 181959.37 | E8: 178007.26 | F8: 170890.59 | G8: 170890.59 | H8: 169950.57 | I8: 167337.33 | J8: 162023.09 | K8: 161032.94 | L8: 159684.4 | M8: 158448.4 | N8: 157613.16 | O8: 157613.16 | P8: 156662.67 | Q8: 154751.53 | R8: 151389.18 | S8: 150969.18 | T8: 150969.18 | U8: 150409.51 | V8: 148110.27 | W8: 143671.64 | X8: 143671.64 | Y8: 140027.79 | Z8: 133372.66 | AA8: 132309.54 | AB8: 130108.02 | AC8: 128555.28 | AD8: 96881.01 | AE8: 82355.97 | AF8: 82005.97 | AG8: 82005.97 | AH8: 76608.17 | AI8: 70373.45 | AJ8: 64817.58 | AK8: 61191.08 | AL8: 57084.15 | AM8: 48781.55 | AN8: 40141.98 | AO8: 39337.38 | AP8: 38241.76 | AQ8: 33760.34 | AR8: 33760.34 | AS8: 32640.23 | AT8: 26660.16 | AU8: 26660.16 | AV8: 26660.16 | AW8: 23395.46 | AX8: 19969.88 | AY8: 16614.51 | AZ8: 14587.14 | BA8: 13455.19 | BB8: 13455.19 | BC8: 9977.67 | BD8: 9977.67 | BE8: 9977.67 | BF8: 9977.67 | BG8: 9977.67 | BH8: 875.54 | BI8: 437.77 | BJ8: 0 | BK8: 0 | BL8: 0
A9: maint_prov_p_m | B9: 6942279.4 | C9: 6397228.7 | D9: 6342435.7 | E9: 5931107.6 | F9: 5410978.9 | G9: 5410978.9 | H9: 5386378.9 | I9: 5047484 | J9: 4901312.8 | K9: 4876841.1 | L9: 4829281.6 | M9: 4538736.6 | N9: 4516571.6 | O9: 4516571.6 | P9: 4490514.8 | Q9: 4345792.6 | R9: 4196215.1 | S9: 4158169.4 | T9: 4158169.4 | U9: 4096723.4 | V9: 4089463.4 | W9: 4064704.6 | X9: 4064704.6 | Y9: 3979313.6 | Z9: 3517381.8 | AA9: 3474864.6 | AB9: 3442290.9 | AC9: 3430800.3 | AD9: 2639586.7 | AE9: 2420696.7 | AF9: 2411879.1 | AG9: 2411879.1 | AH9: 2200269 | AI9: 1975302.5 | AJ9: 1818573.4 | AK9: 1773817.5 | AL9: 1697883.9 | AM9: 1155357.4 | AN9: 902838.75 | AO9: 859143.23 | AP9: 825311.63 | AQ9: 648740.32 | AR9: 648740.32 | AS9: 569987.02 | AT9: 391297.51 | AU9: 391297.51 | AV9: 391297.51 | AW9: 338644.91 | AX9: 227410.67 | AY9: 175692.53 | AZ9: 129329.51 | BA9: 100156.3 | BB9: 100156.3 | BC9: 50718.21 | BD9: 50718.21 | BE9: 50718.21 | BF9: 50718.21 | BG9: 50718.21 | BH9: 6700.32 | BI9: 1675.08 | BJ9: 0 | BK9: 0 | BL9: 0
A10: maintenance_fund | B10: 4316191.9 | C10: 4066856.1 | D10: 4024995.9 | E10: 3808584.2 | F10: 3655750.5 | G10: 3655750.5 | H10: 3639271.5 | I10: 3619089.9 | J10: 3529239.7 | K10: 3525166.5 | L10: 3480302.3 | M10: 3473930.2 | N10: 3453496 | O10: 3453496 | P10: 3447404.9 | Q10: 3379009.6 | R10: 3303156.5 | S10: 3292854.7 | T10: 3292854.7 | U10: 3239794.1 | V10: 3232534.1 | W10: 3207775.3 | X10: 3207775.3 | Y10: 3167235.8 | Z10: 2944560.4 | AA10: 2918135.5 | AB10: 2898173.2 | AC10: 2886682.6 | AD10: 2127257.3 | AE10: 1941367.5 | AF10: 1932549.9 | AG10: 1932549.9 | AH10: 1785349 | AI10: 1601202.7 | AJ10: 1465845.6 | AK10: 1428521.3 | AL10: 1367924.1 | AM10: 987076.03 | AN10: 807074.67 | AO10: 771288.27 | AP10: 755122.1 | AQ10: 599909.66 | AR10: 599909.66 | AS10: 528585.47 | AT10: 369067.23 | AU10: 369067.23 | AV10: 369067.23 | AW10: 316414.63 | AX10: 212671.31 | AY10: 164504.59 | AZ10: 124307.14 | BA10: 98455.51 | BB10: 98455.51 | BC10: 50718.21 | BD10: 50718.21 | BE10: 50718.21 | BF10: 50718.21 | BG10: 50718.21 | BH10: 6700.32 | BI10: 1675.08 | BJ10: 0 | BK10: 0 | BL10: 0
A11: other_fee_p_m | B11: 281559.47 | C11: 279108.83 | D11: 276531.02 | E11: 274028.37 | F11: 268235.32 | G11: 268235.32 | H11: 266368.15 | I11: 263440.54 | J11: 252414.63 | K11: 250140.2 | L11: 247091.68 | M11: 246644.24 | N11: 244818.17 | O11: 244818.17 | P11: 242776 | Q11: 239464.41 | R11: 238371.97 | S11: 238296.97 | T11: 238296.97 | U11: 238221.97 | V11: 233195.77 | W11: 223440.65 | X11: 223440.65 | Y11: 219475.28 | Z11: 205090.17 | AA11: 202811.8 | AB11: 202661.8 | AC11: 201941.8 | AD11: 143544.13 | AE11: 109802.77 | AF11: 107200.81 | AG11: 107200.81 | AH11: 97679.9 | AI11: 95519.9 | AJ11: 88839.3 | AK11: 85543.48 | AL11: 76972.56 | AM11: 68034 | AN11: 51037.38 | AO11: 50887.38 | AP11: 48473.1 | AQ11: 38930.42 | AR11: 38930.42 | AS11: 36570.2 | AT11: 27560.25 | AU11: 27560.25 | AV11: 27560.25 | AW11: 20818.92 | AX11: 17237.07 | AY11: 12058.26 | AZ11: 9769.88 | BA11: 8797.57 | BB11: 8797.57 | BC11: 5880.64 | BD11: 5880.64 | BE11: 5880.64 | BF11: 5880.64 | BG11: 5880.64 | BH11: 2544.04 | BI11: 1272.02 | BJ11: 0 | BK11: 0 | BL11: 0
A12: total_cost | B12: 99085652 | C12: 96985221 | D12: 96393804 | E12: 94720803 | F12: 91318987 | G12: 91318987 | H12: 90890407 | I12: 89595781 | J12: 86977060 | K12: 86106510 | L12: 85432236 | M12: 84502588 | N12: 84084967 | O12: 84084967 | P12: 83609720 | Q12: 82684139 | R12: 81034096 | S12: 80845232 | T12: 80845232 | U12: 80565396 | V12: 79415772 | W12: 77196452 | X12: 77196452 | Y12: 75447119 | Z12: 72175149 | AA12: 71677686 | AB12: 70576916 | AC12: 69800537 | AD12: 54053386 | AE12: 42224801 | AF12: 41620621 | AG12: 41620621 | AH12: 38727947 | AI12: 35408762 | AJ12: 32366910 | AK12: 30553654 | AL12: 28500182 | AM12: 24298680 | AN12: 20048866 | AO12: 19646557 | AP12: 19098746 | AQ12: 16858028 | AR12: 16858028 | AS12: 16297969 | AT12: 13330121 | AU12: 13330121 | AV12: 13330121 | AW12: 11697763 | AX12: 9984963.6 | AY12: 8307271.7 | AZ12: 7293582.6 | BA12: 6727607.5 | BB12: 6727607.5 | BC12: 4988847.3 | BD12: 4988847.3 | BE12: 4988847.3 | BF12: 4988847.3 | BG12: 4988847.3 | BH12: 437774.24 | BI12: 218887.12 | BJ12: 0 | BK12: 0 | BL12: 0
A13: nbv | B13: 78646428 | C13: 77748632 | D13: 76110964 | E13: 74122382 | F13: 71309641 | G13: 70077365 | H13: 68566991 | I13: 66878293 | J13: 64058087 | K13: 62392678 | L13: 60830512 | M13: 59363390 | N13: 57960363 | O13: 56815089 | P13: 55373906 | Q13: 53938021 | R13: 51903529 | S13: 50717697 | T13: 49614751 | U13: 48378891 | V13: 46468868 | W13: 43871661 | X13: 42813183 | Y13: 40808345 | Z13: 38700515 | AA13: 37534665 | AB13: 35882639 | AC13: 34426077 | AD13: 29064244 | AE13: 23808153 | AF13: 23048196 | AG13: 22623816 | AH13: 20646987 | AI13: 18634433 | AJ13: 16845199 | AK13: 15458883 | AL13: 14485406 | AM13: 12402828 | AN13: 9991492.2 | AO13: 9589760.7 | AP13: 9110545 | AQ13: 7818095.6 | AR13: 7633921.9 | AS13: 7205349.8 | AT13: 5916481.6 | AU13: 5767434.7 | AV13: 5618387.9 | AW13: 4993354.8 | AX13: 4154773.8 | AY13: 3270112.5 | AZ13: 2682303.4 | BA13: 2386332.4 | BB13: 2304654.1 | BC13: 1536918.8 | BD13: 1472886.8 | BE13: 1408854.8 | BF13: 1344822.7 | BG13: 1280790.7 | BH13: 101340.6 | BI13: 50670.3 | BJ13: 0 | BK13: 0 | BL13: 0
... A16: olmm_fleet_drop | B16: 0 | C16: 0 | D16: 0 | E16: 0 | F16: 0 | G16: 0 | H16: 0 | I16: 0 | J16: 0 | K16: 1 | L16: 0 | M16: 0 | N16: 0 | O16: 0 | P16: 0 | Q16: 0 | R16: 0 | S16: 0 | T16: 0 | U16: 0 | V16: 0 | W16: 0 | X16: 0 | Y16: 0 | Z16: 1 | AA16: 0 | AB16: 0 | AC16: 0 | AD16: 0 | AE16: 5 | AF16: 0 | AG16: 0 | AH16: 0 | AI16: 0 | AJ16: 0 | AK16: 0 | AL16: 1 | AM16: 0 | AN16: 0 | AO16: 0 | AP16: 0 | AQ16: 0 | AR16: 0 | AS16: 0 | AT16: 0 | AU16: 0 | AV16: 0 | AW16: 0 | AX16: 0 | AY16: 0 | AZ16: 0 | BA16: 0 | BB16: 0 | BC16: 0 | BD16: 0 | BE16: 0 | BF16: 0 | BG16: 0 | BH16: 1 | BI16: 0 | BJ16: 0 | BK16: 0 | BL16: 0

Sheet Central & Commercial
A1: Value | B1: 2025/06/06 | C1: 2025/06/30 | D1: 2025/07/31 | E1: 2025/08/31 | F1: 2025/09/30 | G1: 2025/10/31 | H1: 2025/11/30 | I1: 2025/12/31 | J1: 2026/01/31 | K1: 2026/02/28 | L1: 2026/03/31 | M1: 2026/04/30 | N1: 2026/05/31 | O1: 2026/06/30 | P1: 2026/07/31 | Q1: 2026/08/31 | R1: 2026/09/30 | S1: 2026/10/31 | T1: 2026/11/30 | U1: 2026/12/31 | V1: 2027/01/31 | W1: 2027/02/28 | X1: 2027/03/31 | Y1: 2027/04/30 | Z1: 2027/05/31 | AA1: 2027/06/30 | AB1: 2027/07/31 | AC1: 2027/08/31 | AD1: 2027/09/30 | AE1: 2027/10/31 | AF1: 2027/11/30 | AG1: 2027/12/31 | AH1: 2028/01/31 | AI1: 2028/02/29 | AJ1: 2028/03/31 | AK1: 2028/04/30 | AL1: 2028/05/31 | AM1: 2028/06/30 | AN1: 2028/07/31 | AO1: 2028/08/31 | AP1: 2028/09/30 | AQ1: 2028/10/31 | AR1: 2028/11/30 | AS1: 2028/12/31 | AT1: 2029/01/31 | AU1: 2029/02/28 | AV1: 2029/03/31 | AW1: 2029/04/30 | AX1: 2029/05/31 | AY1: 2029/06/30 | AZ1: 2029/07/31 | BA1: 2029/08/31 | BB1: 2029/09/30 | BC1: 2029/10/31 | BD1: 2029/11/30 | BE1: 2029/12/31 | BF1: 2030/01/31 | BG1: 2030/02/28 | BH1: 2030/03/31 | BI1: 2030/04/30 | BJ1: 2030/05/31 | BK1: 2030/06/30 | BL1: 2030/07/31
A2: fml_count | B2: 489 | C2: 455 | D2: 446 | E2: 438 | F2: 430 | G2: 419 | H2: 407 | I2: 403 | J2: 392 | K2: 384 | L2: 375 | M2: 370 | N2: 360 | O2: 358 | P2: 352 | Q2: 345 | R2: 337 | S2: 334 | T2: 326 | U2: 319 | V2: 317 | W2: 315 | X2: 308 | Y2: 302 | Z2: 278 | AA2: 271 | AB2: 265 | AC2: 259 | AD2: 207 | AE2: 195 | AF2: 158 | AG2: 138 | AH2: 124 | AI2: 121 | AJ2: 118 | AK2: 114 | AL2: 112 | AM2: 108 | AN2: 102 | AO2: 97 | AP2: 85 | AQ2: 84 | AR2: 74 | AS2: 71 | AT2: 70 | AU2: 69 | AV2: 66 | AW2: 53 | AX2: 41 | AY2: 38 | AZ2: 36 | BA2: 33 | BB2: 29 | BC2: 25 | BD2: 24 | BE2: 20 | BF2: 13 | BG2: 12 | BH2: 9 | BI2: 5 | BJ2: 0 | BK2: 0 | BL2: 0
A3: olmm_count | B3: 280 | C3: 280 | D3: 280 | E3: 279 | F3: 279 | G3: 273 | H3: 262 | I3: 262 | J3: 258 | K3: 258 | L3: 258 | M3: 258 | N3: 258 | O3: 258 | P3: 253 | Q3: 228 | R3: 226 | S3: 226 | T3: 222 | U3: 222 | V3: 221 | W3: 215 | X3: 198 | Y3: 198 | Z3: 185 | AA3: 180 | AB3: 179 | AC3: 171 | AD3: 164 | AE3: 157 | AF3: 149 | AG3: 144 | AH3: 141 | AI3: 137 | AJ3: 118 | AK3: 115 | AL3: 103 | AM3: 103 | AN3: 102 | AO3: 93 | AP3: 67 | AQ3: 59 | AR3: 51 | AS3: 51 | AT3: 43 | AU3: 40 | AV3: 36 | AW3: 21 | AX3: 20 | AY3: 20 | AZ3: 19 | BA3: 19 | BB3: 14 | BC3: 13 | BD3: 10 | BE3: 6 | BF3: 6 | BG3: 6 | BH3: 6 | BI3: 6 | BJ3: 6 | BK3: 6 | BL3: 4
A4: pl_count | B4: 0 | C4: 0 | D4: 0 | E4: 0 | F4: 0 | G4: 0 | H4: 0 | I4: 0 | J4: 0 | K4: 0 | L4: 0 | M4: 0 | N4: 0 | O4: 0 | P4: 0 | Q4: 0 | R4: 0 | S4: 0 | T4: 0 | U4: 0 | V4: 0 | W4: 0 | X4: 0 | Y4: 0 | Z4: 0 | AA4: 0 | AB4: 0 | AC4: 0 | AD4: 0 | AE4: 0 | AF4: 0 | AG4: 0 | AH4: 0 | AI4: 0 | AJ4: 0 | AK4: 0 | AL4: 0 | AM4: 0 | AN4: 0 | AO4: 0 | AP4: 0 | AQ4: 0 | AR4: 0 | AS4: 0 | AT4: 0 | AU4: 0 | AV4: 0 | AW4: 0 | AX4: 0 | AY4: 0 | AZ4: 0 | BA4: 0 | BB4: 0 | BC4: 0 | BD4: 0 | BE4: 0 | BF4: 0 | BG4: 0 | BH4: 0 | BI4: 0 | BJ4: 0 | BK4: 0 | BL4: 0
A5: revenue_p_m | B5: 15156089 | C5: 14727820 | D5: 14601697 | E5: 14485619 | F5: 14397506 | G5: 14199748 | H5: 13951530 | I5: 13908962 | J5: 13773239 | K5: 13695708 | L5: 13579651 | M5: 13504249 | N5: 13379914 | O5: 13365531 | P5: 12971988 | Q5: 12285264 | R5: 12085985 | S5: 12069663 | T5: 11643985 | U5: 11516623 | V5: 11447476 | W5: 11309391 | X5: 10901560 | Y5: 10801012 | Z5: 8912397.2 | AA5: 8555919.8 | AB5: 8429126.1 | AC5: 8015799 | AD5: 7389261.9 | AE5: 7046672.7 | AF5: 5930247.1 | AG5: 5638546.5 | AH5: 5482704.9 | AI5: 5358314.3 | AJ5: 4846302.9 | AK5: 4696772.7 | AL5: 4588137.3 | AM5: 4554179 | AN5: 4451110.4 | AO5: 4096252.9 | AP5: 3446013.4 | AQ5: 3160216.7 | AR5: 2912052.2 | AS5: 2774331.1 | AT5: 2434863.1 | AU5: 2371674.1 | AV5: 2265539.2 | AW5: 1684934.6 | AX5: 1004796.7 | AY5: 964179.85 | AZ5: 885264.45 | BA5: 838511.62 | BB5: 721483.95 | BC5: 548730.75 | BD5: 491961.05 | BE5: 426353.42 | BF5: 331322.06 | BG5: 325111.36 | BH5: 274169.65 | BI5: 224995.19 | BJ5: 174349.56 | BK5: 174349.56 | BL5: 121653.35
A6: depreciation_p_m | B6: 8201963.5 | C6: 8033111.6 | D6: 7974913.6 | E6: 7920070.7 | F6: 7890832.7 | G6: 7795628.7 | H6: 7662311.1 | I6: 7644524.7 | J6: 7579210.4 | K6: 7546512.3 | L6: 7489411.4 | M6: 7448470.8 | N6: 7389366.9 | O6: 7384988.4 | P6: 7103488.3 | Q6: 6783277.6 | R6: 6661274.6 | S6: 6655505.6 | T6: 6363040.4 | U6: 6294200.8 | V6: 6246207.7 | W6: 6171696 | X6: 5926868.6 | Y6: 5879392 | Z6: 4881102.3 | AA6: 4661593.6 | AB6: 4598662.1 | AC6: 4347106.8 | AD6: 4019246.1 | AE6: 3824780.3 | AF6: 3268683.4 | AG6: 3123879.9 | AH6: 3050154.4 | AI6: 2985724.7 | AJ6: 2651657.4 | AK6: 2565162.4 | AL6: 2501614.3 | AM6: 2488286.5 | AN6: 2444453.1 | AO6: 2253340.3 | AP6: 1853834.8 | AQ6: 1683177 | AR6: 1555576.9 | AS6: 1488684.2 | AT6: 1275763.3 | AU6: 1233785.4 | AV6: 1172590.7 | AW6: 858723.98 | AX6: 498810.76 | AY6: 481324.73 | AZ6: 439054.25 | BA6: 416147.37 | BB6: 353226.62 | BC6: 252298.58 | BD6: 224053.14 | BE6: 196168.59 | BF6: 154448.33 | BG6: 152487.23 | BH6: 132421.2 | BI6: 112372.34 | BJ6: 94724.61 | BK6: 94724.61 | BL6: 66722.81
A7: interest_p_m | B7: 3953274.1 | C7: 3876094.3 | D7: 3857718.8 | E7: 3831989.9 | F7: 3813492.6 | G7: 3782917.9 | H7: 3724373.6 | I7: 3710995.4 | J7: 3672164.9 | K7: 3650754 | L7: 3619263.5 | M7: 3599665.9 | N7: 3560191.7 | O7: 3556610.7 | P7: 3485680 | Q7: 3214834.8 | R7: 3172988.9 | S7: 3165738.7 | T7: 3083118.7 | U7: 3062154.9 | V7: 3050005.6 | W7: 3003510.4 | X7: 2882510.3 | Y7: 2862657.2 | Z7: 2370337.8 | AA7: 2289400.1 | AB7: 2252085.6 | AC7: 2136601.9 | AD7: 1985862.4 | AE7: 1889335 | AF7: 1582483.5 | AG7: 1499516.8 | AH7: 1460760.6 | AI7: 1427169.7 | AJ7: 1296642.3 | AK7: 1251473.7 | AL7: 1220410.4 | AM7: 1208436.5 | AN7: 1177646 | AO7: 1085661.2 | AP7: 919751.08 | AQ7: 830583.12 | AR7: 758754.84 | AS7: 724749.09 | AT7: 633516.8 | AU7: 619258.78 | AV7: 591174.44 | AW7: 454388.63 | AX7: 304743 | AY7: 293278.72 | AZ7: 268982.75 | BA7: 257063.14 | BB7: 223952.73 | BC7: 177739.72 | BD7: 158991.98 | BE7: 135602.03 | BF7: 109655.59 | BG7: 107546.43 | BH7: 92048.01 | BI7: 77638.56 | BJ7: 59750.34 | BK7: 59750.34 | BL7: 41375.53
A8: admin_p_m | B8: 1060878.7 | C8: 1023716.3 | D8: 1015851.7 | E8: 1008496.2 | F8: 1001665.7 | G8: 978875.64 | H8: 966026.61 | I8: 963464.49 | J8: 953421.55 | K8: 949737.92 | L8: 942139.78 | M8: 936241.1 | N8: 927069.47 | O8: 925269.94 | P8: 905500.95 | Q8: 838326.78 | R8: 826272.74 | S8: 824606.74 | T8: 798582.64 | U8: 792861.27 | V8: 788809.27 | W8: 777972.03 | X8: 748603.79 | Y8: 741703.4 | Z8: 615201.68 | AA8: 597027.75 | AB8: 586536.05 | AC8: 555886.46 | AD8: 525054.67 | AE8: 502876.97 | AF8: 422172.48 | AG8: 404681.27 | AH8: 396133.15 | AI8: 387254.59 | AJ8: 350376.94 | AK8: 341535.14 | AL8: 332992.68 | AM8: 330784.35 | AN8: 323273.4 | AO8: 296319.48 | AP8: 249109.28 | AQ8: 227611 | AR8: 210357.94 | AS8: 199741.9 | AT8: 172832.75 | AU8: 169247.75 | AV8: 161149.13 | AW8: 122252.67 | AX8: 74251.81 | AY8: 72816.83 | AZ8: 66604.45 | BA8: 63143.81 | BB8: 55296.7 | BC8: 42749.23 | BD8: 37278.71 | BE8: 31282.2 | BF8: 27950.92 | BG8: 27710.94 | BH8: 24543.39 | BI8: 21750.22 | BJ8: 18714.61 | BK8: 18714.61 | BL8: 13135.01
A9: maint_prov_p_m | B9: 26687095 | C9: 22420305 | D9: 21269362 | E9: 20671375 | F9: 20073909 | G9: 19335947 | H9: 18373454 | I9: 18152246 | J9: 17698090 | K9: 17289418 | L9: 16710382 | M9: 16462579 | N9: 16186301 | O9: 16086794 | P9: 15645623 | Q9: 15156855 | R9: 14743187 | S9: 14696162 | T9: 14248769 | U9: 13968003 | V9: 13819520 | W9: 13779370 | X9: 13660817 | Y9: 13292718 | Z9: 9655084.6 | AA9: 8996522.5 | AB9: 8749146.1 | AC9: 8510604.4 | AD9: 7386623 | AE9: 7154225.2 | AF9: 4668783.3 | AG9: 4233714.9 | AH9: 4037417.4 | AI9: 3877300.2 | AJ9: 3815225.4 | AK9: 3768272.2 | AL9: 3706443.7 | AM9: 3619001.9 | AN9: 3283320.1 | AO9: 2843451.8 | AP9: 2553079.7 | AQ9: 2514507.7 | AR9: 2095557 | AS9: 1641317.1 | AT9: 1565102.2 | AU9: 1518578.2 | AV9: 1453129.6 | AW9: 1125103.8 | AX9: 581329.81 | AY9: 519736.37 | AZ9: 474119.17 | BA9: 391366.29 | BB9: 300318.78 | BC9: 229986.38 | BD9: 205374.38 | BE9: 167018.78 | BF9: 72203.37 | BG9: 65018.37 | BH9: 31125.27 | BI9: 12939.75 | BJ9: 0 | BK9: 0 | BL9: 0
A10: maintenance_fund | B10: 16351997 | C10: 14769214 | D10: 14115315 | E10: 13841890 | F10: 13427112 | G10: 13123102 | H10: 12673731 | I10: 12530812 | J10: 12582003 | K10: 12536979 | L10: 12155237 | M10: 11936924 | N10: 11740793 | O10: 11675544 | P10: 11485620 | Q10: 11325156 | R10: 11143469 | S10: 11101339 | T10: 10825433 | U10: 10625740 | V10: 10540809 | W10: 10500659 | X10: 10412880 | Y10: 10124423 | Z10: 7350593.5 | AA10: 6858270.6 | AB10: 6718347.7 | AC10: 6552157.6 | AD10: 5544827.9 | AE10: 5338236.7 | AF10: 3602438 | AG10: 3205503.9 | AH10: 3010905.4 | AI10: 2875351.2 | AJ10: 2815896.5 | AK10: 2769386.8 | AL10: 2709667 | AM10: 2628449.8 | AN10: 2316089.1 | AO10: 1962141.4 | AP10: 1694386.5 | AQ10: 1662956.4 | AR10: 1308593.5 | AS10: 1115514.6 | AT10: 1061229.1 | AU10: 1022568.8 | AV10: 957120.24 | AW10: 642889 | AX10: 555151.43 | AY10: 498647.11 | AZ10: 465154.31 | BA10: 384015.44 | BB10: 294033.8 | BC10: 223701.4 | BD10: 199089.4 | BE10: 161096.16 | BF10: 66280.76 | BG10: 59527.66 | BH10: 31125.27 | BI10: 12939.75 | BJ10: 0 | BK10: 0 | BL10: 0
A11: other_fee_p_m | B11: 324408.1 | C11: 294288.83 | D11: 289219.27 | E11: 286285.54 | F11: 283042.03 | G11: 260582.01 | H11: 249290.2 | I11: 245937.92 | J11: 237091.05 | K11: 233274.77 | L11: 229296.84 | M11: 225950.32 | N11: 222931.59 | O11: 222543.59 | P11: 219439.19 | Q11: 208049.65 | R11: 204434.3 | S11: 203590.63 | T11: 198999.28 | U11: 194261.74 | V11: 192840.79 | W11: 188691.89 | X11: 182358.14 | Y11: 179768.04 | Z11: 168439.43 | AA11: 163385.58 | AB11: 158556.2 | AC11: 152506.16 | AD11: 133978.97 | AE11: 128784.24 | AF11: 115061.92 | AG11: 107457.21 | AH11: 103547.53 | AI11: 98460.73 | AJ11: 93298.27 | AK11: 91129.58 | AL11: 87546.66 | AM11: 85756.02 | AN11: 81975.49 | AO11: 78740.13 | AP11: 66746.63 | AQ11: 64202.48 | AR11: 56603.36 | AS11: 55622.88 | AT11: 52732.87 | AU11: 51880.74 | AV11: 49957.26 | AW11: 39358.49 | AX11: 34548.49 | AY11: 31712.11 | AZ11: 30415.19 | BA11: 28994.73 | BB11: 24016.89 | BC11: 20717.05 | BD11: 19927.05 | BE11: 17646.23 | BF11: 10946.36 | BG11: 10482.9 | BH11: 7802.14 | BI11: 4971.92 | BJ11: 1160 | BK11: 1160 | BL11: 420
A12: total_cost | B12: 5.9413179e+08 | C12: 5.7996431e+08 | D12: 5.7619414e+08 | E12: 5.7235753e+08 | F12: 5.6907762e+08 | G12: 5.6185228e+08 | H12: 5.5253198e+08 | I12: 5.5067574e+08 | J12: 5.4510444e+08 | K12: 5.4207484e+08 | L12: 5.3777631e+08 | M12: 5.3502439e+08 | N12: 5.2985544e+08 | O12: 5.2923017e+08 | P12: 5.1719534e+08 | Q12: 4.8017818e+08 | R12: 4.7375517e+08 | S12: 4.7287409e+08 | T12: 4.596125e+08 | U12: 4.5645259e+08 | V12: 4.5446457e+08 | W12: 4.482173e+08 | X12: 4.3071563e+08 | Y12: 4.2763034e+08 | Z12: 3.5756436e+08 | AA12: 3.4403911e+08 | AB12: 3.3889968e+08 | AC12: 3.220108e+08 | AD12: 2.998359e+08 | AE12: 2.8592228e+08 | AF12: 2.4226805e+08 | AG12: 2.305042e+08 | AH12: 2.2490912e+08 | AI12: 2.2002068e+08 | AJ12: 1.9955002e+08 | AK12: 1.9297945e+08 | AL12: 1.8807106e+08 | AM12: 1.8641181e+08 | AN12: 1.8217698e+08 | AO12: 1.6840466e+08 | AP12: 1.4216436e+08 | AQ12: 1.2888248e+08 | AR12: 1.1806317e+08 | AS12: 1.1276514e+08 | AT12: 98581520 | AU12: 96101469 | AV12: 91761940 | AW12: 70325261 | AX12: 46334803 | AY12: 44612815 | AZ12: 40923602 | BA12: 39042478 | BB12: 33801405 | BC12: 26243252 | BD12: 23527991 | BE12: 20318326 | BF12: 16320740 | BG12: 16032763 | BH12: 13844414 | BI12: 11758025 | BJ12: 9357305.2 | BK12: 9357305.2 | BL12: 6567505.2
A13: nbv | B13: 4.5248672e+08 | C13: 4.4814434e+08 | D13: 4.3899576e+08 | E13: 4.2915659e+08 | F13: 4.1955243e+08 | G13: 4.0916116e+08 | H13: 397691565 | I13: 3.8889742e+08 | J13: 3.7823349e+08 | K13: 3.6889118e+08 | L13: 3.5907588e+08 | M13: 3.5033986e+08 | N13: 3.3977631e+08 | O13: 3.3204518e+08 | P13: 3.2298142e+08 | Q13: 2.9325993e+08 | R13: 2.8461545e+08 | S13: 2.7735567e+08 | T13: 2.6810571e+08 | U13: 2.6043258e+08 | V13: 2.5352421e+08 | W13: 2.4445306e+08 | X13: 2.3170955e+08 | Y13: 2.2474853e+08 | Z13: 1.8888832e+08 | AA13: 1.8068001e+08 | AB13: 1.7350683e+08 | AC13: 1.6365578e+08 | AD13: 1.5022793e+08 | AE13: 1.4078163e+08 | AF13: 1.1813067e+08 | AG13: 1.0967213e+08 | AH13: 1.0413236e+08 | AI13: 99173761 | AJ13: 90726272 | AK13: 85003819 | AL13: 81040388 | AM13: 77640080 | AN13: 73094541 | AO13: 66420361 | AP13: 57911857 | AQ13: 51027580 | AR13: 45703071 | AS13: 42846583 | AT13: 37352345 | AU13: 35772020 | AV13: 33247445 | AW13: 25906491 | AX13: 19478037 | AY13: 18230741 | AZ13: 16576160 | BA13: 15626466 | BB13: 13737456 | BC13: 11812284 | BD13: 10549089 | BE13: 8809296 | BF13: 7096728.9 | BG13: 6771969.3 | BH13: 5626952.8 | BI13: 4591025.4 | BJ13: 3126143.4 | BK13: 3031418.8 | BL13: 2135022
... A16: olmm_fleet_drop | B16: 0 | C16: 0 | D16: 0 | E16: 1 | F16: 0 | G16: 6 | H16: 11 | I16: 0 | J16: 4 | K16: 0 | L16: 0 | M16: 0 | N16: 0 | O16: 0 | P16: 5 | Q16: 25 | R16: 2 | S16: 0 | T16: 4 | U16: 0 | V16: 1 | W16: 6 | X16: 17 | Y16: 0 | Z16: 13 | AA16: 5 | AB16: 1 | AC16: 8 | AD16: 7 | AE16: 7 | AF16: 8 | AG16: 5 | AH16: 3 | AI16: 4 | AJ16: 19 | AK16: 3 | AL16: 12 | AM16: 0 | AN16: 1 | AO16: 9 | AP16: 26 | AQ16: 8 | AR16: 8 | AS16: 0 | AT16: 8 | AU16: 3 | AV16: 4 | AW16: 15 | AX16: 1 | AY16: 0 | AZ16: 1 | BA16: 0 | BB16: 5 | BC16: 1 | BD16: 3 | BE16: 4 | BF16: 0 | BG16: 0 | BH16: 0 | BI16: 0 | BJ16: 0 | BK16: 0 | BL16: 2

Sheet Inland
A1: Value | B1: 2025/06/06 | C1: 2025/06/30 | D1: 2025/07/31 | E1: 2025/08/31 | F1: 2025/09/30 | G1: 2025/10/31 | H1: 2025/11/30 | I1: 2025/12/31 | J1: 2026/01/31 | K1: 2026/02/28 | L1: 2026/03/31 | M1: 2026/04/30 | N1: 2026/05/31 | O1: 2026/06/30 | P1: 2026/07/31 | Q1: 2026/08/31 | R1: 2026/09/30 | S1: 2026/10/31 | T1: 2026/11/30 | U1: 2026/12/31 | V1: 2027/01/31 | W1: 2027/02/28 | X1: 2027/03/31 | Y1: 2027/04/30 | Z1: 2027/05/31 | AA1: 2027/06/30 | AB1: 2027/07/31 | AC1: 2027/08/31 | AD1: 2027/09/30 | AE1: 2027/10/31 | AF1: 2027/11/30 | AG1: 2027/12/31 | AH1: 2028/01/31 | AI1: 2028/02/29 | AJ1: 2028/03/31 | AK1: 2028/04/30 | AL1: 2028/05/31 | AM1: 2028/06/30 | AN1: 2028/07/31 | AO1: 2028/08/31 | AP1: 2028/09/30 | AQ1: 2028/10/31 | AR1: 2028/11/30 | AS1: 2028/12/31 | AT1: 2029/01/31 | AU1: 2029/02/28 | AV1: 2029/03/31 | AW1: 2029/04/30 | AX1: 2029/05/31 | AY1: 2029/06/30 | AZ1: 2029/07/31 | BA1: 2029/08/31 | BB1: 2029/09/30 | BC1: 2029/10/31 | BD1: 2029/11/30 | BE1: 2029/12/31 | BF1: 2030/01/31 | BG1: 2030/02/28 | BH1: 2030/03/31 | BI1: 2030/04/30 | BJ1: 2030/05/31 | BK1: 2030/06/30 | BL1: 2030/07/31
A2: fml_count | B2: 7588 | C2: 6835 | D2: 6625 | E2: 6401 | F2: 6198 | G2: 6019 | H2: 5766 | I2: 5546 | J2: 5356 | K2: 5180 | L2: 5008 | M2: 4869 | N2: 4687 | O2: 4439 | P2: 4281 | Q2: 4134 | R2: 3882 | S2: 3698 | T2: 3512 | U2: 3419 | V2: 3286 | W2: 3126 | X2: 2942 | Y2: 2795 | Z2: 2625 | AA2: 2368 | AB2: 2207 | AC2: 2061 | AD2: 1885 | AE2: 1766 | AF2: 1639 | AG2: 1525 | AH2: 1452 | AI2: 1370 | AJ2: 1258 | AK2: 1162 | AL2: 1068 | AM2: 1002 | AN2: 957 | AO2: 887 | AP2: 834 | AQ2: 763 | AR2: 682 | AS2: 614 | AT2: 580 | AU2: 549 | AV2: 502 | AW2: 447 | AX2: 392 | AY2: 359 | AZ2: 272 | BA2: 202 | BB2: 185 | BC2: 165 | BD2: 130 | BE2: 106 | BF2: 87 | BG2: 68 | BH2: 46 | BI2: 21 | BJ2: 11 | BK2: 9 | BL2: 6
A3: olmm_count | B3: 1783 | C3: 1736 | D3: 1729 | E3: 1725 | F3: 1675 | G3: 1660 | H3: 1646 | I3: 1626 | J3: 1622 | K3: 1609 | L3: 1582 | M3: 1547 | N3: 1533 | O3: 1521 | P3: 1488 | Q3: 1453 | R3: 1409 | S3: 1361 | T3: 1339 | U3: 1316 | V3: 1310 | W3: 1281 | X3: 1252 | Y3: 1162 | Z3: 1149 | AA3: 1124 | AB3: 1108 | AC3: 1086 | AD3: 1069 | AE3: 1049 | AF3: 1025 | AG3: 1012 | AH3: 975 | AI3: 939 | AJ3: 906 | AK3: 878 | AL3: 823 | AM3: 726 | AN3: 652 | AO3: 466 | AP3: 403 | AQ3: 267 | AR3: 260 | AS3: 250 | AT3: 249 | AU3: 245 | AV3: 232 | AW3: 203 | AX3: 189 | AY3: 187 | AZ3: 152 | BA3: 142 | BB3: 142 | BC3: 142 | BD3: 139 | BE3: 124 | BF3: 120 | BG3: 107 | BH3: 102 | BI3: 99 | BJ3: 27 | BK3: 14 | BL3: 14
A4: pl_count | B4: 1 | C4: 1 | D4: 1 | E4: 1 | F4: 1 | G4: 1 | H4: 1 | I4: 1 | J4: 1 | K4: 1 | L4: 1 | M4: 1 | N4: 1 | O4: 0 | P4: 0 | Q4: 0 | R4: 0 | S4: 0 | T4: 0 | U4: 0 | V4: 0 | W4: 0 | X4: 0 | Y4: 0 | Z4: 0 | AA4: 0 | AB4: 0 | AC4: 0 | AD4: 0 | AE4: 0 | AF4: 0 | AG4: 0 | AH4: 0 | AI4: 0 | AJ4: 0 | AK4: 0 | AL4: 0 | AM4: 0 | AN4: 0 | AO4: 0 | AP4: 0 | AQ4: 0 | AR4: 0 | AS4: 0 | AT4: 0 | AU4: 0 | AV4: 0 | AW4: 0 | AX4: 0 | AY4: 0 | AZ4: 0 | BA4: 0 | BB4: 0 | BC4: 0 | BD4: 0 | BE4: 0 | BF4: 0 | BG4: 0 | BH4: 0 | BI4: 0 | BJ4: 0 | BK4: 0 | BL4: 0
A5: revenue_p_m | B5: 1.0311533e+08 | C5: 94747081 | D5: 92614010 | E5: 90561599 | F5: 88297921 | G5: 86341097 | H5: 83524880 | I5: 80729685 | J5: 78793362 | K5: 77126425 | L5: 75138701 | M5: 73128551 | N5: 71091709 | O5: 68552090 | P5: 65812192 | Q5: 62993677 | R5: 60152830 | S5: 57544684 | T5: 55369516 | U5: 53946081 | V5: 52559438 | W5: 50502035 | X5: 48123411 | Y5: 45812685 | Z5: 43556705 | AA5: 41239856 | AB5: 38735820 | AC5: 36000019 | AD5: 33765995 | AE5: 31713870 | AF5: 29042840 | AG5: 27427955 | AH5: 26124842 | AI5: 24900684 | AJ5: 22881341 | AK5: 21132195 | AL5: 19051618 | AM5: 17635527 | AN5: 16580320 | AO5: 14987369 | AP5: 13714706 | AQ5: 11705036 | AR5: 10292632 | AS5: 9379589.5 | AT5: 8901671.7 | AU5: 8474870.9 | AV5: 7727438.1 | AW5: 6522635.4 | AX5: 5664392 | AY5: 5365664.5 | AZ5: 4283088.3 | BA5: 3507997.8 | BB5: 3282615.5 | BC5: 3055787.3 | BD5: 2699586 | BE5: 2391864 | BF5: 2096048.8 | BG5: 1750038.7 | BH5: 1479987.6 | BI5: 1117617.9 | BJ5: 391558.94 | BK5: 245831.25 | BL5: 219764.53
A6: depreciation_p_m | B6: 50043111 | C6: 46317167 | D6: 45365077 | E6: 44417109 | F6: 43318988 | G6: 42435459 | H6: 41191053 | I6: 39857015 | J6: 39047614 | K6: 38276716 | L6: 37317951 | M6: 36248906 | N6: 35273581 | O6: 34085921 | P6: 32706395 | Q6: 31129708 | R6: 29817124 | S6: 28494768 | T6: 27472600 | U6: 26750142 | V6: 26123695 | W6: 25081178 | X6: 23916410 | Y6: 22667818 | Z6: 21596972 | AA6: 20595622 | AB6: 19323881 | AC6: 17933789 | AD6: 16853037 | AE6: 15751926 | AF6: 14512482 | AG6: 13683678 | AH6: 13064333 | AI6: 12453129 | AJ6: 11573036 | AK6: 10616087 | AL6: 9444576 | AM6: 8712191.8 | AN6: 8182590.2 | AO6: 7299416.4 | AP6: 6554192 | AQ6: 5479307.8 | AR6: 4834354.6 | AS6: 4419020.8 | AT6: 4209030.9 | AU6: 4007618.3 | AV6: 3665135.2 | AW6: 3044639.5 | AX6: 2635582.7 | AY6: 2517556.2 | AZ6: 2005329.6 | BA6: 1664575.2 | BB6: 1568298.5 | BC6: 1476971.3 | BD6: 1335966.7 | BE6: 1185708.7 | BF6: 1066046 | BG6: 885303.47 | BH6: 753160.16 | BI6: 578583.21 | BJ6: 183202.9 | BK6: 97291.22 | BL6: 87911.38
A7: interest_p_m | B7: 24455892 | C7: 23024794 | D7: 22584690 | E7: 22184814 | F7: 21742934 | G7: 21336838 | H7: 20790489 | I7: 20270314 | J7: 19898800 | K7: 19524889 | L7: 19078659 | M7: 18607925 | N7: 18137712 | O7: 17526862 | P7: 16903690 | Q7: 16239380 | R7: 15528159 | S7: 14885310 | T7: 14384161 | U7: 14030350 | V7: 13691752 | W7: 13195862 | X7: 12610237 | Y7: 12104807 | Z7: 11553015 | AA7: 10992056 | AB7: 10405402 | AC7: 9724270.6 | AD7: 9184117.4 | AE7: 8691642.1 | AF7: 7981874.9 | AG7: 7563508.9 | AH7: 7182167.6 | AI7: 6860765 | AJ7: 6362057.4 | AK7: 5910587.5 | AL7: 5375007.7 | AM7: 4992308.3 | AN7: 4685872.7 | AO7: 4286406.3 | AP7: 3961491 | AQ7: 3414244.9 | AR7: 3029412.4 | AS7: 2755483.4 | AT7: 2616763.3 | AU7: 2492343.3 | AV7: 2270108.2 | AW7: 1922980.7 | AX7: 1667162.8 | AY7: 1568890 | AZ7: 1235913 | BA7: 1000804.4 | BB7: 933223.91 | BC7: 862479.39 | BD7: 743452.31 | BE7: 656534.93 | BF7: 568434.74 | BG7: 473312.35 | BH7: 394204.83 | BI7: 288743.37 | BJ7: 119689.94 | BK7: 82561.69 | BL7: 73925.71
A8: admin_p_m | B8: 6069025 | C8: 5533016.1 | D8: 5415095.2 | E8: 5304927.3 | F8: 5164334.3 | G8: 5056166.6 | H8: 4910657.2 | I8: 4649494.8 | J8: 4546923.8 | K8: 4441953.9 | L8: 4318272.2 | M8: 4213870.2 | N8: 4105551.5 | O8: 3963017.3 | P8: 3816204.7 | Q8: 3684263.7 | R8: 3532073.6 | S8: 3384848.4 | T8: 3232959.4 | U8: 3148994.9 | V8: 3076840.3 | W8: 2963680.2 | X8: 2834796.1 | Y8: 2716432 | Z8: 2572031.7 | AA8: 2446134.8 | AB8: 2309160.8 | AC8: 2142676.6 | AD8: 2044286.1 | AE8: 1926717.2 | AF8: 1785234.2 | AG8: 1703516.1 | AH8: 1627423 | AI8: 1554672.1 | AJ8: 1440352.3 | AK8: 1337864.2 | AL8: 1251640.4 | AM8: 1168116.7 | AN8: 1089847.4 | AO8: 1007041.6 | AP8: 939358.19 | AQ8: 808891.05 | AR8: 725483.53 | AS8: 667694.75 | AT8: 638126.46 | AU8: 614427.02 | AV8: 565319.76 | AW8: 488924.3 | AX8: 442802.16 | AY8: 426806.72 | AZ8: 360489.37 | BA8: 302512.29 | BB8: 290126.56 | BC8: 277483.95 | BD8: 253405.44 | BE8: 233633.64 | BF8: 214292.43 | BG8: 190545.39 | BH8: 178186.21 | BI8: 157101.15 | BJ8: 51536.33 | BK8: 39483.13 | BL8: 38469.37
A9: maint_prov_p_m | B9: 4.0779511e+08 | C9: 3.3261672e+08 | D9: 3.1619989e+08 | E9: 3.0168004e+08 | F9: 2.8693868e+08 | G9: 2.7422449e+08 | H9: 2.5316938e+08 | I9: 2.3722732e+08 | J9: 2.2389839e+08 | K9: 2.1415025e+08 | L9: 2.0346465e+08 | M9: 1.950159e+08 | N9: 1.850127e+08 | O9: 1.7190603e+08 | P9: 1.5994481e+08 | Q9: 1.5120544e+08 | R9: 1.3946804e+08 | S9: 1.3021184e+08 | T9: 1.2091765e+08 | U9: 1.1691289e+08 | V9: 1.1187808e+08 | W9: 1.0565189e+08 | X9: 98365991 | Y9: 93090693 | Z9: 84934427 | AA9: 75907809 | AB9: 68139349 | AC9: 62158755 | AD9: 56942523 | AE9: 51791105 | AF9: 43531536 | AG9: 40584407 | AH9: 38377357 | AI9: 36395245 | AJ9: 31285115 | AK9: 27969473 | AL9: 26052553 | AM9: 23681555 | AN9: 22332273 | AO9: 20479701 | AP9: 19011333 | AQ9: 15565238 | AR9: 11557504 | AS9: 10143467 | AT9: 9294443.3 | AU9: 8645085.4 | AV9: 8017530 | AW9: 7138882.3 | AX9: 6129418.7 | AY9: 5475930.4 | AZ9: 3848969.4 | BA9: 2426562 | BB9: 2097698.3 | BC9: 1723238.4 | BD9: 1239365.4 | BE9: 951488.76 | BF9: 624205.92 | BG9: 419661.55 | BH9: 288868.29 | BI9: 169239.05 | BJ9: 127235.24 | BK9: 111043.8 | BL9: 61982.72
A10: maintenance_fund | B10: 2.4383387e+08 | C10: 2.1232964e+08 | D10: 2.0461262e+08 | E10: 1.9835185e+08 | F10: 1.9161257e+08 | G10: 1.8550238e+08 | H10: 1.7515208e+08 | I10: 1.6676987e+08 | J10: 1.5869959e+08 | K10: 1.5335059e+08 | L10: 1.4699683e+08 | M10: 1.4220658e+08 | N10: 1.36427e+08 | O10: 1.2840734e+08 | P10: 1.2204587e+08 | Q10: 1.1692983e+08 | R10: 1.0921789e+08 | S10: 1.0290276e+08 | T10: 96489987 | U10: 93944956 | V10: 90432919 | W10: 85820819 | X10: 80398660 | Y10: 76311397 | Z10: 70510165 | AA10: 63189043 | AB10: 57105408 | AC10: 52649635 | AD10: 48393631 | AE10: 44618922 | AF10: 38044900 | AG10: 35667408 | AH10: 33646740 | AI10: 31844042 | AJ10: 27537365 | AK10: 24908701 | AL10: 23162573 | AM10: 21275357 | AN10: 20078780 | AO10: 18431291 | AP10: 17085069 | AQ10: 14314939 | AR10: 10714514 | AS10: 9519258.1 | AT10: 8727002.4 | AU10: 8234291.6 | AV10: 7617068.8 | AW10: 6867009 | AX10: 6011694.2 | AY10: 5388110 | AZ10: 3789106.2 | BA10: 2381529.2 | BB10: 2073031.8 | BC10: 1700580.2 | BD10: 1223095.4 | BE10: 938755.63 | BF10: 611472.79 | BG10: 414844.76 | BH10: 284051.5 | BI10: 165400.3 | BJ10: 123396.55 | BK10: 109791.23 | BL10: 60730.15
A11: other_fee_p_m | B11: 4526429.8 | C11: 4087873 | D11: 3972847.1 | E11: 3838086.1 | F11: 3744785.3 | G11: 3649744.3 | H11: 3508742 | I11: 3378020.4 | J11: 3234763.1 | K11: 3166996.7 | L11: 3080922.1 | M11: 3005692.9 | N11: 2904346.3 | O11: 2781227.5 | P11: 2672345.1 | Q11: 2590929.6 | R11: 2378964.1 | S11: 2255651 | T11: 2149872.9 | U11: 2098935.5 | V11: 2015233.8 | W11: 1922602.9 | X11: 1823698.9 | Y11: 1711061.5 | Z11: 1627726.5 | AA11: 1516693.3 | AB11: 1437296.3 | AC11: 1340933.9 | AD11: 1212476 | AE11: 1156197.4 | AF11: 1092794.5 | AG11: 1019205.4 | AH11: 974549.8 | AI11: 925373.42 | AJ11: 867575.09 | AK11: 823080.16 | AL11: 763324.15 | AM11: 706827.51 | AN11: 663686.71 | AO11: 597277.74 | AP11: 558617.03 | AQ11: 493138.04 | AR11: 447365.51 | AS11: 404847.74 | AT11: 390819.48 | AU11: 375327.9 | AV11: 346856.49 | AW11: 316403.45 | AX11: 282908.06 | AY11: 266320.12 | AZ11: 216598.28 | BA11: 174870.99 | BB11: 164003.46 | BC11: 151769.21 | BD11: 132380.97 | BE11: 113450.1 | BF11: 102363.35 | BG11: 88762.42 | BH11: 77036.81 | BI11: 59470.22 | BJ11: 19741.44 | BK11: 11938.99 | BL11: 9265.87
A12: total_cost | B12: 3.7553331e+09 | C12: 3.4892163e+09 | D12: 3.4161173e+09 | E12: 3.3474166e+09 | F12: 3.2719488e+09 | G12: 3.2064911e+09 | H12: 3.1128529e+09 | I12: 3.0170936e+09 | J12: 2.9510723e+09 | K12: 2.8905426e+09 | L12: 2.8206331e+09 | M12: 2.7507047e+09 | N12: 2.6794527e+09 | O12: 2.5865711e+09 | P12: 2.4940736e+09 | Q12: 2.3947032e+09 | R12: 2.2927999e+09 | S12: 2.1983321e+09 | T12: 2.119831e+09 | U12: 2.0685219e+09 | V12: 2.0199854e+09 | W12: 1.9484237e+09 | X12: 1.8657463e+09 | Y12: 1.7909453e+09 | Z12: 1.7125636e+09 | AA12: 1.6309834e+09 | AB12: 1.5432414e+09 | AC12: 1.4442984e+09 | AD12: 1.3651713e+09 | AE12: 1.2910979e+09 | AF12: 1.1890094e+09 | AG12: 1.1281191e+09 | AH12: 1.0761724e+09 | AI12: 1.0300309e+09 | AJ12: 9.5936951e+08 | AK12: 891360832 | AL12: 8.1361459e+08 | AM12: 7.5617229e+08 | AN12: 7.1165712e+08 | AO12: 6.4887941e+08 | AP12: 5.9743188e+08 | AQ12: 5.1414902e+08 | AR12: 4.5750351e+08 | AS12: 4.1851303e+08 | AT12: 3.9885619e+08 | AU12: 3.8031538e+08 | AV12: 3.488837e+08 | AW12: 2.9782414e+08 | AX12: 2.5955242e+08 | AY12: 2.4543079e+08 | AZ12: 1.9556431e+08 | BA12: 1.5627781e+08 | BB12: 1.4641462e+08 | BC12: 1.3627247e+08 | BD12: 1.1866491e+08 | BE12: 1.052912e+08 | BF12: 92797549 | BG12: 77550542 | BH12: 65401996 | BI12: 49424123 | BJ12: 18857893 | BK12: 12344166 | BL12: 11086401
A13: nbv | B13: 2.6659828e+09 | C13: 2.5650701e+09 | D13: 2.48356e+09 | E13: 2.4054714e+09 | F13: 2.3276309e+09 | G13: 2.2522885e+09 | H13: 2.1672106e+09 | I13: 2.0870732e+09 | J13: 2.0173036e+09 | K13: 1.9495464e+09 | L13: 1.8805575e+09 | M13: 1.812688e+09 | N13: 1.7412484e+09 | O13: 1.6612665e+09 | P13: 1.5858772e+09 | Q13: 1.5144171e+09 | R13: 1.4340302e+09 | S13: 1.3634506e+09 | T13: 1.300764e+09 | U13: 1.2514877e+09 | V13: 1.2000876e+09 | W13: 1.1403029e+09 | X13: 1.0758523e+09 | Y13: 1.0214551e+09 | Z13: 9.6269743e+08 | AA13: 9.0126228e+08 | AB13: 8.438959e+08 | AC13: 7.8049944e+08 | AD13: 7.2643225e+08 | AE13: 6.8138714e+08 | AF13: 6.1510309e+08 | AG13: 5.7504778e+08 | AH13: 5.3713463e+08 | AI13: 5.0375664e+08 | AJ13: 4.5900542e+08 | AK13: 4.2296887e+08 | AL13: 3.8331594e+08 | AM13: 3.5349131e+08 | AN13: 3.2725303e+08 | AO13: 2.9935699e+08 | AP13: 2.7605911e+08 | AQ13: 2.4274894e+08 | AR13: 2.1538872e+08 | AS13: 1.9247006e+08 | AT13: 1.7930996e+08 | AU13: 1.6765344e+08 | AV13: 1.4974352e+08 | AW13: 1.2633254e+08 | AX13: 1.0800352e+08 | AY13: 98281112 | AZ13: 76264967 | BA13: 60218758 | BB13: 54366570 | BC13: 48164744 | BD13: 38677121 | BE13: 33016561 | BF13: 26397402 | BG13: 21024071 | BH13: 15999525 | BI13: 9825695 | BJ13: 6137283.4 | BK13: 5554153 | BL13: 4862901.6
... A16: olmm_fleet_drop | B16: 0 | C16: 47 | D16: 7 | E16: 4 | F16: 50 | G16: 15 | H16: 14 | I16: 20 | J16: 4 | K16: 13 | L16: 27 | M16: 35 | N16: 14 | O16: 12 | P16: 33 | Q16: 35 | R16: 44 | S16: 48 | T16: 22 | U16: 23 | V16: 6 | W16: 29 | X16: 29 | Y16: 90 | Z16: 13 | AA16: 25 | AB16: 16 | AC16: 22 | AD16: 17 | AE16: 20 | AF16: 24 | AG16: 13 | AH16: 37 | AI16: 36 | AJ16: 33 | AK16: 28 | AL16: 55 | AM16: 97 | AN16: 74 | AO16: 186 | AP16: 63 | AQ16: 136 | AR16: 7 | AS16: 10 | AT16: 1 | AU16: 4 | AV16: 13 | AW16: 29 | AX16: 14 | AY16: 2 | AZ16: 35 | BA16: 10 | BB16: 0 | BC16: 0 | BD16: 3 | BE16: 15 | BF16: 4 | BG16: 13 | BH16: 5 | BI16: 3 | BJ16: 72 | BK16: 13 | BL16: 0

Sheet Coastal
A1: Value | B1: 2025/06/06 | C1: 2025/06/30 | D1: 2025/07/31 | E1: 2025/08/31 | F1: 2025/09/30 | G1: 2025/10/31 | H1: 2025/11/30 | I1: 2025/12/31 | J1: 2026/01/31 | K1: 2026/02/28 | L1: 2026/03/31 | M1: 2026/04/30 | N1: 2026/05/31 | O1: 2026/06/30 | P1: 2026/07/31 | Q1: 2026/08/31 | R1: 2026/09/30 | S1: 2026/10/31 | T1: 2026/11/30 | U1: 2026/12/31 | V1: 2027/01/31 | W1: 2027/02/28 | X1: 2027/03/31 | Y1: 2027/04/30 | Z1: 2027/05/31 | AA1: 2027/06/30 | AB1: 2027/07/31 | AC1: 2027/08/31 | AD1: 2027/09/30 | AE1: 2027/10/31 | AF1: 2027/11/30 | AG1: 2027/12/31 | AH1: 2028/01/31 | AI1: 2028/02/29 | AJ1: 2028/03/31 | AK1: 2028/04/30 | AL1: 2028/05/31 | AM1: 2028/06/30 | AN1: 2028/07/31 | AO1: 2028/08/31 | AP1: 2028/09/30 | AQ1: 2028/10/31 | AR1: 2028/11/30 | AS1: 2028/12/31 | AT1: 2029/01/31 | AU1: 2029/02/28 | AV1: 2029/03/31 | AW1: 2029/04/30 | AX1: 2029/05/31 | AY1: 2029/06/30 | AZ1: 2029/07/31 | BA1: 2029/08/31 | BB1: 2029/09/30 | BC1: 2029/10/31 | BD1: 2029/11/30 | BE1: 2029/12/31 | BF1: 2030/01/31 | BG1: 2030/02/28 | BH1: 2030/03/31 | BI1: 2030/04/30 | BJ1: 2030/05/31 | BK1: 2030/06/30 | BL1: 2030/07/31
A2: fml_count | B2: 2760 | C2: 2497 | D2: 2416 | E2: 2355 | F2: 2268 | G2: 2208 | H2: 2143 | I2: 2071 | J2: 1997 | K2: 1924 | L2: 1849 | M2: 1774 | N2: 1681 | O2: 1625 | P2: 1554 | Q2: 1504 | R2: 1421 | S2: 1348 | T2: 1283 | U2: 1233 | V2: 1181 | W2: 1137 | X2: 1091 | Y2: 1034 | Z2: 985 | AA2: 913 | AB2: 851 | AC2: 766 | AD2: 708 | AE2: 640 | AF2: 594 | AG2: 555 | AH2: 524 | AI2: 500 | AJ2: 464 | AK2: 420 | AL2: 390 | AM2: 364 | AN2: 345 | AO2: 323 | AP2: 299 | AQ2: 273 | AR2: 242 | AS2: 225 | AT2: 208 | AU2: 199 | AV2: 178 | AW2: 160 | AX2: 149 | AY2: 141 | AZ2: 134 | BA2: 127 | BB2: 124 | BC2: 100 | BD2: 64 | BE2: 56 | BF2: 45 | BG2: 38 | BH2: 31 | BI2: 18 | BJ2: 1 | BK2: 1 | BL2: 1
A3: olmm_count | B3: 254 | C3: 247 | D3: 241 | E3: 224 | F3: 223 | G3: 217 | H3: 212 | I3: 207 | J3: 207 | K3: 203 | L3: 201 | M3: 200 | N3: 200 | O3: 198 | P3: 196 | Q3: 190 | R3: 186 | S3: 185 | T3: 182 | U3: 178 | V3: 177 | W3: 174 | X3: 168 | Y3: 168 | Z3: 164 | AA3: 162 | AB3: 149 | AC3: 143 | AD3: 135 | AE3: 123 | AF3: 115 | AG3: 107 | AH3: 107 | AI3: 100 | AJ3: 93 | AK3: 91 | AL3: 91 | AM3: 91 | AN3: 73 | AO3: 43 | AP3: 42 | AQ3: 39 | AR3: 38 | AS3: 33 | AT3: 32 | AU3: 28 | AV3: 26 | AW3: 17 | AX3: 17 | AY3: 16 | AZ3: 16 | BA3: 16 | BB3: 16 | BC3: 14 | BD3: 7 | BE3: 6 | BF3: 6 | BG3: 6 | BH3: 5 | BI3: 1 | BJ3: 1 | BK3: 1 | BL3: 1
A4: pl_count | B4: 0 | C4: 0 | D4: 0 | E4: 0 | F4: 0 | G4: 0 | H4: 0 | I4: 0 | J4: 0 | K4: 0 | L4: 0 | M4: 0 | N4: 0 | O4: 0 | P4: 0 | Q4: 0 | R4: 0 | S4: 0 | T4: 0 | U4: 0 | V4: 0 | W4: 0 | X4: 0 | Y4: 0 | Z4: 0 | AA4: 0 | AB4: 0 | AC4: 0 | AD4: 0 | AE4: 0 | AF4: 0 | AG4: 0 | AH4: 0 | AI4: 0 | AJ4: 0 | AK4: 0 | AL4: 0 | AM4: 0 | AN4: 0 | AO4: 0 | AP4: 0 | AQ4: 0 | AR4: 0 | AS4: 0 | AT4: 0 | AU4: 0 | AV4: 0 | AW4: 0 | AX4: 0 | AY4: 0 | AZ4: 0 | BA4: 0 | BB4: 0 | BC4: 0 | BD4: 0 | BE4: 0 | BF4: 0 | BG4: 0 | BH4: 0 | BI4: 0 | BJ4: 0 | BK4: 0 | BL4: 0
A5: revenue_p_m | B5: 33842682 | C5: 31499174 | D5: 30678030 | E5: 29823684 | F5: 28854591 | G5: 28286214 | H5: 27482323 | I5: 26510957 | J5: 25764390 | K5: 24907903 | L5: 24088908 | M5: 23310610 | N5: 22362251 | O5: 21786032 | P5: 20876940 | Q5: 20179323 | R5: 19152180 | S5: 18220986 | T5: 17260344 | U5: 16700037 | V5: 16037427 | W5: 15554250 | X5: 14921661 | Y5: 14346729 | Z5: 13679541 | AA5: 12914485 | AB5: 12199015 | AC5: 11137321 | AD5: 10416591 | AE5: 9562646 | AF5: 8973789.8 | AG5: 8452959.2 | AH5: 8061047.3 | AI5: 7730032.7 | AJ5: 7171522.4 | AK5: 6518588.9 | AL5: 6223686.1 | AM5: 6000314.9 | AN5: 5641766.2 | AO5: 5158378.3 | AP5: 4864390.5 | AQ5: 4482173.6 | AR5: 4070129.3 | AS5: 3757944.5 | AT5: 3554498.7 | AU5: 3249717.1 | AV5: 2931687.6 | AW5: 2646861.7 | AX5: 2550673.8 | AY5: 2468332.3 | AZ5: 2395316.4 | BA5: 2327356.3 | BB5: 2255591.1 | BC5: 1799470.4 | BD5: 960306.37 | BE5: 852099.54 | BF5: 740743.88 | BG5: 668859.13 | BH5: 574599.72 | BI5: 218819.86 | BJ5: 25937.67 | BK5: 25937.67 | BL5: 25937.67
A6: depreciation_p_m | B6: 14482658 | C6: 13490819 | D6: 13159317 | E6: 12738267 | F6: 12328367 | G6: 12091322 | H6: 11764171 | I6: 11334264 | J6: 11029281 | K6: 10667473 | L6: 10317755 | M6: 10005299 | N6: 9629391.2 | O6: 9390867.3 | P6: 8970865.3 | Q6: 8654252.6 | R6: 8226328.3 | S6: 7830466.2 | T6: 7452810 | U6: 7209280.1 | V6: 6923862.3 | W6: 6712321.9 | X6: 6451108.1 | Y6: 6218961.1 | Z6: 5954752.7 | AA6: 5644440.3 | AB6: 5328383.1 | AC6: 4879824.5 | AD6: 4558763.7 | AE6: 4184637 | AF6: 3930251.8 | AG6: 3705593.3 | AH6: 3541601.1 | AI6: 3397694.2 | AJ6: 3156486.1 | AK6: 2868134.4 | AL6: 2746422.5 | AM6: 2653016.5 | AN6: 2491231.9 | AO6: 2283772.2 | AP6: 2159446.8 | AQ6: 2012757.8 | AR6: 1814981.2 | AS6: 1658101.9 | AT6: 1582544.8 | AU6: 1412741.6 | AV6: 1275273.6 | AW6: 1133270.5 | AX6: 1097537.7 | AY6: 1063898.6 | AZ6: 1036585.6 | BA6: 1012065.1 | BB6: 978732.13 | BC6: 789053.52 | BD6: 437069.93 | BE6: 387570.6 | BF6: 342891.78 | BG6: 312988.38 | BH6: 271891.07 | BI6: 91329.09 | BJ6: 11657.79 | BK6: 11657.79 | BL6: 11657.79
A7: interest_p_m | B7: 9031672.8 | C7: 8537254.8 | D7: 8347182.5 | E7: 8120291.6 | F7: 7887452.5 | G7: 7743107.2 | H7: 7555822.5 | I7: 7339192.5 | J7: 7155894.6 | K7: 6953344.4 | L7: 6744730.6 | M7: 6550822.6 | N7: 6318854.6 | O7: 6171970.8 | P7: 5939042.6 | Q7: 5768030.9 | R7: 5484221.2 | S7: 5213856.8 | T7: 4975658.6 | U7: 4807190.4 | V7: 4639010.7 | W7: 4501932.5 | X7: 4345659.3 | Y7: 4194276.1 | Z7: 4015795.5 | AA7: 3805885.3 | AB7: 3589490.4 | AC7: 3299442.1 | AD7: 3091055.4 | AE7: 2864480.5 | AF7: 2703656.4 | AG7: 2564954.3 | AH7: 2463701.1 | AI7: 2358793.6 | AJ7: 2201672.5 | AK7: 2025938.3 | AL7: 1938849.9 | AM7: 1866524.1 | AN7: 1739986.8 | AO7: 1568751.6 | AP7: 1476728.1 | AQ7: 1367720.1 | AR7: 1245347 | AS7: 1143590.1 | AT7: 1074539.5 | AU7: 983310.5 | AV7: 882550.56 | AW7: 791574.76 | AX7: 760349.09 | AY7: 734956.27 | AZ7: 707509.34 | BA7: 685227.79 | BB7: 663802.21 | BC7: 538240.86 | BD7: 310646.89 | BE7: 277292.35 | BF7: 241078.64 | BG7: 221729.36 | BH7: 193110.66 | BI7: 75050.54 | BJ7: 7068.08 | BK7: 7068.08 | BL7: 7068.08
A8: admin_p_m | B8: 2302974.1 | C8: 2082100.8 | D8: 2004246.2 | E8: 1956036.8 | F8: 1886865.9 | G8: 1838788.8 | H8: 1780459.5 | I8: 1724663.3 | J8: 1672317.6 | K8: 1608935.4 | L8: 1551400.9 | M8: 1495460.5 | N8: 1426441.1 | O8: 1383891.8 | P8: 1327133.3 | Q8: 1281314.6 | R8: 1203889.6 | S8: 1139655.9 | T8: 1076126.9 | U8: 1036909.3 | V8: 996689.9 | W8: 965546.53 | X8: 928250.53 | Y8: 891428.76 | Z8: 845205.73 | AA8: 799912.8 | AB8: 754489.31 | AC8: 696549.53 | AD8: 644248.26 | AE8: 588318.08 | AF8: 553452.51 | AG8: 523326.95 | AH8: 502420.21 | AI8: 481316.35 | AJ8: 443123.01 | AK8: 406250.08 | AL8: 387567.86 | AM8: 372603.44 | AN8: 349190.61 | AO8: 321305.61 | AP8: 302163.3 | AQ8: 271980.99 | AR8: 251333.56 | AS8: 231580.2 | AT8: 218463.81 | AU8: 195282.94 | AV8: 171235.92 | AW8: 152900.02 | AX8: 145912.24 | AY8: 139977.33 | AZ8: 134129.22 | BA8: 130343.83 | BB8: 127026.66 | BC8: 108922.7 | BD8: 76901.57 | BE8: 68775.47 | BF8: 61568.76 | BG8: 57058.38 | BH8: 49614.07 | BI8: 17915.87 | BJ8: 1906.76 | BK8: 1906.76 | BL8: 1906.76
A9: maint_prov_p_m | B9: 1.4959003e+08 | C9: 1.2886055e+08 | D9: 1.2366873e+08 | E9: 1.2066677e+08 | F9: 1.1347434e+08 | G9: 1.0978353e+08 | H9: 1.0156544e+08 | I9: 96951607 | J9: 92339077 | K9: 87985967 | L9: 83571652 | M9: 79435812 | N9: 73542848 | O9: 70109871 | P9: 66014266 | Q9: 62581626 | R9: 57287825 | S9: 53690005 | T9: 47205294 | U9: 45091953 | V9: 42182458 | W9: 40414089 | X9: 38405435 | Y9: 36586831 | Z9: 35044590 | AA9: 32146832 | AB9: 30389204 | AC9: 24723366 | AD9: 22627558 | AE9: 20346559 | AF9: 18532679 | AG9: 17502559 | AH9: 16355170 | AI9: 15682499 | AJ9: 14617895 | AK9: 13417594 | AL9: 12919154 | AM9: 12371931 | AN9: 11813108 | AO9: 9724877.8 | AP9: 8786782 | AQ9: 6523622.6 | AR9: 5441621.4 | AS9: 5165438.7 | AT9: 4952011.4 | AU9: 4728626.4 | AV9: 4403732.9 | AW9: 4111183.9 | AX9: 3995116.1 | AY9: 3849317.3 | AZ9: 3726018.3 | BA9: 3610192.5 | BB9: 3495500.8 | BC9: 2491897 | BD9: 729211.37 | BE9: 649845.5 | BF9: 345012.46 | BG9: 186262.34 | BH9: 144094.7 | BI9: 97198.39 | BJ9: 60580.39 | BK9: 60580.39 | BL9: 60580.39
A10: maintenance_fund | B10: 73046874 | C10: 64763583 | D10: 62693513 | E10: 61140585 | F10: 58633715 | G10: 56915522 | H10: 53552168 | I10: 52005356 | J10: 49964702 | K10: 47928795 | L10: 45455227 | M10: 43102854 | N10: 40345704 | O10: 38537694 | P10: 36685680 | Q10: 35309860 | R10: 32891937 | S10: 30996853 | T10: 29916881 | U10: 28822094 | V10: 27403474 | W10: 26134231 | X10: 24586722 | Y10: 23402888 | Z10: 22239733 | AA10: 20293884 | AB10: 18954832 | AC10: 16928361 | AD10: 15419494 | AE10: 13774095 | AF10: 12699775 | AG10: 11860389 | AH10: 11044643 | AI10: 10520126 | AJ10: 9646061.7 | AK10: 8926383.9 | AL10: 8510527.9 | AM10: 8024092.1 | AN10: 7567977.8 | AO10: 6745814.9 | AP10: 6124640.4 | AQ10: 5387631.3 | AR10: 4590075.9 | AS10: 4397609 | AT10: 4206496.2 | AU10: 4052794 | AV10: 3745091.1 | AW10: 3493889 | AX10: 3390166.5 | AY10: 3270174.7 | AZ10: 3158075.8 | BA10: 3042250 | BB10: 2940637.6 | BC10: 2073052.2 | BD10: 493325.36 | BE10: 416658.68 | BF10: 325869.07 | BG10: 185329.34 | BH10: 143161.7 | BI10: 96265.39 | BJ10: 59647.39 | BK10: 59647.39 | BL10: 59647.39
A11: other_fee_p_m | B11: 1688422.1 | C11: 1581001.1 | D11: 1540671.6 | E11: 1508780.6 | F11: 1473543.1 | G11: 1442867.5 | H11: 1411951.5 | I11: 1373702.7 | J11: 1319590.7 | K11: 1248064.6 | L11: 1184857.4 | M11: 1131626.6 | N11: 1086090.2 | O11: 1069386.9 | P11: 1027951.3 | Q11: 999186.04 | R11: 961290.79 | S11: 904352.82 | T11: 848506.02 | U11: 829889.54 | V11: 808242.42 | W11: 791818.98 | X11: 726602.8 | Y11: 669271.71 | Z11: 591394.37 | AA11: 554252.06 | AB11: 517940.38 | AC11: 469698.72 | AD11: 434795.19 | AE11: 397139.75 | AF11: 363804.87 | AG11: 325010.54 | AH11: 299001.82 | AI11: 280835.09 | AJ11: 238512.09 | AK11: 196486.64 | AL11: 180114.1 | AM11: 172014.19 | AN11: 158657.38 | AO11: 147452.1 | AP11: 139334.83 | AQ11: 130452.25 | AR11: 120841.99 | AS11: 115179.93 | AT11: 96369.17 | AU11: 92747.1 | AV11: 74236.2 | AW11: 66334.69 | AX11: 60543.46 | AY11: 56353.03 | AZ11: 54466.2 | BA11: 51626.43 | BB11: 50576.43 | BC11: 42128.16 | BD11: 26060.61 | BE11: 22744.99 | BF11: 17697.92 | BG11: 14204.71 | BH11: 11161.5 | BI11: 5506.17 | BJ11: 645.01 | BK11: 645.01 | BL11: 645.01
A12: total_cost | B12: 1.2920936e+09 | C12: 1.205384e+09 | D12: 1.1773996e+09 | E12: 1.1472264e+09 | F12: 1.1128467e+09 | G12: 1.0915853e+09 | H12: 1.062766e+09 | I12: 1.0301251e+09 | J12: 1.0018711e+09 | K12: 9.7237189e+08 | L12: 9.4284406e+08 | M12: 9.1556629e+08 | N12: 8.8125903e+08 | O12: 8.6012347e+08 | P12: 8.2785133e+08 | Q12: 8.0343305e+08 | R12: 7.6520419e+08 | S12: 7.2974176e+08 | T12: 6.9626896e+08 | U12: 6.7390156e+08 | V12: 6.5075546e+08 | W12: 6.326905e+08 | X12: 6.1138017e+08 | Y12: 5.9123885e+08 | Z12: 5.6809611e+08 | AA12: 5.3949375e+08 | AB12: 5.1040723e+08 | AC12: 4.6870926e+08 | AD12: 4.3963758e+08 | AE12: 4.0735261e+08 | AF12: 3.8519175e+08 | AG12: 3.6631757e+08 | AH12: 3.5196665e+08 | AI12: 3.3801661e+08 | AJ12: 3.1678725e+08 | AK12: 2.9173254e+08 | AL12: 2.7994548e+08 | AM12: 2.7014919e+08 | AN12: 2.5277479e+08 | AO12: 2.2907647e+08 | AP12: 2.1609452e+08 | AQ12: 2.0056399e+08 | AR12: 1.8175971e+08 | AS12: 1.6696806e+08 | AT12: 1.5790457e+08 | AU12: 1.4360688e+08 | AV12: 1.2959517e+08 | AW12: 1.1640345e+08 | AX12: 1.1223359e+08 | AY12: 1.0864929e+08 | AZ12: 1.049976e+08 | BA12: 1.0191627e+08 | BB12: 98666884 | BC12: 79676425 | BD12: 45101802 | BE12: 40243440 | BF12: 34712640 | BG12: 31821469 | BH12: 27718531 | BI12: 10557399 | BJ12: 1163163.5 | BK12: 1163163.5 | BL12: 1163163.5
A13: nbv | B13: 9.5286586e+08 | C13: 9.1043988e+08 | D13: 8.81879e+08 | E13: 8.5015773e+08 | F13: 8.1870299e+08 | G13: 7.9546963e+08 | H13: 7.7007436e+08 | I13: 7.4087589e+08 | J13: 7.1443123e+08 | K13: 6.8767792e+08 | L13: 6.6117894e+08 | M13: 6.3586948e+08 | N13: 6.0755185e+08 | O13: 5.873339e+08 | P13: 5.6183636e+08 | Q13: 5.409537e+08 | R13: 5.1156473e+08 | S13: 4.8258964e+08 | T13: 4.5830168e+08 | U13: 4.3891549e+08 | V13: 4.1977533e+08 | W13: 4.0307767e+08 | X13: 3.8553106e+08 | Y13: 3.6811492e+08 | Z13: 3.4872057e+08 | AA13: 3.2692612e+08 | AB13: 3.0607451e+08 | AC13: 2.8027828e+08 | AD13: 2.6013847e+08 | AE13: 2.4005088e+08 | AF13: 2.253902e+08 | AG13: 2.1216882e+08 | AH13: 2.0157507e+08 | AI13: 1.9106108e+08 | AJ13: 1.772425e+08 | AK13: 1.6220782e+08 | AL13: 1.5287495e+08 | AM13: 1.4495747e+08 | AN13: 1.3388488e+08 | AO13: 1.2022708e+08 | AP13: 1.1186118e+08 | AQ13: 1.0318128e+08 | AR13: 93555230 | AS13: 85145292 | AT13: 78248747 | AU13: 72313108 | AV13: 64402301 | AW13: 57300954 | AX13: 53904697 | AY13: 51180094 | AZ13: 48090570 | BA13: 45376031 | BB13: 43081227 | BC13: 34450598 | BD13: 20310083 | BE13: 17921542 | BF13: 15104085 | BG13: 13835058 | BH13: 11860748 | BI13: 5091271.6 | BJ13: 343709.03 | BK13: 332051.24 | BL13: 320393.45
... A16: olmm_fleet_drop | B16: 0 | C16: 7 | D16: 6 | E16: 17 | F16: 1 | G16: 6 | H16: 5 | I16: 5 | J16: 0 | K16: 4 | L16: 2 | M16: 1 | N16: 0 | O16: 2 | P16: 2 | Q16: 6 | R16: 4 | S16: 1 | T16: 3 | U16: 4 | V16: 1 | W16: 3 | X16: 6 | Y16: 0 | Z16: 4 | AA16: 2 | AB16: 13 | AC16: 6 | AD16: 8 | AE16: 12 | AF16: 8 | AG16: 8 | AH16: 0 | AI16: 7 | AJ16: 7 | AK16: 2 | AL16: 0 | AM16: 0 | AN16: 18 | AO16: 30 | AP16: 1 | AQ16: 3 | AR16: 1 | AS16: 5 | AT16: 1 | AU16: 4 | AV16: 2 | AW16: 9 | AX16: 0 | AY16: 1 | AZ16: 0 | BA16: 0 | BB16: 0 | BC16: 2 | BD16: 7 | BE16: 1 | BF16: 0 | BG16: 0 | BH16: 1 | BI16: 4 | BJ16: 0 | BK16: 0 | BL16: 0

Sheet Public Sector
A1: Value | B1: 2025/06/06 | C1: 2025/06/30 | D1: 2025/07/31 | E1: 2025/08/31 | F1: 2025/09/30 | G1: 2025/10/31 | H1: 2025/11/30 | I1: 2025/12/31 | J1: 2026/01/31 | K1: 2026/02/28 | L1: 2026/03/31 | M1: 2026/04/30 | N1: 2026/05/31 | O1: 2026/06/30 | P1: 2026/07/31 | Q1: 2026/08/31 | R1: 2026/09/30 | S1: 2026/10/31 | T1: 2026/11/30 | U1: 2026/12/31 | V1: 2027/01/31 | W1: 2027/02/28 | X1: 2027/03/31 | Y1: 2027/04/30 | Z1: 2027/05/31 | AA1: 2027/06/30 | AB1: 2027/07/31 | AC1: 2027/08/31 | AD1: 2027/09/30 | AE1: 2027/10/31 | AF1: 2027/11/30 | AG1: 2027/12/31 | AH1: 2028/01/31 | AI1: 2028/02/29 | AJ1: 2028/03/31 | AK1: 2028/04/30 | AL1: 2028/05/31 | AM1: 2028/06/30 | AN1: 2028/07/31 | AO1: 2028/08/31 | AP1: 2028/09/30 | AQ1: 2028/10/31 | AR1: 2028/11/30 | AS1: 2028/12/31 | AT1: 2029/01/31 | AU1: 2029/02/28 | AV1: 2029/03/31 | AW1: 2029/04/30 | AX1: 2029/05/31 | AY1: 2029/06/30 | AZ1: 2029/07/31 | BA1: 2029/08/31 | BB1: 2029/09/30 | BC1: 2029/10/31 | BD1: 2029/11/30 | BE1: 2029/12/31 | BF1: 2030/01/31 | BG1: 2030/02/28 | BH1: 2030/03/31 | BI1: 2030/04/30 | BJ1: 2030/05/31 | BK1: 2030/06/30 | BL1: 2030/07/31
A2: fml_count | B2: 277 | C2: 258 | D2: 252 | E2: 252 | F2: 252 | G2: 252 | H2: 238 | I2: 233 | J2: 233 | K2: 233 | L2: 232 | M2: 227 | N2: 225 | O2: 218 | P2: 218 | Q2: 213 | R2: 205 | S2: 199 | T2: 185 | U2: 145 | V2: 133 | W2: 104 | X2: 104 | Y2: 97 | Z2: 84 | AA2: 67 | AB2: 66 | AC2: 64 | AD2: 58 | AE2: 58 | AF2: 47 | AG2: 47 | AH2: 23 | AI2: 21 | AJ2: 21 | AK2: 19 | AL2: 19 | AM2: 19 | AN2: 19 | AO2: 18 | AP2: 16 | AQ2: 16 | AR2: 15 | AS2: 15 | AT2: 15 | AU2: 15 | AV2: 14 | AW2: 14 | AX2: 13 | AY2: 13 | AZ2: 13 | BA2: 13 | BB2: 13 | BC2: 13 | BD2: 13 | BE2: 13 | BF2: 13 | BG2: 13 | BH2: 12 | BI2: 12 | BJ2: 0 | BK2: 0 | BL2: 0
A3: olmm_count | B3: 93 | C3: 93 | D3: 93 | E3: 93 | F3: 93 | G3: 93 | H3: 93 | I3: 93 | J3: 93 | K3: 93 | L3: 93 | M3: 93 | N3: 93 | O3: 93 | P3: 93 | Q3: 93 | R3: 93 | S3: 93 | T3: 93 | U3: 93 | V3: 93 | W3: 93 | X3: 93 | Y3: 93 | Z3: 93 | AA3: 93 | AB3: 93 | AC3: 93 | AD3: 93 | AE3: 92 | AF3: 44 | AG3: 25 | AH3: 9 | AI3: 1 | AJ3: 1 | AK3: 0 | AL3: 0 | AM3: 0 | AN3: 0 | AO3: 0 | AP3: 0 | AQ3: 0 | AR3: 0 | AS3: 0 | AT3: 0 | AU3: 0 | AV3: 0 | AW3: 0 | AX3: 0 | AY3: 0 | AZ3: 0 | BA3: 0 | BB3: 0 | BC3: 0 | BD3: 0 | BE3: 0 | BF3: 0 | BG3: 0 | BH3: 0 | BI3: 0 | BJ3: 0 | BK3: 0 | BL3: 0
A4: pl_count | B4: 0 | C4: 0 | D4: 0 | E4: 0 | F4: 0 | G4: 0 | H4: 0 | I4: 0 | J4: 0 | K4: 0 | L4: 0 | M4: 0 | N4: 0 | O4: 0 | P4: 0 | Q4: 0 | R4: 0 | S4: 0 | T4: 0 | U4: 0 | V4: 0 | W4: 0 | X4: 0 | Y4: 0 | Z4: 0 | AA4: 0 | AB4: 0 | AC4: 0 | AD4: 0 | AE4: 0 | AF4: 0 | AG4: 0 | AH4: 0 | AI4: 0 | AJ4: 0 | AK4: 0 | AL4: 0 | AM4: 0 | AN4: 0 | AO4: 0 | AP4: 0 | AQ4: 0 | AR4: 0 | AS4: 0 | AT4: 0 | AU4: 0 | AV4: 0 | AW4: 0 | AX4: 0 | AY4: 0 | AZ4: 0 | BA4: 0 | BB4: 0 | BC4: 0 | BD4: 0 | BE4: 0 | BF4: 0 | BG4: 0 | BH4: 0 | BI4: 0 | BJ4: 0 | BK4: 0 | BL4: 0
A5: revenue_p_m | B5: 5395903 | C5: 5269001.5 | D5: 5204253.3 | E5: 5204253.3 | F5: 5204253.3 | G5: 5204253.3 | H5: 4860875 | I5: 4729455.7 | J5: 4729455.7 | K5: 4729455.7 | L5: 4650903.1 | M5: 4591580 | N5: 4566117.5 | O5: 4521819 | P5: 4521819 | Q5: 4464770.9 | R5: 4369890.8 | S5: 4304379.5 | T5: 4148313.1 | U5: 3787229.1 | V5: 3692059 | W5: 3330916.5 | X5: 3330916.5 | Y5: 3275754.9 | Z5: 3114119.7 | AA5: 3007701.4 | AB5: 3001396.2 | AC5: 2986417.6 | AD5: 2948828.3 | AE5: 2838890.7 | AF5: 2047088.4 | AG5: 1459698.6 | AH5: 524381.81 | AI5: 360261.37 | AJ5: 360261.37 | AK5: 161704.42 | AL5: 161704.42 | AM5: 161704.42 | AN5: 161704.42 | AO5: 148135.65 | AP5: 118724.66 | AQ5: 118724.66 | AR5: 110662 | AS5: 110662 | AT5: 110662 | AU5: 110662 | AV5: 102122.39 | AW5: 102122.39 | AX5: 94237.81 | AY5: 94237.81 | AZ5: 94237.81 | BA5: 94237.81 | BB5: 94237.81 | BC5: 94237.81 | BD5: 94237.81 | BE5: 94237.81 | BF5: 94237.81 | BG5: 94237.81 | BH5: 75702.09 | BI5: 75702.09 | BJ5: 0 | BK5: 0 | BL5: 0
A6: depreciation_p_m | B6: 2557998.6 | C6: 2517173.4 | D6: 2489784.8 | E6: 2489784.8 | F6: 2489784.8 | G6: 2489784.8 | H6: 2339803.1 | I6: 2275942 | J6: 2275942 | K6: 2275942 | L6: 2231313 | M6: 2205398.8 | N6: 2194890.2 | O6: 2177727.6 | P6: 2177727.6 | Q6: 2153050.5 | R6: 2109988.9 | S6: 2085444.9 | T6: 2017076.4 | U6: 1887388.5 | V6: 1853958.8 | W6: 1719259 | X6: 1719259 | Y6: 1699967.4 | Z6: 1633834.8 | AA6: 1598927.4 | AB6: 1596586.1 | AC6: 1591135.9 | AD6: 1578450.1 | AE6: 1523647.3 | AF6: 1115623.5 | AG6: 740431.9 | AH6: 277974.8 | AI6: 186678.79 | AJ6: 186678.79 | AK6: 60598.16 | AL6: 60598.16 | AM6: 60598.16 | AN6: 60598.16 | AO6: 55065.84 | AP6: 41966.8 | AQ6: 41966.8 | AR6: 38963.81 | AS6: 38963.81 | AT6: 38963.81 | AU6: 38963.81 | AV6: 36008.83 | AW6: 36008.83 | AX6: 33384.54 | AY6: 33384.54 | AZ6: 33384.54 | BA6: 33384.54 | BB6: 33384.54 | BC6: 33384.54 | BD6: 33384.54 | BE6: 33384.54 | BF6: 33384.54 | BG6: 33384.54 | BH6: 25056.54 | BI6: 25056.54 | BJ6: 0 | BK6: 0 | BL6: 0
A7: interest_p_m | B7: 1679596.1 | C7: 1640330.7 | D7: 1617906 | E7: 1617906 | F7: 1617906 | G7: 1617906 | H7: 1543823.5 | I7: 1518014.5 | J7: 1518014.5 | K7: 1518014.5 | L7: 1504559.2 | M7: 1483926.4 | N7: 1474166.6 | O7: 1460976.7 | P7: 1460976.7 | Q7: 1443062.9 | R7: 1413860.1 | S7: 1387955.8 | T7: 1339258.8 | U7: 1240740.9 | V7: 1207618.2 | W7: 1102160 | X7: 1102160 | Y7: 1083892.9 | Z7: 1032691.4 | AA7: 992869.12 | AB7: 990867.24 | AC7: 985656.58 | AD7: 972300.11 | AE7: 939137.37 | AF7: 667109 | AG7: 519677.58 | AH7: 171926.99 | AI7: 115667.7 | AJ7: 115667.7 | AK7: 56036.61 | AL7: 56036.61 | AM7: 56036.61 | AN7: 56036.61 | AO7: 51022.47 | AP7: 41206.3 | AQ7: 41206.3 | AR7: 38618.39 | AS7: 38618.39 | AT7: 38618.39 | AU7: 38618.39 | AV7: 35990.42 | AW7: 35990.42 | AX7: 33313.86 | AY7: 33313.86 | AZ7: 33313.86 | BA7: 33313.86 | BB7: 33313.86 | BC7: 33313.86 | BD7: 33313.86 | BE7: 33313.86 | BF7: 33313.86 | BG7: 33313.86 | BH7: 26087.22 | BI7: 26087.22 | BJ7: 0 | BK7: 0 | BL7: 0
A8: admin_p_m | B8: 279343.8 | C8: 272572.89 | D8: 268894.27 | E8: 268894.27 | F8: 268894.27 | G8: 268894.27 | H8: 258831.06 | I8: 251650.77 | J8: 251650.77 | K8: 251650.77 | L8: 247458.98 | M8: 242347.98 | N8: 240680.51 | O8: 237347.93 | P8: 237347.93 | Q8: 233127.89 | R8: 225204.81 | S8: 219366.4 | T8: 206494.1 | U8: 197709.8 | V8: 191626.67 | W8: 176237.56 | X8: 176237.56 | Y8: 171567.92 | Z8: 161495.43 | AA8: 151551.86 | AB8: 151045.43 | AC8: 149730.19 | AD8: 146362.19 | AE8: 146332.75 | AF8: 115911.13 | AG8: 97260.16 | AH8: 25809.76 | AI8: 15760.14 | AJ8: 15760.14 | AK8: 14716.37 | AL8: 14716.37 | AM8: 14716.37 | AN8: 14716.37 | AO8: 13408.2 | AP8: 10681.78 | AQ8: 10681.78 | AR8: 10012.27 | AS8: 10012.27 | AT8: 10012.27 | AU8: 10012.27 | AV8: 9335.86 | AW8: 9335.86 | AX8: 8698.38 | AY8: 8698.38 | AZ8: 8698.38 | BA8: 8698.38 | BB8: 8698.38 | BC8: 8698.38 | BD8: 8698.38 | BE8: 8698.38 | BF8: 8698.38 | BG8: 8698.38 | BH8: 6779.92 | BI8: 6779.92 | BJ8: 0 | BK8: 0 | BL8: 0
A9: maint_prov_p_m | B9: 8929500.1 | C9: 7371699.7 | D9: 7088896.3 | E9: 7088896.3 | F9: 7088896.3 | G9: 7088896.3 | H9: 5835868.7 | I9: 5543770.8 | J9: 5543770.8 | K9: 5543770.8 | L9: 5484466.8 | M9: 5336526.8 | N9: 5222220.1 | O9: 4962582 | P9: 4962582 | Q9: 4715277 | R9: 4347285 | S9: 4126656.9 | T9: 3564317.5 | U9: 2892091.4 | V9: 2656532.6 | W9: 1959820.7 | X9: 1959820.7 | Y9: 1692910.7 | Z9: 1331956 | AA9: 746387.92 | AB9: 721779.07 | AC9: 672691.79 | AD9: 486219.79 | AE9: 486219.79 | AF9: 360494.03 | AG9: 360494.03 | AH9: 144597.74 | AI9: 131340.14 | AJ9: 131340.14 | AK9: 125097.46 | AL9: 125097.46 | AM9: 125097.46 | AN9: 125097.46 | AO9: 100377.59 | AP9: 34804.39 | AQ9: 34804.39 | AR9: 23578.39 | AS9: 23578.39 | AT9: 23578.39 | AU9: 23578.39 | AV9: 18048.64 | AW9: 18048.64 | AX9: 14906.14 | AY9: 14906.14 | AZ9: 14906.14 | BA9: 14906.14 | BB9: 14906.14 | BC9: 14906.14 | BD9: 14906.14 | BE9: 14906.14 | BF9: 14906.14 | BG9: 14906.14 | BH9: 12951.74 | BI9: 12951.74 | BJ9: 0 | BK9: 0 | BL9: 0
A10: maintenance_fund | B10: 5196580.3 | C10: 4621992.8 | D10: 4785072.9 | E10: 4785072.9 | F10: 4785072.9 | G10: 4785072.9 | H10: 4292931.6 | I10: 4163489.6 | J10: 4163489.6 | K10: 4163489.6 | L10: 4237075.5 | M10: 4089524.8 | N10: 4016090.4 | O10: 3808211.2 | P10: 3808211.2 | Q10: 3625357.7 | R10: 3326848.3 | S10: 3180832.5 | T10: 2803992.9 | U10: 2378683.5 | V10: 2249291.3 | W10: 1627519.5 | X10: 1627519.5 | Y10: 1463156.6 | Z10: 1236568 | AA10: 663100.3 | AB10: 638491.45 | AC10: 589404.17 | AD10: 468862.1 | AE10: 468862.1 | AF10: 346885.45 | AG10: 346885.45 | AH10: 131986.7 | AI10: 122740.08 | AJ10: 122740.08 | AK10: 116497.4 | AL10: 116497.4 | AM10: 116497.4 | AN10: 116497.4 | AO10: 93958.92 | AP10: 34804.39 | AQ10: 34804.39 | AR10: 23578.39 | AS10: 23578.39 | AT10: 23578.39 | AU10: 23578.39 | AV10: 18048.64 | AW10: 18048.64 | AX10: 14906.14 | AY10: 14906.14 | AZ10: 14906.14 | BA10: 14906.14 | BB10: 14906.14 | BC10: 14906.14 | BD10: 14906.14 | BE10: 14906.14 | BF10: 14906.14 | BG10: 14906.14 | BH10: 12951.74 | BI10: 12951.74 | BJ10: 0 | BK10: 0 | BL10: 0
A11: other_fee_p_m | B11: 515815.01 | C11: 508083.08 | D11: 506097.79 | E11: 506097.79 | F11: 506097.79 | G11: 506097.79 | H11: 438237.75 | I11: 413091.28 | J11: 413091.28 | K11: 413091.28 | L11: 398932.77 | M11: 396957.77 | N11: 396393.43 | O11: 392987.31 | P11: 392987.31 | Q11: 389514.28 | R11: 385765.72 | S11: 383435.79 | T11: 377430.79 | U11: 282727.11 | V11: 269503.39 | W11: 198305.57 | X11: 198305.57 | Y11: 195638.15 | Z11: 177693.49 | AA11: 174870.02 | AB11: 174484.35 | AC11: 173713.01 | AD11: 172425.22 | AE11: 150482.49 | AF11: 84314.41 | AG11: 38198.61 | AH11: 21400.67 | AI11: 17536.67 | AJ11: 17536.67 | AK11: 8856.55 | AL11: 8856.55 | AM11: 8856.55 | AN11: 8856.55 | AO11: 8596.52 | AP11: 7807.76 | AQ11: 7807.76 | AR11: 7408.76 | AS11: 7408.76 | AT11: 7408.76 | AU11: 7408.76 | AV11: 6971.76 | AW11: 6971.76 | AX11: 6596.76 | AY11: 6596.76 | AZ11: 6596.76 | BA11: 6596.76 | BB11: 6596.76 | BC11: 6596.76 | BD11: 6596.76 | BE11: 6596.76 | BF11: 6596.76 | BG11: 6596.76 | BH11: 6022.74 | BI11: 6022.74 | BJ11: 0 | BK11: 0 | BL11: 0
A12: total_cost | B12: 2.0416048e+08 | C12: 1.9816228e+08 | D12: 1.9522857e+08 | E12: 1.9522857e+08 | F12: 1.9522857e+08 | G12: 1.9522857e+08 | H12: 1.8632795e+08 | I12: 1.8260857e+08 | J12: 1.8260857e+08 | K12: 1.8260857e+08 | L12: 1.8051267e+08 | M12: 1.7795716e+08 | N12: 1.7669938e+08 | O12: 1.7499231e+08 | P12: 1.7499231e+08 | Q12: 1.7273022e+08 | R12: 1.6897771e+08 | S12: 1.6581018e+08 | T12: 1.5963411e+08 | U12: 1.4563918e+08 | V12: 1.4139379e+08 | W12: 1.2791931e+08 | X12: 1.2791931e+08 | Y12: 1.2562681e+08 | Z12: 1.1901529e+08 | AA12: 1.1404345e+08 | AB12: 1.1379024e+08 | AC12: 1.1313261e+08 | AD12: 1.1144859e+08 | AE12: 1.0791509e+08 | AF12: 78148903 | AG12: 58188879 | AH12: 19905544 | AI12: 13671148 | AJ12: 13671148 | AK12: 7358226.1 | AL12: 7358226.1 | AM12: 7358226.1 | AN12: 7358226.1 | AO12: 6704140.3 | AP12: 5340922.5 | AQ12: 5340922.5 | AR12: 5006164.6 | AS12: 5006164.6 | AT12: 5006164.6 | AU12: 5006164.6 | AV12: 4667956.4 | AW12: 4667956.4 | AX12: 4349215.1 | AY12: 4349215.1 | AZ12: 4349215.1 | BA12: 4349215.1 | BB12: 4349215.1 | BC12: 4349215.1 | BD12: 4349215.1 | BE12: 4349215.1 | BF12: 4349215.1 | BG12: 4349215.1 | BH12: 3389980.2 | BI12: 3389980.2 | BJ12: 0 | BK12: 0 | BL12: 0
A13: nbv | B13: 1.6994579e+08 | C13: 1.6671222e+08 | D13: 1.6238929e+08 | E13: 1.5989951e+08 | F13: 1.5740972e+08 | G13: 1.5491994e+08 | H13: 1.4865386e+08 | I13: 1.4489367e+08 | J13: 1.4261773e+08 | K13: 1.4034179e+08 | L13: 1.3757659e+08 | M13: 1.3369677e+08 | N13: 1.3077647e+08 | O13: 1.2768683e+08 | P13: 1.2550911e+08 | Q13: 1.2214035e+08 | R13: 1.1795646e+08 | S13: 1.1376908e+08 | T13: 1.079948e+08 | U13: 96700799 | V13: 92079266 | W13: 81827588 | X13: 80108329 | Y13: 76979430 | Z13: 71510431 | AA13: 66752101 | AB13: 65009998 | AC13: 63011940 | AD13: 60402546 | AE13: 57208693 | AF13: 40468237 | AG13: 32778752 | AH13: 10382370 | AI13: 7148803 | AJ13: 6962124.2 | AK13: 4875345.2 | AL13: 4814747 | AM13: 4754148.9 | AN13: 4693550.7 | AO13: 4277612 | AP13: 3645270.8 | AQ13: 3603304 | AR13: 3370722.9 | AS13: 3331759.1 | AT13: 3292795.3 | AU13: 3253831.4 | AV13: 3015543.4 | AW13: 2979534.6 | AX13: 2750750.4 | AY13: 2717365.9 | AZ13: 2683981.3 | BA13: 2650596.8 | BB13: 2617212.2 | BC13: 2583827.7 | BD13: 2550443.2 | BE13: 2517058.6 | BF13: 2483674.1 | BG13: 2450289.5 | BH13: 1957350.1 | BI13: 1932293.6 | BJ13: 0 | BK13: 0 | BL13: 0
... A16: olmm_fleet_drop | B16: 0 | C16: 0 | D16: 0 | E16: 0 | F16: 0 | G16: 0 | H16: 0 | I16: 0 | J16: 0 | K16: 0 | L16: 0 | M16: 0 | N16: 0 | O16: 0 | P16: 0 | Q16: 0 | R16: 0 | S16: 0 | T16: 0 | U16: 0 | V16: 0 | W16: 0 | X16: 0 | Y16: 0 | Z16: 0 | AA16: 0 | AB16: 0 | AC16: 0 | AD16: 0 | AE16: 1 | AF16: 48 | AG16: 19 | AH16: 16 | AI16: 8 | AJ16: 0 | AK16: 1 | AL16: 0 | AM16: 0 | AN16: 0 | AO16: 0 | AP16: 0 | AQ16: 0 | AR16: 0 | AS16: 0 | AT16: 0 | AU16: 0 | AV16: 0 | AW16: 0 | AX16: 0 | AY16: 0 | AZ16: 0 | BA16: 0 | BB16: 0 | BC16: 0 | BD16: 0 | BE16: 0 | BF16: 0 | BG16: 0 | BH16: 0 | BI16: 0 | BJ16: 0 | BK16: 0 | BL16: 0

Sheet Legal
A1: Value | B1: 2025/06/06 | C1: 2025/06/30 | D1: 2025/07/31 | E1: 2025/08/31 | F1: 2025/09/30 | G1: 2025/10/31 | H1: 2025/11/30 | I1: 2025/12/31 | J1: 2026/01/31 | K1: 2026/02/28 | L1: 2026/03/31 | M1: 2026/04/30 | N1: 2026/05/31 | O1: 2026/06/30 | P1: 2026/07/31 | Q1: 2026/08/31 | R1: 2026/09/30 | S1: 2026/10/31 | T1: 2026/11/30 | U1: 2026/12/31 | V1: 2027/01/31 | W1: 2027/02/28 | X1: 2027/03/31 | Y1: 2027/04/30 | Z1: 2027/05/31 | AA1: 2027/06/30 | AB1: 2027/07/31 | AC1: 2027/08/31 | AD1: 2027/09/30 | AE1: 2027/10/31 | AF1: 2027/11/30 | AG1: 2027/12/31 | AH1: 2028/01/31 | AI1: 2028/02/29 | AJ1: 2028/03/31 | AK1: 2028/04/30 | AL1: 2028/05/31 | AM1: 2028/06/30 | AN1: 2028/07/31 | AO1: 2028/08/31 | AP1: 2028/09/30 | AQ1: 2028/10/31 | AR1: 2028/11/30 | AS1: 2028/12/31 | AT1: 2029/01/31 | AU1: 2029/02/28 | AV1: 2029/03/31 | AW1: 2029/04/30 | AX1: 2029/05/31 | AY1: 2029/06/30 | AZ1: 2029/07/31 | BA1: 2029/08/31 | BB1: 2029/09/30 | BC1: 2029/10/31 | BD1: 2029/11/30 | BE1: 2029/12/31 | BF1: 2030/01/31 | BG1: 2030/02/28 | BH1: 2030/03/31 | BI1: 2030/04/30 | BJ1: 2030/05/31 | BK1: 2030/06/30 | BL1: 2030/07/31
A2: fml_count | B2: 16 | C2: 4 | D2: 4 | E2: 4 | F2: 4 | G2: 4 | H2: 4 | I2: 4 | J2: 4 | K2: 4 | L2: 4 | M2: 4 | N2: 4 | O2: 4 | P2: 4 | Q2: 4 | R2: 4 | S2: 4 | T2: 4 | U2: 3 | V2: 3 | W2: 3 | X2: 3 | Y2: 3 | Z2: 2 | AA2: 2 | AB2: 2 | AC2: 2 | AD2: 2 | AE2: 1 | AF2: 1 | AG2: 1 | AH2: 1 | AI2: 1 | AJ2: 0 | AK2: 0 | AL2: 0 | AM2: 0 | AN2: 0 | AO2: 0 | AP2: 0 | AQ2: 0 | AR2: 0 | AS2: 0 | AT2: 0 | AU2: 0 | AV2: 0 | AW2: 0 | AX2: 0 | AY2: 0 | AZ2: 0 | BA2: 0 | BB2: 0 | BC2: 0 | BD2: 0 | BE2: 0 | BF2: 0 | BG2: 0 | BH2: 0 | BI2: 0 | BJ2: 0 | BK2: 0 | BL2: 0
A3: olmm_count | B3: 9 | C3: 9 | D3: 9 | E3: 9 | F3: 9 | G3: 9 | H3: 9 | I3: 9 | J3: 9 | K3: 9 | L3: 9 | M3: 9 | N3: 9 | O3: 9 | P3: 9 | Q3: 9 | R3: 6 | S3: 6 | T3: 6 | U3: 6 | V3: 6 | W3: 6 | X3: 6 | Y3: 6 | Z3: 6 | AA3: 6 | AB3: 6 | AC3: 6 | AD3: 6 | AE3: 6 | AF3: 6 | AG3: 6 | AH3: 6 | AI3: 6 | AJ3: 6 | AK3: 6 | AL3: 6 | AM3: 6 | AN3: 0 | AO3: 0 | AP3: 0 | AQ3: 0 | AR3: 0 | AS3: 0 | AT3: 0 | AU3: 0 | AV3: 0 | AW3: 0 | AX3: 0 | AY3: 0 | AZ3: 0 | BA3: 0 | BB3: 0 | BC3: 0 | BD3: 0 | BE3: 0 | BF3: 0 | BG3: 0 | BH3: 0 | BI3: 0 | BJ3: 0 | BK3: 0 | BL3: 0
A4: pl_count | B4: 1 | C4: 1 | D4: 1 | E4: 1 | F4: 1 | G4: 1 | H4: 1 | I4: 1 | J4: 1 | K4: 1 | L4: 1 | M4: 1 | N4: 1 | O4: 1 | P4: 1 | Q4: 1 | R4: 1 | S4: 1 | T4: 1 | U4: 1 | V4: 1 | W4: 1 | X4: 1 | Y4: 1 | Z4: 1 | AA4: 1 | AB4: 1 | AC4: 1 | AD4: 1 | AE4: 1 | AF4: 1 | AG4: 1 | AH4: 1 | AI4: 1 | AJ4: 1 | AK4: 1 | AL4: 1 | AM4: 1 | AN4: 1 | AO4: 1 | AP4: 1 | AQ4: 1 | AR4: 1 | AS4: 1 | AT4: 1 | AU4: 1 | AV4: 1 | AW4: 1 | AX4: 1 | AY4: 1 | AZ4: 1 | BA4: 1 | BB4: 1 | BC4: 1 | BD4: 1 | BE4: 1 | BF4: 1 | BG4: 0 | BH4: 0 | BI4: 0 | BJ4: 0 | BK4: 0 | BL4: 0
A5: revenue_p_m | B5: 451260.4 | C5: 208163.19 | D5: 208163.19 | E5: 208163.19 | F5: 208163.19 | G5: 208163.19 | H5: 208163.19 | I5: 208163.19 | J5: 208163.19 | K5: 208163.19 | L5: 208163.19 | M5: 208163.19 | N5: 208163.19 | O5: 208163.19 | P5: 208163.19 | Q5: 208163.19 | R5: 171525.02 | S5: 171525.02 | T5: 171525.02 | U5: 153121.11 | V5: 153121.11 | W5: 153121.11 | X5: 153121.11 | Y5: 153121.11 | Z5: 134866.7 | AA5: 134866.7 | AB5: 134866.7 | AC5: 134866.7 | AD5: 134866.7 | AE5: 116676.09 | AF5: 116676.09 | AG5: 116676.09 | AH5: 116676.09 | AI5: 116676.09 | AJ5: 98208.33 | AK5: 98208.33 | AL5: 98208.33 | AM5: 98208.33 | AN5: 10057.81 | AO5: 10057.81 | AP5: 10057.81 | AQ5: 10057.81 | AR5: 10057.81 | AS5: 10057.81 | AT5: 10057.81 | AU5: 10057.81 | AV5: 10057.81 | AW5: 10057.81 | AX5: 10057.81 | AY5: 10057.81 | AZ5: 10057.81 | BA5: 10057.81 | BB5: 10057.81 | BC5: 10057.81 | BD5: 10057.81 | BE5: 10057.81 | BF5: 10057.81 | BG5: 0 | BH5: 0 | BI5: 0 | BJ5: 0 | BK5: 0 | BL5: 0
A6: depreciation_p_m | B6: 225168.59 | C6: 111801.25 | D6: 111801.25 | E6: 111801.25 | F6: 111801.25 | G6: 111801.25 | H6: 111801.25 | I6: 111801.25 | J6: 111801.25 | K6: 111801.25 | L6: 111801.25 | M6: 111801.25 | N6: 111801.25 | O6: 111801.25 | P6: 111801.25 | Q6: 111801.25 | R6: 88938.72 | S6: 88938.72 | T6: 88938.72 | U6: 80602.54 | V6: 80602.54 | W6: 80602.54 | X6: 80602.54 | Y6: 80602.54 | Z6: 71847.19 | AA6: 71847.19 | AB6: 71847.19 | AC6: 71847.19 | AD6: 71847.19 | AE6: 63640.97 | AF6: 63640.97 | AG6: 63640.97 | AH6: 63640.97 | AI6: 63640.97 | AJ6: 55422.91 | AK6: 55422.91 | AL6: 55422.91 | AM6: 55422.91 | AN6: 2535.87 | AO6: 2535.87 | AP6: 2535.87 | AQ6: 2535.87 | AR6: 2535.87 | AS6: 2535.87 | AT6: 2535.87 | AU6: 2535.87 | AV6: 2535.87 | AW6: 2535.87 | AX6: 2535.87 | AY6: 2535.87 | AZ6: 2535.87 | BA6: 2535.87 | BB6: 2535.87 | BC6: 2535.87 | BD6: 2535.87 | BE6: 2535.87 | BF6: 2535.87 | BG6: 0 | BH6: 0 | BI6: 0 | BJ6: 0 | BK6: 0 | BL6: 0
A7: interest_p_m | B7: 111104.85 | C7: 61418.16 | D7: 61418.16 | E7: 61418.16 | F7: 61418.16 | G7: 61418.16 | H7: 61418.16 | I7: 61418.16 | J7: 61418.16 | K7: 61418.16 | L7: 61418.16 | M7: 61418.16 | N7: 61418.16 | O7: 61418.16 | P7: 61418.16 | Q7: 61418.16 | R7: 51089.52 | S7: 51089.52 | T7: 51089.52 | U7: 45642.02 | V7: 45642.02 | W7: 45642.02 | X7: 45642.02 | Y7: 45642.02 | Z7: 40592.12 | AA7: 40592.12 | AB7: 40592.12 | AC7: 40592.12 | AD7: 40592.12 | AE7: 35585.37 | AF7: 35585.37 | AG7: 35585.37 | AH7: 35585.37 | AI7: 35585.37 | AJ7: 29883.36 | AK7: 29883.36 | AL7: 29883.36 | AM7: 29883.36 | AN7: 3679.97 | AO7: 3679.97 | AP7: 3679.97 | AQ7: 3679.97 | AR7: 3679.97 | AS7: 3679.97 | AT7: 3679.97 | AU7: 3679.97 | AV7: 3679.97 | AW7: 3679.97 | AX7: 3679.97 | AY7: 3679.97 | AZ7: 3679.97 | BA7: 3679.97 | BB7: 3679.97 | BC7: 3679.97 | BD7: 3679.97 | BE7: 3679.97 | BF7: 3679.97 | BG7: 0 | BH7: 0 | BI7: 0 | BJ7: 0 | BK7: 0 | BL7: 0
A8: admin_p_m | B8: 28386.78 | C8: 17053.75 | D8: 17053.75 | E8: 17053.75 | F8: 17053.75 | G8: 17053.75 | H8: 17053.75 | I8: 17053.75 | J8: 17053.75 | K8: 17053.75 | L8: 17053.75 | M8: 17053.75 | N8: 17053.75 | O8: 17053.75 | P8: 17053.75 | Q8: 17053.75 | R8: 14036.75 | S8: 14036.75 | T8: 14036.75 | U8: 12558.96 | V8: 12558.96 | W8: 12558.96 | X8: 12558.96 | Y8: 12558.96 | Z8: 11111.78 | AA8: 11111.78 | AB8: 11111.78 | AC8: 11111.78 | AD8: 11111.78 | AE8: 9664.6 | AF8: 9664.6 | AG8: 9664.6 | AH8: 9664.6 | AI8: 9664.6 | AJ8: 8972.25 | AK8: 8972.25 | AL8: 8972.25 | AM8: 8972.25 | AN8: 772.16 | AO8: 772.16 | AP8: 772.16 | AQ8: 772.16 | AR8: 772.16 | AS8: 772.16 | AT8: 772.16 | AU8: 772.16 | AV8: 772.16 | AW8: 772.16 | AX8: 772.16 | AY8: 772.16 | AZ8: 772.16 | BA8: 772.16 | BB8: 772.16 | BC8: 772.16 | BD8: 772.16 | BE8: 772.16 | BF8: 772.16 | BG8: 0 | BH8: 0 | BI8: 0 | BJ8: 0 | BK8: 0 | BL8: 0
A9: maint_prov_p_m | B9: 3129004 | C9: 308356.67 | D9: 308356.67 | E9: 308356.67 | F9: 308356.67 | G9: 308356.67 | H9: 308356.67 | I9: 308356.67 | J9: 308356.67 | K9: 308356.67 | L9: 308356.67 | M9: 308356.67 | N9: 308356.67 | O9: 308356.67 | P9: 308356.67 | Q9: 308356.67 | R9: 308356.67 | S9: 308356.67 | T9: 308356.67 | U9: 241632.26 | V9: 241632.26 | W9: 241632.26 | X9: 241632.26 | Y9: 241632.26 | Z9: 172313.28 | AA9: 172313.28 | AB9: 172313.28 | AC9: 172313.28 | AD9: 172313.28 | AE9: 98346.4 | AF9: 98346.4 | AG9: 98346.4 | AH9: 98346.4 | AI9: 98346.4 | AJ9: 2788 | AK9: 2788 | AL9: 2788 | AM9: 2788 | AN9: 2788 | AO9: 2788 | AP9: 2788 | AQ9: 2788 | AR9: 2788 | AS9: 2788 | AT9: 2788 | AU9: 2788 | AV9: 2788 | AW9: 2788 | AX9: 2788 | AY9: 2788 | AZ9: 2788 | BA9: 2788 | BB9: 2788 | BC9: 2788 | BD9: 2788 | BE9: 2788 | BF9: 2788 | BG9: 0 | BH9: 0 | BI9: 0 | BJ9: 0 | BK9: 0 | BL9: 0
A10: maintenance_fund | B10: 1427590.9 | C10: 231220.5 | D10: 231220.5 | E10: 231220.5 | F10: 231220.5 | G10: 231220.5 | H10: 231220.5 | I10: 231220.5 | J10: 231220.5 | K10: 231220.5 | L10: 231220.5 | M10: 231220.5 | N10: 231220.5 | O10: 231220.5 | P10: 231220.5 | Q10: 231220.5 | R10: 231220.5 | S10: 231220.5 | T10: 231220.5 | U10: 164496.09 | V10: 164496.09 | W10: 164496.09 | X10: 164496.09 | Y10: 164496.09 | Z10: 112218.83 | AA10: 112218.83 | AB10: 112218.83 | AC10: 112218.83 | AD10: 112218.83 | AE10: 61267.46 | AF10: 61267.46 | AG10: 61267.46 | AH10: 61267.46 | AI10: 61267.46 | AJ10: 2788 | AK10: 2788 | AL10: 2788 | AM10: 2788 | AN10: 2788 | AO10: 2788 | AP10: 2788 | AQ10: 2788 | AR10: 2788 | AS10: 2788 | AT10: 2788 | AU10: 2788 | AV10: 2788 | AW10: 2788 | AX10: 2788 | AY10: 2788 | AZ10: 2788 | BA10: 2788 | BB10: 2788 | BC10: 2788 | BD10: 2788 | BE10: 2788 | BF10: 2788 | BG10: 0 | BH10: 0 | BI10: 0 | BJ10: 0 | BK10: 0 | BL10: 0
A11: other_fee_p_m | B11: 9992.98 | C11: 5435.48 | D11: 5435.48 | E11: 5435.48 | F11: 5435.48 | G11: 5435.48 | H11: 5435.48 | I11: 5435.48 | J11: 5435.48 | K11: 5435.48 | L11: 5435.48 | M11: 5435.48 | N11: 5435.48 | O11: 5435.48 | P11: 5435.48 | Q11: 5435.48 | R11: 5005.48 | S11: 5005.48 | T11: 5005.48 | U11: 4560.43 | V11: 4560.43 | W11: 4560.43 | X11: 4560.43 | Y11: 4560.43 | Z11: 4117.89 | AA11: 4117.89 | AB11: 4117.89 | AC11: 4117.89 | AD11: 4117.89 | AE11: 3675.35 | AF11: 3675.35 | AG11: 3675.35 | AH11: 3675.35 | AI11: 3675.35 | AJ11: 3232.81 | AK11: 3232.81 | AL11: 3232.81 | AM11: 3232.81 | AN11: 2372.81 | AO11: 2372.81 | AP11: 2372.81 | AQ11: 2372.81 | AR11: 2372.81 | AS11: 2372.81 | AT11: 2372.81 | AU11: 2372.81 | AV11: 2372.81 | AW11: 2372.81 | AX11: 2372.81 | AY11: 2372.81 | AZ11: 2372.81 | BA11: 2372.81 | BB11: 2372.81 | BC11: 2372.81 | BD11: 2372.81 | BE11: 2372.81 | BF11: 2372.81 | BG11: 0 | BH11: 0 | BI11: 0 | BJ11: 0 | BK11: 0 | BL11: 0
A12: total_cost | B12: 16833577 | C12: 8989476.3 | D12: 8989476.3 | E12: 8989476.3 | F12: 8989476.3 | G12: 8989476.3 | H12: 8989476.3 | I12: 8989476.3 | J12: 8989476.3 | K12: 8989476.3 | L12: 8989476.3 | M12: 8989476.3 | N12: 8989476.3 | O12: 8989476.3 | P12: 8989476.3 | Q12: 8989476.3 | R12: 7480976.3 | S12: 7480976.3 | T12: 7480976.3 | U12: 6762722.1 | V12: 6762722.1 | W12: 6762722.1 | X12: 6762722.1 | Y12: 6762722.1 | Z12: 6059776.3 | AA12: 6059776.3 | AB12: 6059776.3 | AC12: 6059776.3 | AD12: 6059776.3 | AE12: 5356830.4 | AF12: 5356830.4 | AG12: 5356830.4 | AH12: 5356830.4 | AI12: 5356830.4 | AJ12: 4551549.6 | AK12: 4551549.6 | AL12: 4551549.6 | AM12: 4551549.6 | AN12: 451503.01 | AO12: 451503.01 | AP12: 451503.01 | AQ12: 451503.01 | AR12: 451503.01 | AS12: 451503.01 | AT12: 451503.01 | AU12: 451503.01 | AV12: 451503.01 | AW12: 451503.01 | AX12: 451503.01 | AY12: 451503.01 | AZ12: 451503.01 | BA12: 451503.01 | BB12: 451503.01 | BC12: 451503.01 | BD12: 451503.01 | BE12: 451503.01 | BF12: 451503.01 | BG12: 0 | BH12: 0 | BI12: 0 | BJ12: 0 | BK12: 0 | BL12: 0
A13: nbv | B13: 8148882.9 | C13: 6249638.5 | D13: 6137837.3 | E13: 6026036 | F13: 5914234.8 | G13: 5802433.5 | H13: 5690632.3 | I13: 5578831 | J13: 5467029.8 | K13: 5355228.5 | L13: 5243427.3 | M13: 5131626 | N13: 5019824.8 | O13: 4908023.5 | P13: 4796222.3 | Q13: 4684421 | R13: 4155198.3 | S13: 4066259.6 | T13: 3977320.9 | U13: 3516055.4 | V13: 3435452.9 | W13: 3354850.3 | X13: 3274247.8 | Y13: 3193645.3 | Z13: 2821138.2 | AA13: 2749291 | AB13: 2677443.8 | AC13: 2605596.6 | AD13: 2533749.4 | AE13: 2182564.2 | AF13: 2118923.2 | AG13: 2055282.3 | AH13: 1991641.3 | AI13: 1928000.3 | AJ13: 1551471.1 | AK13: 1496048.2 | AL13: 1440625.2 | AM13: 1385202.3 | AN13: 350068.21 | AO13: 347532.34 | AP13: 344996.47 | AQ13: 342460.6 | AR13: 339924.73 | AS13: 337388.86 | AT13: 334852.99 | AU13: 332317.12 | AV13: 329781.25 | AW13: 327245.38 | AX13: 324709.51 | AY13: 322173.64 | AZ13: 319637.77 | BA13: 317101.9 | BB13: 314566.03 | BC13: 312030.16 | BD13: 309494.29 | BE13: 306958.42 | BF13: 304422.55 | BG13: 0 | BH13: 0 | BI13: 0 | BJ13: 0 | BK13: 0 | BL13: 0
... A16: olmm_fleet_drop | B16: 0 | C16: 0 | D16: 0 | E16: 0 | F16: 0 | G16: 0 | H16: 0 | I16: 0 | J16: 0 | K16: 0 | L16: 0 | M16: 0 | N16: 0 | O16: 0 | P16: 0 | Q16: 0 | R16: 3 | S16: 0 | T16: 0 | U16: 0 | V16: 0 | W16: 0 | X16: 0 | Y16: 0 | Z16: 0 | AA16: 0 | AB16: 0 | AC16: 0 | AD16: 0 | AE16: 0 | AF16: 0 | AG16: 0 | AH16: 0 | AI16: 0 | AJ16: 0 | AK16: 0 | AL16: 0 | AM16: 0 | AN16: 6 | AO16: 0 | AP16: 0 | AQ16: 0 | AR16: 0 | AS16: 0 | AT16: 0 | AU16: 0 | AV16: 0 | AW16: 0 | AX16: 0 | AY16: 0 | AZ16: 0 | BA16: 0 | BB16: 0 | BC16: 0 | BD16: 0 | BE16: 0 | BF16: 0 | BG16: 0 | BH16: 0 | BI16: 0 | BJ16: 0 | BK16: 0 | BL16: 0

Sheet iLease
A1: Value | B1: 2025/06/06 | C1: 2025/06/30 | D1: 2025/07/31 | E1: 2025/08/31 | F1: 2025/09/30 | G1: 2025/10/31 | H1: 2025/11/30 | I1: 2025/12/31 | J1: 2026/01/31 | K1: 2026/02/28 | L1: 2026/03/31 | M1: 2026/04/30 | N1: 2026/05/31 | O1: 2026/06/30 | P1: 2026/07/31 | Q1: 2026/08/31 | R1: 2026/09/30 | S1: 2026/10/31 | T1: 2026/11/30 | U1: 2026/12/31 | V1: 2027/01/31 | W1: 2027/02/28 | X1: 2027/03/31 | Y1: 2027/04/30 | Z1: 2027/05/31 | AA1: 2027/06/30 | AB1: 2027/07/31 | AC1: 2027/08/31 | AD1: 2027/09/30 | AE1: 2027/10/31 | AF1: 2027/11/30 | AG1: 2027/12/31 | AH1: 2028/01/31 | AI1: 2028/02/29 | AJ1: 2028/03/31 | AK1: 2028/04/30 | AL1: 2028/05/31 | AM1: 2028/06/30 | AN1: 2028/07/31 | AO1: 2028/08/31 | AP1: 2028/09/30 | AQ1: 2028/10/31 | AR1: 2028/11/30 | AS1: 2028/12/31 | AT1: 2029/01/31 | AU1: 2029/02/28 | AV1: 2029/03/31 | AW1: 2029/04/30 | AX1: 2029/05/31 | AY1: 2029/06/30 | AZ1: 2029/07/31 | BA1: 2029/08/31 | BB1: 2029/09/30 | BC1: 2029/10/31 | BD1: 2029/11/30 | BE1: 2029/12/31 | BF1: 2030/01/31 | BG1: 2030/02/28 | BH1: 2030/03/31 | BI1: 2030/04/30 | BJ1: 2030/05/31 | BK1: 2030/06/30 | BL1: 2030/07/31
A2: fml_count | B2: 0 | C2: 0 | D2: 0 | E2: 0 | F2: 0 | G2: 0 | H2: 0 | I2: 0 | J2: 0 | K2: 0 | L2: 0 | M2: 0 | N2: 0 | O2: 0 | P2: 0 | Q2: 0 | R2: 0 | S2: 0 | T2: 0 | U2: 0 | V2: 0 | W2: 0 | X2: 0 | Y2: 0 | Z2: 0 | AA2: 0 | AB2: 0 | AC2: 0 | AD2: 0 | AE2: 0 | AF2: 0 | AG2: 0 | AH2: 0 | AI2: 0 | AJ2: 0 | AK2: 0 | AL2: 0 | AM2: 0 | AN2: 0 | AO2: 0 | AP2: 0 | AQ2: 0 | AR2: 0 | AS2: 0 | AT2: 0 | AU2: 0 | AV2: 0 | AW2: 0 | AX2: 0 | AY2: 0 | AZ2: 0 | BA2: 0 | BB2: 0 | BC2: 0 | BD2: 0 | BE2: 0 | BF2: 0 | BG2: 0 | BH2: 0 | BI2: 0 | BJ2: 0 | BK2: 0 | BL2: 0
A3: olmm_count | B3: 0 | C3: 0 | D3: 0 | E3: 0 | F3: 0 | G3: 0 | H3: 0 | I3: 0 | J3: 0 | K3: 0 | L3: 0 | M3: 0 | N3: 0 | O3: 0 | P3: 0 | Q3: 0 | R3: 0 | S3: 0 | T3: 0 | U3: 0 | V3: 0 | W3: 0 | X3: 0 | Y3: 0 | Z3: 0 | AA3: 0 | AB3: 0 | AC3: 0 | AD3: 0 | AE3: 0 | AF3: 0 | AG3: 0 | AH3: 0 | AI3: 0 | AJ3: 0 | AK3: 0 | AL3: 0 | AM3: 0 | AN3: 0 | AO3: 0 | AP3: 0 | AQ3: 0 | AR3: 0 | AS3: 0 | AT3: 0 | AU3: 0 | AV3: 0 | AW3: 0 | AX3: 0 | AY3: 0 | AZ3: 0 | BA3: 0 | BB3: 0 | BC3: 0 | BD3: 0 | BE3: 0 | BF3: 0 | BG3: 0 | BH3: 0 | BI3: 0 | BJ3: 0 | BK3: 0 | BL3: 0
A4: pl_count | B4: 9 | C4: 9 | D4: 9 | E4: 9 | F4: 9 | G4: 9 | H4: 9 | I4: 9 | J4: 9 | K4: 9 | L4: 9 | M4: 9 | N4: 9 | O4: 9 | P4: 9 | Q4: 9 | R4: 9 | S4: 9 | T4: 9 | U4: 9 | V4: 9 | W4: 9 | X4: 9 | Y4: 9 | Z4: 9 | AA4: 8 | AB4: 8 | AC4: 8 | AD4: 8 | AE4: 8 | AF4: 8 | AG4: 8 | AH4: 8 | AI4: 7 | AJ4: 7 | AK4: 7 | AL4: 6 | AM4: 6 | AN4: 6 | AO4: 6 | AP4: 6 | AQ4: 6 | AR4: 6 | AS4: 6 | AT4: 6 | AU4: 6 | AV4: 6 | AW4: 6 | AX4: 6 | AY4: 6 | AZ4: 6 | BA4: 6 | BB4: 6 | BC4: 6 | BD4: 5 | BE4: 5 | BF4: 5 | BG4: 4 | BH4: 3 | BI4: 0 | BJ4: 0 | BK4: 0 | BL4: 0
A5: revenue_p_m | B5: 150718.92 | C5: 150718.92 | D5: 150718.92 | E5: 150718.92 | F5: 150718.92 | G5: 150718.92 | H5: 150718.92 | I5: 150718.92 | J5: 150718.92 | K5: 150718.92 | L5: 150718.92 | M5: 150718.92 | N5: 150718.92 | O5: 150718.92 | P5: 150718.92 | Q5: 150718.92 | R5: 150718.92 | S5: 150718.92 | T5: 150718.92 | U5: 150718.92 | V5: 150718.92 | W5: 150718.92 | X5: 150718.92 | Y5: 150718.92 | Z5: 150718.92 | AA5: 120063.5 | AB5: 120063.5 | AC5: 120063.5 | AD5: 120063.5 | AE5: 120063.5 | AF5: 120063.5 | AG5: 120063.5 | AH5: 120063.5 | AI5: 112818.8 | AJ5: 112818.8 | AK5: 112818.8 | AL5: 104055.85 | AM5: 104055.85 | AN5: 104055.85 | AO5: 104055.85 | AP5: 104055.85 | AQ5: 104055.85 | AR5: 104055.85 | AS5: 104055.85 | AT5: 104055.85 | AU5: 104055.85 | AV5: 104055.85 | AW5: 104055.85 | AX5: 104055.85 | AY5: 104055.85 | AZ5: 104055.85 | BA5: 104055.85 | BB5: 104055.85 | BC5: 104055.85 | BD5: 92453.67 | BE5: 92453.67 | BF5: 92453.67 | BG5: 71410.76 | BH5: 60243.86 | BI5: 0 | BJ5: 0 | BK5: 0 | BL5: 0
A6: depreciation_p_m | B6: 59074.53 | C6: 59074.53 | D6: 59074.53 | E6: 59074.53 | F6: 59074.53 | G6: 59074.53 | H6: 59074.53 | I6: 59074.53 | J6: 59074.53 | K6: 59074.53 | L6: 59074.53 | M6: 59074.53 | N6: 59074.53 | O6: 59074.53 | P6: 59074.53 | Q6: 59074.53 | R6: 59074.53 | S6: 59074.53 | T6: 59074.53 | U6: 59074.53 | V6: 59074.53 | W6: 59074.53 | X6: 59074.53 | Y6: 59074.53 | Z6: 59074.53 | AA6: 43126.61 | AB6: 43126.61 | AC6: 43126.61 | AD6: 43126.61 | AE6: 43126.61 | AF6: 43126.61 | AG6: 43126.61 | AH6: 43126.61 | AI6: 40750.68 | AJ6: 40750.68 | AK6: 40750.68 | AL6: 38339.49 | AM6: 38339.49 | AN6: 38339.49 | AO6: 38339.49 | AP6: 38339.49 | AQ6: 38339.49 | AR6: 38339.49 | AS6: 38339.49 | AT6: 38339.49 | AU6: 38339.49 | AV6: 38339.49 | AW6: 38339.49 | AX6: 38339.49 | AY6: 38339.49 | AZ6: 38339.49 | BA6: 38339.49 | BB6: 38339.49 | BC6: 38339.49 | BD6: 35055.84 | BE6: 35055.84 | BF6: 35055.84 | BG6: 28312.95 | BH6: 25259.47 | BI6: 0 | BJ6: 0 | BK6: 0 | BL6: 0
A7: interest_p_m | B7: 44741.89 | C7: 44741.89 | D7: 44741.89 | E7: 44741.89 | F7: 44741.89 | G7: 44741.89 | H7: 44741.89 | I7: 44741.89 | J7: 44741.89 | K7: 44741.89 | L7: 44741.89 | M7: 44741.89 | N7: 44741.89 | O7: 44741.89 | P7: 44741.89 | Q7: 44741.89 | R7: 44741.89 | S7: 44741.89 | T7: 44741.89 | U7: 44741.89 | V7: 44741.89 | W7: 44741.89 | X7: 44741.89 | Y7: 44741.89 | Z7: 44741.89 | AA7: 37918.49 | AB7: 37918.49 | AC7: 37918.49 | AD7: 37918.49 | AE7: 37918.49 | AF7: 37918.49 | AG7: 37918.49 | AH7: 37918.49 | AI7: 36693.94 | AJ7: 36693.94 | AK7: 36693.94 | AL7: 33856.54 | AM7: 33856.54 | AN7: 33856.54 | AO7: 33856.54 | AP7: 33856.54 | AQ7: 33856.54 | AR7: 33856.54 | AS7: 33856.54 | AT7: 33856.54 | AU7: 33856.54 | AV7: 33856.54 | AW7: 33856.54 | AX7: 33856.54 | AY7: 33856.54 | AZ7: 33856.54 | BA7: 33856.54 | BB7: 33856.54 | BC7: 33856.54 | BD7: 29975.78 | BE7: 29975.78 | BF7: 29975.78 | BG7: 21864.63 | BH7: 17952.07 | BI7: 0 | BJ7: 0 | BK7: 0 | BL7: 0
A8: admin_p_m | B8: 12132.78 | C8: 12132.78 | D8: 12132.78 | E8: 12132.78 | F8: 12132.78 | G8: 12132.78 | H8: 12132.78 | I8: 12132.78 | J8: 12132.78 | K8: 12132.78 | L8: 12132.78 | M8: 12132.78 | N8: 12132.78 | O8: 12132.78 | P8: 12132.78 | Q8: 12132.78 | R8: 12132.78 | S8: 12132.78 | T8: 12132.78 | U8: 12132.78 | V8: 12132.78 | W8: 12132.78 | X8: 12132.78 | Y8: 12132.78 | Z8: 12132.78 | AA8: 10154.79 | AB8: 10154.79 | AC8: 10154.79 | AD8: 10154.79 | AE8: 10154.79 | AF8: 10154.79 | AG8: 10154.79 | AH8: 10154.79 | AI8: 9778.7 | AJ8: 9778.7 | AK8: 9778.7 | AL8: 9107.11 | AM8: 9107.11 | AN8: 9107.11 | AO8: 9107.11 | AP8: 9107.11 | AQ8: 9107.11 | AR8: 9107.11 | AS8: 9107.11 | AT8: 9107.11 | AU8: 9107.11 | AV8: 9107.11 | AW8: 9107.11 | AX8: 9107.11 | AY8: 9107.11 | AZ8: 9107.11 | BA8: 9107.11 | BB8: 9107.11 | BC8: 9107.11 | BD8: 8122.77 | BE8: 8122.77 | BF8: 8122.77 | BG8: 6071.01 | BH8: 5091.91 | BI8: 0 | BJ8: 0 | BK8: 0 | BL8: 0
A9: maint_prov_p_m | B9: 117102.29 | C9: 117102.29 | D9: 117102.29 | E9: 117102.29 | F9: 117102.29 | G9: 117102.29 | H9: 117102.29 | I9: 117102.29 | J9: 117102.29 | K9: 117102.29 | L9: 117102.29 | M9: 117102.29 | N9: 117102.29 | O9: 117102.29 | P9: 117102.29 | Q9: 117102.29 | R9: 117102.29 | S9: 117102.29 | T9: 117102.29 | U9: 117102.29 | V9: 117102.29 | W9: 117102.29 | X9: 117102.29 | Y9: 117102.29 | Z9: 117102.29 | AA9: 43714 | AB9: 43714 | AC9: 43714 | AD9: 43714 | AE9: 43714 | AF9: 43714 | AG9: 43714 | AH9: 43714 | AI9: 24952.08 | AJ9: 24952.08 | AK9: 24952.08 | AL9: 24433.58 | AM9: 24433.58 | AN9: 24433.58 | AO9: 24433.58 | AP9: 24433.58 | AQ9: 24433.58 | AR9: 24433.58 | AS9: 24433.58 | AT9: 24433.58 | AU9: 24433.58 | AV9: 24433.58 | AW9: 24433.58 | AX9: 24433.58 | AY9: 24433.58 | AZ9: 24433.58 | BA9: 24433.58 | BB9: 24433.58 | BC9: 24433.58 | BD9: 17572.04 | BE9: 17572.04 | BF9: 17572.04 | BG9: 12856.04 | BH9: 9987 | BI9: 0 | BJ9: 0 | BK9: 0 | BL9: 0
A10: maintenance_fund | B10: 112388.55 | C10: 112388.55 | D10: 112388.55 | E10: 112388.55 | F10: 112388.55 | G10: 112388.55 | H10: 112388.55 | I10: 112388.55 | J10: 112388.55 | K10: 112388.55 | L10: 112388.55 | M10: 112388.55 | N10: 112388.55 | O10: 112388.55 | P10: 112388.55 | Q10: 112388.55 | R10: 112388.55 | S10: 112388.55 | T10: 112388.55 | U10: 112388.55 | V10: 112388.55 | W10: 112388.55 | X10: 112388.55 | Y10: 112388.55 | Z10: 112388.55 | AA10: 43714 | AB10: 43714 | AC10: 43714 | AD10: 43714 | AE10: 43714 | AF10: 43714 | AG10: 43714 | AH10: 43714 | AI10: 24952.08 | AJ10: 24952.08 | AK10: 24952.08 | AL10: 24433.58 | AM10: 24433.58 | AN10: 24433.58 | AO10: 24433.58 | AP10: 24433.58 | AQ10: 24433.58 | AR10: 24433.58 | AS10: 24433.58 | AT10: 24433.58 | AU10: 24433.58 | AV10: 24433.58 | AW10: 24433.58 | AX10: 24433.58 | AY10: 24433.58 | AZ10: 24433.58 | BA10: 24433.58 | BB10: 24433.58 | BC10: 24433.58 | BD10: 17572.04 | BE10: 17572.04 | BF10: 17572.04 | BG10: 12856.04 | BH10: 9987 | BI10: 0 | BJ10: 0 | BK10: 0 | BL10: 0
A11: other_fee_p_m | B11: 24531.85 | C11: 24531.85 | D11: 24531.85 | E11: 24531.85 | F11: 24531.85 | G11: 24531.85 | H11: 24531.85 | I11: 24531.85 | J11: 24531.85 | K11: 24531.85 | L11: 24531.85 | M11: 24531.85 | N11: 24531.85 | O11: 24531.85 | P11: 24531.85 | Q11: 24531.85 | R11: 24531.85 | S11: 24531.85 | T11: 24531.85 | U11: 24531.85 | V11: 24531.85 | W11: 24531.85 | X11: 24531.85 | Y11: 24531.85 | Z11: 24531.85 | AA11: 20967.01 | AB11: 20967.01 | AC11: 20967.01 | AD11: 20967.01 | AE11: 20967.01 | AF11: 20967.01 | AG11: 20967.01 | AH11: 20967.01 | AI11: 18871.5 | AJ11: 18871.5 | AK11: 18871.5 | AL11: 16547.23 | AM11: 16547.23 | AN11: 16547.23 | AO11: 16547.23 | AP11: 16547.23 | AQ11: 16547.23 | AR11: 16547.23 | AS11: 16547.23 | AT11: 16547.23 | AU11: 16547.23 | AV11: 16547.23 | AW11: 16547.23 | AX11: 16547.23 | AY11: 16547.23 | AZ11: 16547.23 | BA11: 16547.23 | BB11: 16547.23 | BC11: 16547.23 | BD11: 14074.02 | BE11: 14074.02 | BF11: 14074.02 | BG11: 11115.91 | BH11: 8611.41 | BI11: 0 | BJ11: 0 | BK11: 0 | BL11: 0
A12: total_cost | B12: 6047395.4 | C12: 6047395.4 | D12: 6047395.4 | E12: 6047395.4 | F12: 6047395.4 | G12: 6047395.4 | H12: 6047395.4 | I12: 6047395.4 | J12: 6047395.4 | K12: 6047395.4 | L12: 6047395.4 | M12: 6047395.4 | N12: 6047395.4 | O12: 6047395.4 | P12: 6047395.4 | Q12: 6047395.4 | R12: 6047395.4 | S12: 6047395.4 | T12: 6047395.4 | U12: 6047395.4 | V12: 6047395.4 | W12: 6047395.4 | X12: 6047395.4 | Y12: 6047395.4 | Z12: 6047395.4 | AA12: 5077411.7 | AB12: 5077411.7 | AC12: 5077411.7 | AD12: 5077411.7 | AE12: 5077411.7 | AF12: 5077411.7 | AG12: 5077411.7 | AH12: 5077411.7 | AI12: 4889364.8 | AJ12: 4889364.8 | AK12: 4889364.8 | AL12: 4553569.1 | AM12: 4553569.1 | AN12: 4553569.1 | AO12: 4553569.1 | AP12: 4553569.1 | AQ12: 4553569.1 | AR12: 4553569.1 | AS12: 4553569.1 | AT12: 4553569.1 | AU12: 4553569.1 | AV12: 4553569.1 | AW12: 4553569.1 | AX12: 4553569.1 | AY12: 4553569.1 | AZ12: 4553569.1 | BA12: 4553569.1 | BB12: 4553569.1 | BC12: 4553569.1 | BD12: 4061397.8 | BE12: 4061397.8 | BF12: 4061397.8 | BG12: 3035517.8 | BH12: 2545965.2 | BI12: 0 | BJ12: 0 | BK12: 0 | BL12: 0
A13: nbv | B13: 5736675 | C13: 5736675 | D13: 5677600.5 | E13: 5618525.9 | F13: 5559451.4 | G13: 5500376.9 | H13: 5441302.3 | I13: 5382227.8 | J13: 5323153.3 | K13: 5264078.8 | L13: 5205004.2 | M13: 5145929.7 | N13: 5086855.2 | O13: 5027780.6 | P13: 4968706.1 | Q13: 4909631.6 | R13: 4850557 | S13: 4791482.5 | T13: 4732408 | U13: 4673333.5 | V13: 4614258.9 | W13: 4555184.4 | X13: 4496109.9 | Y13: 4437035.3 | Z13: 4377960.8 | AA13: 3907124.2 | AB13: 3863997.6 | AC13: 3820871 | AD13: 3777744.4 | AE13: 3734617.7 | AF13: 3691491.1 | AG13: 3648364.5 | AH13: 3605237.9 | AI13: 3485733 | AJ13: 3444982.4 | AK13: 3404231.7 | AL13: 3112077 | AM13: 3073737.5 | AN13: 3035398 | AO13: 2997058.5 | AP13: 2958719 | AQ13: 2920379.6 | AR13: 2882040.1 | AS13: 2843700.6 | AT13: 2805361.1 | AU13: 2767021.6 | AV13: 2728682.1 | AW13: 2690342.6 | AX13: 2652003.1 | AY13: 2613663.6 | AZ13: 2575324.1 | BA13: 2536984.7 | BB13: 2498645.2 | BC13: 2460305.7 | BD13: 2123530.2 | BE13: 2088474.4 | BF13: 2053418.6 | BG13: 1390313.2 | BH13: 1055656.5 | BI13: 0 | BJ13: 0 | BK13: 0 | BL13: 0
... A16: olmm_fleet_drop | B16: 0 | C16: 0 | D16: 0 | E16: 0 | F16: 0 | G16: 0 | H16: 0 | I16: 0 | J16: 0 | K16: 0 | L16: 0 | M16: 0 | N16: 0 | O16: 0 | P16: 0 | Q16: 0 | R16: 0 | S16: 0 | T16: 0 | U16: 0 | V16: 0 | W16: 0 | X16: 0 | Y16: 0 | Z16: 0 | AA16: 0 | AB16: 0 | AC16: 0 | AD16: 0 | AE16: 0 | AF16: 0 | AG16: 0 | AH16: 0 | AI16: 0 | AJ16: 0 | AK16: 0 | AL16: 0 | AM16: 0 | AN16: 0 | AO16: 0 | AP16: 0 | AQ16: 0 | AR16: 0 | AS16: 0 | AT16: 0 | AU16: 0 | AV16: 0 | AW16: 0 | AX16: 0 | AY16: 0 | AZ16: 0 | BA16: 0 | BB16: 0 | BC16: 0 | BD16: 0 | BE16: 0 | BF16: 0 | BG16: 0 | BH16: 0 | BI16: 0 | BJ16: 0 | BK16: 0 | BL16: 0

Sheet Company Cars
A1: Value | B1: 2025/06/06 | C1: 2025/06/30 | D1: 2025/07/31 | E1: 2025/08/31 | F1: 2025/09/30 | G1: 2025/10/31 | H1: 2025/11/30 | I1: 2025/12/31 | J1: 2026/01/31 | K1: 2026/02/28 | L1: 2026/03/31 | M1: 2026/04/30 | N1: 2026/05/31 | O1: 2026/06/30 | P1: 2026/07/31 | Q1: 2026/08/31 | R1: 2026/09/30 | S1: 2026/10/31 | T1: 2026/11/30 | U1: 2026/12/31 | V1: 2027/01/31 | W1: 2027/02/28 | X1: 2027/03/31 | Y1: 2027/04/30 | Z1: 2027/05/31 | AA1: 2027/06/30 | AB1: 2027/07/31 | AC1: 2027/08/31 | AD1: 2027/09/30 | AE1: 2027/10/31 | AF1: 2027/11/30 | AG1: 2027/12/31 | AH1: 2028/01/31 | AI1: 2028/02/29 | AJ1: 2028/03/31 | AK1: 2028/04/30 | AL1: 2028/05/31 | AM1: 2028/06/30 | AN1: 2028/07/31 | AO1: 2028/08/31 | AP1: 2028/09/30 | AQ1: 2028/10/31 | AR1: 2028/11/30 | AS1: 2028/12/31 | AT1: 2029/01/31 | AU1: 2029/02/28 | AV1: 2029/03/31 | AW1: 2029/04/30 | AX1: 2029/05/31 | AY1: 2029/06/30 | AZ1: 2029/07/31 | BA1: 2029/08/31 | BB1: 2029/09/30 | BC1: 2029/10/31 | BD1: 2029/11/30 | BE1: 2029/12/31 | BF1: 2030/01/31 | BG1: 2030/02/28 | BH1: 2030/03/31 | BI1: 2030/04/30 | BJ1: 2030/05/31 | BK1: 2030/06/30 | BL1: 2030/07/31
A2: fml_count | B2: 2 | C2: 2 | D2: 2 | E2: 2 | F2: 2 | G2: 2 | H2: 2 | I2: 2 | J2: 2 | K2: 2 | L2: 1 | M2: 1 | N2: 1 | O2: 1 | P2: 1 | Q2: 1 | R2: 1 | S2: 1 | T2: 1 | U2: 1 | V2: 1 | W2: 1 | X2: 1 | Y2: 1 | Z2: 1 | AA2: 1 | AB2: 1 | AC2: 1 | AD2: 1 | AE2: 1 | AF2: 1 | AG2: 1 | AH2: 1 | AI2: 1 | AJ2: 1 | AK2: 1 | AL2: 0 | AM2: 0 | AN2: 0 | AO2: 0 | AP2: 0 | AQ2: 0 | AR2: 0 | AS2: 0 | AT2: 0 | AU2: 0 | AV2: 0 | AW2: 0 | AX2: 0 | AY2: 0 | AZ2: 0 | BA2: 0 | BB2: 0 | BC2: 0 | BD2: 0 | BE2: 0 | BF2: 0 | BG2: 0 | BH2: 0 | BI2: 0 | BJ2: 0 | BK2: 0 | BL2: 0
A3: olmm_count | B3: 0 | C3: 0 | D3: 0 | E3: 0 | F3: 0 | G3: 0 | H3: 0 | I3: 0 | J3: 0 | K3: 0 | L3: 0 | M3: 0 | N3: 0 | O3: 0 | P3: 0 | Q3: 0 | R3: 0 | S3: 0 | T3: 0 | U3: 0 | V3: 0 | W3: 0 | X3: 0 | Y3: 0 | Z3: 0 | AA3: 0 | AB3: 0 | AC3: 0 | AD3: 0 | AE3: 0 | AF3: 0 | AG3: 0 | AH3: 0 | AI3: 0 | AJ3: 0 | AK3: 0 | AL3: 0 | AM3: 0 | AN3: 0 | AO3: 0 | AP3: 0 | AQ3: 0 | AR3: 0 | AS3: 0 | AT3: 0 | AU3: 0 | AV3: 0 | AW3: 0 | AX3: 0 | AY3: 0 | AZ3: 0 | BA3: 0 | BB3: 0 | BC3: 0 | BD3: 0 | BE3: 0 | BF3: 0 | BG3: 0 | BH3: 0 | BI3: 0 | BJ3: 0 | BK3: 0 | BL3: 0
A4: pl_count | B4: 2 | C4: 2 | D4: 2 | E4: 2 | F4: 2 | G4: 2 | H4: 2 | I4: 2 | J4: 2 | K4: 2 | L4: 2 | M4: 2 | N4: 2 | O4: 2 | P4: 2 | Q4: 2 | R4: 2 | S4: 2 | T4: 2 | U4: 2 | V4: 2 | W4: 2 | X4: 2 | Y4: 2 | Z4: 2 | AA4: 2 | AB4: 2 | AC4: 2 | AD4: 2 | AE4: 2 | AF4: 2 | AG4: 2 | AH4: 2 | AI4: 1 | AJ4: 1 | AK4: 0 | AL4: 0 | AM4: 0 | AN4: 0 | AO4: 0 | AP4: 0 | AQ4: 0 | AR4: 0 | AS4: 0 | AT4: 0 | AU4: 0 | AV4: 0 | AW4: 0 | AX4: 0 | AY4: 0 | AZ4: 0 | BA4: 0 | BB4: 0 | BC4: 0 | BD4: 0 | BE4: 0 | BF4: 0 | BG4: 0 | BH4: 0 | BI4: 0 | BJ4: 0 | BK4: 0 | BL4: 0
A5: revenue_p_m | B5: 40982.51 | C5: 40982.51 | D5: 40982.51 | E5: 40982.51 | F5: 40982.51 | G5: 40982.51 | H5: 40982.51 | I5: 40982.51 | J5: 40982.51 | K5: 40982.51 | L5: 35601.17 | M5: 35601.17 | N5: 35601.17 | O5: 35601.17 | P5: 35601.17 | Q5: 35601.17 | R5: 35601.17 | S5: 35601.17 | T5: 35601.17 | U5: 35601.17 | V5: 35601.17 | W5: 35601.17 | X5: 35601.17 | Y5: 35601.17 | Z5: 35601.17 | AA5: 35601.17 | AB5: 35601.17 | AC5: 35601.17 | AD5: 35601.17 | AE5: 35601.17 | AF5: 35601.17 | AG5: 35601.17 | AH5: 35601.17 | AI5: 21234.24 | AJ5: 21234.24 | AK5: 8045.15 | AL5: 0 | AM5: 0 | AN5: 0 | AO5: 0 | AP5: 0 | AQ5: 0 | AR5: 0 | AS5: 0 | AT5: 0 | AU5: 0 | AV5: 0 | AW5: 0 | AX5: 0 | AY5: 0 | AZ5: 0 | BA5: 0 | BB5: 0 | BC5: 0 | BD5: 0 | BE5: 0 | BF5: 0 | BG5: 0 | BH5: 0 | BI5: 0 | BJ5: 0 | BK5: 0 | BL5: 0
A6: depreciation_p_m | B6: 15765.88 | C6: 15765.88 | D6: 15765.88 | E6: 15765.88 | F6: 15765.88 | G6: 15765.88 | H6: 15765.88 | I6: 15765.88 | J6: 15765.88 | K6: 15765.88 | L6: 13411.01 | M6: 13411.01 | N6: 13411.01 | O6: 13411.01 | P6: 13411.01 | Q6: 13411.01 | R6: 13411.01 | S6: 13411.01 | T6: 13411.01 | U6: 13411.01 | V6: 13411.01 | W6: 13411.01 | X6: 13411.01 | Y6: 13411.01 | Z6: 13411.01 | AA6: 13411.01 | AB6: 13411.01 | AC6: 13411.01 | AD6: 13411.01 | AE6: 13411.01 | AF6: 13411.01 | AG6: 13411.01 | AH6: 13411.01 | AI6: 7428.43 | AJ6: 7428.43 | AK6: 2938.22 | AL6: 0 | AM6: 0 | AN6: 0 | AO6: 0 | AP6: 0 | AQ6: 0 | AR6: 0 | AS6: 0 | AT6: 0 | AU6: 0 | AV6: 0 | AW6: 0 | AX6: 0 | AY6: 0 | AZ6: 0 | BA6: 0 | BB6: 0 | BC6: 0 | BD6: 0 | BE6: 0 | BF6: 0 | BG6: 0 | BH6: 0 | BI6: 0 | BJ6: 0 | BK6: 0 | BL6: 0
A7: interest_p_m | B7: 12658.26 | C7: 12658.26 | D7: 12658.26 | E7: 12658.26 | F7: 12658.26 | G7: 12658.26 | H7: 12658.26 | I7: 12658.26 | J7: 12658.26 | K7: 12658.26 | L7: 11326.85 | M7: 11326.85 | N7: 11326.85 | O7: 11326.85 | P7: 11326.85 | Q7: 11326.85 | R7: 11326.85 | S7: 11326.85 | T7: 11326.85 | U7: 11326.85 | V7: 11326.85 | W7: 11326.85 | X7: 11326.85 | Y7: 11326.85 | Z7: 11326.85 | AA7: 11326.85 | AB7: 11326.85 | AC7: 11326.85 | AD7: 11326.85 | AE7: 11326.85 | AF7: 11326.85 | AG7: 11326.85 | AH7: 11326.85 | AI7: 7236.7 | AJ7: 7236.7 | AK7: 2780.54 | AL7: 0 | AM7: 0 | AN7: 0 | AO7: 0 | AP7: 0 | AQ7: 0 | AR7: 0 | AS7: 0 | AT7: 0 | AU7: 0 | AV7: 0 | AW7: 0 | AX7: 0 | AY7: 0 | AZ7: 0 | BA7: 0 | BB7: 0 | BC7: 0 | BD7: 0 | BE7: 0 | BF7: 0 | BG7: 0 | BH7: 0 | BI7: 0 | BJ7: 0 | BK7: 0 | BL7: 0
A8: admin_p_m | B8: 2858.33 | C8: 2858.33 | D8: 2858.33 | E8: 2858.33 | F8: 2858.33 | G8: 2858.33 | H8: 2858.33 | I8: 2858.33 | J8: 2858.33 | K8: 2858.33 | L8: 2848.33 | M8: 2848.33 | N8: 2848.33 | O8: 2848.33 | P8: 2848.33 | Q8: 2848.33 | R8: 2848.33 | S8: 2848.33 | T8: 2848.33 | U8: 2848.33 | V8: 2848.33 | W8: 2848.33 | X8: 2848.33 | Y8: 2848.33 | Z8: 2848.33 | AA8: 2848.33 | AB8: 2848.33 | AC8: 2848.33 | AD8: 2848.33 | AE8: 2848.33 | AF8: 2848.33 | AG8: 2848.33 | AH8: 2848.33 | AI8: 1798.18 | AJ8: 1798.18 | AK8: 677.08 | AL8: 0 | AM8: 0 | AN8: 0 | AO8: 0 | AP8: 0 | AQ8: 0 | AR8: 0 | AS8: 0 | AT8: 0 | AU8: 0 | AV8: 0 | AW8: 0 | AX8: 0 | AY8: 0 | AZ8: 0 | BA8: 0 | BB8: 0 | BC8: 0 | BD8: 0 | BE8: 0 | BF8: 0 | BG8: 0 | BH8: 0 | BI8: 0 | BJ8: 0 | BK8: 0 | BL8: 0
A9: maint_prov_p_m | B9: 46986.3 | C9: 46986.3 | D9: 46986.3 | E9: 46986.3 | F9: 46986.3 | G9: 46986.3 | H9: 46986.3 | I9: 46986.3 | J9: 46986.3 | K9: 46986.3 | L9: 15747.3 | M9: 15747.3 | N9: 15747.3 | O9: 15747.3 | P9: 15747.3 | Q9: 15747.3 | R9: 15747.3 | S9: 15747.3 | T9: 15747.3 | U9: 15747.3 | V9: 15747.3 | W9: 15747.3 | X9: 15747.3 | Y9: 15747.3 | Z9: 15747.3 | AA9: 15747.3 | AB9: 15747.3 | AC9: 15747.3 | AD9: 15747.3 | AE9: 15747.3 | AF9: 15747.3 | AG9: 15747.3 | AH9: 15747.3 | AI9: 11107.3 | AJ9: 11107.3 | AK9: 1181.3 | AL9: 0 | AM9: 0 | AN9: 0 | AO9: 0 | AP9: 0 | AQ9: 0 | AR9: 0 | AS9: 0 | AT9: 0 | AU9: 0 | AV9: 0 | AW9: 0 | AX9: 0 | AY9: 0 | AZ9: 0 | BA9: 0 | BB9: 0 | BC9: 0 | BD9: 0 | BE9: 0 | BF9: 0 | BG9: 0 | BH9: 0 | BI9: 0 | BJ9: 0 | BK9: 0 | BL9: 0
A10: maintenance_fund | B10: 36206.34 | C10: 36206.34 | D10: 36206.34 | E10: 36206.34 | F10: 36206.34 | G10: 36206.34 | H10: 36206.34 | I10: 36206.34 | J10: 36206.34 | K10: 36206.34 | L10: 15747.3 | M10: 15747.3 | N10: 15747.3 | O10: 15747.3 | P10: 15747.3 | Q10: 15747.3 | R10: 15747.3 | S10: 15747.3 | T10: 15747.3 | U10: 15747.3 | V10: 15747.3 | W10: 15747.3 | X10: 15747.3 | Y10: 15747.3 | Z10: 15747.3 | AA10: 15747.3 | AB10: 15747.3 | AC10: 15747.3 | AD10: 15747.3 | AE10: 15747.3 | AF10: 15747.3 | AG10: 15747.3 | AH10: 15747.3 | AI10: 11107.3 | AJ10: 11107.3 | AK10: 1181.3 | AL10: 0 | AM10: 0 | AN10: 0 | AO10: 0 | AP10: 0 | AQ10: 0 | AR10: 0 | AS10: 0 | AT10: 0 | AU10: 0 | AV10: 0 | AW10: 0 | AX10: 0 | AY10: 0 | AZ10: 0 | BA10: 0 | BB10: 0 | BC10: 0 | BD10: 0 | BE10: 0 | BF10: 0 | BG10: 0 | BH10: 0 | BI10: 0 | BJ10: 0 | BK10: 0 | BL10: 0
A11: other_fee_p_m | B11: 5724.74 | C11: 5724.74 | D11: 5724.74 | E11: 5724.74 | F11: 5724.74 | G11: 5724.74 | H11: 5724.74 | I11: 5724.74 | J11: 5724.74 | K11: 5724.74 | L11: 5196.68 | M11: 5196.68 | N11: 5196.68 | O11: 5196.68 | P11: 5196.68 | Q11: 5196.68 | R11: 5196.68 | S11: 5196.68 | T11: 5196.68 | U11: 5196.68 | V11: 5196.68 | W11: 5196.68 | X11: 5196.68 | Y11: 5196.68 | Z11: 5196.68 | AA11: 5196.68 | AB11: 5196.68 | AC11: 5196.68 | AD11: 5196.68 | AE11: 5196.68 | AF11: 5196.68 | AG11: 5196.68 | AH11: 5196.68 | AI11: 2880.63 | AJ11: 2880.63 | AK11: 468.01 | AL11: 0 | AM11: 0 | AN11: 0 | AO11: 0 | AP11: 0 | AQ11: 0 | AR11: 0 | AS11: 0 | AT11: 0 | AU11: 0 | AV11: 0 | AW11: 0 | AX11: 0 | AY11: 0 | AZ11: 0 | BA11: 0 | BB11: 0 | BC11: 0 | BD11: 0 | BE11: 0 | BF11: 0 | BG11: 0 | BH11: 0 | BI11: 0 | BJ11: 0 | BK11: 0 | BL11: 0
A12: total_cost | B12: 1666609.7 | C12: 1666609.7 | D12: 1666609.7 | E12: 1666609.7 | F12: 1666609.7 | G12: 1666609.7 | H12: 1666609.7 | I12: 1666609.7 | J12: 1666609.7 | K12: 1666609.7 | L12: 1424171.8 | M12: 1424171.8 | N12: 1424171.8 | O12: 1424171.8 | P12: 1424171.8 | Q12: 1424171.8 | R12: 1424171.8 | S12: 1424171.8 | T12: 1424171.8 | U12: 1424171.8 | V12: 1424171.8 | W12: 1424171.8 | X12: 1424171.8 | Y12: 1424171.8 | Z12: 1424171.8 | AA12: 1424171.8 | AB12: 1424171.8 | AC12: 1424171.8 | AD12: 1424171.8 | AE12: 1424171.8 | AF12: 1424171.8 | AG12: 1424171.8 | AH12: 1424171.8 | AI12: 899096.18 | AJ12: 899096.18 | AK12: 338544.01 | AL12: 0 | AM12: 0 | AN12: 0 | AO12: 0 | AP12: 0 | AQ12: 0 | AR12: 0 | AS12: 0 | AT12: 0 | AU12: 0 | AV12: 0 | AW12: 0 | AX12: 0 | AY12: 0 | AZ12: 0 | BA12: 0 | BB12: 0 | BC12: 0 | BD12: 0 | BE12: 0 | BF12: 0 | BG12: 0 | BH12: 0 | BI12: 0 | BJ12: 0 | BK12: 0 | BL12: 0
A13: nbv | B13: 1523080 | C13: 1523080 | D13: 1507314.1 | E13: 1491548.2 | F13: 1475782.4 | G13: 1460016.5 | H13: 1444250.6 | I13: 1428484.7 | J13: 1412718.8 | K13: 1396952.9 | L13: 1221169.7 | M13: 1207758.7 | N13: 1194347.7 | O13: 1180936.7 | P13: 1167525.6 | Q13: 1154114.6 | R13: 1140703.6 | S13: 1127292.6 | T13: 1113881.6 | U13: 1100470.6 | V13: 1087059.6 | W13: 1073648.6 | X13: 1060237.6 | Y13: 1046826.6 | Z13: 1033415.6 | AA13: 1020004.5 | AB13: 1006593.5 | AC13: 993182.52 | AD13: 979771.51 | AE13: 966360.5 | AF13: 952949.49 | AG13: 939538.48 | AH13: 926127.47 | AI13: 603013.69 | AJ13: 595585.26 | AK13: 238644.53 | AL13: 0 | AM13: 0 | AN13: 0 | AO13: 0 | AP13: 0 | AQ13: 0 | AR13: 0 | AS13: 0 | AT13: 0 | AU13: 0 | AV13: 0 | AW13: 0 | AX13: 0 | AY13: 0 | AZ13: 0 | BA13: 0 | BB13: 0 | BC13: 0 | BD13: 0 | BE13: 0 | BF13: 0 | BG13: 0 | BH13: 0 | BI13: 0 | BJ13: 0 | BK13: 0 | BL13: 0
... A16: olmm_fleet_drop | B16: 0 | C16: 0 | D16: 0 | E16: 0 | F16: 0 | G16: 0 | H16: 0 | I16: 0 | J16: 0 | K16: 0 | L16: 0 | M16: 0 | N16: 0 | O16: 0 | P16: 0 | Q16: 0 | R16: 0 | S16: 0 | T16: 0 | U16: 0 | V16: 0 | W16: 0 | X16: 0 | Y16: 0 | Z16: 0 | AA16: 0 | AB16: 0 | AC16: 0 | AD16: 0 | AE16: 0 | AF16: 0 | AG16: 0 | AH16: 0 | AI16: 0 | AJ16: 0 | AK16: 0 | AL16: 0 | AM16: 0 | AN16: 0 | AO16: 0 | AP16: 0 | AQ16: 0 | AR16: 0 | AS16: 0 | AT16: 0 | AU16: 0 | AV16: 0 | AW16: 0 | AX16: 0 | AY16: 0 | AZ16: 0 | BA16: 0 | BB16: 0 | BC16: 0 | BD16: 0 | BE16: 0 | BF16: 0 | BG16: 0 | BH16: 0 | BI16: 0 | BJ16: 0 | BK16: 0 | BL16: 0

Sheet ZAM
A1: Value | B1: 2025/06/06 | C1: 2025/06/30 | D1: 2025/07/31 | E1: 2025/08/31 | F1: 2025/09/30 | G1: 2025/10/31 | H1: 2025/11/30 | I1: 2025/12/31 | J1: 2026/01/31 | K1: 2026/02/28 | L1: 2026/03/31 | M1: 2026/04/30 | N1: 2026/05/31 | O1: 2026/06/30 | P1: 2026/07/31 | Q1: 2026/08/31 | R1: 2026/09/30 | S1: 2026/10/31 | T1: 2026/11/30 | U1: 2026/12/31 | V1: 2027/01/31 | W1: 2027/02/28 | X1: 2027/03/31 | Y1: 2027/04/30 | Z1: 2027/05/31 | AA1: 2027/06/30 | AB1: 2027/07/31 | AC1: 2027/08/31 | AD1: 2027/09/30 | AE1: 2027/10/31 | AF1: 2027/11/30 | AG1: 2027/12/31 | AH1: 2028/01/31 | AI1: 2028/02/29 | AJ1: 2028/03/31 | AK1: 2028/04/30 | AL1: 2028/05/31 | AM1: 2028/06/30 | AN1: 2028/07/31 | AO1: 2028/08/31 | AP1: 2028/09/30 | AQ1: 2028/10/31 | AR1: 2028/11/30 | AS1: 2028/12/31 | AT1: 2029/01/31 | AU1: 2029/02/28 | AV1: 2029/03/31 | AW1: 2029/04/30 | AX1: 2029/05/31 | AY1: 2029/06/30 | AZ1: 2029/07/31 | BA1: 2029/08/31 | BB1: 2029/09/30 | BC1: 2029/10/31 | BD1: 2029/11/30 | BE1: 2029/12/31 | BF1: 2030/01/31 | BG1: 2030/02/28 | BH1: 2030/03/31 | BI1: 2030/04/30 | BJ1: 2030/05/31 | BK1: 2030/06/30 | BL1: 2030/07/31
A2: fml_count | B2: 497 | C2: 474 | D2: 469 | E2: 457 | F2: 450 | G2: 443 | H2: 420 | I2: 414 | J2: 406 | K2: 401 | L2: 389 | M2: 380 | N2: 373 | O2: 371 | P2: 358 | Q2: 352 | R2: 340 | S2: 323 | T2: 309 | U2: 286 | V2: 276 | W2: 267 | X2: 259 | Y2: 238 | Z2: 235 | AA2: 221 | AB2: 199 | AC2: 182 | AD2: 162 | AE2: 149 | AF2: 138 | AG2: 132 | AH2: 122 | AI2: 116 | AJ2: 105 | AK2: 105 | AL2: 98 | AM2: 92 | AN2: 88 | AO2: 82 | AP2: 70 | AQ2: 66 | AR2: 65 | AS2: 65 | AT2: 63 | AU2: 58 | AV2: 43 | AW2: 30 | AX2: 27 | AY2: 23 | AZ2: 23 | BA2: 22 | BB2: 14 | BC2: 12 | BD2: 7 | BE2: 7 | BF2: 7 | BG2: 7 | BH2: 2 | BI2: 1 | BJ2: 0 | BK2: 0 | BL2: 0
A3: olmm_count | B3: 25 | C3: 25 | D3: 25 | E3: 25 | F3: 25 | G3: 25 | H3: 25 | I3: 25 | J3: 25 | K3: 25 | L3: 25 | M3: 25 | N3: 25 | O3: 25 | P3: 25 | Q3: 25 | R3: 25 | S3: 25 | T3: 25 | U3: 25 | V3: 25 | W3: 25 | X3: 25 | Y3: 25 | Z3: 25 | AA3: 25 | AB3: 25 | AC3: 25 | AD3: 25 | AE3: 25 | AF3: 25 | AG3: 25 | AH3: 25 | AI3: 25 | AJ3: 10 | AK3: 10 | AL3: 10 | AM3: 10 | AN3: 10 | AO3: 10 | AP3: 10 | AQ3: 10 | AR3: 0 | AS3: 0 | AT3: 0 | AU3: 0 | AV3: 0 | AW3: 0 | AX3: 0 | AY3: 0 | AZ3: 0 | BA3: 0 | BB3: 0 | BC3: 0 | BD3: 0 | BE3: 0 | BF3: 0 | BG3: 0 | BH3: 0 | BI3: 0 | BJ3: 0 | BK3: 0 | BL3: 0
A4: pl_count | B4: 0 | C4: 0 | D4: 0 | E4: 0 | F4: 0 | G4: 0 | H4: 0 | I4: 0 | J4: 0 | K4: 0 | L4: 0 | M4: 0 | N4: 0 | O4: 0 | P4: 0 | Q4: 0 | R4: 0 | S4: 0 | T4: 0 | U4: 0 | V4: 0 | W4: 0 | X4: 0 | Y4: 0 | Z4: 0 | AA4: 0 | AB4: 0 | AC4: 0 | AD4: 0 | AE4: 0 | AF4: 0 | AG4: 0 | AH4: 0 | AI4: 0 | AJ4: 0 | AK4: 0 | AL4: 0 | AM4: 0 | AN4: 0 | AO4: 0 | AP4: 0 | AQ4: 0 | AR4: 0 | AS4: 0 | AT4: 0 | AU4: 0 | AV4: 0 | AW4: 0 | AX4: 0 | AY4: 0 | AZ4: 0 | BA4: 0 | BB4: 0 | BC4: 0 | BD4: 0 | BE4: 0 | BF4: 0 | BG4: 0 | BH4: 0 | BI4: 0 | BJ4: 0 | BK4: 0 | BL4: 0
A5: revenue_p_m | B5: 826725.84 | C5: 797227.84 | D5: 790499.5 | E5: 774966.1 | F5: 763201.58 | G5: 753434.26 | H5: 724341.88 | I5: 714894.32 | J5: 701547.45 | K5: 694980.74 | L5: 669822.24 | M5: 657284.11 | N5: 645943.8 | O5: 640184.79 | P5: 617482.88 | Q5: 604730.59 | R5: 585363.73 | S5: 559167.08 | T5: 540182.64 | U5: 499993.56 | V5: 478903.43 | W5: 463120.97 | X5: 451377.66 | Y5: 418835.34 | Z5: 411754.92 | AA5: 389022.77 | AB5: 352119.48 | AC5: 321428.53 | AD5: 282149.88 | AE5: 263241.4 | AF5: 244267.04 | AG5: 231514.47 | AH5: 212502.97 | AI5: 203435 | AJ5: 166368.48 | AK5: 166368.48 | AL5: 155712.65 | AM5: 146143.17 | AN5: 140660.27 | AO5: 132966.23 | AP5: 118165.81 | AQ5: 112418.8 | AR5: 101849.63 | AS5: 101849.63 | AT5: 99238.53 | AU5: 91934 | AV5: 66822.25 | AW5: 44600.05 | AX5: 39712.62 | AY5: 34406.13 | AZ5: 34406.13 | BA5: 33132.41 | BB5: 19950.81 | BC5: 17093.5 | BD5: 9150.53 | BE5: 9150.53 | BF5: 9150.53 | BG5: 9150.53 | BH5: 4156.53 | BI5: 2380.13 | BJ5: 0 | BK5: 0 | BL5: 0
A6: depreciation_p_m | B6: 376056.57 | C6: 362678.52 | D6: 359793.8 | E6: 353097.54 | F6: 348360.87 | G6: 343929.25 | H6: 332228.2 | I6: 328329.34 | J6: 321501.48 | K6: 318688.18 | L6: 305147.33 | M6: 299587 | N6: 293854.32 | O6: 290753.43 | P6: 279437.41 | Q6: 273029.11 | R6: 264318.56 | S6: 252332.95 | T6: 244492.65 | U6: 226293.8 | V6: 215804.98 | W6: 208643.26 | X6: 203518.01 | Y6: 186911.59 | Z6: 183398.67 | AA6: 173210.92 | AB6: 156282.22 | AC6: 141609.39 | AD6: 122921.54 | AE6: 115092.5 | AF6: 106754.07 | AG6: 100862.15 | AH6: 91995.77 | AI6: 88117.42 | AJ6: 67776.71 | AK6: 67776.71 | AL6: 62907.69 | AM6: 58793.44 | AN6: 56434.38 | AO6: 53448.36 | AP6: 47753.62 | AQ6: 45478.99 | AR6: 40354.47 | AS6: 40354.47 | AT6: 39311.15 | AU6: 36071 | AV6: 26033.69 | AW6: 17289.98 | AX6: 15025.83 | AY6: 13075.11 | AZ6: 13075.11 | BA6: 12545.23 | BB6: 7476.04 | BC6: 6381.3 | BD6: 3316.25 | BE6: 3316.25 | BF6: 3316.25 | BG6: 3316.25 | BH6: 1595.3 | BI6: 914.25 | BJ6: 0 | BK6: 0 | BL6: 0
A7: interest_p_m | B7: 128903.23 | C7: 124860.76 | D7: 123868.91 | E7: 121810.17 | F7: 120162.3 | G7: 118698.6 | H7: 115587.11 | I7: 114339.67 | J7: 112641.24 | K7: 111680.23 | L7: 108423.95 | M7: 106819.36 | N7: 105286.72 | O7: 104608.71 | P7: 101490.01 | Q7: 99724.28 | R7: 97066.14 | S7: 92862.81 | T7: 89413.12 | U7: 82690.09 | V7: 79545.45 | W7: 76963.39 | X7: 75057.54 | Y7: 69635.9 | Z7: 68618.03 | AA7: 64913.56 | AB7: 59377.25 | AC7: 54701.99 | AD7: 48473.57 | AE7: 45148.99 | AF7: 42055.34 | AG7: 39709.74 | AH7: 37358.2 | AI7: 35910.09 | AJ7: 28792.36 | AK7: 28792.36 | AL7: 27065.78 | AM7: 25547.66 | AN7: 24554.5 | AO7: 23301.3 | AP7: 20760.36 | AQ7: 19801.69 | AR7: 17359.39 | AS7: 17359.39 | AT7: 16975.3 | AU7: 15831 | AV7: 11385.58 | AW7: 7757.28 | AX7: 7056.21 | AY7: 6209.26 | AZ7: 6209.26 | BA7: 5965.26 | BB7: 3595.71 | BC7: 3077.29 | BD7: 1589 | BE7: 1589 | BF7: 1589 | BG7: 1589 | BH7: 811.45 | BI7: 473.3 | BJ7: 0 | BK7: 0 | BL7: 0
A8: admin_p_m | B8: 72508.78 | C8: 69648.38 | D8: 69003 | E8: 67373 | F8: 66148.3 | G8: 65446.62 | H8: 62230.47 | I8: 61321.29 | J8: 60168.1 | K8: 59547.95 | L8: 57901.88 | M8: 56712.61 | N8: 55913.14 | O8: 55562.63 | P8: 53715.69 | Q8: 52782.87 | R8: 51181.71 | S8: 49166.34 | T8: 47450.67 | U8: 44083.98 | V8: 42540.05 | W8: 41453.47 | X8: 40422.35 | Y8: 37883.06 | Z8: 37365.79 | AA8: 35548.85 | AB8: 32452.07 | AC8: 30051.23 | AD8: 27087.28 | AE8: 25391.11 | AF8: 23882.05 | AG8: 22840.44 | AH8: 21364.74 | AI8: 20697.18 | AJ8: 16503.05 | AK8: 16503.05 | AL8: 15803.05 | AM8: 15031.19 | AN8: 14519.18 | AO8: 13808.39 | AP8: 12088.32 | AQ8: 11563.89 | AR8: 9441.27 | AS8: 9441.27 | AT8: 9188.21 | AU8: 8539.63 | AV8: 6179.31 | AW8: 4091.52 | AX8: 3659 | AY8: 3163.48 | AZ8: 3163.48 | BA8: 3043.48 | BB8: 1889.9 | BC8: 1649.9 | BD8: 820.62 | BE8: 820.62 | BF8: 820.62 | BG8: 820.62 | BH8: 411.52 | BI8: 238.78 | BJ8: 0 | BK8: 0 | BL8: 0
A9: maint_prov_p_m | B9: 2682176.3 | C9: 2499045.1 | D9: 2452907.6 | E9: 2346587.2 | F9: 2266934.2 | G9: 2198234.1 | H9: 2021165.7 | I9: 1959887.1 | J9: 1899407.2 | K9: 1860688.8 | L9: 1780946 | M9: 1725091.3 | N9: 1685042.1 | O9: 1667084.3 | P9: 1571057.5 | Q9: 1525825.2 | R9: 1440760.7 | S9: 1343612.3 | T9: 1263981.2 | U9: 1100380.2 | V9: 1029964.4 | W9: 976584.31 | X9: 925589.07 | Y9: 813189.92 | Z9: 797603.4 | AA9: 734993.89 | AB9: 630731.52 | AC9: 565266.12 | AD9: 487794.75 | AE9: 432236.41 | AF9: 398852.44 | AG9: 378893.29 | AH9: 348856.89 | AI9: 331227.23 | AJ9: 305212.59 | AK9: 305212.59 | AL9: 303573.04 | AM9: 288573.43 | AN9: 280241.59 | AO9: 253817.47 | AP9: 196518 | AQ9: 180733.35 | AR9: 179003.79 | AS9: 179003.79 | AT9: 175127.19 | AU9: 163831.23 | AV9: 122893.35 | AW9: 70577.24 | AX9: 66854.7 | AY9: 51453.81 | AZ9: 51453.81 | BA9: 48584.94 | BB9: 23598.09 | BC9: 17832.54 | BD9: 5240.03 | BE9: 5240.03 | BF9: 5240.03 | BG9: 5240.03 | BH9: 1280.33 | BI9: 359.84 | BJ9: 0 | BK9: 0 | BL9: 0
A10: maintenance_fund | B10: 1763348 | C10: 1669771.5 | D10: 1647399.9 | E10: 1586869.4 | F10: 1542379.7 | G10: 1500382.9 | H10: 1420419.5 | I10: 1395333.7 | J10: 1358950 | K10: 1336479.6 | L10: 1289995.9 | M10: 1258814.8 | N10: 1237657.6 | O10: 1229682.3 | P10: 1172576.7 | Q10: 1146458.2 | R10: 1089343.1 | S10: 1032939.7 | T10: 980964.04 | U10: 868988.42 | V10: 826803.55 | W10: 786047.73 | X10: 756521.4 | Y10: 676193.07 | Z10: 663433.11 | AA10: 612953.72 | AB10: 530005.83 | AC10: 473356.5 | AD10: 411808.43 | AE10: 372314.1 | AF10: 342963.59 | AG10: 323861.48 | AH10: 298451.51 | AI10: 283520.9 | AJ10: 262001.43 | AK10: 262001.43 | AL10: 260361.88 | AM10: 247876.2 | AN10: 240189.29 | AO10: 216629.72 | AP10: 167645.3 | AQ10: 152874.22 | AR10: 151277.59 | AS10: 151277.59 | AT10: 147615.27 | AU10: 138994.94 | AV10: 107331.89 | AW10: 63672.69 | AX10: 61275.69 | AY10: 46688.39 | AZ10: 46688.39 | BA10: 44013.87 | BB10: 20525.99 | BC10: 14837.49 | BD10: 3097.75 | BE10: 3097.75 | BF10: 3097.75 | BG10: 3097.75 | BH10: 1280.33 | BI10: 359.84 | BJ10: 0 | BK10: 0 | BL10: 0
A11: other_fee_p_m | B11: 118230.21 | C11: 113365.03 | D11: 112103.47 | E11: 109574.35 | F11: 107096.98 | G11: 105757.41 | H11: 100575.97 | I11: 99203.71 | J11: 97354 | K11: 96410.66 | L11: 92958.44 | M11: 90723.78 | N11: 89010.27 | O11: 88506.4 | P11: 85789.44 | Q11: 84027.4 | R11: 81274.24 | S11: 77272.04 | T11: 74297.31 | U11: 68990.81 | V11: 66463.79 | W11: 64073.92 | X11: 62284.27 | Y11: 58024.62 | Z11: 57006.78 | AA11: 53397.9 | AB11: 48352.86 | AC11: 44140.08 | AD11: 38612.2 | AE11: 35667.22 | AF11: 32708.32 | AG11: 30752.63 | AH11: 29346.31 | AI11: 27969.37 | AJ11: 25269.14 | AK11: 25269.14 | AL11: 23548.46 | AM11: 22159.72 | AN11: 21298.49 | AO11: 20071.55 | AP11: 17687.35 | AQ11: 16836.67 | AR11: 16204.02 | AS11: 16204.02 | AT11: 15826.4 | AU11: 14688 | AV11: 10601.85 | AW11: 7002.28 | AX11: 6255.92 | AY11: 5424.59 | AZ11: 5424.59 | BA11: 5200.59 | BB11: 3156.62 | BC11: 2673.3 | BD11: 1438.09 | BE11: 1438.09 | BF11: 1438.09 | BG11: 1438.09 | BH11: 671.59 | BI11: 393.96 | BJ11: 0 | BK11: 0 | BL11: 0
A12: total_cost | B12: 24107894 | C12: 23295261 | D12: 23100431 | E12: 22656512 | F12: 22241693 | G12: 21957976 | H12: 21041367 | I12: 20776003 | J12: 20396760 | K12: 20187607 | L12: 19517426 | M12: 19144569 | N12: 18855380 | O12: 18740699 | P12: 18136930 | Q12: 17813248 | R12: 17325060 | S12: 16580116 | T12: 16029049 | U12: 14903680 | V12: 14355792 | W12: 13887305 | X12: 13539590 | Y12: 12457859 | Z12: 12272173 | AA12: 11585165 | AB12: 10582361 | AC12: 9752157.6 | AD12: 8606658.4 | AE12: 8042326.2 | AF12: 7481572.4 | AG12: 7090727.7 | AH12: 6646900.6 | AI12: 6387269.3 | AJ12: 5193046.4 | AK12: 5193046.4 | AL12: 4869244.6 | AM12: 4596493.8 | AN12: 4419837.9 | AO12: 4191512.8 | AP12: 3723837.2 | AQ12: 3550244.3 | AR12: 3236258.2 | AS12: 3236258.2 | AT12: 3164005.8 | AU12: 2942831.3 | AV12: 2119812.2 | AW12: 1434977.9 | AX12: 1296539.3 | AY12: 1137118.8 | AZ12: 1137118.8 | BA12: 1092024.6 | BB12: 656731.34 | BC12: 561893.89 | BD12: 289642.25 | BE12: 289642.25 | BF12: 289642.25 | BG12: 289642.25 | BH12: 145245.7 | BI12: 84277.59 | BJ12: 0 | BK12: 0 | BL12: 0
A13: nbv | B13: 16737871 | C13: 16424469 | D13: 15985768 | E13: 15472848 | F13: 14991066 | G13: 14531130 | H13: 13888401 | I13: 13466638 | J13: 13018763 | K13: 12620855 | L13: 12056661 | M13: 11625631 | N13: 11214389 | O13: 10888579 | P13: 10364667 | Q13: 9978359.7 | R13: 9537988.4 | S13: 8991375.9 | T13: 8527464.6 | U13: 7881516 | V13: 7484418.1 | W13: 7094606.9 | X13: 6766425.4 | Y13: 6255943.2 | Z13: 6016058.5 | AA13: 5559007.3 | AB13: 5047696.2 | AC13: 4623424.9 | AD13: 4089981.2 | AE13: 3751551.5 | AF13: 3403598.5 | AG13: 3159150.9 | AH13: 2933856.6 | AI13: 2740034.4 | AJ13: 2355230.3 | AK13: 2287453.6 | AL13: 2066290.8 | AM13: 1909399.6 | AN13: 1784826 | AO13: 1654372.3 | AP13: 1459869.9 | AQ13: 1353576.4 | AR13: 1234022 | AS13: 1193667.5 | AT13: 1131498.3 | AU13: 1039411.5 | AV13: 741502.02 | AW13: 528725.46 | AX13: 485262.49 | AY13: 426080.54 | AZ13: 413005.43 | BA13: 386235.2 | BB13: 239195.63 | BC13: 202553.94 | BD13: 109077 | BE13: 105760.75 | BF13: 102444.5 | BG13: 99128.25 | BH13: 52951.5 | BI13: 31251.09 | BJ13: 0 | BK13: 0 | BL13: 0
... A16: olmm_fleet_drop | B16: 0 | C16: 0 | D16: 0 | E16: 0 | F16: 0 | G16: 0 | H16: 0 | I16: 0 | J16: 0 | K16: 0 | L16: 0 | M16: 0 | N16: 0 | O16: 0 | P16: 0 | Q16: 0 | R16: 0 | S16: 0 | T16: 0 | U16: 0 | V16: 0 | W16: 0 | X16: 0 | Y16: 0 | Z16: 0 | AA16: 0 | AB16: 0 | AC16: 0 | AD16: 0 | AE16: 0 | AF16: 0 | AG16: 0 | AH16: 0 | AI16: 0 | AJ16: 15 | AK16: 0 | AL16: 0 | AM16: 0 | AN16: 0 | AO16: 0 | AP16: 0 | AQ16: 0 | AR16: 10 | AS16: 0 | AT16: 0 | AU16: 0 | AV16: 0 | AW16: 0 | AX16: 0 | AY16: 0 | AZ16: 0 | BA16: 0 | BB16: 0 | BC16: 0 | BD16: 0 | BE16: 0 | BF16: 0 | BG16: 0 | BH16: 0 | BI16: 0 | BJ16: 0 | BK16: 0 | BL16: 0

Sheet ZMK
A1: Value | B1: 2025/06/06 | C1: 2025/06/30 | D1: 2025/07/31 | E1: 2025/08/31 | F1: 2025/09/30 | G1: 2025/10/31 | H1: 2025/11/30 | I1: 2025/12/31 | J1: 2026/01/31 | K1: 2026/02/28 | L1: 2026/03/31 | M1: 2026/04/30 | N1: 2026/05/31 | O1: 2026/06/30 | P1: 2026/07/31 | Q1: 2026/08/31 | R1: 2026/09/30 | S1: 2026/10/31 | T1: 2026/11/30 | U1: 2026/12/31 | V1: 2027/01/31 | W1: 2027/02/28 | X1: 2027/03/31 | Y1: 2027/04/30 | Z1: 2027/05/31 | AA1: 2027/06/30 | AB1: 2027/07/31 | AC1: 2027/08/31 | AD1: 2027/09/30 | AE1: 2027/10/31 | AF1: 2027/11/30 | AG1: 2027/12/31 | AH1: 2028/01/31 | AI1: 2028/02/29 | AJ1: 2028/03/31 | AK1: 2028/04/30 | AL1: 2028/05/31 | AM1: 2028/06/30 | AN1: 2028/07/31 | AO1: 2028/08/31 | AP1: 2028/09/30 | AQ1: 2028/10/31 | AR1: 2028/11/30 | AS1: 2028/12/31 | AT1: 2029/01/31 | AU1: 2029/02/28 | AV1: 2029/03/31 | AW1: 2029/04/30 | AX1: 2029/05/31 | AY1: 2029/06/30 | AZ1: 2029/07/31 | BA1: 2029/08/31 | BB1: 2029/09/30 | BC1: 2029/10/31 | BD1: 2029/11/30 | BE1: 2029/12/31 | BF1: 2030/01/31 | BG1: 2030/02/28 | BH1: 2030/03/31 | BI1: 2030/04/30 | BJ1: 2030/05/31 | BK1: 2030/06/30 | BL1: 2030/07/31
A2: fml_count | B2: 31 | C2: 31 | D2: 31 | E2: 31 | F2: 31 | G2: 31 | H2: 31 | I2: 31 | J2: 31 | K2: 31 | L2: 31 | M2: 31 | N2: 31 | O2: 31 | P2: 31 | Q2: 31 | R2: 31 | S2: 31 | T2: 31 | U2: 31 | V2: 31 | W2: 31 | X2: 31 | Y2: 31 | Z2: 31 | AA2: 31 | AB2: 31 | AC2: 31 | AD2: 31 | AE2: 31 | AF2: 31 | AG2: 31 | AH2: 31 | AI2: 31 | AJ2: 31 | AK2: 31 | AL2: 31 | AM2: 31 | AN2: 31 | AO2: 31 | AP2: 31 | AQ2: 31 | AR2: 31 | AS2: 31 | AT2: 31 | AU2: 31 | AV2: 31 | AW2: 31 | AX2: 31 | AY2: 31 | AZ2: 31 | BA2: 17 | BB2: 15 | BC2: 14 | BD2: 14 | BE2: 14 | BF2: 0 | BG2: 0 | BH2: 0 | BI2: 0 | BJ2: 0 | BK2: 0 | BL2: 0
A3: olmm_count | B3: 0 | C3: 0 | D3: 0 | E3: 0 | F3: 0 | G3: 0 | H3: 0 | I3: 0 | J3: 0 | K3: 0 | L3: 0 | M3: 0 | N3: 0 | O3: 0 | P3: 0 | Q3: 0 | R3: 0 | S3: 0 | T3: 0 | U3: 0 | V3: 0 | W3: 0 | X3: 0 | Y3: 0 | Z3: 0 | AA3: 0 | AB3: 0 | AC3: 0 | AD3: 0 | AE3: 0 | AF3: 0 | AG3: 0 | AH3: 0 | AI3: 0 | AJ3: 0 | AK3: 0 | AL3: 0 | AM3: 0 | AN3: 0 | AO3: 0 | AP3: 0 | AQ3: 0 | AR3: 0 | AS3: 0 | AT3: 0 | AU3: 0 | AV3: 0 | AW3: 0 | AX3: 0 | AY3: 0 | AZ3: 0 | BA3: 0 | BB3: 0 | BC3: 0 | BD3: 0 | BE3: 0 | BF3: 0 | BG3: 0 | BH3: 0 | BI3: 0 | BJ3: 0 | BK3: 0 | BL3: 0
A4: pl_count | B4: 0 | C4: 0 | D4: 0 | E4: 0 | F4: 0 | G4: 0 | H4: 0 | I4: 0 | J4: 0 | K4: 0 | L4: 0 | M4: 0 | N4: 0 | O4: 0 | P4: 0 | Q4: 0 | R4: 0 | S4: 0 | T4: 0 | U4: 0 | V4: 0 | W4: 0 | X4: 0 | Y4: 0 | Z4: 0 | AA4: 0 | AB4: 0 | AC4: 0 | AD4: 0 | AE4: 0 | AF4: 0 | AG4: 0 | AH4: 0 | AI4: 0 | AJ4: 0 | AK4: 0 | AL4: 0 | AM4: 0 | AN4: 0 | AO4: 0 | AP4: 0 | AQ4: 0 | AR4: 0 | AS4: 0 | AT4: 0 | AU4: 0 | AV4: 0 | AW4: 0 | AX4: 0 | AY4: 0 | AZ4: 0 | BA4: 0 | BB4: 0 | BC4: 0 | BD4: 0 | BE4: 0 | BF4: 0 | BG4: 0 | BH4: 0 | BI4: 0 | BJ4: 0 | BK4: 0 | BL4: 0
A5: revenue_p_m | B5: 759925.93 | C5: 759925.93 | D5: 759925.93 | E5: 759925.93 | F5: 759925.93 | G5: 759925.93 | H5: 759925.93 | I5: 759925.93 | J5: 759925.93 | K5: 759925.93 | L5: 759925.93 | M5: 759925.93 | N5: 759925.93 | O5: 759925.93 | P5: 759925.93 | Q5: 759925.93 | R5: 759925.93 | S5: 759925.93 | T5: 759925.93 | U5: 759925.93 | V5: 759925.93 | W5: 759925.93 | X5: 759925.93 | Y5: 759925.93 | Z5: 759925.93 | AA5: 759925.93 | AB5: 759925.93 | AC5: 759925.93 | AD5: 759925.93 | AE5: 759925.93 | AF5: 759925.93 | AG5: 759925.93 | AH5: 759925.93 | AI5: 759925.93 | AJ5: 759925.93 | AK5: 759925.93 | AL5: 759925.93 | AM5: 759925.93 | AN5: 759925.93 | AO5: 759925.93 | AP5: 759925.93 | AQ5: 759925.93 | AR5: 759925.93 | AS5: 759925.93 | AT5: 759925.93 | AU5: 759925.93 | AV5: 759925.93 | AW5: 759925.93 | AX5: 759925.93 | AY5: 759925.93 | AZ5: 759925.93 | BA5: 404290.1 | BB5: 348334.1 | BC5: 307968.22 | BD5: 307968.22 | BE5: 307968.22 | BF5: 0 | BG5: 0 | BH5: 0 | BI5: 0 | BJ5: 0 | BK5: 0 | BL5: 0
A6: depreciation_p_m | B6: 254132.16 | C6: 254132.16 | D6: 254132.16 | E6: 254132.16 | F6: 254132.16 | G6: 254132.16 | H6: 254132.16 | I6: 254132.16 | J6: 254132.16 | K6: 254132.16 | L6: 254132.16 | M6: 254132.16 | N6: 254132.16 | O6: 254132.16 | P6: 254132.16 | Q6: 254132.16 | R6: 254132.16 | S6: 254132.16 | T6: 254132.16 | U6: 254132.16 | V6: 254132.16 | W6: 254132.16 | X6: 254132.16 | Y6: 254132.16 | Z6: 254132.16 | AA6: 254132.16 | AB6: 254132.16 | AC6: 254132.16 | AD6: 254132.16 | AE6: 254132.16 | AF6: 254132.16 | AG6: 254132.16 | AH6: 254132.16 | AI6: 254132.16 | AJ6: 254132.16 | AK6: 254132.16 | AL6: 254132.16 | AM6: 254132.16 | AN6: 254132.16 | AO6: 254132.16 | AP6: 254132.16 | AQ6: 254132.16 | AR6: 254132.16 | AS6: 254132.16 | AT6: 254132.16 | AU6: 254132.16 | AV6: 254132.16 | AW6: 254132.16 | AX6: 254132.16 | AY6: 254132.16 | AZ6: 254132.16 | BA6: 143279.69 | BB6: 125748.17 | BC6: 111752.48 | BD6: 111752.48 | BE6: 111752.48 | BF6: 0 | BG6: 0 | BH6: 0 | BI6: 0 | BJ6: 0 | BK6: 0 | BL6: 0
A7: interest_p_m | B7: 219737.56 | C7: 219737.56 | D7: 219737.56 | E7: 219737.56 | F7: 219737.56 | G7: 219737.56 | H7: 219737.56 | I7: 219737.56 | J7: 219737.56 | K7: 219737.56 | L7: 219737.56 | M7: 219737.56 | N7: 219737.56 | O7: 219737.56 | P7: 219737.56 | Q7: 219737.56 | R7: 219737.56 | S7: 219737.56 | T7: 219737.56 | U7: 219737.56 | V7: 219737.56 | W7: 219737.56 | X7: 219737.56 | Y7: 219737.56 | Z7: 219737.56 | AA7: 219737.56 | AB7: 219737.56 | AC7: 219737.56 | AD7: 219737.56 | AE7: 219737.56 | AF7: 219737.56 | AG7: 219737.56 | AH7: 219737.56 | AI7: 219737.56 | AJ7: 219737.56 | AK7: 219737.56 | AL7: 219737.56 | AM7: 219737.56 | AN7: 219737.56 | AO7: 219737.56 | AP7: 219737.56 | AQ7: 219737.56 | AR7: 219737.56 | AS7: 219737.56 | AT7: 219737.56 | AU7: 219737.56 | AV7: 219737.56 | AW7: 219737.56 | AX7: 219737.56 | AY7: 219737.56 | AZ7: 219737.56 | BA7: 102500.81 | BB7: 84366.61 | BC7: 71852.76 | BD7: 71852.76 | BE7: 71852.76 | BF7: 0 | BG7: 0 | BH7: 0 | BI7: 0 | BJ7: 0 | BK7: 0 | BL7: 0
A8: admin_p_m | B8: 64448.05 | C8: 64448.05 | D8: 64448.05 | E8: 64448.05 | F8: 64448.05 | G8: 64448.05 | H8: 64448.05 | I8: 64448.05 | J8: 64448.05 | K8: 64448.05 | L8: 64448.05 | M8: 64448.05 | N8: 64448.05 | O8: 64448.05 | P8: 64448.05 | Q8: 64448.05 | R8: 64448.05 | S8: 64448.05 | T8: 64448.05 | U8: 64448.05 | V8: 64448.05 | W8: 64448.05 | X8: 64448.05 | Y8: 64448.05 | Z8: 64448.05 | AA8: 64448.05 | AB8: 64448.05 | AC8: 64448.05 | AD8: 64448.05 | AE8: 64448.05 | AF8: 64448.05 | AG8: 64448.05 | AH8: 64448.05 | AI8: 64448.05 | AJ8: 64448.05 | AK8: 64448.05 | AL8: 64448.05 | AM8: 64448.05 | AN8: 64448.05 | AO8: 64448.05 | AP8: 64448.05 | AQ8: 64448.05 | AR8: 64448.05 | AS8: 64448.05 | AT8: 64448.05 | AU8: 64448.05 | AV8: 64448.05 | AW8: 64448.05 | AX8: 64448.05 | AY8: 64448.05 | AZ8: 64448.05 | BA8: 30503.55 | BB8: 25111.19 | BC8: 21642.6 | BD8: 21642.6 | BE8: 21642.6 | BF8: 0 | BG8: 0 | BH8: 0 | BI8: 0 | BJ8: 0 | BK8: 0 | BL8: 0
A9: maint_prov_p_m | B9: 1088606.5 | C9: 1088606.5 | D9: 1088606.5 | E9: 1088606.5 | F9: 1088606.5 | G9: 1088606.5 | H9: 1088606.5 | I9: 1088606.5 | J9: 1088606.5 | K9: 1088606.5 | L9: 1088606.5 | M9: 1088606.5 | N9: 1088606.5 | O9: 1088606.5 | P9: 1088606.5 | Q9: 1088606.5 | R9: 1088606.5 | S9: 1088606.5 | T9: 1088606.5 | U9: 1088606.5 | V9: 1088606.5 | W9: 1088606.5 | X9: 1088606.5 | Y9: 1088606.5 | Z9: 1088606.5 | AA9: 1088606.5 | AB9: 1088606.5 | AC9: 1088606.5 | AD9: 1088606.5 | AE9: 1088606.5 | AF9: 1088606.5 | AG9: 1088606.5 | AH9: 1088606.5 | AI9: 1088606.5 | AJ9: 1088606.5 | AK9: 1088606.5 | AL9: 1088606.5 | AM9: 1088606.5 | AN9: 1088606.5 | AO9: 1088606.5 | AP9: 1088606.5 | AQ9: 1088606.5 | AR9: 1088606.5 | AS9: 1088606.5 | AT9: 1088606.5 | AU9: 1088606.5 | AV9: 1088606.5 | AW9: 1088606.5 | AX9: 1088606.5 | AY9: 1088606.5 | AZ9: 1088606.5 | BA9: 474366.18 | BB9: 370905.18 | BC9: 328849.5 | BD9: 328849.5 | BE9: 328849.5 | BF9: 0 | BG9: 0 | BH9: 0 | BI9: 0 | BJ9: 0 | BK9: 0 | BL9: 0
A10: maintenance_fund | B10: 937222.51 | C10: 937222.51 | D10: 937222.51 | E10: 937222.51 | F10: 937222.51 | G10: 937222.51 | H10: 937222.51 | I10: 937222.51 | J10: 937222.51 | K10: 937222.51 | L10: 937222.51 | M10: 937222.51 | N10: 937222.51 | O10: 937222.51 | P10: 937222.51 | Q10: 937222.51 | R10: 937222.51 | S10: 937222.51 | T10: 937222.51 | U10: 937222.51 | V10: 937222.51 | W10: 937222.51 | X10: 937222.51 | Y10: 937222.51 | Z10: 937222.51 | AA10: 937222.51 | AB10: 937222.51 | AC10: 937222.51 | AD10: 937222.51 | AE10: 937222.51 | AF10: 937222.51 | AG10: 937222.51 | AH10: 937222.51 | AI10: 937222.51 | AJ10: 937222.51 | AK10: 937222.51 | AL10: 937222.51 | AM10: 937222.51 | AN10: 937222.51 | AO10: 937222.51 | AP10: 937222.51 | AQ10: 937222.51 | AR10: 937222.51 | AS10: 937222.51 | AT10: 937222.51 | AU10: 937222.51 | AV10: 937222.51 | AW10: 937222.51 | AX10: 937222.51 | AY10: 937222.51 | AZ10: 937222.51 | BA10: 441873.32 | BB10: 353369.01 | BC10: 312388.69 | BD10: 312388.69 | BE10: 312388.69 | BF10: 0 | BG10: 0 | BH10: 0 | BI10: 0 | BJ10: 0 | BK10: 0 | BL10: 0
A11: other_fee_p_m | B11: 78811.17 | C11: 78811.17 | D11: 78811.17 | E11: 78811.17 | F11: 78811.17 | G11: 78811.17 | H11: 78811.17 | I11: 78811.17 | J11: 78811.17 | K11: 78811.17 | L11: 78811.17 | M11: 78811.17 | N11: 78811.17 | O11: 78811.17 | P11: 78811.17 | Q11: 78811.17 | R11: 78811.17 | S11: 78811.17 | T11: 78811.17 | U11: 78811.17 | V11: 78811.17 | W11: 78811.17 | X11: 78811.17 | Y11: 78811.17 | Z11: 78811.17 | AA11: 78811.17 | AB11: 78811.17 | AC11: 78811.17 | AD11: 78811.17 | AE11: 78811.17 | AF11: 78811.17 | AG11: 78811.17 | AH11: 78811.17 | AI11: 78811.17 | AJ11: 78811.17 | AK11: 78811.17 | AL11: 78811.17 | AM11: 78811.17 | AN11: 78811.17 | AO11: 78811.17 | AP11: 78811.17 | AQ11: 78811.17 | AR11: 78811.17 | AS11: 78811.17 | AT11: 78811.17 | AU11: 78811.17 | AV11: 78811.17 | AW11: 78811.17 | AX11: 78811.17 | AY11: 78811.17 | AZ11: 78811.17 | BA11: 46633.09 | BB11: 42081.27 | BC11: 36950.48 | BD11: 36950.48 | BE11: 36950.48 | BF11: 0 | BG11: 0 | BH11: 0 | BI11: 0 | BJ11: 0 | BK11: 0 | BL11: 0
A12: total_cost | B12: 22746424 | C12: 22746424 | D12: 22746424 | E12: 22746424 | F12: 22746424 | G12: 22746424 | H12: 22746424 | I12: 22746424 | J12: 22746424 | K12: 22746424 | L12: 22746424 | M12: 22746424 | N12: 22746424 | O12: 22746424 | P12: 22746424 | Q12: 22746424 | R12: 22746424 | S12: 22746424 | T12: 22746424 | U12: 22746424 | V12: 22746424 | W12: 22746424 | X12: 22746424 | Y12: 22746424 | Z12: 22746424 | AA12: 22746424 | AB12: 22746424 | AC12: 22746424 | AD12: 22746424 | AE12: 22746424 | AF12: 22746424 | AG12: 22746424 | AH12: 22746424 | AI12: 22746424 | AJ12: 22746424 | AK12: 22746424 | AL12: 22746424 | AM12: 22746424 | AN12: 22746424 | AO12: 22746424 | AP12: 22746424 | AQ12: 22746424 | AR12: 22746424 | AS12: 22746424 | AT12: 22746424 | AU12: 22746424 | AV12: 22746424 | AW12: 22746424 | AX12: 22746424 | AY12: 22746424 | AZ12: 22746424 | BA12: 10765993 | BB12: 8862800.4 | BC12: 7638591 | BD12: 7638591 | BE12: 7638591 | BF12: 0 | BG12: 0 | BH12: 0 | BI12: 0 | BJ12: 0 | BK12: 0 | BL12: 0
A13: nbv | B13: 21045989 | C13: 21045989 | D13: 20791856 | E13: 20537724 | F13: 20283592 | G13: 20029460 | H13: 19775328 | I13: 19521196 | J13: 19267063 | K13: 19012931 | L13: 18758799 | M13: 18504667 | N13: 18250535 | O13: 17996403 | P13: 17742270 | Q13: 17488138 | R13: 17234006 | S13: 16979874 | T13: 16725742 | U13: 16471610 | V13: 16217478 | W13: 15963345 | X13: 15709213 | Y13: 15455081 | Z13: 15200949 | AA13: 14946817 | AB13: 14692685 | AC13: 14438552 | AD13: 14184420 | AE13: 13930288 | AF13: 13676156 | AG13: 13422024 | AH13: 13167892 | AI13: 12913759 | AJ13: 12659627 | AK13: 12405495 | AL13: 12151363 | AM13: 11897231 | AN13: 11643099 | AO13: 11388966 | AP13: 11134834 | AQ13: 10880702 | AR13: 10626570 | AS13: 10372438 | AT13: 10118306 | AU13: 9864173.5 | AV13: 9610041.4 | AW13: 9355909.2 | AX13: 9101777.1 | AY13: 8847644.9 | AZ13: 8593512.7 | BA13: 2899244.6 | BB13: 1904664 | BC13: 1380452.1 | BD13: 1268699.6 | BE13: 1156947.1 | BF13: 0 | BG13: 0 | BH13: 0 | BI13: 0 | BJ13: 0 | BK13: 0 | BL13: 0
... A16: olmm_fleet_drop | B16: 0 | C16: 0 | D16: 0 | E16: 0 | F16: 0 | G16: 0 | H16: 0 | I16: 0 | J16: 0 | K16: 0 | L16: 0 | M16: 0 | N16: 0 | O16: 0 | P16: 0 | Q16: 0 | R16: 0 | S16: 0 | T16: 0 | U16: 0 | V16: 0 | W16: 0 | X16: 0 | Y16: 0 | Z16: 0 | AA16: 0 | AB16: 0 | AC16: 0 | AD16: 0 | AE16: 0 | AF16: 0 | AG16: 0 | AH16: 0 | AI16: 0 | AJ16: 0 | AK16: 0 | AL16: 0 | AM16: 0 | AN16: 0 | AO16: 0 | AP16: 0 | AQ16: 0 | AR16: 0 | AS16: 0 | AT16: 0 | AU16: 0 | AV16: 0 | AW16: 0 | AX16: 0 | AY16: 0 | AZ16: 0 | BA16: 0 | BB16: 0 | BC16: 0 | BD16: 0 | BE16: 0 | BF16: 0 | BG16: 0 | BH16: 0 | BI16: 0 | BJ16: 0 | BK16: 0 | BL16: 0

Sheet Summary
D2: F2025-Q3 | E2: F2025-Q4 | F2: F2026-Q1 | G2: F2026-Q2 | H2: F2026-Q3 | I2: F2026-Q4 | J2: F2027-Q1 | K2: F2027-Q2 | L2: F2027-Q3 | M2: F2027-Q4 | N2: F2028-Q1 | O2: F2028-Q2 | P2: F2028-Q3 | Q2: F2028-Q4 | R2: F2029-Q1 | S2: F2029-Q2 | T2: F2029-Q3 | U2: F2029-Q4 | V2: F2030-Q1 | W2: F2030-Q2 | X2: F2030-Q3
B4: GHC | C4: Revenue | D4: 2464196.9 | E4: 7346584.1 | F4: 7307150 | G4: 7110987.9 | H4: 6622605.1 | I4: 5637912.5 | J4: 5217139 | K4: 5061897.6 | L4: 4586442.9 | M4: 3921007.2 | N4: 3921007.2 | O4: 3783904.8 | P4: 3783904.8 | Q4: 3707885.8 | R4: 3666698.8 | S4: 3666698.8 | T4: 2446390.3 | U4: 106566.24 | V4: 0 | W4: 0 | X4: 0
C5: Fleet Count FML | D5: 139 | E5: 135 | F5: 134 | G5: 120 | H5: 104 | I5: 65 | J5: 65 | K5: 58 | L5: 46 | M5: 46 | N5: 46 | O5: 44 | P5: 44 | Q5: 42 | R5: 42 | S5: 42 | T5: 1 | U5: 0 | V5: 0 | W5: 0 | X5: 0
C6: Fleet Count OLMM | D6: 0 | E6: 0 | F6: 0 | G6: 0 | H6: 0 | I6: 0 | J6: 0 | K6: 0 | L6: 0 | M6: 0 | N6: 0 | O6: 0 | P6: 0 | Q6: 0 | R6: 0 | S6: 0 | T6: 0 | U6: 0 | V6: 0 | W6: 0 | X6: 0
C7: Fleet Count PL | D7: 0 | E7: 0 | F7: 0 | G7: 0 | H7: 0 | I7: 0 | J7: 0 | K7: 0 | L7: 0 | M7: 0 | N7: 0 | O7: 0 | P7: 0 | Q7: 0 | R7: 0 | S7: 0 | T7: 0 | U7: 0 | V7: 0 | W7: 0 | X7: 0
B8: BOT | C8: Revenue | D8: 4172192.8 | E8: 12019208 | F8: 11276324 | G8: 10800210 | H8: 9431475.3 | I8: 8190408.2 | J8: 7064070.6 | K8: 6183012.4 | L8: 5490138.8 | M8: 4803128.3 | N8: 4206896.5 | O8: 3960908.7 | P8: 2832363.8 | Q8: 2209288.5 | R8: 1620989.8 | S8: 1231335.8 | T8: 1000763.6 | U8: 873906.26 | V8: 602797.27 | W8: 403537.34 | X8: 45172.83
C9: Fleet Count FML | D9: 381 | E9: 362 | F9: 334 | G9: 310 | H9: 255 | I9: 217 | J9: 192 | K9: 171 | L9: 158 | M9: 139 | N9: 125 | O9: 114 | P9: 67 | Q9: 52 | R9: 40 | S9: 30 | T9: 25 | U9: 21 | V9: 12 | W9: 8 | X9: 4
C10: Fleet Count OLMM | D10: 20 | E10: 19 | F10: 16 | G10: 15 | H10: 14 | I10: 13 | J10: 13 | K10: 11 | L10: 8 | M10: 6 | N10: 5 | O10: 4 | P10: 4 | Q10: 2 | R10: 2 | S10: 2 | T10: 2 | U10: 1 | V10: 1 | W10: 0 | X10: 0
C11: Fleet Count PL | D11: 0 | E11: 0 | F11: 0 | G11: 0 | H11: 0 | I11: 0 | J11: 0 | K11: 0 | L11: 0 | M11: 0 | N11: 0 | O11: 0 | P11: 0 | Q11: 0 | R11: 0 | S11: 0 | T11: 0 | U11: 0 | V11: 0 | W11: 0 | X11: 0
B12: MOZ | C12: Revenue | D12: 20132176 | E12: 59954480 | F12: 57260127 | G12: 54356171 | H12: 51648479 | I12: 48203894 | J12: 44928320 | K12: 44573738 | L12: 39426946 | M12: 31588564 | N12: 26287581 | O12: 21874308 | P12: 17878155 | Q12: 11870226 | R12: 8561128.7 | S12: 7809304.3 | T12: 5663439.1 | U12: 2304930.4 | V12: 1112244.2 | W12: 79641.68 | X12: 0
C13: Fleet Count FML | D13: 224 | E13: 222 | F13: 212 | G13: 199 | H13: 193 | I13: 184 | J13: 180 | K13: 179 | L13: 156 | M13: 98 | N13: 84 | O13: 74 | P13: 69 | Q13: 44 | R13: 34 | S13: 32 | T13: 15 | U13: 7 | V13: 3 | W13: 0 | X13: 0
C14: Fleet Count OLMM | D14: 41 | E14: 40 | F14: 38 | G14: 37 | H14: 34 | I14: 22 | J14: 22 | K14: 22 | L14: 20 | M14: 20 | N14: 14 | O14: 13 | P14: 11 | Q14: 1 | R14: 1 | S14: 0 | T14: 0 | U14: 0 | V14: 0 | W14: 0 | X14: 0
C15: Fleet Count PL | D15: 0 | E15: 0 | F15: 0 | G15: 0 | H15: 0 | I15: 0 | J15: 0 | K15: 0 | L15: 0 | M15: 0 | N15: 0 | O15: 0 | P15: 0 | Q15: 0 | R15: 0 | S15: 0 | T15: 0 | U15: 0 | V15: 0 | W15: 0 | X15: 0
B16: NAM | C16: Revenue | D16: 15239223 | E16: 43544645 | F16: 40600932 | G16: 38554930 | H16: 36734110 | I16: 34679424 | J16: 33100010 | K16: 31488271 | L16: 29323487 | M16: 26848804 | N16: 23259628 | O16: 20420569 | P16: 17459443 | Q16: 15592652 | R16: 12825380 | S16: 10432512 | T16: 8145642.9 | U16: 6384272.8 | V16: 3583867.3 | W16: 1643285.5 | X16: 296662.07
C17: Fleet Count FML | D17: 943 | E17: 856 | F17: 766 | G17: 717 | H17: 682 | I17: 635 | J17: 610 | K17: 561 | L17: 527 | M17: 473 | N17: 401 | O17: 348 | P17: 309 | Q17: 265 | R17: 205 | S17: 165 | T17: 131 | U17: 102 | V17: 61 | W17: 39 | X17: 30
C18: Fleet Count OLMM | D18: 262 | E18: 259 | F18: 248 | G18: 232 | H18: 216 | I18: 200 | J18: 194 | K18: 185 | L18: 163 | M18: 146 | N18: 133 | O18: 113 | P18: 100 | Q18: 88 | R18: 79 | S18: 60 | T18: 45 | U18: 30 | V18: 10 | W18: 2 | X18: 1
C19: Fleet Count PL | D19: 0 | E19: 0 | F19: 0 | G19: 0 | H19: 0 | I19: 0 | J19: 0 | K19: 0 | L19: 0 | M19: 0 | N19: 0 | O19: 0 | P19: 0 | Q19: 0 | R19: 0 | S19: 0 | T19: 0 | U19: 0 | V19: 0 | W19: 0 | X19: 0
B20: GHA | C20: Revenue | D20: 8735.23 | E20: 18879.75 | F20: 3608.66 | G20: 0 | H20: 0 | I20: 0 | J20: 0 | K20: 0 | L20: 0 | M20: 0 | N20: 0 | O20: 0 | P20: 0 | Q20: 0 | R20: 0 | S20: 0 | T20: 0 | U20: 0 | V20: 0 | W20: 0 | X20: 0
C21: Fleet Count FML | D21: 11 | E21: 4 | F21: 0 | G21: 0 | H21: 0 | I21: 0 | J21: 0 | K21: 0 | L21: 0 | M21: 0 | N21: 0 | O21: 0 | P21: 0 | Q21: 0 | R21: 0 | S21: 0 | T21: 0 | U21: 0 | V21: 0 | W21: 0 | X21: 0
C22: Fleet Count OLMM | D22: 0 | E22: 0 | F22: 0 | G22: 0 | H22: 0 | I22: 0 | J22: 0 | K22: 0 | L22: 0 | M22: 0 | N22: 0 | O22: 0 | P22: 0 | Q22: 0 | R22: 0 | S22: 0 | T22: 0 | U22: 0 | V22: 0 | W22: 0 | X22: 0
C23: Fleet Count PL | D23: 0 | E23: 0 | F23: 0 | G23: 0 | H23: 0 | I23: 0 | J23: 0 | K23: 0 | L23: 0 | M23: 0 | N23: 0 | O23: 0 | P23: 0 | Q23: 0 | R23: 0 | S23: 0 | T23: 0 | U23: 0 | V23: 0 | W23: 0 | X23: 0
B24: Inland | C24: Revenue | D24: 94747081 | E24: 2.7147353e+08 | F24: 2.5059566e+08 | G24: 2.3105849e+08 | H24: 2.1277235e+08 | I24: 1.889587e+08 | J24: 1.6686028e+08 | K24: 1.5118488e+08 | L24: 1.3060925e+08 | M24: 1.0850183e+08 | N24: 88184666 | O24: 73906868 | P24: 57819339 | Q24: 45282396 | R24: 31377257 | S24: 25103981 | T24: 17552692 | U24: 11073702 | V24: 8147237.2 | W24: 5326075 | X24: 1117617.9
C25: Fleet Count FML | D25: 6835 | E25: 6198 | F25: 5546 | G25: 5008 | H25: 4439 | I25: 3882 | J25: 3419 | K25: 2942 | L25: 2368 | M25: 1885 | N25: 1525 | O25: 1258 | P25: 1002 | Q25: 834 | R25: 614 | S25: 502 | T25: 359 | U25: 185 | V25: 106 | W25: 46 | X25: 21
C26: Fleet Count OLMM | D26: 1736 | E26: 1675 | F26: 1626 | G26: 1582 | H26: 1521 | I26: 1409 | J26: 1316 | K26: 1252 | L26: 1124 | M26: 1069 | N26: 1012 | O26: 906 | P26: 726 | Q26: 403 | R26: 250 | S26: 232 | T26: 187 | U26: 142 | V26: 124 | W26: 102 | X26: 99
C27: Fleet Count PL | D27: 1 | E27: 1 | F27: 1 | G27: 1 | H27: 0 | I27: 0 | J27: 0 | K27: 0 | L27: 0 | M27: 0 | N27: 0 | O27: 0 | P27: 0 | Q27: 0 | R27: 0 | S27: 0 | T27: 0 | U27: 0 | V27: 0 | W27: 0 | X27: 0
B28: LES | C28: Revenue | D28: 2773746.7 | E28: 8088133.6 | F28: 7780164.9 | G28: 7393018.1 | H28: 7231655 | I28: 7073483 | J28: 6938708.6 | K28: 6698953.7 | L28: 6255271.3 | M28: 5400938.8 | N28: 3116806.5 | O28: 2682340.1 | P28: 2117248.2 | Q28: 1499648.5 | R28: 1286398.4 | S28: 1039238.4 | T28: 768957.59 | U28: 540944.75 | V28: 396790.5 | W28: 280061.58 | X28: 7767.29
C29: Fleet Count FML | D29: 170 | E29: 152 | F29: 148 | G29: 138 | H29: 134 | I29: 126 | J29: 124 | K29: 118 | L29: 108 | M29: 90 | N29: 79 | O29: 62 | P29: 42 | Q29: 29 | R29: 24 | S29: 18 | T29: 10 | U29: 7 | V29: 4 | W29: 2 | X29: 1
C30: Fleet Count OLMM | D30: 9 | E30: 9 | F30: 9 | G30: 8 | H30: 8 | I30: 8 | J30: 8 | K30: 8 | L30: 7 | M30: 7 | N30: 2 | O30: 2 | P30: 1 | Q30: 1 | R30: 1 | S30: 1 | T30: 1 | U30: 1 | V30: 1 | W30: 0 | X30: 0
C31: Fleet Count PL | D31: 0 | E31: 0 | F31: 0 | G31: 0 | H31: 0 | I31: 0 | J31: 0 | K31: 0 | L31: 0 | M31: 0 | N31: 0 | O31: 0 | P31: 0 | Q31: 0 | R31: 0 | S31: 0 | T31: 0 | U31: 0 | V31: 0 | W31: 0 | X31: 0
B32: Central & Commercial | C32: Revenue | D32: 14727820 | E32: 43484822 | F32: 42060240 | G32: 41048597 | H32: 40249694 | I32: 37343237 | J32: 35230272 | K32: 33658427 | L32: 28269329 | M32: 23834187 | N32: 18615466 | O32: 15687322 | P32: 13839089 | Q32: 11993377 | R32: 8846599.9 | S32: 7072076.5 | T32: 3653911.2 | U32: 2445260 | V32: 1467045.2 | W32: 930603.07 | X32: 224995.19
C33: Fleet Count FML | D33: 455 | E33: 430 | F33: 403 | G33: 375 | H33: 358 | I33: 337 | J33: 319 | K33: 308 | L33: 271 | M33: 207 | N33: 138 | O33: 118 | P33: 108 | Q33: 85 | R33: 71 | S33: 66 | T33: 38 | U33: 29 | V33: 20 | W33: 9 | X33: 5
C34: Fleet Count OLMM | D34: 280 | E34: 279 | F34: 262 | G34: 258 | H34: 258 | I34: 226 | J34: 222 | K34: 198 | L34: 180 | M34: 164 | N34: 144 | O34: 118 | P34: 103 | Q34: 67 | R34: 51 | S34: 36 | T34: 20 | U34: 14 | V34: 6 | W34: 6 | X34: 6
C35: Fleet Count PL | D35: 0 | E35: 0 | F35: 0 | G35: 0 | H35: 0 | I35: 0 | J35: 0 | K35: 0 | L35: 0 | M35: 0 | N35: 0 | O35: 0 | P35: 0 | Q35: 0 | R35: 0 | S35: 0 | T35: 0 | U35: 0 | V35: 0 | W35: 0 | X35: 0
B36: Coastal | C36: Revenue | D36: 31499174 | E36: 89356305 | F36: 82279494 | G36: 74761200 | H36: 67458893 | I36: 60208443 | J36: 52181367 | K36: 46513338 | L36: 40940755 | M36: 33752928 | N36: 26989395 | O36: 22962602 | P36: 18742590 | Q36: 15664535 | R36: 12310247 | S36: 9735903.4 | T36: 7665867.8 | U36: 6978263.8 | V36: 3611876.3 | W36: 1984202.7 | X36: 218819.86
C37: Fleet Count FML | D37: 2497 | E37: 2268 | F37: 2071 | G37: 1849 | H37: 1625 | I37: 1421 | J37: 1233 | K37: 1091 | L37: 913 | M37: 708 | N37: 555 | O37: 464 | P37: 364 | Q37: 299 | R37: 225 | S37: 178 | T37: 141 | U37: 124 | V37: 56 | W37: 31 | X37: 18
C38: Fleet Count OLMM | D38: 247 | E38: 223 | F38: 207 | G38: 201 | H38: 198 | I38: 186 | J38: 178 | K38: 168 | L38: 162 | M38: 135 | N38: 107 | O38: 93 | P38: 91 | Q38: 42 | R38: 33 | S38: 26 | T38: 16 | U38: 16 | V38: 6 | W38: 5 | X38: 1
C39: Fleet Count PL | D39: 0 | E39: 0 | F39: 0 | G39: 0 | H39: 0 | I39: 0 | J39: 0 | K39: 0 | L39: 0 | M39: 0 | N39: 0 | O39: 0 | P39: 0 | Q39: 0 | R39: 0 | S39: 0 | T39: 0 | U39: 0 | V39: 0 | W39: 0 | X39: 0
B40: Public Sector | C40: Revenue | D40: 5269001.5 | E40: 15612760 | F40: 14794584 | G40: 14109814 | H40: 13679516 | I40: 13356481 | J40: 12239922 | K40: 10353892 | L40: 9397576 | M40: 8936642.1 | N40: 6345677.7 | O40: 1244904.6 | P40: 485113.26 | Q40: 428564.73 | R40: 340048.66 | S40: 323446.39 | T40: 290598.01 | U40: 282713.43 | V40: 282713.43 | W40: 264177.71 | X40: 75702.09
C41: Fleet Count FML | D41: 258 | E41: 252 | F41: 233 | G41: 232 | H41: 218 | I41: 205 | J41: 145 | K41: 104 | L41: 67 | M41: 58 | N41: 47 | O41: 21 | P41: 19 | Q41: 16 | R41: 15 | S41: 14 | T41: 13 | U41: 13 | V41: 13 | W41: 12 | X41: 12
C42: Fleet Count OLMM | D42: 93 | E42: 93 | F42: 93 | G42: 93 | H42: 93 | I42: 93 | J42: 93 | K42: 93 | L42: 93 | M42: 93 | N42: 25 | O42: 1 | P42: 0 | Q42: 0 | R42: 0 | S42: 0 | T42: 0 | U42: 0 | V42: 0 | W42: 0 | X42: 0
C43: Fleet Count PL | D43: 0 | E43: 0 | F43: 0 | G43: 0 | H43: 0 | I43: 0 | J43: 0 | K43: 0 | L43: 0 | M43: 0 | N43: 0 | O43: 0 | P43: 0 | Q43: 0 | R43: 0 | S43: 0 | T43: 0 | U43: 0 | V43: 0 | W43: 0 | X43: 0
B44: Legal | C44: Revenue | D44: 208163.19 | E44: 624489.57 | F44: 624489.57 | G44: 624489.57 | H44: 624489.57 | I44: 587851.4 | J44: 496171.15 | K44: 459363.33 | L44: 422854.51 | M44: 404600.1 | N44: 350028.27 | O44: 331560.51 | P44: 294624.99 | Q44: 30173.43 | R44: 30173.43 | S44: 30173.43 | T44: 30173.43 | U44: 30173.43 | V44: 30173.43 | W44: 10057.81 | X44: 0
C45: Fleet Count FML | D45: 4 | E45: 4 | F45: 4 | G45: 4 | H45: 4 | I45: 4 | J45: 3 | K45: 3 | L45: 2 | M45: 2 | N45: 1 | O45: 0 | P45: 0 | Q45: 0 | R45: 0 | S45: 0 | T45: 0 | U45: 0 | V45: 0 | W45: 0 | X45: 0
